Workbook

Sheet Capital de Trabajo
B5: Grupo Xanalab
B6: Al 30 de Junio del 2025
B7: Analisis Financiero de Capital de Trabajo
B10: Activos | G10: MXN | I10: Fuentes de Recursos | O10: MXN
B12: Detalle de Cuentas por Cobrar | I12: Detalle de Cuentas por Pagar Operativas
B14: *** Detalle de principales clientes | I14: *** Detalle de principales proveedores
B20: Total de Cuentas por Cobrar | G20: 41982958 | I20: Total de Cuentas por Pagar Operativas | O20: 16383076
B22: Detalle de Inventario | I22: Detalle de Cuentas por Pagar Contigentes y NO Operativas
B24: Materia prima | I24: *** Detalle de principales contingencias a cargo y cuentas no operativas por pagar.
B25: Producto terminado
B26: Empaque
B27: Otros
B29: Total de Inventarios | G29: 28209330 | I29: Total de Cuentas por Pagar Contingentes y NO Operativas | O29: 16500000
B31: Detalle de Activos Fijos | I31: Detalle de Cuentas por Pagar entre Partes Relacionadas
I32: IVA
B33: Terrenos
B34: Edificios
B35: Maquinaria y equipo
B36: Equipo de Transporte
B37: Mobiliario y equipo
B39: Total de Activos Fijos | G39: 46811280 | I39: Total de Cuentas por Pagar a Partes Relacionadas | O39: =+SUM(O31:O38) -> 0
B41: Detalle de Arrendamientos | I41: Detalle de Deuda con Costo (Créditos Bancarios y Arrendamientos)
B43: Terrenos en Arrendamiento | I43: Capital X
B44: Edificios en Arrendamiento | I44: Santander
B45: Maquinaria y equipo en Arrendamiento | I45: Banregio
B46: Equipo de Transporte en Arrendamiento | I46: Capix
B47: Mobiliario y equipo en Arrendamiento
B49: Total de Arrendamientos | G49: 15643526 | I49: Total de Deuda | O49: 84288718
B51: Detalle de Intangibles | I51: Detalle de Capital
B53: Marca Biomiral | I53: *** Detalle de deuda convertida en acciones en favor de NUVARI
B54: Marcas - otras
B55: Marcas - otras
B56: Licencias COFEPRIS
B57: Licencias Otras
B59: Total de Intangibles | G59: 24000000 | I59: Total de Capital | O59: 64500000
B61: Total de Activos | F61: ∑ | G61: =+G59+G49+G39+G29+G20 -> 1.5664709e+08 | I61: Total de Pasivos y Capital | N61: ∑ | O61: =+O59+O49+O39+O29+O20 -> 1.8167179e+08
B65: Capital de Trabajo Neto | F65: ∑ | G65: =+G61-O61 -> -25024700

Sheet Flujo
B5: Grupo Xanalab
B6: Al 30 de Junio del 2025
B7: Flujo
G9: 2025 | I9: 2026 | K9: 2027
B10: Detalle | G10: MXN | I10: MXN | K10: MXN
B12: EBITDA | G12: =+SUM('IS (ROLLING)'!P61:AA61) -> 19665572 | I12: =+'IS (ROLLING)'!AP61 -> 55133517 | K12: =+'IS (ROLLING)'!BD61 -> 85011815
A14: (-) | B14: Gastos Financieros | G14: ='IS (ROLLING)'!AB64 -> 14822493 | I14: ='IS (ROLLING)'!AP64 -> 16508198 | K14: ='IS (ROLLING)'!BD64 -> 7363493.7
A15: (-) | B15: Impuestos
A16: (-) | B16: Capital Expenditure (CapEx) | G16: ='Cashflow (ROLLING) CAP'!N36 -> 5100000 | I16: ='Cashflow (ROLLING) CAP'!AA36 -> 9000000 | K16: ='Cashflow (ROLLING) CAP'!AN36 -> 3600000
A17: (-) | B17: Pago Créditos Bancarios | G17: =SUM('Cashflow (ROLLING) CAP'!N48:N52) -> 45483744 | I17: =SUM('Cashflow (ROLLING) CAP'!AA48:AA52) -> 21061379 | K17: =SUM('Cashflow (ROLLING) CAP'!AN48:AN52) -> 14157784
A18: (-) | B18: Pago de Arrendamientos | G18: =SUM('Cashflow (ROLLING) CAP'!N53:N54) -> 3891757.7 | I18: ='Cashflow (ROLLING) CAP'!AA54 -> 3694116.4 | K18: ='Cashflow (ROLLING) CAP'!AN54 -> 3529152.9
A19: (-) | B19: Pago de Contigencias (Impuestos+Actualizciones y Recargos) | G19: ='Cashflow (ROLLING) CAP'!N47 -> 7500000 | I19: ='Cashflow (ROLLING) CAP'!AA47 -> 7500000 | K19: ='Cashflow (ROLLING) CAP'!AN47 -> 0
A20: (-) | B20: Pago de Contigencias (Otros) | G20: ='Cashflow (ROLLING) CAP'!N37 -> 650000 | I20: ='Cashflow (ROLLING) CAP'!AA37 -> 300000 | K20: ='Cashflow (ROLLING) CAP'!AN37 -> 0
B22: Free Cash Flow (FCF) | G22: =+G12-SUM(G14:G20) -> -57782422 | I22: =+I12-SUM(I14:I20) -> -2930176.9 | K22: =+K12-SUM(K14:K20) -> 56361384

Sheet 1Q Consolidado
A1: Xana Lab SA de CV - Farmiral SA de CV | K1: Xana Lab SA de CV - Farmiral SA de CV | Q1: Xana Lab SA de CV - Farmiral SA de CV | W1: Xana Lab SA de CV - Farmiral SA de CV
A2: Estado de Resultados por mes de enero a marzo 2025 | K2: Estado de Resultados del 01 al 31de Enero 2025 | Q2: Estado de Resultados del 01 al 28 de Febrero 2025 | W2: Estado de Resultados del 01 al 31 de Marzo 2025
B4: Periodo | C4: % | D4: Periodo | E4: % | F4: Periodo | G4: % | H4: Acumulado | I4: % | L4: Periodo | M4: % | N4: Acumulado | O4: % | R4: Periodo | S4: % | T4: Acumulado | U4: % | X4: Periodo | Y4: % | Z4: Acumulado | AA4: %
A6: I n g r e s o s | B6: ENERO | D6: FEBRERO | F6: MARZO | H6: ENERO A MARZO | K6: I n g r e s o s | Q6: I n g r e s o s | W6: I n g r e s o s
A8: Ventas de producto grav a tasa gral | K8: Ventas de producto grav a tasa gral | Q8: Ventas de producto grav a tasa gral | W8: Ventas de producto grav a tasa gral
A9: Maquila | B9: 10514791 | C9: 67.199073 | D9: 8719963 | E9: 56.322545 | F9: 5524668.5 | G9: 46.018346 | H9: 24759422 | I9: 57.400141 | K9: Maquila | L9: 10514791 | M9: 67.199073 | N9: 10514791 | O9: 67.199073 | Q9: Maquila | R9: 8719963 | S9: 56.322545 | T9: 19234754 | U9: 61.789641 | W9: Maquila | X9: 5524668.5 | Y9: 46.018346 | Z9: 24759422 | AA9: 57.400141
A10: Marca Propia | B10: 795925.39 | C10: 5.0866869 | D10: 4286349.3 | E10: 27.68568 | F10: 5389707.1 | G10: 44.89417 | H10: 10388496 | I10: 24.083806 | K10: Marca Propia | L10: 795925.39 | M10: 5.0866869 | N10: 795925.39 | O10: 5.0866869 | Q10: Marca Propia | R10: 4286349.3 | S10: 27.68568 | T10: 5082274.7 | U10: 16.326278 | W10: Marca Propia | X10: 5389707.1 | Y10: 44.89417 | Z10: 10388496 | AA10: 24.083806
A11: Biomiral | K11: Biomiral | Q11: Biomiral | W11: Biomiral | Z11: 0
A12: Distribuidores | B12: 5007487.3 | C12: 32.002397 | D12: 2933807.5 | E12: 18.949565 | F12: 2082595.7 | G12: 17.347214 | H12: 10023891 | I12: 23.238536 | K12: Distribuidores | L12: 5007487.3 | M12: 32.002397 | N12: 5007487.3 | O12: 32.002397 | Q12: Distribuidores | R12: 2933807.5 | S12: 18.949565 | T12: 7941294.8 | U12: 25.510582 | W12: Distribuidores | X12: 2082595.7 | Y12: 17.347214 | Z12: 10023891 | AA12: 23.238536
A13: Retail | B13: 612222.09 | C13: 3.9126558 | D13: 58624.64 | E13: 0.3786586 | F13: 105829.02 | G13: 0.88151469 | H13: 776393.02 | I13: 1.7999236 | K13: Retail | L13: 612222.09 | M13: 3.9126558 | N13: 612222.09 | O13: 3.9126558 | Q13: Retail | R13: 58624.64 | S13: 0.3786586 | T13: 670846.73 | U13: 2.1550252 | W13: Retail | X13: 105829.02 | Y13: 0.88151469 | Z13: 776393.02 | AA13: 1.7999236
A15: Total Biomiral | B15: 5619709.4 | C15: 35.915053 | D15: 2992432.2 | E15: 19.328224 | F15: 2188424.7 | G15: 18.228729 | H15: 10800284 | I15: 25.03846 | K15: Total Biomiral | L15: 5619709.4 | M15: 35.915053 | N15: 5619709.4 | O15: 35.915053 | Q15: Total Biomiral | R15: 2992432.2 | S15: 19.328224 | T15: 8612141.6 | U15: 27.665607 | W15: Total Biomiral | X15: 2188424.7 | Y15: 18.228729 | Z15: 10800284 | AA15: 25.03846
A18: Total Ventas de producto grav a tasa gral | B18: 16930425 | C18: 108.20081 | D18: 15998744 | E18: 103.33645 | F18: 13102800 | G18: 109.14124 | H18: 45948201 | I18: 106.52241 | K18: Total Ventas de producto grav a tasa gral | L18: 16930425 | M18: 108.20081 | N18: 16930425 | O18: 108.20081 | Q18: Total Ventas de producto grav a tasa gral | R18: 15998744 | S18: 103.33645 | T18: 32929170 | U18: 105.78153 | W18: Total Ventas de producto grav a tasa gral | X18: 13102800 | Y18: 109.14124 | Z18: 45948201 | AA18: 106.52241
A20: Dev, desctos o bonifi s vtas y/o serv tasa gral | K20: Dev, desctos o bonifi s vtas y/o serv tasa gral | Q20: Dev, desctos o bonifi s vtas y/o serv tasa gral | W20: Dev, desctos o bonifi s vtas y/o serv tasa gral
A21: Devoluciones s/venta | B21: 672752.42 | C21: 4.2994997 | D21: 130501.52 | E21: 0.84291388 | F21: 70436.43 | G21: 0.58670814 | H21: 873690.37 | I21: 2.0254895 | K21: Devoluciones s/venta | L21: 672752.42 | M21: 4.2994997 | N21: 672752.42 | O21: 4.2994997 | Q21: Devoluciones s/venta | R21: 130501.52 | S21: 0.84291388 | T21: 803253.94 | U21: 2.5803695 | W21: Devoluciones s/venta | X21: 70436.43 | Y21: 0.58670814 | Z21: 873690.37 | AA21: 2.0254895
A22: Descuento por MKT | B22: 225525.48 | C22: 1.4413129 | D22: 127931.18 | E22: 0.82631196 | F22: 528110.88 | G22: 4.3989588 | H22: 881567.54 | I22: 2.0437513 | K22: Descuento por MKT | L22: 225525.48 | M22: 1.4413129 | N22: 225525.48 | O22: 1.4413129 | Q22: Descuento por MKT | R22: 127931.18 | S22: 0.82631196 | T22: 353456.66 | U22: 1.1354427 | W22: Descuento por MKT | X22: 528110.88 | Y22: 4.3989588 | Z22: 881567.54 | AA22: 2.0437513
A23: Descuento relacion comercial | B23: 142524.59 | C23: 0.91086172 | D23: 83969.78 | E23: 0.54236374 | F23: -2757.34 | G23: -0.022967573 | H23: 139968.21 | I23: 0.32449041 | K23: Descuento relacion comercial | L23: 142524.59 | M23: 0.91086172 | N23: 142524.59 | O23: 0.91086172 | Q23: Descuento relacion comercial | R23: 83969.78 | S23: 0.54236374 | T23: 226494.37 | U23: 0.72758955 | W23: Descuento relacion comercial | X23: -2757.34 | Y23: -0.022967573 | Z23: 139968.21 | AA23: 0.32449041
A24: Descuento por piezas faltantes | B24: 24524 | C24: 0.15673066 | D24: 56.08 | E24: 0.00036222268 | F24: 1691.53 | G24: 0.014089789 | H24: 26271.61 | I24: 0.060905869 | K24: Descuento por piezas faltantes | L24: 24524 | M24: 0.15673066 | N24: 24524 | O24: 0.15673066 | Q24: Descuento por piezas faltantes | R24: 56.08 | S24: 0.00036222268 | T24: 24580.08 | U24: 0.078960945 | W24: Descuento por piezas faltantes | X24: 1691.53 | Y24: 0.014089789 | Z24: 26271.61 | AA24: 0.060905869
A25: Descuento por piezas dañadas | B25: 236.38 | C25: 0.0015106831 | D25: 1169.71 | E25: 0.0075551978 | F25: 257169.66 | G25: 2.1421235 | H25: 258575.75 | I25: 0.59946005 | K25: Descuento por piezas dañadas | L25: 236.38 | M25: 0.0015106831 | N25: 236.38 | O25: 0.0015106831 | Q25: Descuento por piezas dañadas | R25: 1169.71 | S25: 0.0075551978 | T25: 1406.09 | U25: 0.0045169175 | W25: Descuento por piezas dañadas | X25: 257169.66 | Y25: 2.1421235 | Z25: 258575.75 | AA25: 0.59946005
A26: Descuento por pronto pago (cumplimiento tyc) | B26: 215833.58 | C26: 1.3793728 | D26: 131373.67 | E26: 0.84854712 | F26: 216430.88 | G26: 1.8027853 | H26: 563638.13 | I26: 1.3066908 | K26: Descuento por pronto pago (cumplimiento tyc) | L26: 215833.58 | M26: 1.3793728 | N26: 215833.58 | O26: 1.3793728 | Q26: Descuento por pronto pago (cumplimiento tyc) | R26: 131373.67 | S26: 0.84854712 | T26: 347207.25 | U26: 1.1153671 | W26: Descuento por pronto pago (cumplimiento tyc) | X26: 216430.88 | Y26: 1.8027853 | Z26: 563638.13 | AA26: 1.3066908
A27: Descuento por error en precio | B27: 198.28 | C27: 0.0012671895 | D27: 3990.92 | E27: 0.025777492 | F27: 9131.35 | G27: 0.076060604 | H27: 13320.55 | I27: 0.030881232 | K27: Descuento por error en precio | L27: 198.28 | M27: 0.0012671895 | N27: 198.28 | O27: 0.0012671895 | Q27: Descuento por error en precio | R27: 3990.92 | S27: 0.025777492 | T27: 4189.2 | U27: 0.013457368 | W27: Descuento por error en precio | X27: 9131.35 | Y27: 0.076060604 | Z27: 13320.55 | AA27: 0.030881232
A28: Descuentos diversos | B28: 74404.91 | C28: 0.47551503 | D28: 35521.1 | E28: 0.22943203 | F28: 17226 | G28: 0.1434859 | H28: 127152.01 | I28: 0.29477842 | K28: Descuentos diversos | L28: 74404.91 | M28: 0.47551503 | N28: 74404.91 | O28: 0.47551503 | Q28: Descuentos diversos | R28: 35521.1 | S28: 0.22943203 | T28: 109926.01 | U28: 0.35312585 | W28: Descuentos diversos | X28: 17226 | Y28: 0.1434859 | Z28: 127152.01 | AA28: 0.29477842
A29: Descuento por caducidad del producto | B29: 0 | C29: 0 | D29: 9951.22 | E29: 0.064275278 | F29: 0 | G29: 0 | H29: 9951.22 | I29: 0.023070063 | K29: Descuento por caducidad del producto | L29: 0 | M29: 0 | N29: 0 | O29: 0 | Q29: Descuento por caducidad del producto | R29: 9951.22 | S29: 0.064275278 | T29: 9951.22 | U29: 0.031967257 | W29: Descuento por caducidad del producto | X29: 0 | Y29: 0 | Z29: 9951.22 | AA29: 0.023070063
A31: Total Dev | B31: -1355999.6 | C31: -8.6660707 | D31: -524465.18 | E31: -3.3875389 | F31: -1097439.4 | G31: -9.1412445 | H31: -2894135.4 | I31: -6.7095177 | K31: Total Dev | L31: -1355999.6 | M31: -8.6660707 | N31: -1355999.6 | O31: -8.6660707 | Q31: Total Dev | R31: -524465.18 | S31: -3.3875389 | T31: -1880464.8 | U31: -6.0407972 | W31: Total Dev | X31: -1097439.4 | Y31: -9.1412445 | Z31: -2894135.4 | AA31: -6.7095177
A33: Otros Ingresos | B33: =B31-B35 -> -1428799.6 | K33: Otros Ingresos | Q33: Otros Ingresos | W33: Otros Ingresos
A34: Descuento por relacion comercial | B34: 0 | C34: 0 | D34: 0 | E34: 0 | F34: 0 | G34: 0 | H34: 0 | I34: 0 | K34: Descuento por relacion comercial | L34: 0 | M34: 0 | N34: 0 | O34: 0 | Q34: Descuento por relacion comercial | R34: 0 | S34: 0 | T34: 0 | U34: 0 | W34: Descuento por relacion comercial | X34: 0 | Y34: 0 | Z34: 0 | AA34: 0
A35: Factura para afectar Nota de credito | B35: 72800 | C35: 0.46525819 | D35: 0 | E35: 0 | F35: 0 | G35: 0 | H35: 72800 | I35: 0.16877334 | K35: Factura para afectar Nota de credito | L35: 72800 | M35: 0.46525819 | N35: 72800 | O35: 0.46525819 | Q35: Factura para afectar Nota de credito | R35: 0 | S35: 0 | T35: 72800 | U35: 0.23386241 | W35: Factura para afectar Nota de credito | X35: 0 | Y35: 0 | Z35: 72800 | AA35: 0.16877334
A37: Total Otros Ingresos | B37: 72800 | C37: 0.46525819 | D37: 0 | E37: 0 | F37: 0 | G37: 0 | H37: 72800 | I37: 0.16877334 | K37: Total Otros Ingresos | L37: 72800 | M37: 0.46525819 | N37: 72800 | O37: 0.46525819 | Q37: Total Otros Ingresos | R37: 0 | S37: 0 | T37: 72800 | U37: 0.23386241 | W37: Total Otros Ingresos | X37: 0 | Y37: 0 | Z37: 72800 | AA37: 0.16877334
A40: Total Ingresos | B40: 15647226 | C40: 100 | D40: 15482189 | E40: 100 | F40: 12005361 | G40: 100 | H40: 43134776 | I40: 100 | K40: Total Ingresos | L40: 15647226 | M40: 100 | N40: 15647226 | O40: 100 | Q40: Total Ingresos | R40: 15482189 | S40: 100 | T40: 31129415 | U40: 100 | W40: Total Ingresos | X40: 12005361 | Y40: 100 | Z40: 43134776 | AA40: 100
B41: =B18+B33 -> 15501626 | D41: =D18+D31+D35 -> 15474279 | F41: =F18+F31+F35 -> 12005361 | H41: =H18+H31+H35 -> 43126866
A42: E g r e s o s | K42: E g r e s o s | Q42: E g r e s o s | W42: E g r e s o s
A44: Costos Directos | K44: Costos Directos | Q44: Costos Directos | W44: Costos Directos
A45: Materia Prima | B45: 6374777.3 | C45: 40.740623 | D45: 6554330.4 | E45: 42.334649 | F45: 4958570.6 | G45: 41.30297 | H45: 17887678 | I45: 41.469274 | K45: Materia Prima | L45: 6374777.3 | M45: 40.740623 | N45: 6374777.3 | O45: 40.740623 | Q45: Materia Prima | R45: 6554330.4 | S45: 42.334649 | T45: 12929108 | U45: 41.533411 | W45: Materia Prima | X45: 4958570.6 | Y45: 41.30297 | Z45: 17887678 | AA45: 41.469274
A46: Material Empaque | B46: 0 | C46: 0 | D46: 0 | E46: 0 | F46: 0 | G46: 0 | H46: 0 | I46: 0 | K46: Material Empaque | L46: 0 | M46: 0 | N46: 0 | O46: 0 | Q46: Material Empaque | R46: 0 | S46: 0 | T46: 0 | U46: 0 | W46: Material Empaque | X46: 0 | Y46: 0 | Z46: 0 | AA46: 0
A47: Fletes y logistica | B47: 21135.54 | C47: 0.13507532 | D47: 41265.29 | E47: 0.26653395 | F47: 111265.6 | G47: 0.9267993 | H47: 173666.43 | I47: 0.4026135 | K47: Fletes y logistica | L47: 21135.54 | M47: 0.13507532 | N47: 21135.54 | O47: 0.13507532 | Q47: Fletes y logistica | R47: 41265.29 | S47: 0.26653395 | T47: 62400.83 | U47: 0.20045616 | W47: Fletes y logistica | X47: 111265.6 | Y47: 0.9267993 | Z47: 173666.43 | AA47: 0.4026135
A48: Maniobras | B48: 136080 | C48: 0.86967493 | D48: 0 | E48: 0 | F48: 0 | G48: 0 | H48: 136080 | I48: 0.31547631 | K48: Maniobras | L48: 136080 | M48: 0.86967493 | N48: 136080 | O48: 0.86967493 | Q48: Maniobras | R48: 0 | S48: 0 | T48: 136080 | U48: 0.43714281 | W48: Maniobras | X48: 0 | Y48: 0 | Z48: 136080 | AA48: 0.31547631
A49: Mano de obra directa | B49: 2785345.6 | C49: 17.800891 | D49: 1656923.7 | E49: 10.702128 | F49: 1531318.2 | G49: 12.755287 | H49: 5973587.6 | I49: 13.848658 | K49: Mano de obra directa | L49: 2785345.6 | M49: 17.800891 | N49: 2785345.6 | O49: 17.800891 | Q49: Mano de obra directa | R49: 1656923.7 | S49: 10.702128 | T49: 4442269.4 | U49: 14.270327 | W49: Mano de obra directa | X49: 1531318.2 | Y49: 12.755287 | Z49: 5973587.6 | AA49: 13.848658
A50: Seguridad social Produccion | B50: 321486.85 | C50: 2.0545933 | D50: 648536.46 | E50: 4.1889197 | F50: 151553.91 | G50: 1.2623853 | H50: 1121577.2 | I50: 2.6001694 | K50: Seguridad social Produccion | L50: 321486.85 | M50: 2.0545933 | N50: 321486.85 | O50: 2.0545933 | Q50: Seguridad social Produccion | R50: 648536.46 | S50: 4.1889197 | T50: 970023.31 | U50: 3.1160988 | W50: Seguridad social Produccion | X50: 151553.91 | Y50: 1.2623853 | Z50: 1121577.2 | AA50: 2.6001694
A51: Gastos Generales de Produccion | B51: 126383.45 | C51: 0.80770516 | D51: 94135 | E51: 0.60802125 | F51: 105836.74 | G51: 0.881579 | H51: 326355.19 | I51: 0.75659415 | K51: Gastos Generales de Produccion | L51: 126383.45 | M51: 0.80770516 | N51: 126383.45 | O51: 0.80770516 | Q51: Gastos Generales de Produccion | R51: 94135 | S51: 0.60802125 | T51: 220518.45 | U51: 0.70839253 | W51: Gastos Generales de Produccion | X51: 105836.74 | Y51: 0.881579 | Z51: 326355.19 | AA51: 0.75659415
A52: Otros conceptos de costo | B52: 0 | C52: 0 | D52: 0 | E52: 0 | F52: 28585.2 | G52: 0.23810363 | H52: 28585.2 | I52: 0.0662695 | K52: Otros conceptos de costo | L52: 0 | M52: 0 | N52: 0 | O52: 0 | Q52: Otros conceptos de costo | R52: 0 | S52: 0 | T52: 0 | U52: 0 | W52: Otros conceptos de costo | X52: 28585.2 | Y52: 0.23810363 | Z52: 28585.2 | AA52: 0.0662695
B53: =SUM(B46:B52) -> 3390431.5 | C53: =SUM(C46:C52) -> 21.66794 | D53: =SUM(D46:D52) -> 2440860.5 | E53: =SUM(E46:E52) -> 15.765603 | F53: =SUM(F46:F52) -> 1928559.7 | G53: =SUM(G46:G52) -> 16.064154 | H53: =SUM(H46:H52) -> 7759851.6 | I53: =SUM(I46:I52) -> 17.989781
A54: Total Costos Directos | B54: 9765208.8 | C54: 62.408563 | D54: 8995190.9 | E54: 58.100252 | F54: 6887130.3 | G54: 57.367124 | H54: 25647530 | I54: 59.459055 | K54: Total Costos Directos | L54: 9765208.8 | M54: 62.408563 | N54: 9765208.8 | O54: 62.408563 | Q54: Total Costos Directos | R54: 8995190.9 | S54: 58.100252 | T54: 18760400 | U54: 60.265828 | W54: Total Costos Directos | X54: 6887130.3 | Y54: 57.367124 | Z54: 25647530 | AA54: 59.459055
B55: =B41-B54 -> 5736417 | D55: =D41-D54 -> 6479088.4 | F55: =F41-F54 -> 5118230.6 | H55: =H41-H54 -> 17479336
A56: Compras | B56: 0 | C56: 0 | D56: 0 | E56: 0 | F56: 0 | G56: 0 | H56: 0 | I56: 0 | K56: Compras | L56: 0 | M56: 0 | N56: 0 | O56: 0 | Q56: Compras | R56: 0 | S56: 0 | T56: 0 | U56: 0 | W56: Compras | X56: 0 | Y56: 0 | Z56: 0 | AA56: 0
A57: Devoluciones | B57: 0 | C57: 0 | D57: 0 | E57: 0 | F57: 0 | G57: 0 | H57: 0 | I57: 0 | K57: Devoluciones | L57: 0 | M57: 0 | N57: 0 | O57: 0 | Q57: Devoluciones | R57: 0 | S57: 0 | T57: 0 | U57: 0 | W57: Devoluciones | X57: 0 | Y57: 0 | Z57: 0 | AA57: 0
A58: Costos Indirectos | K58: Costos Indirectos | Q58: Costos Indirectos | W58: Costos Indirectos
A59: Nomina Soporte a la Operacion | B59: 445712.72 | C59: 2.8485096 | D59: 266593.35 | E59: 1.7219358 | F59: 319531.94 | G59: 2.6615771 | H59: 1031838 | I59: 2.3921256 | K59: Nomina Soporte a la Operacion | L59: 445712.72 | M59: 2.8485096 | N59: 445712.72 | O59: 2.8485096 | Q59: Nomina Soporte a la Operacion | R59: 266593.35 | S59: 1.7219358 | T59: 712306.07 | U59: 2.288209 | W59: Nomina Soporte a la Operacion | X59: 319531.94 | Y59: 2.6615771 | Z59: 1031838 | AA59: 2.3921256
A60: Seguridad Social Soporte a la Operacion | B60: 28908 | C60: 0.18474841 | D60: 88954.66 | E60: 0.57456126 | F60: 19362.42 | G60: 0.16128145 | H60: 137225.08 | I60: 0.31813097 | K60: Seguridad Social Soporte a la Operacion | L60: 28908 | M60: 0.18474841 | N60: 28908 | O60: 0.18474841 | Q60: Seguridad Social Soporte a la Operacion | R60: 88954.66 | S60: 0.57456126 | T60: 117862.66 | U60: 0.37862151 | W60: Seguridad Social Soporte a la Operacion | X60: 19362.42 | Y60: 0.16128145 | Z60: 137225.08 | AA60: 0.31813097
A61: Gastos Indirectos de Fabricacion | B61: 920000.38 | C61: 5.879639 | D61: 1195074 | E61: 7.7190245 | F61: 1243395.3 | G61: 10.357001 | H61: 3358469.7 | I61: 7.7859909 | K61: Gastos Indirectos de Fabricacion | L61: 920000.38 | M61: 5.879639 | N61: 920000.38 | O61: 5.879639 | Q61: Gastos Indirectos de Fabricacion | R61: 1195074 | S61: 7.7190245 | T61: 2115074.4 | U61: 6.7944559 | W61: Gastos Indirectos de Fabricacion | X61: 1243395.3 | Y61: 10.357001 | Z61: 3358469.7 | AA61: 7.7859909
A62: Nomina Cadena de Suministros/Almacen | B62: 0 | C62: 0 | D62: 83797.32 | E62: 0.54124982 | F62: 144668.54 | G62: 1.2050328 | H62: 228465.86 | I62: 0.52965584 | K62: Nomina Cadena de Suministros/Almacen | L62: 0 | M62: 0 | N62: 0 | O62: 0 | Q62: Nomina Cadena de Suministros/Almacen | R62: 83797.32 | S62: 0.54124982 | T62: 83797.32 | U62: 0.26919016 | W62: Nomina Cadena de Suministros/Almacen | X62: 144668.54 | Y62: 1.2050328 | Z62: 228465.86 | AA62: 0.52965584
A63: Seguridad Social CS/Almacen | B63: 0 | C63: 0 | D63: 21318.37 | E63: 0.1376961 | F63: 10928.24 | G63: 0.091028001 | H63: 32246.61 | I63: 0.074757802 | K63: Seguridad Social CS/Almacen | L63: 0 | M63: 0 | N63: 0 | O63: 0 | Q63: Seguridad Social CS/Almacen | R63: 21318.37 | S63: 0.1376961 | T63: 21318.37 | U63: 0.068483041 | W63: Seguridad Social CS/Almacen | X63: 10928.24 | Y63: 0.091028001 | Z63: 32246.61 | AA63: 0.074757802
A64: Nomina Mantenimiento | B64: 0 | C64: 0 | D64: 32121.04 | E64: 0.20747092 | F64: 74160.63 | G64: 0.61772929 | H64: 106281.67 | I64: 0.2463944 | K64: Nomina Mantenimiento | L64: 0 | M64: 0 | N64: 0 | O64: 0 | Q64: Nomina Mantenimiento | R64: 32121.04 | S64: 0.20747092 | T64: 32121.04 | U64: 0.10318549 | W64: Nomina Mantenimiento | X64: 74160.63 | Y64: 0.61772929 | Z64: 106281.67 | AA64: 0.2463944
A65: Seguridad Social Mtto | B65: 0 | C65: 0 | D65: 7166.8 | E65: 0.046290612 | F65: 5248.73 | G65: 0.043719885 | H65: 12415.53 | I65: 0.02878311 | K65: Seguridad Social Mtto | L65: 0 | M65: 0 | N65: 0 | O65: 0 | Q65: Seguridad Social Mtto | R65: 7166.8 | S65: 0.046290612 | T65: 7166.8 | U65: 0.023022598 | W65: Seguridad Social Mtto | X65: 5248.73 | Y65: 0.043719885 | Z65: 12415.53 | AA65: 0.02878311
A67: Total Costos Indirectos | B67: 1394621.1 | C67: 8.9128969 | D67: 1695025.5 | E67: 10.948229 | F67: 1817295.8 | G67: 15.13737 | H67: 4906942.5 | I67: 11.375839 | K67: Total Costos Indirectos | L67: 1394621.1 | M67: 8.9128969 | N67: 1394621.1 | O67: 8.9128969 | Q67: Total Costos Indirectos | R67: 1695025.5 | S67: 10.948229 | T67: 3089646.6 | U67: 9.9251677 | W67: Total Costos Indirectos | X67: 1817295.8 | Y67: 15.13737 | Z67: 4906942.5 | AA67: 11.375839
B68: =B55-B67 -> 4341795.9 | D68: =D55-D67 -> 4784062.9 | F68: =F55-F67 -> 3300934.8 | H68: =H55-H67 -> 12572394
A69: Costo de activo fijo | B69: 0 | C69: 0 | D69: 0 | E69: 0 | F69: 0 | G69: 0 | H69: 0 | I69: 0 | K69: Costo de activo fijo | L69: 0 | M69: 0 | N69: 0 | O69: 0 | Q69: Costo de activo fijo | R69: 0 | S69: 0 | T69: 0 | U69: 0 | W69: Costo de activo fijo | X69: 0 | Y69: 0 | Z69: 0 | AA69: 0
A70: Gastos | K70: Gastos | Q70: Gastos | W70: Gastos
A71: Gastos generales | B71: 1038843.7 | C71: 6.639156 | D71: 1567535 | E71: 10.124763 | F71: 1453615.1 | G71: 12.10805 | H71: 4059993.8 | I71: 9.4123448 | K71: Gastos generales | L71: 1038843.7 | M71: 6.639156 | N71: 1038843.7 | O71: 6.639156 | Q71: Gastos generales | R71: 1567535 | S71: 10.124763 | T71: 2606378.7 | U71: 8.3727199 | W71: Gastos generales | X71: 1453615.1 | Y71: 12.10805 | Z71: 4059993.8 | AA71: 9.4123448
A72: Gastos de venta y marketing | B72: 1297260.9 | C72: 8.290677 | D72: 740995.56 | E72: 4.7861162 | F72: 1116550.7 | G72: 9.3004341 | H72: 3154807.2 | I72: 7.313837 | K72: Gastos de venta y marketing | L72: 1297260.9 | M72: 8.290677 | N72: 1297260.9 | O72: 8.290677 | Q72: Gastos de venta y marketing | R72: 740995.56 | S72: 4.7861162 | T72: 2038256.5 | U72: 6.5476866 | W72: Gastos de venta y marketing | X72: 1116550.7 | Y72: 9.3004341 | Z72: 3154807.2 | AA72: 7.313837
A73: Gastos de administración | B73: 566716.52 | C73: 3.6218339 | D73: 450290.05 | E73: 2.9084392 | F73: 342612.51 | G73: 2.8538293 | H73: 1359619.1 | I73: 3.1520254 | K73: Gastos de administración | L73: 566716.52 | M73: 3.6218339 | N73: 566716.52 | O73: 3.6218339 | Q73: Gastos de administración | R73: 450290.05 | S73: 2.9084392 | T73: 1017006.6 | U73: 3.2670276 | W73: Gastos de administración | X73: 342612.51 | Y73: 2.8538293 | Z73: 1359619.1 | AA73: 3.1520254
A74: Gastos de calidad | B74: 169679.14 | C74: 1.084404 | D74: 191455.83 | E74: 1.2366199 | F74: 197448.62 | G74: 1.6446704 | H74: 558583.59 | I74: 1.2949727 | K74: Gastos de calidad | L74: 169679.14 | M74: 1.084404 | N74: 169679.14 | O74: 1.084404 | Q74: Gastos de calidad | R74: 191455.83 | S74: 1.2366199 | T74: 361134.97 | U74: 1.1601084 | W74: Gastos de calidad | X74: 197448.62 | Y74: 1.6446704 | Z74: 558583.59 | AA74: 1.2949727
A75: Gastos de desarrollo | B75: 253774.22 | C75: 1.621848 | D75: 210297.05 | E75: 1.358316 | F75: 198676.11 | G75: 1.6548949 | H75: 662747.38 | I75: 1.5364572 | K75: Gastos de desarrollo | L75: 253774.22 | M75: 1.621848 | N75: 253774.22 | O75: 1.621848 | Q75: Gastos de desarrollo | R75: 210297.05 | S75: 1.358316 | T75: 464071.27 | U75: 1.4907806 | W75: Gastos de desarrollo | X75: 198676.11 | Y75: 1.6548949 | Z75: 662747.38 | AA75: 1.5364572
A76: Gastos de direccion | B76: 540732.19 | C76: 3.4557704 | D76: 382277.69 | E76: 2.469145 | F76: 372318.32 | G76: 3.1012672 | H76: 1295328.2 | I76: 3.0029789 | K76: Gastos de direccion | L76: 540732.19 | M76: 3.4557704 | N76: 540732.19 | O76: 3.4557704 | Q76: Gastos de direccion | R76: 382277.69 | S76: 2.469145 | T76: 923009.88 | U76: 2.965073 | W76: Gastos de direccion | X76: 372318.32 | Y76: 3.1012672 | Z76: 1295328.2 | AA76: 3.0029789
A77: Participación de los trabaj en las utilidades | B77: 0 | C77: 0 | D77: 0 | E77: 0 | F77: 0 | G77: 0 | H77: 0 | I77: 0 | K77: Participación de los trabaj en las utilidades | L77: 0 | M77: 0 | N77: 0 | O77: 0 | Q77: Participación de los trabaj en las utilidades | R77: 0 | S77: 0 | T77: 0 | U77: 0 | W77: Participación de los trabaj en las utilidades | X77: 0 | Y77: 0 | Z77: 0 | AA77: 0
A78: Participación en resultados de asociadas | B78: 0 | C78: 0 | D78: 0 | E78: 0 | F78: 0 | G78: 0 | H78: 0 | I78: 0 | K78: Participación en resultados de asociadas | L78: 0 | M78: 0 | N78: 0 | O78: 0 | Q78: Participación en resultados de asociadas | R78: 0 | S78: 0 | T78: 0 | U78: 0 | W78: Participación en resultados de asociadas | X78: 0 | Y78: 0 | Z78: 0 | AA78: 0
A79: Participación de los trabaj en utilidades dif | B79: 0 | C79: 0 | D79: 0 | E79: 0 | F79: 0 | G79: 0 | H79: 0 | I79: 0 | K79: Participación de los trabaj en utilidades dif | L79: 0 | M79: 0 | N79: 0 | O79: 0 | Q79: Participación de los trabaj en utilidades dif | R79: 0 | S79: 0 | T79: 0 | U79: 0 | W79: Participación de los trabaj en utilidades dif | X79: 0 | Y79: 0 | Z79: 0 | AA79: 0
A80: Impuesto Sobre la renta | B80: 0 | C80: 0 | D80: 0 | E80: 0 | F80: 0 | G80: 0 | H80: 0 | I80: 0 | K80: Impuesto Sobre la renta | L80: 0 | M80: 0 | N80: 0 | O80: 0 | Q80: Impuesto Sobre la renta | R80: 0 | S80: 0 | T80: 0 | U80: 0 | W80: Impuesto Sobre la renta | X80: 0 | Y80: 0 | Z80: 0 | AA80: 0
A81: Gastos no deducibles para CUFIN | B81: 0 | C81: 0 | D81: 0 | E81: 0 | F81: 0 | G81: 0 | H81: 0 | I81: 0 | K81: Gastos no deducibles para CUFIN | L81: 0 | M81: 0 | N81: 0 | O81: 0 | Q81: Gastos no deducibles para CUFIN | R81: 0 | S81: 0 | T81: 0 | U81: 0 | W81: Gastos no deducibles para CUFIN | X81: 0 | Y81: 0 | Z81: 0 | AA81: 0
A82: Depreciacion Contable | B82: 0 | C82: 0 | D82: 0 | E82: 0 | F82: 0 | G82: 0 | H82: 0 | I82: 0 | K82: Depreciacion Contable | L82: 0 | M82: 0 | N82: 0 | O82: 0 | Q82: Depreciacion Contable | R82: 0 | S82: 0 | T82: 0 | U82: 0 | W82: Depreciacion Contable | X82: 0 | Y82: 0 | Z82: 0 | AA82: 0
A83: Amortización contable | B83: 548247.02 | C83: 3.503797 | D83: 565406.04 | E83: 3.6519774 | F83: 533458.37 | G83: 4.4435013 | H83: 1647111.4 | I83: 3.8185232 | K83: Amortización contable | L83: 548247.02 | M83: 3.503797 | N83: 548247.02 | O83: 3.503797 | Q83: Amortización contable | R83: 565406.04 | S83: 3.6519774 | T83: 1113653.1 | U83: 3.5774944 | W83: Amortización contable | X83: 533458.37 | Y83: 4.4435013 | Z83: 1647111.4 | AA83: 3.8185232
B84: =B68-SUM(B71:B83) -> -73457.9 | D84: =D68-SUM(D71:D83) -> 675805.73 | F84: =F68-SUM(F71:F83) -> -913744.98 | H84: =H68-SUM(H71:H83) -> -165797.15
A85: Total Gastos | B85: 7372286.6 | C85: 47.115614 | D85: 6408702.3 | E85: 41.394032 | F85: 6720684.7 | G85: 55.980697 | H85: 20501674 | I85: 47.529339 | K85: Total Gastos | L85: 7372286.6 | M85: 47.115614 | N85: 7372286.6 | O85: 47.115614 | Q85: Total Gastos | R85: 6408702.3 | S85: 41.394032 | T85: 13780989 | U85: 44.26999 | W85: Total Gastos | X85: 6720684.7 | Y85: 55.980697 | Z85: 20501674 | AA85: 47.529339
A87: Resultado integral de financiamiento | K87: Resultado integral de financiamiento | Q87: Resultado integral de financiamiento | W87: Resultado integral de financiamiento
A88: Gastos financieros | B88: 1344504 | C88: 8.592603 | D88: 1290476.5 | E88: 8.3352328 | F88: 1077858 | G88: 8.9781387 | H88: 3712838.4 | I88: 8.6075293 | K88: Gastos financieros | L88: 1344504 | M88: 8.592603 | N88: 1344504 | O88: 8.592603 | Q88: Gastos financieros | R88: 1290476.5 | S88: 8.3352328 | T88: 2634980.5 | U88: 8.4646001 | W88: Gastos financieros | X88: 1077858 | Y88: 8.9781387 | Z88: 3712838.4 | AA88: 8.6075293
A89: Productos financieros | B89: -83163.19 | C89: -0.5314884 | D89: -13739.15 | E89: -0.08874165 | F89: -90942.7 | G89: -0.75751742 | H89: -187845.04 | I89: -0.43548398 | K89: Productos financieros | L89: -83163.19 | M89: -0.5314884 | N89: -83163.19 | O89: -0.5314884 | Q89: Productos financieros | R89: -13739.15 | S89: -0.08874165 | T89: -96902.34 | U89: -0.31128867 | W89: Productos financieros | X89: -90942.7 | Y89: -0.75751742 | Z89: -187845.04 | AA89: -0.43548398
A90: Otros gastos | B90: 0 | C90: 0 | D90: 0 | E90: 0 | F90: 0 | G90: 0 | H90: 0 | I90: 0 | K90: Otros gastos | L90: 0 | M90: 0 | N90: 0 | O90: 0 | Q90: Otros gastos | R90: 0 | S90: 0 | T90: 0 | U90: 0 | W90: Otros gastos | X90: 0 | Y90: 0 | Z90: 0 | AA90: 0
A91: Otros productos | B91: 0 | C91: 0 | D91: 0 | E91: 0 | F91: 0 | G91: 0 | H91: 0 | I91: 0 | K91: Otros productos | L91: 0 | M91: 0 | N91: 0 | O91: 0 | Q91: Otros productos | R91: 0 | S91: 0 | T91: 0 | U91: 0 | W91: Otros productos | X91: 0 | Y91: 0 | Z91: 0 | AA91: 0
A93: Total Resultado integral de financiamiento | B93: 1261340.8 | C93: 8.0611146 | D93: 1276737.4 | E93: 8.2464912 | F93: 986915.25 | G93: 8.2206213 | H93: 3524993.4 | I93: 8.1720453 | K93: Total Resultado integral de financiamiento | L93: 1261340.8 | M93: 8.0611146 | N93: 1261340.8 | O93: 8.0611146 | Q93: Total Resultado integral de financiamiento | R93: 1276737.4 | S93: 8.2464912 | T93: 2538078.2 | U93: 8.1533115 | W93: Total Resultado integral de financiamiento | X93: 986915.25 | Y93: 8.2206213 | Z93: 3524993.4 | AA93: 8.1720453
A96: Total Egresos | B96: 19793457 | C96: 126.49819 | D96: 18375656 | E96: 118.689 | F96: 16412026 | G96: 136.70581 | H96: 54581139 | I96: 126.53628 | K96: Total Egresos | L96: 19793457 | M96: 126.49819 | N96: 19793457 | O96: 126.49819 | Q96: Total Egresos | R96: 18375656 | S96: 118.689 | T96: 38169113 | U96: 122.6143 | W96: Total Egresos | X96: 16412026 | Y96: 136.70581 | Z96: 54581139 | AA96: 126.53628
A100: Utilidad (o Pérdida) | B100: -4146231.5 | C100: -26.498189 | D100: -2893467 | E100: -18.689004 | F100: -4406665.2 | G100: -36.705812 | H100: -11446364 | I100: -26.536277 | K100: Utilidad (o Pérdida) | L100: -4146231.5 | M100: -26.498189 | N100: 1684826.8 | O100: 10.767575 | Q100: Utilidad (o Pérdida) | R100: -2893467 | S100: -18.689004 | T100: -7039698.5 | U100: -22.614298 | W100: Utilidad (o Pérdida) | X100: -4406665.2 | Y100: -36.705812 | Z100: -11446364 | AA100: -26.536277
A103: Gastos financieros de ejercicios anteriores | B103: 2083410.8 | C103: 13.314889 | D103: 2097712.6 | E103: 13.549199 | F103: 2322379 | G103: 19.344516 | H103: 6503502.3 | I103: 15.077167 | K103: Gastos financieros de ejercicios anteriores | L103: 2083410.8 | M103: 13.314889 | N103: 2083410.8 | O103: 13.314889 | Q103: Gastos financieros de ejercicios anteriores | R103: 2097712.6 | S103: 13.549199 | T103: 4181123.3 | U103: 13.431423 | W103: Gastos financieros de ejercicios anteriores | X103: 2322379 | Y103: 19.344516 | Z103: 6503502.3 | AA103: 15.077167
A104: Gastos operativos de ejercicios anteriores | B104: 873622.03 | C104: 5.5832391 | D104: 202732.55 | E104: 1.3094566 | F104: 183625.93 | G104: 1.5295328 | H104: 1259980.5 | I104: 2.9210318 | K104: Gastos operativos de ejercicios anteriores | L104: 873622.03 | M104: 5.5832391 | N104: 873622.03 | O104: 5.5832391 | Q104: Gastos operativos de ejercicios anteriores | R104: 202732.55 | S104: 1.3094566 | T104: 1076354.6 | U104: 3.4576769 | W104: Gastos operativos de ejercicios anteriores | X104: 183625.93 | Y104: 1.5295328 | Z104: 1259980.5 | AA104: 2.9210318
B105: =SUM(B103:B104) -> 2957032.8 | D105: =SUM(D103:D104) -> 2300445.1 | F105: =SUM(F103:F104) -> 2506004.9 | H105: =SUM(H103:H104) -> 7763482.8
A107: Utilidad (o Pérdida) sin operaciones ejercicios anteriores | B107: -1189198.7 | C107: -7.600061 | D107: -593021.87 | E107: -3.830349 | F107: -1900660.2 | G107: -15.831763 | H107: -3682880.8 | I107: -8.538078 | K107: Utilidad (o Pérdida) sin operaciones ejercicios anteriores | L107: -1189198.7 | M107: -7.600061 | N107: -1189198.7 | O107: 29.665703 | Q107: Utilidad (o Pérdida) sin operaciones ejercicios anteriores | R107: -593021.87 | S107: -3.830349 | T107: -1782220.6 | U107: -5.7251978 | W107: Utilidad (o Pérdida) sin operaciones ejercicios anteriores | X107: -1900660.2 | Y107: -15.831763 | Z107: -3682880.8 | AA107: -8.538078

Sheet Linea Sesajal
C2: Monto | D2: 65000000
C3: Tasa | D3: 0.135
C4: Use of Funds
C5: WC | D5: =D2*0.3 -> 19500000
C6: Debt | D6: =D2*0.7 -> 45500000
D10: 6 | E10: 7 | F10: 8 | G10: 9 | H10: 10 | I10: 11 | J10: 12 | K10: 2025 | L10: 1 | M10: 2 | N10: 3 | O10: 4 | P10: 5 | Q10: 6 | R10: 7 | S10: 8 | T10: 9 | U10: 10 | V10: 11 | W10: 12 | X10: 2026 | Y10: 1 | Z10: 2 | AA10: 3 | AB10: 4 | AC10: 5 | AD10: 6 | AE10: 7 | AF10: 8 | AG10: 9 | AH10: 10 | AI10: 11 | AJ10: 12 | AK10: 2027
B11: Capital X | C11: Capital X BOP | D11: ='[1]Interest Ex Comp'!C6 -> 26325913
B12: Capital X | C12: Vencimientos v Capital X | D12: =3621046.2-2000000+564540.69-265771.23 -> 1919815.7 | E12: =9279261.66+2223775.68 -> 11503037 | F12: =8584220.4+2111385.96 -> 10695606 | G12: =1040155.47+832701.4 -> 1872856.9
B13: Capital X | C13: Facturación KPS | D13: =8869900-400000 -> 8469900 | E13: =10937625+3000000 -> 13937625 | F13: =7452000+3000000 -> 10452000 | G13: =5490600+3000000 -> 8490600 | H13: 3615100 | I13: 6540100 | J13: 4591100
B14: Capital X | C14: Nuevos Vencimientos KPS | G14: =(D13+E13)/2 -> 11203762 | H14: =(E13+F13)/2 -> 12194812 | I14: =(F13+G13)/2 -> 9471300 | J14: =(G13+H13)/2 -> 6052850
C16: FLUJO DE OPERACIONES
C17: Flujo Neto de Operación Modelo | D17: ='Cashflow (ROLLING) CAP'!G25 -> -1272887.1 | E17: ='Cashflow (ROLLING) CAP'!H25 -> -58721.611 | F17: ='Cashflow (ROLLING) CAP'!I25 -> 3028285.7 | G17: ='Cashflow (ROLLING) CAP'!J25 -> 1986246.5 | H17: ='Cashflow (ROLLING) CAP'!K25 -> 4019526.4 | I17: ='Cashflow (ROLLING) CAP'!L25 -> 5088108.9 | J17: ='Cashflow (ROLLING) CAP'!M25 -> 3904674.8 | K17: =SUM(D17:J17) -> 16695234 | L17: ='Cashflow (ROLLING) CAP'!O25 -> 3109617.5 | M17: ='Cashflow (ROLLING) CAP'!P25 -> 2190048.2 | N17: ='Cashflow (ROLLING) CAP'!L25 -> 5088108.9 | O17: ='Cashflow (ROLLING) CAP'!R25 -> 4468012.1 | P17: ='Cashflow (ROLLING) CAP'!S25 -> 2174583.7 | Q17: ='Cashflow (ROLLING) CAP'!T25 -> -241120.19 | R17: ='Cashflow (ROLLING) CAP'!U25 -> 3306471.5 | S17: ='Cashflow (ROLLING) CAP'!V25 -> 4979840.6 | T17: ='Cashflow (ROLLING) CAP'!W25 -> 2864018.7 | U17: ='Cashflow (ROLLING) CAP'!X25 -> 6295349.5 | V17: ='Cashflow (ROLLING) CAP'!Y25 -> 7627057.6 | W17: ='Cashflow (ROLLING) CAP'!Z25 -> 6268728.4 | X17: =SUM(L17:W17) -> 48130716 | Y17: ='Cashflow (ROLLING) CAP'!AB25 -> 5389307.7 | Z17: ='Cashflow (ROLLING) CAP'!AC25 -> 4243541 | AA17: ='Cashflow (ROLLING) CAP'!AD25 -> 6253589.1 | AB17: ='Cashflow (ROLLING) CAP'!AE25 -> 7205504.2 | AC17: ='Cashflow (ROLLING) CAP'!AF25 -> 4311318.2 | AD17: ='Cashflow (ROLLING) CAP'!AG25 -> 1247348.4 | AE17: ='Cashflow (ROLLING) CAP'!AH25 -> 5229713.4 | AF17: ='Cashflow (ROLLING) CAP'!AI25 -> 7465391.7 | ... AJ17: ='Cashflow (ROLLING) CAP'!AM25 -> 8948999.5 | AK17: =SUM(Y17:AJ17) -> 74689577
B18: WC | C18: Crecimiento v Modelo | E18: 7308875.2 | F18: 6103093 | G18: 1517615.4 | H18: 0 | I18: 0 | J18: 0
B19: WC | C19: Req Adicional Modelo WC H2 | E19: =(D18*0.4)*(100/30) -> 0 | F19: =(E18*0.4) -> 2923550.1 | G19: =(F18*0.4) -> 2441237.2 | H19: =(G18*0.4) -> 607046.16 | I19: =(H18*0.4)*(100/30) -> 0 | J19: =(J18*0.4)*(100/30) -> 0 | K19: =SUM(D19:J19) -> 5971833.4
C20: Flujo Neto de Operaciones | D20: =D17-D19 -> -1272887.1 | E20: =E17-E19 -> -58721.611 | F20: =F17-F19 -> 104735.58 | G20: =G17-G19 -> -454990.68 | H20: =H17-H19 -> 3412480.3 | I20: =I17-I19 -> 5088108.9 | J20: =J17-J19 -> 3904674.8 | K20: =SUM(D20:J20) -> 10723400 | L20: =L17-L19 -> 3109617.5 | M20: =M17-M19 -> 2190048.2 | N20: =N17-N19 -> 5088108.9 | O20: =O17-O19 -> 4468012.1 | P20: =P17-P19 -> 2174583.7 | Q20: =Q17-Q19 -> -241120.19 | R20: =R17-R19 -> 3306471.5 | S20: =S17-S19 -> 4979840.6 | ... W20: =W17-W19 -> 6268728.4 | Y20: =Y17-Y19 -> 5389307.7 | Z20: =Z17-Z19 -> 4243541 | AA20: =AA17-AA19 -> 6253589.1 | AB20: =AB17-AB19 -> 7205504.2 | AC20: =AC17-AC19 -> 4311318.2 | AD20: =AD17-AD19 -> 1247348.4 | AE20: =AE17-AE19 -> 5229713.4 | AF20: =AF17-AF19 -> 7465391.7 | ... AJ20: =AJ17-AJ19 -> 8948999.5
C22: Escenarios Intereses
C23: Reestructura Sesajal | D23: 1200000 | E23: ='Interest Expense'!R31 -> 860955.61 | F23: ='Interest Expense'!S31 -> 1267197.2 | G23: ='Interest Expense'!T31 -> 1435839.3 | H23: ='Interest Expense'!U31 -> 1503784.3 | I23: ='Interest Expense'!V31 -> 1497283.3 | J23: ='Interest Expense'!W31 -> 1490677.2 | K23: =SUM(D23:J23) -> 9255736.9 | L23: ='Interest Expense'!Y31 -> 1483963.4 | M23: ='Interest Expense'!Z31 -> 1477139.7 | N23: ='Interest Expense'!AA31 -> 1456401.4 | O23: ='Interest Expense'!AB31 -> 1430517.1 | P23: ='Interest Expense'!AC31 -> 1409802 | Q23: ='Interest Expense'!AD31 -> 1385909.2 | R23: ='Interest Expense'!AE31 -> 1365318.4 | S23: ='Interest Expense'!AF31 -> 1341888.3 | ... W23: ='Interest Expense'!AJ31 -> 1258523.4 | X23: =SUM(L23:W23) -> 16508198 | Y23: ='Interest Expense'!AL31 -> 725835.34 | Z23: ='Interest Expense'!AM31 -> 705709.12 | AA23: ='Interest Expense'!AN31 -> 685472.38 | AB23: ='Interest Expense'!AO31 -> 665122.74 | AC23: ='Interest Expense'!AP31 -> 644657.74 | AD23: ='Interest Expense'!AQ31 -> 624074.88 | AE23: ='Interest Expense'!AR31 -> 603371.62 | AF23: ='Interest Expense'!AS31 -> 582545.34 | ... AJ23: ='Interest Expense'!AW31 -> 501626.27 | AK23: =SUM(Y23:AJ23) -> 7363493.7
C24: Reestructura Nuvari | D24: ='Interest Expense'!Q43 -> 1188520.6 | E24: ='Interest Expense'!R43 -> 1712746.7 | F24: ='Interest Expense'!S43 -> 1886689.5 | G24: ='Interest Expense'!T43 -> 1964133.3 | H24: ='Interest Expense'!U43 -> 2029898.3 | I24: ='Interest Expense'!V43 -> 2004383.5 | J24: ='Interest Expense'!W43 -> 2010277.3 | K24: =SUM(D24:J24) -> 12796649 | L24: ='Interest Expense'!Y43 -> 2003563.5 | M24: ='Interest Expense'!Z43 -> 1996739.8 | N24: ='Interest Expense'!AA43 -> 1989803.6 | O24: ='Interest Expense'!AB43 -> 1977721.4 | P24: ='Interest Expense'!AC43 -> 1970808.4 | Q24: ='Interest Expense'!AD43 -> 1960717.7 | R24: ='Interest Expense'!AE43 -> 1953929 | S24: ='Interest Expense'!AF43 -> 1944300.9 | ... W24: ='Interest Expense'!AJ43 -> 1916144.4 | X24: =SUM(L24:W24) -> 23502514 | Y24: ='Interest Expense'!AL43 -> 1076611.1 | Z24: ='Interest Expense'!AM43 -> 1070287 | AA24: ='Interest Expense'!AN43 -> 1063852.3 | AB24: ='Interest Expense'!AO43 -> 1057304.8 | AC24: ='Interest Expense'!AP43 -> 1050641.9 | AD24: ='Interest Expense'!AQ43 -> 1043861.1 | AE24: ='Interest Expense'!AR43 -> 1036959.9 | AF24: ='Interest Expense'!AS43 -> 0 | ... AJ24: ='Interest Expense'!AW43 -> 0
C27: Flujo Neto con Sesajal | D27: =D20-D23 -> -2472887.1 | E27: =E20-E23 -> -919677.22 | F27: =F20-F23 -> -1162461.6 | G27: =G20-G23 -> -1890830 | H27: =H20-H23 -> 1908696 | I27: =I20-I23 -> 3590825.6 | J27: =J20-J23 -> 2413997.6 | K27: =SUM(D27:J27) -> 1467663.2 | L27: =L20-L23 -> 1625654.1 | M27: =M20-M23 -> 712908.5 | N27: =N20-N23 -> 3631707.5 | O27: =O20-O23 -> 3037495 | P27: =P20-P23 -> 764781.71 | Q27: =Q20-Q23 -> -1627029.4 | R27: =R20-R23 -> 1941153 | S27: =S20-S23 -> 3637952.3 | ... W27: =W20-W23 -> 5010205 | X27: =SUM(L27:W27) -> 31622518 | Y27: =Y20-Y23 -> 4663472.3 | Z27: =Z20-Z23 -> 3537831.9 | AA27: =AA20-AA23 -> 5568116.7 | AB27: =AB20-AB23 -> 6540381.5 | AC27: =AC20-AC23 -> 3666660.4 | AD27: =AD20-AD23 -> 623273.56 | AE27: =AE20-AE23 -> 4626341.8 | AF27: =AF20-AF23 -> 6882846.3 | ... AJ27: =AJ20-AJ23 -> 8447373.3 | AK27: =SUM(Y27:AJ27) -> 67326083
C28: Flujo Acumulado c/ Sesajal | D28: =D27 -> -2472887.1 | E28: =E27+D28 -> -3392564.3 | F28: =F27+E28 -> -4555026 | G28: =G27+F28 -> -6445855.9 | H28: =H27+G28 -> -4537160 | I28: =I27+H28 -> -946334.4 | J28: =J27+I28 -> 1467663.2 | K28: =J28 -> 1467663.2 | L28: =L27+K28 -> 3093317.3 | M28: =M27+L28 -> 3806225.8 | N28: =N27+M28 -> 7437933.3 | O28: =O27+N28 -> 10475428 | P28: =P27+O28 -> 11240210 | Q28: =Q27+P28 -> 9613180.7 | R28: =R27+Q28 -> 11554334 | S28: =S27+R28 -> 15192286 | ... W28: =W27+V28 -> 33090181 | X28: =W28 -> 33090181 | Y28: =Y27+X28 -> 37753654 | Z28: =Z27+Y28 -> 41291486 | AA28: =AA27+Z28 -> 46859602 | AB28: =AB27+AA28 -> 53399984 | AC28: =AC27+AB28 -> 57066644 | AD28: =AD27+AC28 -> 57689918 | AE28: =AE27+AD28 -> 62316260 | AF28: =AF27+AE28 -> 69199106 | ... AJ28: =AJ27+AI28 -> 1.0041626e+08 | AK28: =AJ28 -> 1.0041626e+08
C30: Flujo Neto con Nuvari | D30: =D20-D24 -> -2461407.7 | E30: =E20-E24 -> -1771468.3 | F30: =F20-F24 -> -1781953.9 | G30: =G20-G24 -> -2419124 | H30: =H20-H24 -> 1382582 | I30: =I20-I24 -> 3083725.4 | J30: =J20-J24 -> 1894397.5 | K30: =SUM(D30:J30) -> -2073249 | L30: =L20-L24 -> 1106053.9 | M30: =M20-M24 -> 193308.37 | N30: =N20-N24 -> 3098305.3 | O30: =O20-O24 -> 2490290.7 | P30: =P20-P24 -> 203775.33 | Q30: =Q20-Q24 -> -2201837.8 | R30: =R20-R24 -> 1352542.5 | S30: =S20-S24 -> 3035539.6 | ... W30: =W20-W24 -> 4352584 | X30: =SUM(L30:W30) -> 24628202 | Y30: =Y20-Y24 -> 4312696.5 | Z30: =Z20-Z24 -> 3173254 | AA30: =AA20-AA24 -> 5189736.7 | AB30: =AB20-AB24 -> 6148199.4 | AC30: =AC20-AC24 -> 3260676.3 | AD30: =AD20-AD24 -> 203487.35 | AE30: =AE20-AE24 -> 4192753.5 | AF30: =AF20-AF24 -> 7465391.7 | ... AJ30: =AJ20-AJ24 -> 8948999.5 | AK30: =SUM(Y30:AJ30) -> 67290059
C31: Flujo Acumulado c/ Nuvari | D31: =D30 -> -2461407.7 | E31: =E30+D31 -> -4232876 | F31: =F30+E31 -> -6014829.9 | G31: =G30+F31 -> -8433953.9 | H31: =H30+G31 -> -7051371.9 | I31: =I30+H31 -> -3967646.4 | J31: =J30+I31 -> -2073249 | K31: =J31 -> -2073249 | L31: =L30+K31 -> -967195.02 | M31: =M30+L31 -> -773886.65 | N31: =N30+M31 -> 2324418.7 | O31: =O30+N31 -> 4814709.4 | P31: =P30+O31 -> 5018484.7 | Q31: =Q30+P31 -> 2816646.9 | R31: =R30+Q31 -> 4169189.4 | S31: =S30+R31 -> 7204729 | ... W31: =W30+V31 -> 22554953 | X31: =W31 -> 22554953 | Y31: =Y30+X31 -> 26867650 | Z31: =Z30+Y31 -> 30040904 | AA31: =AA30+Z31 -> 35230640 | AB31: =AB30+AA31 -> 41378840 | AC31: =AC30+AB31 -> 44639516 | AD31: =AD30+AC31 -> 44843003 | AE31: =AE30+AD31 -> 49035757 | AF31: =AF30+AE31 -> 56501149 | ... AJ31: =AJ30+AI31 -> 89845012 | AK31: =AJ31 -> 89845012
C36: Use of Funds
C37: WC | D37: =IF(D27<0,-D27,0) -> 2472887.1 | E37: =IF(E27<0,-E27,0) -> 919677.22 | F37: =IF(F27<0,-F27,0) -> 1162461.6 | G37: =IF(G27<0,-G27,0) -> 1890830 | H37: =IF(H27<0,-H27,0) -> 0 | I37: =IF(I27<0,-I27,0) -> 0 | J37: =IF(J27<0,-J27,0) -> 0 | K37: =SUM(D37:J37) -> 6445855.9 | X37: =SUM(L37:W37) -> 0 | AK37: =SUM(Y37:AJ37) -> 0
C38: CAPEX | E38: 750000 | F38: 750000 | G38: 750000 | H38: 750000 | I38: 750000 | J38: 750000 | K38: =SUM(D38:J38) -> 4500000 | L38: 750000 | M38: 750000 | N38: 750000 | O38: 750000 | P38: 750000 | Q38: 750000 | R38: 750000 | S38: 750000 | T38: 750000 | U38: 750000 | V38: 750000 | W38: 750000 | X38: =SUM(L38:W38) -> 9000000 | AK38: =SUM(Y38:AJ38) -> 0
C39: Total para WC/CAPEX | D39: =SUM(D37:D38) -> 2472887.1 | E39: =SUM(E37:E38) -> 1669677.2 | F39: =SUM(F37:F38) -> 1912461.6 | G39: =SUM(G37:G38) -> 2640830 | H39: =SUM(H37:H38) -> 750000 | I39: =SUM(I37:I38) -> 750000 | J39: =SUM(J37:J38) -> 750000 | K39: =SUM(D39:J39) -> 10945856 | X39: =SUM(L39:W39) -> 0 | AK39: =SUM(Y39:AJ39) -> 0
C40: Uso para WC Acumulado | D40: =D39 -> 2472887.1 | E40: =E39+D40 -> 4142564.3 | F40: =F39+E40 -> 6055026 | G40: =G39+F40 -> 8695855.9 | H40: =H39+G40 -> 9445855.9 | I40: =I39+H40 -> 10195856 | J40: =J39+I40 -> 10945856 | K40: =J40 -> 10945856 | X40: =W40 -> 0 | AK40: =AJ40 -> 0
C41: Uso para WC (%) | D41: =D40/$D$5 -> 0.12681472 | E41: =E40/$D$5 -> 0.2124392 | F41: =F40/$D$5 -> 0.31051415 | G41: =G40/$D$5 -> 0.44594133 | H41: =H40/$D$5 -> 0.48440287 | I41: =I40/$D$5 -> 0.52286441 | J41: =J40/$D$5 -> 0.56132594 | K41: =J41 -> 0.56132594 | X41: =W41 -> 0 | AK41: =AJ41 -> 0
C43: Capital X | D43: =D12 -> 1919815.7 | E43: =E12 -> 11503037 | F43: =F12 -> 10695606 | G43: =G12 -> 1872856.9 | H43: =H12 -> 0 | I43: =I12 -> 0 | J43: =J12 -> 0 | K43: =SUM(D43:J43) -> 25991316 | L43: 100% Uso de la linea | X43: =SUM(L43:W43) -> 0 | AK43: =SUM(Y43:AJ43) -> 0
C44: Arrendamas | K44: =SUM(D44:J44) -> 0 | X44: =SUM(L44:W44) -> 0 | AK44: =SUM(Y44:AJ44) -> 0
C45: Nuvari | E45: 13500000 | K45: =SUM(D45:J45) -> 13500000 | X45: =SUM(L45:W45) -> 0 | AK45: =SUM(Y45:AJ45) -> 0
C46: Capix | E46: 0 | G46: 1000000 | H46: 1000000 | K46: =SUM(D46:J46) -> 2000000 | X46: =SUM(L46:W46) -> 0 | AK46: =SUM(Y46:AJ46) -> 0
C47: Total para Deuda | D47: =SUM(D43:D46) -> 1919815.7 | E47: =SUM(E43:E46) -> 25003037 | F47: =SUM(F43:F46) -> 10695606 | G47: =SUM(G43:G46) -> 2872856.9 | H47: =SUM(H43:H46) -> 1000000 | K47: =SUM(D47:J47) -> 41491316 | X47: =SUM(L47:W47) -> 0 | AK47: =SUM(Y47:AJ47) -> 0
C48: Uso para Deuda Acumulado | D48: =D47 -> 1919815.7 | E48: =E47+D48 -> 26922853 | F48: =F47+E48 -> 37618459 | G48: =G47+F48 -> 40491316 | H48: =H47+G48 -> 41491316 | I48: =I47+H48 -> 41491316 | J48: =J47+I48 -> 41491316 | K48: =J48 -> 41491316 | X48: =W48 -> 0 | AK48: =AJ48 -> 0
C49: Uso para Deuda (%) | D49: =D48/$D$6 -> 0.042193751 | E49: =E48/$D$6 -> 0.59171105 | F49: =F48/$D$6 -> 0.82677933 | G49: =G48/$D$6 -> 0.88991904 | H49: =H48/$D$6 -> 0.91189706 | I49: =I48/$D$6 -> 0.91189706 | J49: =J48/$D$6 -> 0.91189706 | K49: =J49 -> 0.91189706 | X49: =W49 -> 0 | AK49: =AJ49 -> 0
C51: Disposición Total por periodo | E51: 36000000 | F51: 12794983 | G51: 5000000 | H51: =H47+H39 -> 1750000 | I51: =I47+I39 -> 750000 | J51: =J47+J39 -> 750000 | K51: =SUM(D51:J51) -> 57044983 | X51: =SUM(L51:W51) -> 0 | AK51: =SUM(Y51:AJ51) -> 0
C52: Uso Total Acumulado | D52: =SUM($D51:D51) -> 0 | E52: =SUM($D51:E51) -> 36000000 | F52: =SUM($D51:F51) -> 48794983 | G52: =SUM($D51:G51) -> 53794983 | H52: =SUM($D51:H51) -> 55544983 | I52: =SUM($D51:I51) -> 56294983 | J52: =SUM($D51:J51) -> 57044983 | K52: =J52 -> 57044983 | X52: =W52 -> 0 | AK52: =AJ52 -> 0
C53: Uso Total (%) | D53: =D52/$D$2 -> 0 | E53: =E52/$D$2 -> 0.55384615 | F53: =F52/$D$2 -> 0.75069205 | G53: =G52/$D$2 -> 0.82761513 | H53: =H52/$D$2 -> 0.85453821 | I53: =I52/$D$2 -> 0.86607667 | J53: =J52/$D$2 -> 0.87761513 | K53: =J53 -> 0.87761513 | X53: =W53 -> 0 | AK53: =AJ53 -> 0
C55: Interest Expense | D55: 28732.668 | E55: 478766.84 | F55: 622710.4 | G55: 643780.04 | H55: 643780.04 | I55: 643780.04 | J55: 643780.04
C56: PAGO DE DEUDA
C57: Arrendamas | K57: =SUM(D57:J57) -> 0 | X57: =SUM(L57:W57) -> 0 | AK57: =SUM(Y57:AJ57) -> 0
C58: Nuvari | K58: =SUM(D58:J58) -> 0 | X58: =SUM(L58:W58) -> 0 | AK58: =SUM(Y58:AJ58) -> 0
C59: Capix | K59: =SUM(D59:J59) -> 0 | L59: 1000000 | M59: 1000000 | N59: 1000000 | O59: 1000000 | P59: 1000000 | Q59: 1000000 | R59: 1000000 | S59: 1000000 | T59: 1000000 | U59: 1000000 | V59: 1000000 | W59: 1000000 | X59: =SUM(L59:W59) -> 12000000 | Y59: 1000000 | Z59: 1000000 | AA59: 1000000 | AB59: 1000000 | AC59: 1000000 | AD59: 1000000 | AE59: 1000000 | AF59: 1000000 | AG59: 1000000 | AH59: 1000000 | AI59: 1000000 | AJ59: 748000 | AK59: =SUM(Y59:AJ59) -> 11748000
C60: Sesajal | K60: =SUM(D60:J60) -> 0 | L60: 1000000 | M60: 1000000 | N60: 1000000 | O60: 2000000 | P60: 2000000 | Q60: 2000000 | R60: 2000000 | S60: 2000000 | T60: 2000000 | U60: 2000000 | V60: 2000000 | W60: 2000000 | X60: =SUM(L60:W60) -> 21000000 | Y60: 2000000 | Z60: 2000000 | AA60: 2000000 | AB60: 2000000 | AC60: 2000000 | AD60: 2000000 | AE60: 2000000 | AF60: 2000000 | AG60: 2000000 | AH60: 2000000 | AI60: 2000000 | AJ60: 2000000 | AK60: =SUM(Y60:AJ60) -> 24000000
C61: FLUJO DESPUES DE PAGO DE DEUDA | D61: =D27-SUM(D57:D60) -> -2472887.1 | E61: =E27-SUM(E57:E60) -> -919677.22 | F61: =F27-SUM(F57:F60) -> -1162461.6 | G61: =G27-SUM(G57:G60) -> -1890830 | H61: =H27-SUM(H57:H60) -> 1908696 | I61: =I27-SUM(I57:I60) -> 3590825.6 | J61: =J27-SUM(J57:J60) -> 2413997.6 | K61: =SUM(D61:J61) -> 1467663.2 | L61: =L27-SUM(L57:L60) -> -374345.92 | M61: =M27-SUM(M57:M60) -> -1287091.5 | N61: =N27-SUM(N57:N60) -> 1631707.5 | O61: =O27-SUM(O57:O60) -> 37495.007 | P61: =P27-SUM(P57:P60) -> -2235218.3 | Q61: =Q27-SUM(Q57:Q60) -> -4627029.4 | R61: =R27-SUM(R57:R60) -> -1058847 | S61: =S27-SUM(S57:S60) -> 637952.28 | ... W61: =W27-SUM(W57:W60) -> 2010205 | X61: =SUM(L61:W61) -> -1377481.8 | Y61: =Y27-SUM(Y57:Y60) -> 1663472.3 | Z61: =Z27-SUM(Z57:Z60) -> 537831.87 | AA61: =AA27-SUM(AA57:AA60) -> 2568116.7 | AB61: =AB27-SUM(AB57:AB60) -> 3540381.5 | AC61: =AC27-SUM(AC57:AC60) -> 666660.42 | AD61: =AD27-SUM(AD57:AD60) -> -2376726.4 | AE61: =AE27-SUM(AE57:AE60) -> 1626341.8 | AF61: =AF27-SUM(AF57:AF60) -> 3882846.3 | ... AJ61: =AJ27-SUM(AJ57:AJ60) -> 5699373.3 | AK61: =SUM(Y61:AJ61) -> 31578083
C62: FLUJO ACUMULADO DESPUES DE PAGO DE DEUDA | D62: =D61 -> -2472887.1 | E62: =E61+D62 -> -3392564.3 | F62: =F61+E62 -> -4555026 | G62: =G61+F62 -> -6445855.9 | H62: =H61+G62 -> -4537160 | I62: =I61+H62 -> -946334.4 | J62: =J61+I62 -> 1467663.2 | K62: =J62 -> 1467663.2 | L62: =L61+J62 -> 1093317.3 | M62: =M61+L62 -> -193774.22 | N62: =N61+M62 -> 1437933.3 | O62: =O61+N62 -> 1475428.3 | P62: =P61+O62 -> -759789.96 | Q62: =Q61+P62 -> -5386819.3 | R62: =R61+Q62 -> -6445666.3 | S62: =S61+R62 -> -5807714 | T62: =T61+S62 -> -7263838.6 | ... W62: =W61+V62 -> 90181.444 | X62: =W62 -> 90181.444 | Y62: =Y61+X62 -> 1753653.8 | Z62: =Z61+Y62 -> 2291485.6 | AA62: =AA61+Z62 -> 4859602.3 | AB62: =AB61+AA62 -> 8399983.8 | AC62: =AC61+AB62 -> 9066644.2 | AD62: =AD61+AC62 -> 6689917.7 | AE62: =AE61+AD62 -> 8316259.6 | AF62: =AF61+AE62 -> 12199106 | ... AJ62: =AJ61+AI62 -> 31668265 | AK62: =AJ62 -> 31668265
C64: LINEA SESAJAL | D64: =D52-D60 -> 0 | E64: =D64+E51-E60 -> 36000000 | F64: =E64+F51-F60 -> 48794983 | G64: =F64+G51-G60 -> 53794983 | H64: =G64+H51-H60 -> 55544983 | I64: =H64+I51-I60 -> 56294983 | J64: =I64+J51-J60 -> 57044983 | K64: =J64 -> 57044983 | L64: =K64+L51-L60 -> 56044983 | M64: =L64+M51-M60 -> 55044983 | N64: =M64+N51-N60 -> 54044983 | O64: =N64+O51-O60 -> 52044983 | P64: =O64+P51-P60 -> 50044983 | Q64: =P64+Q51-Q60 -> 48044983 | R64: =Q64+R51-R60 -> 46044983 | S64: =R64+S51-S60 -> 44044983 | ... W64: =V64+W51-W60 -> 36044983 | X64: =W64 -> 36044983 | Y64: =X64+Y51-Y60 -> 34044983 | Z64: =Y64+Z51-Z60 -> 32044983 | AA64: =Z64+AA51-AA60 -> 30044983 | AB64: =AA64+AB51-AB60 -> 28044983 | AC64: =AB64+AC51-AC60 -> 26044983 | AD64: =AC64+AD51-AD60 -> 24044983 | AE64: =AD64+AE51-AE60 -> 22044983 | AF64: =AE64+AF51-AF60 -> 20044983 | ... AJ64: =AI64+AJ51-AJ60 -> 12044983 | AK64: =AJ64 -> 12044983
C65: LINEA CAPIX | D65: ='Interest Expense'!C23-D59 -> 26748000 | E65: =D65-E59 -> 26748000 | F65: =E65-F59 -> 26748000 | G65: =F65-G59 -> 26748000 | H65: =G65-H59 -> 26748000 | I65: =H65-I59 -> 26748000 | J65: =I65-J59 -> 26748000 | K65: =J65 -> 26748000 | L65: =K65-L59 -> 25748000 | M65: =L65-M59 -> 24748000 | N65: =M65-N59 -> 23748000 | O65: =N65-O59 -> 22748000 | P65: =O65-P59 -> 21748000 | Q65: =P65-Q59 -> 20748000 | R65: =Q65-R59 -> 19748000 | S65: =R65-S59 -> 18748000 | ... W65: =V65-W59 -> 14748000 | X65: =W65 -> 14748000 | Y65: =X65-Y59 -> 13748000 | Z65: =Y65-Z59 -> 12748000 | AA65: =Z65-AA59 -> 11748000 | AB65: =AA65-AB59 -> 10748000 | AC65: =AB65-AC59 -> 9748000 | AD65: =AC65-AD59 -> 8748000 | AE65: =AD65-AE59 -> 7748000 | AF65: =AE65-AF59 -> 6748000 | ... AJ65: =AI65-AJ59 -> 3000000 | AK65: =AJ65 -> 3000000
C67: EFECTO NO RESOLUCIÓN | E67: ='Interest Expense'!S43-'Linea Sesajal'!E23 -> 1025733.9 | F67: ='Interest Expense'!T43-'Linea Sesajal'!F23 -> 696936.06 | G67: ='Interest Expense'!U43-'Linea Sesajal'!G23 -> 594059 | H67: ='Interest Expense'!V43-'Linea Sesajal'!H23 -> 500599.16 | I67: ='Interest Expense'!W43-'Linea Sesajal'!I23 -> 512993.95 | J67: ='Interest Expense'!Y43-'Linea Sesajal'!J23 -> 512886.37 | K67: =SUM(D67:J67) -> 3843208.4

Sheet Cashflow (ROLLING) CAP
A1: 2025
A2: Prom | B2: ='[2]P&L CONSOLIDADO Mensual'!$C$94 -> 19.0171 | C2: ='[2]P&L CONSOLIDADO Mensual'!$F$94 -> 18.6222 | D2: ='[2]P&L CONSOLIDADO Mensual'!$I$94 -> 18.3887 | E2: ='[2]P&L CONSOLIDADO Mensual'!$L$94 -> 18.0879 | F2: ='[2]P&L CONSOLIDADO Mensual'!$O$94 -> 17.7489 | G2: ='[2]P&L CONSOLIDADO Mensual'!$R$94 -> 17.2688 | H2: ='[2]P&L CONSOLIDADO Mensual'!$U$94 -> 0 | I2: ='[2]P&L CONSOLIDADO Mensual'!$X$94 -> 0 | J2: ='[2]P&L CONSOLIDADO Mensual'!$AA$94 -> 0 | K2: ='[2]P&L CONSOLIDADO Mensual'!$AD$94 -> 0 | L2: ='[2]P&L CONSOLIDADO Mensual'!$AG$94 -> 0 | M2: ='[2]P&L CONSOLIDADO Mensual'!$AJ$94 -> 0 | N2: ='[2]P&L CONSOLIDADO Mensual'!$AN$94 -> 0 | P2: =687500 -> 687500 | Q2: 0.275 | R2: =(Q2/365)*80*S2 -> 687500 | S2: 11406250 | T2: =P2-R2 -> 0 | AA2: ='[2]P&L CONSOLIDADO Mensual'!$AN$94 -> 0 | AN2: ='[2]P&L CONSOLIDADO Mensual'!$AN$94 -> 0
A3: ='[2]P&L CONSOLIDADO Mensual'!B95 -> 19.3615 | B3: ='[2]P&L CONSOLIDADO Mensual'!$C$95 -> 18.7793 | C3: ='[2]P&L CONSOLIDADO Mensual'!$F$95 -> 18.4077 | D3: ='[2]P&L CONSOLIDADO Mensual'!$I$95 -> 18.0932 | E3: ='[2]P&L CONSOLIDADO Mensual'!$L$95 -> 18.0723 | F3: ='[2]P&L CONSOLIDADO Mensual'!$O$95 -> 17.6532 | G3: ='[2]P&L CONSOLIDADO Mensual'!$R$95 -> 17.1187 | H3: ='[2]P&L CONSOLIDADO Mensual'!$U$95 -> 17 | I3: ='[2]P&L CONSOLIDADO Mensual'!$X$95 -> 17 | J3: ='[2]P&L CONSOLIDADO Mensual'!$AA$95 -> 17 | K3: ='[2]P&L CONSOLIDADO Mensual'!$AD$95 -> 17.5 | L3: ='[2]P&L CONSOLIDADO Mensual'!$AG$95 -> 17.5 | M3: ='[2]P&L CONSOLIDADO Mensual'!$AJ$95 -> 17.5 | N3: ='[2]P&L CONSOLIDADO Mensual'!$AN$95 -> 17.635367 | AA3: ='[2]P&L CONSOLIDADO Mensual'!$AN$95 -> 17.635367 | AN3: ='[2]P&L CONSOLIDADO Mensual'!$AN$95 -> 17.635367
B4: Enero Real | C4: Febrero Real | D4: Marzo Real | E4: Abril | F4: Mayo | G4: Junio | H4: Julio | I4: Agosto | J4: Septiembre | K4: Octubre | L4: Noviembre | M4: Diciembre | N4: Total | O4: Enero | P4: Febero | Q4: Marzo | R4: Abril | S4: Mayo | T4: Junio | U4: Julio | V4: Agosto | W4: Septiembre | X4: Octubre | Y4: Noviembre | Z4: Diciembre | AA4: Total | AB4: Enero | AC4: Febero | AD4: Marzo | AE4: Abril | AF4: Mayo | AG4: Junio | AH4: Julio | AI4: Agosto | AJ4: Septiembre | AK4: Octubre | AL4: Noviembre | AM4: Diciembre | AN4: Total
A6: COBRANZA | F6: =(C158+D158)/2 -> 14260345 | G6: =(D158+E158)/2 -> 14870117 | H6: =(E158+F158)/2 -> 19009321 | I6: =(F158+G158)/2 -> 19040750 | J6: =(G158+H158)/2 -> 20273981 | K6: =(H158+I158)/2 -> 24100483 | L6: =(I158+J158)/2 -> 23696498 | M6: =(J158+K158)/2 -> 22301535 | N6: =SUM(B6,C6,D6,E6,F6,G6,H6,I6,J6,K6,L6,M6) -> 1.5755303e+08 | O6: =(K158+L158)/2 -> 21006410 | P6: =(L158+M158)/2 -> 20598558 | Q6: =(M158+O158)/2 -> 22155402 | R6: =(O158+P158)/2 -> 21548104 | S6: =(P158+Q158)/2 -> 18095932 | T6: =(Q158+R158)/2 -> 19012086 | U6: =(R158+S158)/2 -> 23924452 | V6: =(S158+T158)/2 -> 23903384 | W6: =(T158+U158)/2 -> 25450155 | X6: =(U158+V158)/2 -> 30085459 | Y6: =(V158+W158)/2 -> 29620623 | Z6: =(W158+X158)/2 -> 27876918 | AA6: =SUM(O6,P6,Q6,R6,S6,T6,U6,V6,W6,X6,Y6,Z6) -> 2.8327748e+08 | AB6: =(X158+Y158)/2 -> 26258012 | AC6: =(Y158+Z158)/2 -> 25748197 | AD6: =(Z158+AB158)/2 -> 27675386 | AE6: =(AB158+AC158)/2 -> 26915921 | AF6: =(AC158+AD158)/2 -> 22692721 | AG6: =(AD158+AE158)/2 -> 23589175 | AH6: =(AE158+AF158)/2 -> 29564240 | AI6: =(AF158+AG158)/2 -> 29777183 | AJ6: =(AG158+AH158)/2 -> 31540657 | AK6: =(AH158+AI158)/2 -> 37088171 | AL6: =(AI158+AJ158)/2 -> 36560233 | AM6: =(AJ158+AK158)/2 -> 34531059 | AN6: =SUM(AB6,AC6,AD6,AE6,AF6,AG6,AH6,AI6,AJ6,AK6,AL6,AM6) -> 3.5194096e+08
A7: Intercompañías | F7: =F6*$AQ7 -> 10970093 | G7: =G6*$AQ7 -> 11439174 | H7: =H6*$AQ7 -> 14623350 | I7: =I6*$AQ7 -> 14647528 | J7: =J6*$AQ7 -> 15596219 | K7: =K6*$AQ7 -> 18539842 | L7: =L6*$AQ7 -> 18229068 | M7: =M6*$AQ7 -> 17155960 | N7: =SUM(B7,C7,D7,E7,F7,G7,H7,I7,J7,K7,L7,M7) -> 1.2120123e+08 | AA7: =SUM(O7,P7,Q7,R7,S7,T7,U7,V7,W7,X7,Y7,Z7) -> 0 | AN7: =SUM(AB7,AC7,AD7,AE7,AF7,AG7,AH7,AI7,AJ7,AK7,AL7,AM7) -> 0 | AQ7: 0.76927264 | AR7: =N7/($N$7+$N$8) -> 0.81252764
A8: Terceros | F8: =F7*$AQ8 -> 2531100.7 | G8: =G7*$AQ8 -> 2639330.6 | H8: =H7*$AQ8 -> 3374007.1 | I8: =I7*$AQ8 -> 3379585.5 | J8: =J7*$AQ8 -> 3598474.5 | K8: =K7*$AQ8 -> 4277648.9 | L8: =L7*$AQ8 -> 4205944.8 | M8: =M7*$AQ8 -> 3958349.5 | N8: =SUM(B8,C8,D8,E8,F8,G8,H8,I8,J8,K8,L8,M8) -> 27964441 | AA8: =SUM(O8,P8,Q8,R8,S8,T8,U8,V8,W8,X8,Y8,Z8) -> 0 | AN8: =SUM(AB8,AC8,AD8,AE8,AF8,AG8,AH8,AI8,AJ8,AK8,AL8,AM8) -> 0 | AQ8: 0.23072736 | AR8: =N8/($N$7+$N$8) -> 0.18747236
A9: Otros Ingresos
A11: PAGOS | F11: =+F13+F16+F18 -> 15405064 | G11: =+G13+G16+G18 -> 16143005 | H11: =+H13+H16+H18 -> 19068042 | I11: =+I13+I16+I18 -> 16012464 | J11: =+J13+J16+J18 -> 18287735 | K11: =+K13+K16+K18 -> 20080957 | L11: =+L13+L16+L18 -> 18608389 | M11: =+M13+M16+M18 -> 18396860 | ... AN11: =+AN13+AN16+AN18 -> 2.7725138e+08
A13: Materia Prima | B13: =B14+B15 -> 7018327 | C13: =C14+C15 -> 6012174 | D13: =D14+D15 -> 4998331 | E13: =C159 -> 6015156.4 | F13: =D159 -> 5001313.3 | G13: =E159 -> 6747553.1 | H13: =F159 -> 9012876 | I13: =G159 -> 7262528.2 | J13: =H159 -> 10160675 | K13: =I159 -> 11742139 | L13: =J159 -> 10489663 | M13: =K159 -> 10119142 | N13: =SUM(B13,C13,D13,E13,F13,G13,H13,I13,J13,K13,L13,M13) -> 94579878 | O13: =L159 -> 9023722.2 | P13: =M159 -> 9812380.5 | Q13: =O159 -> 10128671 | R13: =P159 -> 8834817.6 | S13: =Q159 -> 6800166.5 | T13: =R159 -> 10450621 | U13: =S159 -> 11722360 | V13: =T159 -> 9736100.8 | W13: =U159 -> 13679304 | X13: =V159 -> 14677673 | ... Z13: =X159 -> 12648927 | AA13: =SUM(O13,P13,Q13,R13,S13,T13,U13,V13,W13,X13,Y13,Z13) -> 1.3062682e+08 | AB13: =Y159 -> 11279653 | AC13: =Z159 -> 12265476 | AD13: =AB159 -> 12550599 | AE13: =AC159 -> 10961010 | AF13: =AD159 -> 8498859.5 | AG13: =AE159 -> 12755107 | AH13: =AF159 -> 14470091 | AI13: =AG159 -> 12076273 | AJ13: =AH159 -> 16756796 | AK13: =AI159 -> 18002606 | ... AM13: =AK159 -> 15612480 | AN13: =SUM(AB13,AC13,AD13,AE13,AF13,AG13,AH13,AI13,AJ13,AK13,AL13,AM13) -> 1.6132779e+08 | AQ13: =SUM(B13,C13,D13,E13,F13:M13) -> 94579878 | AS13: "COSTO" en Flujo | AT13: COSTO en P&L
A14: MP Nacional | B14: =(B$141-B$16)*$AR14 -> 4765471.5 | C14: =(C$141-C$16)*$AR14 -> 4082289.7 | D14: =(D$141-D$16)*$AR14 -> 3393886.3 | E14: =(E$141-E$16)*$AR14 -> 4579589.9 | F14: =(F$141-F$16)*$AR14 -> 6117753 | G14: =(G$141-G$16)*$AR14 -> 4929260 | H14: =(H$141-H$16)*$AR14 -> 6897113.3 | I14: =(I$141-I$16)*$AR14 -> 7970933.1 | ... M14: =(M$141-M$16)*$AR14 -> 6660619.7 | N14: =SUM(B14,C14,D14,E14,F14,G14,H14,I14,J14,K14,L14,M14) -> 69511443 | AA14: =SUM(O14,P14,Q14,R14,S14,T14,U14,V14,W14,X14,Y14,Z14) -> 0 | AN14: =SUM(AB14,AC14,AD14,AE14,AF14,AG14,AH14,AI14,AJ14,AK14,AL14,AM14) -> 0 | AQ14: =SUM(B14,C14,D14,E14,F14:M14) -> 69511443 | AR14: 0.67900391 | AS14: =N13+N16 -> 94615667 | AT14: =N159 -> 1.0240846e+08
A15: MP Internacional | B15: =(B$141-B$16)*$AR15 -> 2252855.5 | C15: =(C$141-C$16)*$AR15 -> 1929884.3 | D15: =(D$141-D$16)*$AR15 -> 1604444.7 | E15: =(E$141-E$16)*$AR15 -> 2164980.8 | F15: =(F$141-F$16)*$AR15 -> 2892140.6 | G15: =(G$141-G$16)*$AR15 -> 2330285.8 | H15: =(H$141-H$16)*$AR15 -> 3260579.7 | I15: =(I$141-I$16)*$AR15 -> 3768223.3 | ... M15: =(M$141-M$16)*$AR15 -> 3148778.4 | N15: =SUM(B15,C15,D15,E15,F15,G15,H15,I15,J15,K15,L15,M15) -> 32861227 | AA15: =SUM(O15,P15,Q15,R15,S15,T15,U15,V15,W15,X15,Y15,Z15) -> 0 | AN15: =SUM(AB15,AC15,AD15,AE15,AF15,AG15,AH15,AI15,AJ15,AK15,AL15,AM15) -> 0 | AQ15: =SUM(B15,C15,D15,E15,F15:M15) -> 32861227 | AR15: 0.32099609
A16: Empaque | B16: 2982.3957 | C16: 2982.3957 | D16: 2982.3957 | E16: 2982.3957 | F16: 2982.3957 | G16: 2982.3957 | H16: 2982.3957 | I16: 2982.3957 | J16: 2982.3957 | K16: 2982.3957 | L16: 2982.3957 | M16: 2982.3957 | N16: =SUM(B16,C16,D16,E16,F16,G16,H16,I16,J16,K16,L16,M16) -> 35788.749 | AA16: =SUM(O16,P16,Q16,R16,S16,T16,U16,V16,W16,X16,Y16,Z16) -> 0 | AN16: =SUM(AB16,AC16,AD16,AE16,AF16,AG16,AH16,AI16,AJ16,AK16,AL16,AM16) -> 0 | AQ16: =SUM(B16,C16,D16,E16,F16:M16) -> 35788.749
A18: OBS | B18: =SUM(B19:B23) -> 12019046 | C18: =SUM(C19:C23) -> 10041523 | D18: =SUM(D19:D23) -> 10835222 | E18: =SUM(E19:E23) -> 9669395.3 | F18: =SUM(F19:F23) -> 10400768 | G18: =SUM(G19:G23) -> 9392469 | H18: =SUM(H19:H23) -> 10052184 | I18: =SUM(I19:I23) -> 8746953.6 | ... M18: =SUM(M19:M23) -> 8274735.7 | N18: =SUM(B18,C18,D18,E18,F18,G18,H18,I18,J18,K18,L18,M18) -> 1.1400795e+08 | O18: =SUM(O19:O23) -> 8873070.3 | P18: =SUM(P19:P23) -> 8596128.9 | Q18: =SUM(Q19:Q23) -> 8297611.1 | R18: =SUM(R19:R23) -> 8245274.6 | S18: =SUM(S19:S23) -> 9121181.6 | T18: =SUM(T19:T23) -> 8802585.1 | U18: =SUM(U19:U23) -> 8895621 | V18: =SUM(V19:V23) -> 9187442.8 | ... Z18: =SUM(Z19:Z23) -> 8959262.6 | AA18: =SUM(O18,P18,Q18,R18,S18,T18,U18,V18,W18,X18,Y18,Z18) -> 1.0587893e+08 | AB18: =SUM(AB19:AB23) -> 9589052 | AC18: =SUM(AC19:AC23) -> 9239180.3 | AD18: =SUM(AD19:AD23) -> 8871197.8 | AE18: =SUM(AE19:AE23) -> 8749407.4 | AF18: =SUM(AF19:AF23) -> 9882542.9 | AG18: =SUM(AG19:AG23) -> 9586720.2 | AH18: =SUM(AH19:AH23) -> 9864435.5 | AI18: =SUM(AI19:AI23) -> 10235518 | ... AM18: =SUM(AM19:AM23) -> 9969579.3 | AN18: =SUM(AB18,AC18,AD18,AE18,AF18,AG18,AH18,AI18,AJ18,AK18,AL18,AM18) -> 1.1592359e+08
A19: Fletes | B19: =B163 -> 494367.56 | C19: =C163 -> 396171.07 | D19: =D163 -> 343227.86 | E19: =E163 -> 535156.62 | F19: =F163 -> 519993.99 | G19: =G163 -> 560717.72 | H19: =H163 -> 570275.01 | I19: =I163 -> 764149.51 | ... M19: =M163 -> 653773.02 | N19: =SUM(B19,C19,D19,E19,F19,G19,H19,I19,J19,K19,L19,M19) -> 6810595.6 | O19: =O163 -> 702680.18 | P19: =P163 -> 616591.51 | Q19: =Q163 -> 491322.68 | R19: =R163 -> 672682.58 | S19: =S163 -> 792079.78 | T19: =T163 -> 671392.71 | U19: =U163 -> 886780.02 | V19: =V163 -> 955186.89 | ... Z19: =Z163 -> 817216.27 | AA19: =SUM(O19,P19,Q19,R19,S19,T19,U19,V19,W19,X19,Y19,Z19) -> 9071886.7 | AB19: =AB163 -> 877195.11 | AC19: =AC163 -> 770718.45 | AD19: =AD163 -> 618631.79 | AE19: =AE163 -> 825603.44 | AF19: =AF163 -> 984452.05 | AG19: =AG163 -> 838640.8 | AH19: =AH163 -> 1092419.8 | AI19: =AI163 -> 1178284.6 | ... AM19: =AM163 -> 1013921.6 | AN19: =SUM(AB19,AC19,AD19,AE19,AF19,AG19,AH19,AI19,AJ19,AK19,AL19,AM19) -> 11258737 | AQ19: =SUM(B19,C19,D19,E19,F19:M19) -> 6810595.6 | AR19: =N19/N$18 -> 0.059737899
A20: Directos | B20: =B160 -> 3242912.5 | C20: =C160 -> 2305460.2 | D20: =D160 -> 1787305.3 | E20: =E160 -> 2025486 | F20: =F160 -> 2081617.5 | G20: =G160 -> 2047912.4 | H20: =H160 -> 1940260.9 | I20: =I160 -> 1795060.9 | ... M20: =M160 -> 1388185.9 | N20: =SUM(B20,C20,D20,E20,F20,G20,H20,I20,J20,K20,L20,M20) -> 22778759 | O20: =O160 -> 1388185.9 | P20: =P160 -> 1388185.9 | Q20: =Q160 -> 1388185.9 | R20: =R160 -> 1388185.9 | S20: =S160 -> 1388185.9 | T20: =T160 -> 1388185.9 | U20: =U160 -> 1388185.9 | V20: =V160 -> 1388185.9 | ... Z20: =Z160 -> 1388185.9 | AA20: =SUM(O20,P20,Q20,R20,S20,T20,U20,V20,W20,X20,Y20,Z20) -> 16658230 | AB20: =AB160 -> 1388185.9 | AC20: =AC160 -> 1388185.9 | AD20: =AD160 -> 1388185.9 | AE20: =AE160 -> 1388185.9 | AF20: =AF160 -> 1388185.9 | AG20: =AG160 -> 1388185.9 | AH20: =AH160 -> 1388185.9 | AI20: =AI160 -> 1388185.9 | ... AM20: =AM160 -> 1388185.9 | AN20: =SUM(AB20,AC20,AD20,AE20,AF20,AG20,AH20,AI20,AJ20,AK20,AL20,AM20) -> 16658230 | AQ20: =SUM(B20,C20,D20,E20,F20:M20) -> 22778759 | AR20: =N20/N$18 -> 0.19979974
A21: Indirectos | B21: =B161 -> 2217469.1 | C21: =C161 -> 2265220.1 | D21: =D161 -> 2320283.3 | E21: =E161 -> 2494447.6 | F21: =F161 -> 2406419.4 | G21: =G161 -> 2922932.4 | H21: =H161 -> 2546501 | I21: =I161 -> 2776624.5 | ... M21: =M161 -> 2714790.3 | N21: =SUM(B21,C21,D21,E21,F21,G21,H21,I21,J21,K21,L21,M21) -> 30824400 | O21: =O161 -> 2911985 | P21: =P161 -> 2851722.9 | Q21: =Q161 -> 2764034.7 | R21: =R161 -> 2890986.7 | S21: =S161 -> 3006239.7 | T21: =T161 -> 2856384.1 | U21: =U161 -> 3007155.2 | V21: =V161 -> 3055040 | ... Z21: =Z161 -> 2946184.6 | AA21: =SUM(O21,P21,Q21,R21,S21,T21,U21,V21,W21,X21,Y21,Z21) -> 35138300 | AB21: =AB161 -> 3082509.7 | AC21: =AC161 -> 3007976.1 | AD21: =AD161 -> 2901515.4 | AE21: =AE161 -> 3046395.6 | AF21: =AF161 -> 3191481.8 | AG21: =AG161 -> 3102917.6 | AH21: =AH161 -> 3280562.9 | AI21: =AI161 -> 3340668.2 | ... AM21: =AM161 -> 3212110.5 | AN21: =SUM(AB21,AC21,AD21,AE21,AF21,AG21,AH21,AI21,AJ21,AK21,AL21,AM21) -> 37814442 | AQ21: =SUM(B21,C21,D21,E21,F21:M21) -> 30824400 | AR21: =N21/N$18 -> 0.27037061
A22: Ventas | B22: =B164 -> 1160984.1 | C22: =C164 -> 1314802.3 | D22: =D164 -> 1630274.2 | E22: =E164 -> 1744545.4 | F22: =F164 -> 2118876.6 | G22: =G164 -> 1773434.4 | H22: =H164 -> 2415689.7 | I22: =I164 -> 1507233.9 | ... M22: =M164 -> 1632497.8 | N22: =SUM(B22,C22,D22,E22,F22,G22,H22,I22,J22,K22,L22,M22) -> 19918588 | O22: =O164 -> 1797219 | P22: =P164 -> 1680976.5 | Q22: =Q164 -> 1616293.8 | R22: =R164 -> 1225418.9 | S22: =S164 -> 1846776.1 | T22: =T164 -> 1818836.8 | U22: =U164 -> 1669816.4 | V22: =V164 -> 1833945.3 | ... Z22: =Z164 -> 1875586.4 | AA22: =SUM(O22,P22,Q22,R22,S22,T22,U22,V22,W22,X22,Y22,Z22) -> 20987892 | AB22: =AB164 -> 2231079.7 | AC22: =AC164 -> 2079964.4 | AD22: =AD164 -> 1995876.9 | AE22: =AE164 -> 1487739.5 | AF22: =AF164 -> 2290465.3 | AG22: =AG164 -> 2253320.1 | AH22: =AH164 -> 2057314.5 | AI22: =AI164 -> 2268116.3 | ... AM22: =AM164 -> 2322492 | AN22: =SUM(AB22,AC22,AD22,AE22,AF22,AG22,AH22,AI22,AJ22,AK22,AL22,AM22) -> 25949136 | AQ22: =SUM(B22,C22,D22,E22,F22:M22) -> 19918588 | AR22: =N22/N$18 -> 0.17471227
A23: Admin | B23: =B165 -> 4903313 | C23: =C165 -> 3759869.5 | D23: =D165 -> 4754130.9 | E23: =E165 -> 2869759.6 | F23: =F165 -> 3273861.1 | G23: =G165 -> 2087472 | H23: =H165 -> 2579457.4 | I23: =I165 -> 1903884.7 | ... M23: =M165 -> 1885488.6 | N23: =SUM(B23,C23,D23,E23,F23,G23,H23,I23,J23,K23,L23,M23) -> 33675610 | O23: =O165 -> 2073000.2 | P23: =P165 -> 2058652.1 | Q23: =Q165 -> 2037774 | R23: =R165 -> 2068000.6 | S23: =S165 -> 2087900.2 | T23: =T165 -> 2067785.6 | U23: =U165 -> 1943683.5 | V23: =V165 -> 1955084.7 | ... Z23: =Z165 -> 1932089.6 | AA23: =SUM(O23,P23,Q23,R23,S23,T23,U23,V23,W23,X23,Y23,Z23) -> 24022623 | AB23: =AB165 -> 2010081.6 | AC23: =AC165 -> 1992335.5 | AD23: =AD165 -> 1966987.8 | AE23: =AE165 -> 2001483 | AF23: =AF165 -> 2027957.8 | AG23: =AG165 -> 2003655.9 | AH23: =AH165 -> 2045952.4 | AI23: =AI165 -> 2060263.2 | ... AM23: =AM165 -> 2032869.4 | AN23: =SUM(AB23,AC23,AD23,AE23,AF23,AG23,AH23,AI23,AJ23,AK23,AL23,AM23) -> 24243046 | AQ23: =SUM(B23,C23,D23,E23,F23:M23) -> 33675610 | AR23: =N23/N$18 -> 0.29537948
A25: Efectivo generado por las operaciones | B25: =+B6-B11 -> 0 | C25: =+C6-C11 -> 0 | D25: =+D6-D11 -> 0 | E25: =+E6-E11 -> 0 | F25: =+F6-F11 -> -1144719.4 | G25: =+G6-G11 -> -1272887.1 | H25: =+H6-H11 -> -58721.611 | I25: =+I6-I11 -> 3028285.7 | ... M25: =+M6-M11 -> 3904674.8 | N25: =SUM(B25,C25,D25,E25,F25,G25,H25,I25,J25,K25,L25,M25) -> 15550514 | O25: =+O6-O11 -> 3109617.5 | P25: =+P6-P11 -> 2190048.2 | Q25: =+Q6-Q11 -> 3729120.1 | R25: =+R6-R11 -> 4468012.1 | S25: =+S6-S11 -> 2174583.7 | T25: =+T6-T11 -> -241120.19 | U25: =+U6-U11 -> 3306471.5 | V25: =+V6-V11 -> 4979840.6 | ... Z25: =+Z6-Z11 -> 6268728.4 | AA25: =SUM(O25,P25,Q25,R25,S25,T25,U25,V25,W25,X25,Y25,Z25) -> 46771728 | AB25: =+AB6-AB11 -> 5389307.7 | AC25: =+AC6-AC11 -> 4243541 | AD25: =+AD6-AD11 -> 6253589.1 | AE25: =+AE6-AE11 -> 7205504.2 | AF25: =+AF6-AF11 -> 4311318.2 | AG25: =+AG6-AG11 -> 1247348.4 | AH25: =+AH6-AH11 -> 5229713.4 | AI25: =+AI6-AI11 -> 7465391.7 | ... AM25: =+AM6-AM11 -> 8948999.5 | AN25: =SUM(AB25,AC25,AD25,AE25,AF25,AG25,AH25,AI25,AJ25,AK25,AL25,AM25) -> 74689577
A26: Gastos Financieros | F26: 1645386.8 | G26: 1200000 | H26: ='Interest Expense'!R31 -> 860955.61 | I26: ='Interest Expense'!S31 -> 1267197.2 | J26: ='Interest Expense'!T31 -> 1435839.3 | K26: ='Interest Expense'!U31 -> 1503784.3 | L26: ='Interest Expense'!V31 -> 1497283.3 | M26: ='Interest Expense'!W31 -> 1490677.2 | N26: =SUM(B26,C26,D26,E26,F26,G26,H26,I26,J26,K26,L26,M26) -> 10901124 | O26: ='Interest Expense'!Y31 -> 1483963.4 | P26: ='Interest Expense'!Z31 -> 1477139.7 | Q26: ='Interest Expense'!AA31 -> 1456401.4 | R26: ='Interest Expense'!AB31 -> 1430517.1 | S26: ='Interest Expense'!AC31 -> 1409802 | T26: ='Interest Expense'!AD31 -> 1385909.2 | U26: ='Interest Expense'!AE31 -> 1365318.4 | V26: ='Interest Expense'!AF31 -> 1341888.3 | ... Z26: ='Interest Expense'!AJ31 -> 1258523.4 | AA26: =SUM(O26,P26,Q26,R26,S26,T26,U26,V26,W26,X26,Y26,Z26) -> 16508198 | AB26: ='Interest Expense'!AM31 -> 705709.12 | AC26: ='Interest Expense'!AN31 -> 685472.38 | AD26: ='Interest Expense'!AO31 -> 665122.74 | AE26: ='Interest Expense'!AP31 -> 644657.74 | AF26: ='Interest Expense'!AQ31 -> 624074.88 | AG26: ='Interest Expense'!AR31 -> 603371.62 | AH26: ='Interest Expense'!AS31 -> 582545.34 | AI26: ='Interest Expense'!AT31 -> 561593.37 | ... AL26: ='Interest Expense'!AW31 -> 501626.27 | AM26: ='Interest Expense'!AY31 -> 481367.22 | AN26: =SUM(AB26,AC26,AD26,AE26,AF26,AG26,AH26,AI26,AJ26,AK26,AL26,AM26) -> 7119025.5 | AQ26: =SUM(B26,C26,D26,E26,F26:M26) -> 10901124 | AR26: 0
A27: Impuestos | B27: =+B28-B29-B30-B31 -> 0 | C27: =+C28-C29-C30-C31 -> 0 | D27: =+D28-D29-D30-D31 -> 0 | E27: =+E28-E29-E30-E31 -> 0 | F27: =+F28-F29-F30-F31 -> 0 | G27: =+G28-G29-G30-G31 -> 0 | H27: =+H28-H29-H30-H31 -> 0 | I27: =+I28-I29-I30-I31 -> 0 | ... N27: =+N28-N29-N30-N31 -> 0 | AA27: =+AA28-AA29-AA30-AA31 -> 0 | AN27: =+AN28-AN29-AN30-AN31 -> 0
A28: IVA recuperado / Capital | N28: =SUM(B28,C28,D28,E28,F28,G28,H28,I28,J28,K28,L28,M28) -> 0 | AA28: =SUM(O28,P28,Q28,R28,S28,T28,U28,V28,W28,X28,Y28,Z28) -> 0 | AN28: =SUM(AB28,AC28,AD28,AE28,AF28,AG28,AH28,AI28,AJ28,AK28,AL28,AM28) -> 0 | AQ28: =SUM(B28,C28,D28,E28,F28:M28) -> 0
A29: Retenciones de Impuestos | N29: =SUM(B29,C29,D29,E29,F29,G29,H29,I29,J29,K29,L29,M29) -> 0 | AA29: =SUM(O29,P29,Q29,R29,S29,T29,U29,V29,W29,X29,Y29,Z29) -> 0 | AN29: =SUM(AB29,AC29,AD29,AE29,AF29,AG29,AH29,AI29,AJ29,AK29,AL29,AM29) -> 0 | AQ29: =SUM(B29,C29,D29,E29,F29:M29) -> 0
A30: ISR pago provisional | E30: ='Cashflow (ROLLING) CAP'!E172 -> 0 | F30: ='Cashflow (ROLLING) CAP'!F172 -> 0 | G30: ='Cashflow (ROLLING) CAP'!G172 -> 0 | H30: ='Cashflow (ROLLING) CAP'!H172 -> 0 | I30: ='Cashflow (ROLLING) CAP'!I172 -> 0 | J30: ='Cashflow (ROLLING) CAP'!J172 -> 0 | K30: ='Cashflow (ROLLING) CAP'!K172 -> 0 | L30: ='Cashflow (ROLLING) CAP'!L172 -> 0 | M30: ='Cashflow (ROLLING) CAP'!M172 -> 0 | N30: =SUM(B30,C30,D30,E30,F30,G30,H30,I30,J30,K30,L30,M30) -> 0 | AA30: =SUM(O30,P30,Q30,R30,S30,T30,U30,V30,W30,X30,Y30,Z30) -> 0 | AN30: =SUM(AB30,AC30,AD30,AE30,AF30,AG30,AH30,AI30,AJ30,AK30,AL30,AM30) -> 0 | AQ30: =SUM(B30,C30,D30,E30,F30:M30) -> 0
A31: Deuda IVA | B31: 0 | C31: 0 | D31: 0 | N31: =SUM(B31,C31,D31,E31,F31,G31,H31,I31,J31,K31,L31,M31) -> 0 | AA31: =SUM(O31,P31,Q31,R31,S31,T31,U31,V31,W31,X31,Y31,Z31) -> 0 | AN31: =SUM(AB31,AC31,AD31,AE31,AF31,AG31,AH31,AI31,AJ31,AK31,AL31,AM31) -> 0 | AQ31: =SUM(B31,C31,D31,E31,F31:M31) -> 0
A34: FLUJO NETO DE OPERACIÓN | B34: =+B25-B26+B27 -> 0 | C34: =+C25-C26+C27 -> 0 | D34: =+D25-D26+D27 -> 0 | E34: =+E25-E26+E27 -> 0 | F34: =+F25-F26+F27 -> -2790106.2 | G34: =+G25-G26+G27 -> -2472887.1 | H34: =+H25-H26+H27 -> -919677.22 | I34: =+I25-I26+I27 -> 1761088.5 | ... AN34: =+AN25-AN26+AN27 -> 67570552
A36: CAPEX | E36: 200000 | F36: 200000 | G36: 200000 | H36: 750000 | I36: 750000 | J36: 750000 | K36: 750000 | L36: 750000 | M36: 750000 | N36: =SUM(B36,C36,D36,E36,F36,G36,H36,I36,J36,K36,L36,M36) -> 5100000 | O36: 750000 | P36: 750000 | Q36: 750000 | R36: 750000 | S36: 750000 | T36: 750000 | U36: 750000 | V36: 750000 | W36: 750000 | X36: 750000 | Y36: 750000 | Z36: 750000 | AA36: =SUM(O36,P36,Q36,R36,S36,T36,U36,V36,W36,X36,Y36,Z36) -> 9000000 | AB36: 300000 | AC36: 300000 | AD36: 300000 | AE36: 300000 | AF36: 300000 | AG36: 300000 | AH36: 300000 | AI36: 300000 | AJ36: 300000 | AK36: 300000 | AL36: 300000 | AM36: 300000 | AN36: =SUM(AB36,AC36,AD36,AE36,AF36,AG36,AH36,AI36,AJ36,AK36,AL36,AM36) -> 3600000 | AQ36: =SUM(B36,C36,D36,E36,F36:M36) -> 5100000
A37: Otras Deudas Pre-Operación | G37: 150000 | H37: 150000 | I37: 150000 | J37: 50000 | K37: 50000 | L37: 50000 | M37: 50000 | N37: =SUM(B37,C37,D37,E37,F37,G37,H37,I37,J37,K37,L37,M37) -> 650000 | O37: 25000 | P37: 25000 | Q37: 25000 | R37: 25000 | S37: 25000 | T37: 25000 | U37: 25000 | V37: 25000 | W37: 25000 | X37: 25000 | Y37: 25000 | Z37: 25000 | AA37: =SUM(O37,P37,Q37,R37,S37,T37,U37,V37,W37,X37,Y37,Z37) -> 300000 | AN37: =SUM(AB37,AC37,AD37,AE37,AF37,AG37,AH37,AI37,AJ37,AK37,AL37,AM37) -> 0 | AQ37: =SUM(B37,C37,D37,E37,F37:M37) -> 650000
A39: FLUJO NETO DE INVERSIÓN | B39: =-B36-B37 -> 0 | C39: =-C36-C37 -> 0 | D39: =-D36-D37 -> 0 | E39: =-E36-E37 -> -200000 | F39: =-F36-F37 -> -200000 | G39: =-G36-G37 -> -350000 | H39: =-H36-H37 -> -900000 | I39: =-I36-I37 -> -900000 | ... T39: =-T36-T37 -> -775000 | AA39: =-AA36-AA37 -> -9300000 | AN39: =-AN36-AN37 -> -3600000
E41: 30000000
N44: =SUM(B44,C44,D44,E44,F44,G44,H48,I48,J48,K44,L44,M44) -> 24071501 | AA44: =SUM(O44,P44,Q44,R44,S44,T44,U48,V48,W48,X44,Y44,Z44) -> 0 | AN44: =SUM(AB44,AC44,AD44,AE44,AF44,AG44,AH48,AI48,AJ48,AK44,AL44,AM44) -> 0
A45: Disposición de Deuda | H45: 33000000 | I45: 14000000 | J45: 6000000 | N45: =SUM(B45,C45,D45,E45,F45,G45,H45,I45,J45,K45,L45,M45) -> 53000000 | AA45: =SUM(O45,P45,Q45,R45,S45,T45,U45,V45,W45,X45,Y45,Z45) -> 0 | AN45: =SUM(AB45,AC45,AD45,AE45,AF45,AG45,AH45,AI45,AJ45,AK45,AL45,AM45) -> 0
A46: Pago de Deuda
A47: IVA | I47: 1500000 | J47: 1500000 | K47: 1500000 | L47: 1500000 | M47: 1500000 | N47: =SUM(B47,C47,D47,E47,F47,G47,H47,I47,J47,K47,L47,M47) -> 7500000 | O47: 1500000 | P47: 1500000 | Q47: 1500000 | R47: 1500000 | S47: 1500000 | AA47: =SUM(O47,P47,Q47,R47,S47,T47,U47,V47,W47,X47,Y47,Z47) -> 7500000 | AN47: =SUM(AB47,AC47,AD47,AE47,AF47,AG47,AH47,AI47,AJ47,AK47,AL47,AM47) -> 0
A48: Capital X | H48: ='Linea Sesajal'!E43 -> 11503037 | I48: ='Linea Sesajal'!F43 -> 10695606 | J48: ='Linea Sesajal'!G43 -> 1872856.9 | N48: =SUM(B48,C48,D48,E48,F48,G48,H48,I48,J48,K48,L48,M48) -> 24071501 | AA48: =SUM(O48,P48,Q48,R48,S48,T48,U48,V48,W48,X48,Y48,Z48) -> 0 | AN48: =SUM(AB48,AC48,AD48,AE48,AF48,AG48,AH48,AI48,AJ48,AK48,AL48,AM48) -> 0
A49: Capix | K49: 500000 | L49: 500000 | M49: 500000 | N49: =SUM(B49,C49,D49,E49,F49,G49,H49,I49,J49,K49,L49,M49) -> 1500000 | O49: 500000 | P49: 500000 | Q49: 500000 | R49: 500000 | S49: 500000 | T49: 500000 | U49: 500000 | V49: 500000 | W49: 500000 | X49: 500000 | Y49: 500000 | Z49: 500000 | AA49: =SUM(O49,P49,Q49,R49,S49,T49,U49,V49,W49,X49,Y49,Z49) -> 6000000 | AN49: =SUM(AB49,AC49,AD49,AE49,AF49,AG49,AH49,AI49,AJ49,AK49,AL49,AM49) -> 0
A50: Nuvari | H50: 16000000 | N50: =SUM(B50,C50,D50,E50,F50,G50,H50,I50,J50,K50,L50,M50) -> 16000000 | AA50: =SUM(O50,P50,Q50,R50,S50,T50,U50,V50,W50,X50,Y50,Z50) -> 0 | AN50: =SUM(AB50,AC50,AD50,AE50,AF50,AG50,AH50,AI50,AJ50,AK50,AL50,AM50) -> 0
A51: Sesajal | N51: =SUM(B51,C51,D51,E51,F51,G51,H51,I51,J51,K51,L51,M51) -> 0 | O51: 1105000 | P51: 1105000 | Q51: 1105000 | R51: 1105000 | S51: 1105000 | T51: 1105000 | U51: 1105000 | V51: 1105000 | W51: 1105000 | X51: 1105000 | Y51: 1105000 | Z51: 1105000 | AA51: =SUM(O51,P51,Q51,R51,S51,T51,U51,V51,W51,X51,Y51,Z51) -> 13260000 | AB51: 1105000 | AC51: 1105000 | AD51: 1105000 | AE51: 1105000 | AF51: 1105000 | AG51: 1105000 | AH51: 1105000 | AI51: 1105000 | AJ51: 1105000 | AK51: 1105000 | AL51: 1105000 | AM51: 1105000 | AN51: =SUM(AB51,AC51,AD51,AE51,AF51,AG51,AH51,AI51,AJ51,AK51,AL51,AM51) -> 13260000
A52: Creditos Otros | B52: {=TRANSPOSE('CREDITOS'!CF56:CF67)} -> 709985.63 | C52: 651234.5 | D52: 651362.66 | E52: 651493.63 | F52: 165660.05 | G52: 165796.65 | H52: 152417.85 | I52: 152560.52 | J52: 152706.27 | K52: 152855.19 | L52: 153007.33 | M52: 153162.76 | N52: =SUM(B52,C52,D52,E52,F52,G52,H52,I52,J52,K52,L52,M52) -> 3912243 | O52: {=TRANSPOSE('CREDITOS'!CF68:CF79)} -> 153321.57 | P52: 153483.81 | Q52: 153649.57 | R52: 153818.92 | S52: 153991.95 | T52: 154168.72 | U52: 154349.32 | V52: 154533.83 | W52: 154722.34 | X52: 154914.93 | Y52: 155111.7 | Z52: 105312.73 | AA52: =SUM(O52,P52,Q52,R52,S52,T52,U52,V52,W52,X52,Y52,Z52) -> 1801379.4 | AB52: {=TRANSPOSE('CREDITOS'!CF80:CF91)} -> 105518.12 | AC52: 105727.96 | AD52: 105942.34 | AE52: 106161.37 | AF52: 106385.14 | AG52: 106613.77 | AH52: 106847.34 | AI52: 107085.98 | AJ52: 11496.458 | AK52: 11745.548 | AL52: 12000.034 | AM52: 12260.035 | AN52: =SUM(AB52,AC52,AD52,AE52,AF52,AG52,AH52,AI52,AJ52,AK52,AL52,AM52) -> 897784.1
A53: Arrendamas | I53: =344458.36+183627.17+207227.31 -> 735312.84 | N53: =SUM(B53,C53,D53,E53,F53,G53,H53,I53,J53,K53,L53,M53) -> 735312.84
A54: Arrendamientos | B54: {=TRANSPOSE(ARRENDAMIENTOS!KF57:KF68)} -> 237459.2 | C54: 277409.44 | D54: 418800.85 | E54: 225124.11 | F54: 229400.32 | G54: 233770.93 | H54: 271383.62 | I54: 238809.71 | J54: 243402.5 | K54: 277247.12 | L54: 249398.02 | M54: 254239.06 | N54: =SUM(B54,C54,D54,E54,F54,G54,H54,I54,J54,K54,L54,M54) -> 3156444.9 | O54: {=TRANSPOSE(ARRENDAMIENTOS!KF69:KF80)} -> 259187.68 | P54: 264246.29 | Q54: 269417.36 | R54: 449311.08 | S54: 270498.93 | T54: 392739.31 | U54: 265542.85 | V54: 372847.98 | W54: 377681.75 | X54: 259686.72 | Y54: 254034.9 | Z54: 258921.52 | AA54: =SUM(O54,P54,Q54,R54,S54,T54,U54,V54,W54,X54,Y54,Z54) -> 3694116.4 | AB54: {=TRANSPOSE(ARRENDAMIENTOS!KF81:KF92)} -> 263914.02 | AC54: 269014.69 | AD54: 274225.87 | AE54: 279549.96 | AF54: 284989.4 | AG54: 290546.7 | AH54: 296224.41 | AI54: 302025.14 | AJ54: 307951.55 | AK54: 314006.36 | AL54: 320192.36 | AM54: 326512.39 | AN54: =SUM(AB54,AC54,AD54,AE54,AF54,AG54,AH54,AI54,AJ54,AK54,AL54,AM54) -> 3529152.9
A55: Total Pago de Deuda | B55: =SUM(B47:B52) -> 709985.63 | C55: =SUM(C47:C52) -> 651234.5 | D55: =SUM(D47:D54) -> 1070163.5 | E55: =SUM(E47:E54) -> 876617.74 | F55: =SUM(F47:F54) -> 395060.37 | G55: =SUM(G47:G54) -> 399567.58 | H55: =SUM(H47:H54) -> 27926839 | I55: =SUM(I47:I54) -> 13322289 | J55: =SUM(J47:J54) -> 3768965.6 | K55: =SUM(K47:K54) -> 2430102.3 | ... M55: =SUM(M47:M54) -> 2407401.8 | N55: =SUM(B55,C55,D55,E55,F55,G55,H55,I55,J55,K55,L55,M55) -> 56360633 | AA55: =SUM(O55,P55,Q55,R55,S55,T55,U55,V55,W55,X55,Y55,Z55) -> 0 | AN55: =SUM(AB55,AC55,AD55,AE55,AF55,AG55,AH55,AI55,AJ55,AK55,AL55,AM55) -> 0
A57: FLUJO NETO DE FINANCIACIÓN | H57: =H45-H55 -> 5073161.2 | I57: =I45-I55 -> 677710.57 | J57: =J45-J55 -> 2231034.4 | K57: =K45-K55 -> -2430102.3 | L57: =L45-L55 -> -2402405.3 | M57: =M45-M55 -> -2407401.8 | N57: =SUM(B57,C57,D57,E57,F57,G57,H57,I57,J57,K57,L57,M57) -> 741996.65 | O57: =O45-O55 -> 0 | P57: =P45-P55 -> 0 | Q57: =Q45-Q55 -> 0 | R57: =R45-R55 -> 0 | S57: =S45-S55 -> 0 | T57: =T45-T55 -> 0 | U57: =U45-U55 -> 0 | V57: =V45-V55 -> 0 | ... Z57: =Z45-Z55 -> 0 | AA57: =SUM(O57,P57,Q57,R57,S57,T57,U57,V57,W57,X57,Y57,Z57) -> 0 | AN57: =SUM(AB57,AC57,AD57,AE57,AF57,AG57,AH57,AI57,AJ57,AK57,AL57,AM57) -> 0
A59: FLUJO NETO | D59: 0 | H59: =+H34+H39+H57 -> 3253484 | I59: =+I34+I39+I57 -> 1538799 | J59: =+J34+J39+J57 -> 1981441.6 | K59: =+K34+K39+K57 -> -714360.19 | L59: =+L34+L39+L57 -> 388420.22 | M59: =+M34+M39+M57 -> -793404.22 | N59: =SUM(B59,C59,D59,E59,F59,G59,H59,I59,J59,K59,L59,M59) -> 5654380.4 | O59: =+O34+O39+O57 -> 850654.08 | P59: =+P34+P39+P57 -> -62091.499 | Q59: =+Q34+Q39+Q57 -> 1497718.8 | R59: =+R34+R39+R57 -> 2262495 | S59: =+S34+S39+S57 -> -10218.286 | T59: =+T34+T39+T57 -> -2402029.4 | U59: =+U34+U39+U57 -> 1941153 | V59: =+V34+V39+V57 -> 3637952.3 | ... Z59: =+Z34+Z39+Z57 -> 5010205
A61: EFECTIVO INICIAL | D61: =C63 -> 0 | F61: =E63 -> 0 | G61: =F63 -> 0 | H61: =G63 -> 0 | I61: =H63 -> 3253484 | J61: =I63 -> 4792283 | K61: =J63 -> 6773724.6 | L61: =K63 -> 6059364.4 | M61: =L63 -> 6447784.6 | O61: =M63 -> 5654380.4 | P61: =O63 -> 6505034.5 | Q61: =P63 -> 6442943 | R61: =Q63 -> 7940661.8 | S61: =R63 -> 10203157 | T61: =S63 -> 10192938 | U61: =T63 -> 7790909.1 | V61: =U63 -> 9732062.1 | W61: =V63 -> 13370014 | ... Z61: =Y63 -> 26257705
A63: EFECTIVO FINAL | D63: =+D59+D61 -> 0 | F63: =+F59+F61 -> 0 | G63: =+G59+G61 -> 0 | H63: =+H59+H61 -> 3253484 | I63: =+I59+I61 -> 4792283 | J63: =+J59+J61 -> 6773724.6 | K63: =+K59+K61 -> 6059364.4 | L63: =+L59+L61 -> 6447784.6 | M63: =+M59+M61 -> 5654380.4 | O63: =+O59+O61 -> 6505034.5 | P63: =+P59+P61 -> 6442943 | Q63: =+Q59+Q61 -> 7940661.8 | R63: =+R59+R61 -> 10203157 | S63: =+S59+S61 -> 10192938 | T63: =+T59+T61 -> 7790909.1 | U63: =+U59+U61 -> 9732062.1 | V63: =+V59+V61 -> 13370014 | ... Z63: =+Z59+Z61 -> 31267910
F64: Remedir el modelo, el efectivo final en todos los meses es negativo
A65: Trailing 12M Revenue | B65: 221000000
A66: Trailing 12M Costs | B66: 94000000
F67: =(F68/$B$65)*365 -> 61.108597 | G67: 65 | H67: 70 | I67: 75 | J67: 75 | K67: 75 | L67: 75 | M67: 75 | O67: 75 | P67: 75 | Q67: 75 | R67: 75 | S67: 75 | T67: 75
A68: CxC BOP | F68: 37000000 | G68: =(G67/365)*($B$65-($B$65/12)+F158) -> 39775658 | H68: =(H67/365)*($B$65-($B$65/12)+G158) -> 42171174 | I68: =(I67/365)*($B$65-($B$65/12)+H158) -> 46401798 | J68: =(J67/365)*($B$65-($B$65/12)+I158) -> 46755935 | K68: =(K67/365)*($B$65-($B$65/12)+J158) -> 46235777 | L68: =(L67/365)*($B$65-($B$65/12)+K158) -> 46182662 | M68: =(M67/365)*($B$65-($B$65/12)+L158) -> 45703534 | O68: =(O67/365)*($B$65-($B$65/12)+O158) -> 46343333 | P68: =(P67/365)*($B$65-($B$65/12)+P158) -> 45765477 | Q68: =(Q67/365)*($B$65-($B$65/12)+Q158) -> 44924632 | R68: =(R67/365)*($B$65-($B$65/12)+R158) -> 46141979 | S68: =(S67/365)*($B$65-($B$65/12)+S158) -> 46943412 | T68: =(T67/365)*($B$65-($B$65/12)+T158) -> 46133321
A69: Changes CxC | F69: =F70-F68 -> 2775658.1 | G69: =G70-G68 -> 2395515.4 | H69: =H70-H68 -> 4230624.1 | I69: =I70-I68 -> 354137.45 | J69: =J70-J68 -> -520158.52 | K69: =K70-K68 -> -53114.214 | L69: =L70-L68 -> -479128.85 | M69: =M70-M68 -> 639799.21 | O69: =O70-O68 -> -577855.47 | P69: =P70-P68 -> -840845.54 | Q69: =Q70-Q68 -> 1217347.3 | R69: =R70-R68 -> 801433.26 | S69: =S70-S68 -> -810091.27 | T69: =T70-T68 -> 507192.92
A70: CxC EOP | F70: =G68 -> 39775658 | G70: =H68 -> 42171174 | H70: =I68 -> 46401798 | I70: =J68 -> 46755935 | J70: =K68 -> 46235777 | K70: =L68 -> 46182662 | L70: =M68 -> 45703534 | M70: =O68 -> 46343333 | O70: =P68 -> 45765477 | P70: =Q68 -> 44924632 | Q70: =R68 -> 46141979 | R70: =S68 -> 46943412 | S70: =T68 -> 46133321 | T70: 46640514
F71: =(F72/$B$66)*365 -> 104.06383 | G71: 100 | H71: 100 | I71: 100 | J71: 100 | K71: 100 | L71: 100 | M71: 100 | O71: 100 | P71: 100 | Q71: 100 | R71: 100 | S71: 100 | T71: 100
A72: Inventory BOP | F72: 26800000 | G72: =(G71/365)*($B$66-($B$66/12)+G$159) -> 25597040 | H72: =(H71/365)*($B$66-($B$66/12)+H$159) -> 26391053 | I72: =(I71/365)*($B$66-($B$66/12)+I$159) -> 26824330 | J72: =(J71/365)*($B$66-($B$66/12)+J$159) -> 26481186 | K72: =(K71/365)*($B$66-($B$66/12)+K$159) -> 26379674 | L72: =(L71/365)*($B$66-($B$66/12)+L$159) -> 26079559 | M72: =(M71/365)*($B$66-($B$66/12)+M$159) -> 26295629 | O72: =(O71/365)*($B$66-($B$66/12)+O$159) -> 26382284 | P72: =(P71/365)*($B$66-($B$66/12)+P$159) -> 26027804 | Q72: =(Q71/365)*($B$66-($B$66/12)+Q$159) -> 25470365 | R72: =(R71/365)*($B$66-($B$66/12)+R$159) -> 26470490 | S72: =(S71/365)*($B$66-($B$66/12)+S$159) -> 26818911 | T72: =(T71/365)*($B$66-($B$66/12)+T$159) -> 26274731
A73: Changes Inventory | F73: =F74-F72 -> -1202960.3 | G73: =G74-G72 -> 794012.95 | H73: =H74-H72 -> 433277.61 | I73: =I74-I72 -> -343144 | J73: =J74-J72 -> -101512.67 | K73: =K74-K72 -> -300114.99 | L73: =L74-L72 -> 216070.77 | M73: =M74-M72 -> 86654.945 | O73: =O74-O72 -> -354480.4 | P73: =P74-P72 -> -557438.64 | Q73: =Q74-Q72 -> 1000124.5 | R73: =R74-R72 -> 348421.49 | S73: =S74-S72 -> -544180.48 | T73: =T74-T72 -> 2269250.7
A74: Inventory EOP | F74: =G72 -> 25597040 | G74: =H72 -> 26391053 | H74: =I72 -> 26824330 | I74: =J72 -> 26481186 | J74: =K72 -> 26379674 | K74: =L72 -> 26079559 | L74: =M72 -> 26295629 | M74: =O72 -> 26382284 | O74: =P72 -> 26027804 | P74: =Q72 -> 25470365 | Q74: =R72 -> 26470490 | R74: =S72 -> 26818911 | S74: =T72 -> 26274731 | T74: 28543982
F75: =(F76/$B$66)*365 -> 80.183511 | G75: 80.183511 | H75: 80.183511 | I75: 80.183511 | J75: 80.183511 | K75: 80.183511 | L75: 80.183511 | M75: 80.183511 | O75: 80.183511 | P75: 80.183511 | Q75: 80.183511 | R75: 80.183511 | S75: 80.183511 | T75: 80.183511
A76: CxP BOP | F76: 20650000 | G76: =(G75/365)*($B$66-($B$66/12)+G$159) -> 20524605 | H76: =(H75/365)*($B$66-($B$66/12)+H$159) -> 21161272 | I76: =(I75/365)*($B$66-($B$66/12)+I$159) -> 21508690 | J76: =(J75/365)*($B$66-($B$66/12)+J$159) -> 21233545 | K76: =(K75/365)*($B$66-($B$66/12)+K$159) -> 21152148 | L76: =(L75/365)*($B$66-($B$66/12)+L$159) -> 20911506 | M76: =(M75/365)*($B$66-($B$66/12)+M$159) -> 21084759 | O76: =(O75/365)*($B$66-($B$66/12)+O$159) -> 21154242 | P76: =(P75/365)*($B$66-($B$66/12)+P$159) -> 20870007 | Q76: =(Q75/365)*($B$66-($B$66/12)+Q$159) -> 20423033 | R76: =(R75/365)*($B$66-($B$66/12)+R$159) -> 21224968 | S76: =(S75/365)*($B$66-($B$66/12)+S$159) -> 21504345 | T76: =(T75/365)*($B$66-($B$66/12)+T$159) -> 21068002
A77: Changes CxP | F77: =F78-F76 -> -125394.96 | G77: =G78-G76 -> 636667.46 | H77: =H78-H76 -> 347417.2 | I77: =I78-I76 -> -275144.9 | J77: =J78-J76 -> -81396.426 | K77: =K78-K76 -> -240642.74 | L77: =L78-L76 -> 173253.13 | M77: =M78-M76 -> 69482.977 | O77: =O78-O76 -> -284234.83 | P77: =P78-P76 -> -446973.87 | Q77: =Q78-Q76 -> 801934.97 | R77: =R78-R76 -> 279376.58 | S77: =S78-S76 -> -436343.01 | T77: =T78-T76 -> 1819564.9
A78: CxP EOP | F78: =G76 -> 20524605 | G78: =H76 -> 21161272 | H78: =I76 -> 21508690 | I78: =J76 -> 21233545 | J78: =K76 -> 21152148 | K78: =L76 -> 20911506 | L78: =M76 -> 21084759 | M78: =O76 -> 21154242 | O78: =P76 -> 20870007 | P78: =Q76 -> 20423033 | Q78: =R76 -> 21224968 | R78: =S76 -> 21504345 | S78: =T76 -> 21068002 | T78: 22887566
A80: Change in WC | F80: =F69+F73-F77 -> 1698092.8 | G80: =G69+G73-G77 -> 2552860.9 | H80: =H69+H73-H77 -> 4316484.5 | I80: =I69+I73-I77 -> 286138.35 | J80: =J69+J73-J77 -> -540274.77 | K80: =K69+K73-K77 -> -112586.47 | L80: =L69+L73-L77 -> -436311.21 | M80: =M69+M73-M77 -> 656971.18 | O80: =O69+O73-O77 -> -648101.04 | P80: =P69+P73-P77 -> -951310.31 | Q80: =Q69+Q73-Q77 -> 1415536.8 | R80: =R69+R73-R77 -> 870478.17 | S80: =S69+S73-S77 -> -917928.74 | T80: =T69+T73-T77 -> 956878.74
A82: OPERATING CASHFLOW | F82: =F166-F80 -> -339451.93 | G82: =G166-G80 -> -1898643.8 | H82: =H166-H80 -> -1290595.4 | I82: =I166-I80 -> 4186986.7 | J82: =J166-J80 -> 4357313.9 | K82: =K166-K80 -> 3829899.3 | L82: =L166-L80 -> 3137374.8 | M82: =M166-M80 -> 2612498 | O82: =O166-O80 -> 4600579 | P82: =P166-P80 -> 3662353.1 | Q82: =Q166-Q80 -> -463440.13 | R82: =R166-R80 -> 2407923.8 | S82: =S166-S80 -> 5948993.9 | T82: =T166-T80 -> 2436597.4 | AO82: =AO166-AO80 -> 0
A84: INVESTING CASHFLOW
A87: DEUDA
A89: Saldo Inicial | B89: 75534.165 | C89: =B94 -> 76337.787 | D89: =C94 -> 77100.295 | E89: =D94 -> 77767.652 | F89: =E94 -> 77814.326 | G89: =F94 -> 78688.65 | H89: =G94 -> 79935.72 | I89: =H94 -> 99000 | J89: =I94 -> 3403393.6 | ... M89: =L94 -> 7530536.8 | N89: =B89 -> 75534.165 | AA89: =O89 -> 0 | AN89: =AB89 -> 0
A90: Disposición | B90: =+B45 -> 0 | C90: =+C45 -> 0 | D90: =+D45 -> 0 | E90: =+E45 -> 0 | F90: =+F45 -> 0 | G90: =+G45 -> 0 | H90: =+H45 -> 33000000 | I90: =+I45 -> 14000000 | ... M90: =+M45 -> 0 | N90: =SUM(B90,C90,D90,E90,F90,G90,H90,I90,J90,K90,L90,M90) -> 53000000 | AA90: =SUM(O90,P90,Q90,R90,S90,T90,U90,V90,W90,X90,Y90,Z90) -> 0 | AN90: =SUM(AB90,AC90,AD90,AE90,AF90,AG90,AH90,AI90,AJ90,AK90,AL90,AM90) -> 0
A91: Pago | B91: =+B44 -> 0 | C91: =+C44 -> 0 | D91: =+D44 -> 0 | E91: =+E44 -> 0 | F91: =+F44 -> 0 | G91: =+G44 -> 0 | H91: =+H48 -> 11503037 | I91: =+I48 -> 10695606 | J91: =+J48 -> 1872856.9 | K91: =+K44 -> 0 | L91: =+L44 -> 0 | M91: =+M44 -> 0 | N91: =SUM(B91,C91,D91,E91,F91,G91,H91,I91,J91,K91,L91,M91) -> 24071501 | AA91: =SUM(O91,P91,Q91,R91,S91,T91,U91,V91,W91,X91,Y91,Z91) -> 0 | AN91: =SUM(AB91,AC91,AD91,AE91,AF91,AG91,AH91,AI91,AJ91,AK91,AL91,AM91) -> 0
A92: Efecto por conversión deuda MXN a USD | B92: -803.62265 | C92: -762.50734 | D92: -667.35695 | E92: -46.67435 | F92: =-915456.469696268/1000--41.1326282055088 -> -874.32384 | G92: =-1247069.91141318/1000 -> -1247.0699 | N92: =SUM(B92,C92,D92,E92,F92,G92,H92,I92,J92,K92,L92,M92) -> -4401.555 | AA92: =SUM(O92,P92,Q92,R92,S92,T92,U92,V92,W92,X92,Y92,Z92) -> 0 | AN92: =SUM(AB92,AC92,AD92,AE92,AF92,AG92,AH92,AI92,AJ92,AK92,AL92,AM92) -> 0
A94: Saldo Final Sesajal | B94: =+B89+B90-B91-B92 -> 76337.787 | C94: =+C89+C90-C91-C92 -> 77100.295 | D94: =+D89+D90-D91-D92 -> 77767.652 | E94: =+E89+E90-E91-E92 -> 77814.326 | F94: =+F89+F90-F91-F92 -> 78688.65 | G94: =+G89+G90-G91-G92 -> 79935.72 | H94: 99000 | I94: =+I89+I90-I91-I92 -> 3403393.6 | J94: =+J89+J90-J91-J92 -> 7530536.8 | K94: =+K89+K90-K91-K92 -> 7530536.8 | L94: =+L89+L90-L91-L92 -> 7530536.8 | M94: =+M89+M90-M91-M92 -> 7530536.8 | N94: =+N89+N90-N91-N92 -> 29008435 | AA94: =+AA89+AA90-AA91-AA92 -> 0 | AN94: =+AN89+AN90-AN91-AN92 -> 0
M95: =G94-M94 -> -7450601.1
A96: Arrendamientos | B96: 3733 | C96: 3733 | D96: 3900 | E96: 3733 | F96: 3733 | G96: =2050+2071 -> 4121 | H96: =G96 -> 4121 | I96: =H96 -> 4121 | J96: =I96 -> 4121 | K96: =J96 -> 4121 | L96: =K96 -> 4121 | M96: =L96 -> 4121 | N96: =M96 -> 4121 | AA96: =Z96 -> 0 | AN96: =AM96 -> 0
A97: Villa Avocado | B97: 10000 | C97: 10000 | D97: 12500 | E97: =D97 -> 12500 | F97: =E97 -> 12500 | G97: =10818333.37/1000 -> 10818.333 | H97: =G97 -> 10818.333 | I97: =H97 -> 10818.333 | J97: =I97 -> 10818.333 | K97: =J97 -> 10818.333 | L97: =K97 -> 10818.333 | M97: =L97 -> 10818.333 | N97: =M97 -> 10818.333 | AA97: =Z97 -> 0 | AN97: =AM97 -> 0
A98: Total Deuda | B98: =+B94+B96+B97 -> 90070.787 | C98: =+C94+C96+C97 -> 90833.295 | D98: =+D94+D96+D97 -> 94167.652 | E98: =+E94+E96+E97 -> 94047.326 | F98: =+F94+F96+F97 -> 94921.65 | G98: =+G94+G96+G97 -> 94875.053 | H98: =+H94+H96+H97 -> 113939.33 | I98: =+I94+I96+I97 -> 3418333 | ... N98: =+N94+N96+N97 -> 29023374 | AA98: =+AA94+AA96+AA97 -> 0 | AN98: =+AN94+AN96+AN97 -> 0
D99: =D100*D113 -> 90198.835 | G99: =G100*G113 -> 133250 | J99: =J100*J113 -> 122686.99 | M99: =M100*M113 -> 136357.18
A100: EBITDA Consolidado TTM 2023 | D100: =+D102+D101+D103+($M$106-D106)+($M$108-D108)+($M$107-D107) -> 18039.767 | G100: =+G102+G101+G103+($M$106-G106)+($M$108-G108)+($M$107-G107) -> 26650.001 | H100: =G98/G113 -> 18975.011 | I100: =+G98/21000 -> 4.5178597 | J100: =+J102+J101+J103+($M$106-J106)+($M$108-J108)+($M$107-J107) -> 30671.748 | K100: =+J98/J113 -> 1886369 | M100: =+M102+M101+M103+($M$106-M106)+($M$108-M108)+($M$107-M107) -> 35883.467 | N100: =+M98/M113 -> 1985651.6 | AA100: =+Z98/Z113 -> #DIV/0! | AN100: =+AM98/AM113 -> #DIV/0!
A101: EBITDA C.Humano 2023 | D101: 400 | G101: 7237 | H101: =+G101-D101 -> 6837 | J101: =(83000/J3)+G101 -> 12119.353 | K101: =J101-G101 -> 4882.3529 | M101: =(83000/M3)+J101 -> 16862.21 | N101: =M101-J101 -> 4742.8571 | AA101: =Z101-W101 -> 0 | AN101: =AM101-AJ101 -> 0
A102: EBITDA Villa Avocado 2023 | D102: 4000 | G102: =8242856.92430608/1000 -> 8242.8569 | H102: =G102-D102 -> 4242.8569 | J102: =0+G102 -> 8242.8569 | K102: =J102-G102 -> 0 | M102: =2827+J102 -> 11069.857 | N102: =M102-J102 -> 2827 | AA102: =Z102-W102 -> 0 | AN102: =AM102-AJ102 -> 0
A103: EBITDA C.Animal 2023 | D103: 1911 | G103: 3840.4003 | H103: =+G103-D103 -> 1929.4003 | J103: =1592+G103 -> 5432.4003 | K103: =+J103-G103 -> 1592 | M103: =2519+J103 -> 7951.4003 | N103: =+M103-J103 -> 2519 | AA103: =+Z103-W103 -> 0 | AN103: =+AM103-AJ103 -> 0
A106: EBITDA C.Humano 2022 | D106: =5512-7381-1890+2267+250-D107 -> -1971 | G106: =17552-13768-4562+2680+510-G107 -> 1461 | H106: =+G106-D106 -> 3432 | J106: =24518-21335-5381+5455+766-J107 -> 4292 | K106: =+J106-G106 -> 2831 | M106: =35723-28351-6696+8332+1029-M107-2106 -> 2645 | N106: =+M106-J106 -> -1647 | AA106: =+Z106-W106 -> 0 | AN106: =+AM106-AJ106 -> 0 | AQ106: =M106+M107 -> 7931
A107: EBITDA Villa Avocado 2022 | D107: =1114-650+265 -> 729 | G107: =1320-934+565 -> 951 | H107: =+G107-D107 -> 222 | J107: =134-1245+842 -> -269 | K107: =+J107-G107 -> -1220 | M107: =5363-1602+1525 -> 5286 | N107: =+M107-J107 -> 5555 | AA107: =+Z107-W107 -> 0 | AN107: =+AM107-AJ107 -> 0
A108: EBITDA C.Animal 2022 | D108: =(29787-18865-2545+5295)/20.5127 -> 666.51392 | G108: =(62333-36318-7674+10283)/20.2786 -> 1411.5373 | H108: =+G108-D108 -> 745.02337 | J108: =(93338-52553-13186+18065)/20.2668 -> 2253.1431 | K108: =+J108-G108 -> 841.60579 | M108: 3222.2809 | N108: =+M108-J108 -> 969.13788 | AA108: =+Z108-W108 -> 0 | AN108: =+AM108-AJ108 -> 0
A110: Debt/EBITDA | D110: =D98/D100 -> 5.2200037 | G110: =G98/G100 -> 3.5600394 | J110: =J98/J100 -> 246.00737 | M110: =M98/M100 -> 210.27723
A112: COVENANT EBITDA Consolidado TTM | D112: =D98/D113 -> 18833.53 | G112: =G98/G113 -> 18975.011 | I112: =29*3.5 -> 101.5 | J112: =J98/J113 -> 1886369 | M112: =M98/M113 -> 1985651.6
A113: COVENANT Debt/EBITDA <= | D113: 5 | G113: 5 | J113: 4 | M113: 3.8
A115: Índice de Cobertura de Deuda
A117: Porción circulante del LP | D117: =400+12769.6194212088 -> 13169.619 | G117: =400+12100.9944512088 -> 12500.994 | J117: =400+11869.8694812088 -> 12269.869 | M117: =400+13915.530231685 -> 14315.53
A118: Interés consolidado TTM | D118: =+D119+D120+$M$121-D121 -> 8694.2217 | G118: =+G119+G120+$M$121-G121 -> 9255.7217 | J118: =+J119+J120+$M$121-J121 -> 8634.6784 | M118: =+M119+M120+$M$121-M121 -> 8097.9896
A119: Interés Villa Avocado 2023 | D119: =10000*6.9%*90/360 -> 172.5 | G119: =10000*6.9%*180/360 -> 345 | J119: =10000*6.9%*270/360 -> 517.5 | M119: =10000*6.9%*360/360 -> 690
A120: Interés Sesajal 2023 | D120: 2198 | G120: 4252 | J120: 5828.4568 | M120: 7407.9896
A121: Interés Consolidado 2022 | D121: 1348 | G121: 3013 | J121: 5383 | M121: =7052+((75000+12800)*8.47%*30/360) -> 7671.7217
A122: EBITDA/(Porción c. LP+Gasto intereses TTM) | D122: =D100/(D117+D118) -> 0.82509596 | G122: =G100/(G117+G118) -> 1.2249092 | J122: =J100/(J117+J118) -> 1.4672285 | M122: =M100/(M117+M118) -> 1.6009742
A123: COVENANT EBITDA/(Porción c. LP+Gasto intereses TTM) >= | D123: 1 | G123: 1.25 | J123: 1.25 | M123: 1.25
A124: CAPITAL DE TRABAJO
A126: INVENTARIOS
A127: Saldo Inicial | B127: 24000000 | C127: 24000000 | D127: 24000000 | E127: 24000000 | F127: 24000000 | G127: 24000000 | H127: 24000000 | I127: 24000000 | J127: 24000000 | K127: 24000000 | L127: 24000000 | M127: 24000000 | N127: 24000000 | AA127: 24000000 | AN127: 24000000 | AQ127: =B127 -> 24000000
A128: Compras | B128: =+B130-B127+B129 -> 7021309.4 | C128: =+C130-C127+C129 -> 6015156.4 | D128: =+D130-D127+D129 -> 5001313.3 | E128: =+E130-E127+E129 -> 6747553.1 | F128: =+F130-F127+F129 -> 9012876 | G128: =+G130-G127+G129 -> 7262528.2 | H128: =+H130-H127+H129 -> 10160675 | I128: =+I130-I127+I129 -> 11742139 | ... N128: =+N130-N127+N129 -> 1.0240846e+08 | AA128: =+AA130-AA127+AA129 -> 1.3533585e+08 | AN128: =+AN130-AN127+AN129 -> 1.6685e+08 | AQ128: =SUM(B128,C128,D128,E128,F128,G128,H128,I128,J128,K128,L128,M128) -> 1.0240846e+08
A129: Costo de MP + M + Em | B129: =+B159 -> 7021309.4 | C129: =+C159 -> 6015156.4 | D129: =+D159 -> 5001313.3 | E129: =+E159 -> 6747553.1 | F129: =+F159 -> 9012876 | G129: =+G159 -> 7262528.2 | H129: =+H159 -> 10160675 | I129: =+I159 -> 11742139 | ... N129: =+N159 -> 1.0240846e+08 | AA129: =+AA159 -> 1.3533585e+08 | AN129: =+AN159 -> 1.6685e+08 | AQ129: =SUM(B129,C129,D129,E129,F129,G129,H129,I129,J129,K129,L129,M129) -> 1.0240846e+08
A130: Inventario Final | B130: 24000000 | C130: 24000000 | D130: 24000000 | E130: 24000000 | F130: 24000000 | G130: 24000000 | H130: 24000000 | I130: 24000000 | J130: 24000000 | K130: 24000000 | L130: 24000000 | M130: 24000000 | N130: 24000000 | AA130: 24000000 | AN130: 24000000 | AQ130: =M130 -> 24000000 | AR130: =AQ130-AQ127 -> 0
...

Sheet IS (ROLLING)
BK7: 14603982 | BL7: 8000000 | BM7: 8000000 | BN7: 8000000 | BO7: 8000000 | BP7: 8000000 | BQ7: 8000000 | BR7: 8000000 | BS7: 8000000 | BT7: 8000000 | BU7: 23085702 | BV7: 8000000 | BW7: 8000000 | BX7: 8000000 | BY7: 8000000 | BZ7: 8000000 | CA7: 8000000 | CB7: 8000000 | CC7: 8000000 | CD7: 8000000 | CE7: 19370357 | CF7: 8000000 | CG7: 8000000 | CH7: 8000000 | CI7: 8000000 | CJ7: 8000000 | CK7: 8000000 | CL7: 8000000 | CM7: 8000000 | CN7: 8000000 | CO7: 23764811 | CP7: 8000000 | CQ7: 8000000 | CR7: 8000000 | CS7: 8000000 | CT7: 8000000 | CU7: 8000000 | CV7: 8000000 | CW7: 8000000 | CX7: 8000000 | CY7: 22053812
B9: INCOME STATEMENT (ROLLING FCST) | AP9: =(AP18/AB18)-100% -> 0.25 | BD9: =(BD18/AP18)-100% -> 0.24105793
B10: PERIODO | BD10: =(BD18/AB18)-100% -> 0.55132241
B11: MES | C11: 1 | D11: 2 | E11: 3 | F11: 4 | G11: 5 | H11: 6 | I11: 7 | J11: 8 | K11: 9 | L11: 10 | M11: 11 | N11: 12 | P11: 1 | Q11: 2 | R11: 3 | S11: 4 | T11: 5 | U11: 6 | V11: 7 | W11: 8 | X11: 9 | Y11: 10 | Z11: 11 | AA11: 12 | AB11: 2025 | AD11: 1 | AE11: 2 | AF11: 3 | AG11: 4 | AH11: 5 | AI11: 6 | AJ11: 7 | AK11: 8 | AL11: 9 | AM11: 10 | AN11: 11 | AO11: 12 | AP11: 2026 | AR11: 1 | AS11: 2 | AT11: 3 | AU11: 4 | AV11: 5 | AW11: 6 | AX11: 7 | AY11: 8 | AZ11: 9 | BA11: 10 | BB11: 11 | BC11: 12 | BD11: 2027 | BE11: 2028 | BF11: 2028 | BG11: Comentarios
B12: QTR | C12: 1 | D12: 1 | E12: 1 | F12: 2 | G12: 2 | H12: 2 | I12: 3 | J12: 3 | K12: 3 | L12: 4 | M12: 4 | N12: 4 | P12: 1 | Q12: 1 | R12: 1 | S12: 2 | T12: 2 | U12: 2 | V12: 3 | W12: 3 | X12: 3 | Y12: 4 | Z12: 4 | AA12: 4 | AD12: 1 | AE12: 1 | AF12: 1 | AG12: 2 | AH12: 2 | AI12: 2 | AJ12: 3 | AK12: 3 | AL12: 3 | AM12: 4 | AN12: 4 | AO12: 4 | AR12: 1 | AS12: 1 | AT12: 1 | AU12: 2 | AV12: 2 | AW12: 2 | AX12: 3 | AY12: 3 | AZ12: 3 | BA12: 4 | BB12: 4 | BC12: 4
B13: YEAR | C13: 2024 | D13: 2024 | E13: 2024 | F13: 2024 | G13: 2024 | H13: 2024 | I13: 2024 | J13: 2024 | K13: 2024 | L13: 2024 | M13: 2024 | N13: 2024 | P13: 2025 | Q13: 2025 | R13: 2025 | S13: 2025 | T13: 2025 | U13: 2025 | V13: 2025 | W13: 2025 | X13: 2025 | Y13: 2025 | Z13: 2025 | AA13: 2025 | AD13: 2026 | AE13: 2026 | AF13: 2026 | AG13: 2026 | AH13: 2026 | AI13: 2026 | AJ13: 2026 | AK13: 2026 | AL13: 2026 | AM13: 2026 | AN13: 2026 | AO13: 2026 | AR13: 2027 | AS13: 2027 | AT13: 2027 | AU13: 2027 | AV13: 2027 | AW13: 2027 | AX13: 2027 | AY13: 2027 | AZ13: 2027 | BA13: 2027 | BB13: 2027 | BC13: 2027
B15: Maquila | P15: 9677100.6 | Q15: 8226802.9 | R15: 5356720.1 | S15: 13035711 | T15: 11700675 | U15: 8685547.9 | V15: 15512994 | W15: 16143512 | X15: 14196904 | Y15: 12303555 | Z15: 10392541 | AA15: 12161452 | AB15: =SUM(P15:AA15) -> 1.3739352e+08 | AD15: =P15*1.25 -> 12096376 | AE15: =Q15*1.25 -> 10283504 | AF15: =R15*1.25 -> 6695900.2 | AG15: =S15*1.25 -> 16294639 | AH15: =T15*1.25 -> 14625844 | AI15: =U15*1.25 -> 10856935 | AJ15: =V15*1.25 -> 19391243 | AK15: =W15*1.25 -> 20179390 | ... AO15: =AA15*1.25 -> 15201815 | AP15: =SUM(AD15:AO15) -> 1.7174189e+08 | AR15: =AD15*1.2 -> 14515651 | AS15: =AE15*1.2 -> 12340204 | AT15: =AF15*1.2 -> 8035080.2 | AU15: =AG15*1.2 -> 19553566 | AV15: =AH15*1.2 -> 17551013 | AW15: =AI15*1.2 -> 13028322 | AX15: =AJ15*1.2 -> 23269491 | AY15: =AK15*1.2 -> 24215269 | ... BC15: =AO15*1.2 -> 18242178 | BD15: =SUM(AR15:BC15) -> 2.0609027e+08 | BE15: =BD15*1.1 -> 2.266993e+08 | BF15: =BE15*1.1 -> 2.4936923e+08 | BG15: La proyección de ingresos por maquila contempla ingresos con Grisi, KPS y Laboratorios Best. Ver detalle de CXC y principales clientes contemplados en esta proyección.
B16: Private Label | T16: 732871.29 | U16: 852760.66 | V16: 1184249.6 | W16: 1557459 | X16: 1323398 | Y16: 1477644 | Z16: 1744133 | AA16: 1522217 | AB16: =SUM(P16:AA16) -> 10394733 | AD16: =P16*1.25 -> 0 | AE16: =Q16*1.25 -> 0 | AF16: =R16*1.25 -> 0 | AG16: =S16*1.25 -> 0 | AH16: =T16*1.25 -> 916089.11 | AI16: =U16*1.25 -> 1065950.8 | AJ16: =V16*1.25 -> 1480312 | AK16: =W16*1.25 -> 1946823.8 | ... AO16: =AA16*1.25 -> 1902771.2 | AP16: =SUM(AD16:AO16) -> 12993416 | AR16: =AD16*1.25 -> 0 | AS16: =AE16*1.25 -> 0 | AT16: =AF16*1.25 -> 0 | AU16: =AG16*1.25 -> 0 | AV16: =AH16*1.25 -> 1145111.4 | AW16: =AI16*1.25 -> 1332438.5 | AX16: =AJ16*1.25 -> 1850390.1 | AY16: =AK16*1.25 -> 2433529.7 | ... BC16: =AO16*1.25 -> 2378464.1 | BD16: =SUM(AR16:BC16) -> 16241770 | BE16: =BD16*1.2 -> 19490124 | BF16: =BE16*1.2 -> 23388148
B17: Biomiral | P17: 9061037.6 | Q17: 8215637.3 | R17: 7745218.1 | S17: 4902491.2 | T17: 8688581.2 | U17: 8365497.1 | V17: 6950223.2 | W17: =OFFSET(INDEX(BIOMIRAL_PVT_LBL[], MATCH("TOTAL INC NUEVOS CANALES", BIOMIRAL_PVT_LBL[Column3], 0), MATCH("BIOMIRAL-ENE", 'BIOMIRAL PVT LBL'!2:2, 0)),0,V11)+OFFSET(INDEX(BIOMIRAL_PVT_LBL[], MATCH("TOTAL INC NUEVOS CANALES", BIOMIRAL_PVT_LBL[Column3], 0), MATCH("INNOV-ENE", 'BIOMIRAL PVT LBL'!2:2, 0)),0,V11) -> 7770679 | X17: =OFFSET(INDEX(BIOMIRAL_PVT_LBL[], MATCH("TOTAL INC NUEVOS CANALES", BIOMIRAL_PVT_LBL[Column3], 0), MATCH("BIOMIRAL-ENE", 'BIOMIRAL PVT LBL'!2:2, 0)),0,W11)+OFFSET(INDEX(BIOMIRAL_PVT_LBL[], MATCH("TOTAL INC NUEVOS CANALES", BIOMIRAL_PVT_LBL[Column3], 0), MATCH("INNOV-ENE", 'BIOMIRAL PVT LBL'!2:2, 0)),0,W11) -> 7368248.7 | Y17: =OFFSET(INDEX(BIOMIRAL_PVT_LBL[], MATCH("TOTAL INC NUEVOS CANALES", BIOMIRAL_PVT_LBL[Column3], 0), MATCH("BIOMIRAL-ENE", 'BIOMIRAL PVT LBL'!2:2, 0)),0,X11)+OFFSET(INDEX(BIOMIRAL_PVT_LBL[], MATCH("TOTAL INC NUEVOS CANALES", BIOMIRAL_PVT_LBL[Column3], 0), MATCH("INNOV-ENE", 'BIOMIRAL PVT LBL'!2:2, 0)),0,X11) -> 8843587 | Z17: =OFFSET(INDEX(BIOMIRAL_PVT_LBL[], MATCH("TOTAL INC NUEVOS CANALES", BIOMIRAL_PVT_LBL[Column3], 0), MATCH("BIOMIRAL-ENE", 'BIOMIRAL PVT LBL'!2:2, 0)),0,Y11)+OFFSET(INDEX(BIOMIRAL_PVT_LBL[], MATCH("TOTAL INC NUEVOS CANALES", BIOMIRAL_PVT_LBL[Column3], 0), MATCH("INNOV-ENE", 'BIOMIRAL PVT LBL'!2:2, 0)),0,Y11) -> 8108764.8 | AA17: 8108764.8 | AB17: =SUM(P17:AA17) -> 94128730 | AD17: =P17*1.25 -> 11326297 | AE17: =Q17*1.25 -> 10269547 | AF17: =R17*1.25 -> 9681522.6 | AG17: =S17*1.25 -> 6128114 | AH17: =T17*1.25 -> 10860727 | AI17: =U17*1.25 -> 10456871 | AJ17: =V17*1.25 -> 8687779 | AK17: =W17*1.25 -> 9713348.8 | ... AO17: =AA17*1.25 -> 10135956 | AP17: =SUM(AD17:AO17) -> 1.1766091e+08 | AR17: =AD17*1.3 -> 14724186 | AS17: =AE17*1.3 -> 13350411 | AT17: =AF17*1.3 -> 12585979 | AU17: =AG17*1.3 -> 7966548.2 | AV17: =AH17*1.3 -> 14118944 | AW17: =AI17*1.3 -> 13593933 | AX17: =AJ17*1.3 -> 11294113 | AY17: =AK17*1.3 -> 12627353 | ... BC17: =AO17*1.3 -> 13176743 | BD17: =SUM(AR17:BC17) -> 1.5295919e+08 | BE17: =BD17*1.25 -> 1.9119898e+08 | BF17: =BE17*1.25 -> 2.3899873e+08 | BG17: La proyección de Biomiral contempla las ventas realizadas a traves de la marca comercial "Biomiral".
B18: GROSS REVENUE | P18: =SUM(P15:P17) -> 18738138 | Q18: =SUM(Q15:Q17) -> 16442440 | R18: =SUM(R15:R17) -> 13101938 | S18: =SUM(S15:S17) -> 17938202 | T18: =SUM(T15:T17) -> 21122128 | U18: =SUM(U15:U17) -> 17903806 | V18: =SUM(V15:V17) -> 23647467 | W18: =SUM(W15:W17) -> 25471650 | ... AA18: =SUM(AA15:AA17) -> 21792434 | AB18: =SUM(P18:AA18) -> 2.4191698e+08 | AD18: =SUM(AD15:AD17) -> 23422673 | AE18: =SUM(AE15:AE17) -> 20553050 | AF18: =SUM(AF15:AF17) -> 16377423 | AG18: =SUM(AG15:AG17) -> 22422753 | AH18: =SUM(AH15:AH17) -> 26402659 | AI18: =SUM(AI15:AI17) -> 22379757 | AJ18: =SUM(AJ15:AJ17) -> 29559334 | AK18: =SUM(AK15:AK17) -> 31839563 | ... AO18: =SUM(AO15:AO17) -> 27240542 | AP18: =SUM(AD18:AO18) -> 3.0239622e+08 | AR18: =SUM(AR15:AR17) -> 29239837 | AS18: =SUM(AS15:AS17) -> 25690615 | AT18: =SUM(AT15:AT17) -> 20621060 | AU18: =SUM(AU15:AU17) -> 27520115 | AV18: =SUM(AV15:AV17) -> 32815068 | AW18: =SUM(AW15:AW17) -> 27954693 | AX18: =SUM(AX15:AX17) -> 36413994 | AY18: =SUM(AY15:AY17) -> 39276152 | ... BC18: =SUM(BC15:BC17) -> 33797385 | BD18: =SUM(AR18:BC18) -> 3.7529123e+08 | BE18: =SUM(BE15:BE17) -> 4.3738841e+08 | BF18: =SUM(BF15:BF17) -> 5.1175611e+08
B19: GROSS REVENUE | P19: =P18/P22 -> 1.0644269 | Q19: =Q18/Q22 -> 1.0259334 | R19: =R18/R22 -> 1.0486686 | S19: =S18/S22 -> 1.0251073 | T19: =T18/T22 -> 1.0168418 | U19: =U18/U22 -> 1.0343512 | V19: =V18/V22 -> 1.0175878 | W19: =W18/W22 -> 1.0204082 | ... AA19: =AA18/AA22 -> 1.0204082 | AB19: =AB18/AB$22 -> 1.0263498 | AD19: =AD18/AD$22 -> 1.0204082 | AE19: =AE18/AE$22 -> 1.0204082 | AF19: =AF18/AF$22 -> 1.0204082 | AG19: =AG18/AG$22 -> 1.0204082 | AH19: =AH18/AH$22 -> 1.0204082 | AI19: =AI18/AI$22 -> 1.0204082 | AJ19: =AJ18/AJ$22 -> 1.0204082 | AK19: =AK18/AK$22 -> 1.0204082 | ... AP19: =AP18/AP$22 -> 1.0204082 | BD19: =BD18/BD$22 -> 1.0204082 | BE19: =BE18/BE$22 -> 1.025641 | BF19: =BF18/BF$22 -> 1.025641
B20: Descuentos | S20: =S$18*ASSUMPTIONS!$C12 -> 0 | T20: =T$18*ASSUMPTIONS!$C12 -> 0 | U20: =U$18*ASSUMPTIONS!$C12 -> 0 | V20: =V$18*ASSUMPTIONS!$C12 -> 0 | W20: =W$18*ASSUMPTIONS!$C12 -> 0 | X20: =X$18*ASSUMPTIONS!$C12 -> 0 | Y20: =Y$18*ASSUMPTIONS!$C12 -> 0 | Z20: =Z$18*ASSUMPTIONS!$C12 -> 0 | AA20: =AA$18*ASSUMPTIONS!$C12 -> 0 | AB20: =SUM(P20:AA20) -> 0 | AP20: =SUM(AD20:AO20) -> 0 | BD20: =SUM(AR20:BC20) -> 0 | BE20: =SUM(AS20:BD20) -> 0 | BF20: =SUM(AT20:BE20) -> 0
B21: Devoluciones | P21: 1134168.4 | Q21: 415629.29 | R21: 608059.55 | S21: 439349.09 | T21: 349842.16 | U21: 594591.44 | V21: 408718.56 | W21: =W$18*ASSUMPTIONS!$C13 -> 509433.01 | X21: =X$18*ASSUMPTIONS!$C13 -> 457771.01 | Y21: =Y$18*ASSUMPTIONS!$C13 -> 452495.72 | Z21: =Z$18*ASSUMPTIONS!$C13 -> 404908.77 | AA21: =AA$18*ASSUMPTIONS!$C13 -> 435848.68 | AB21: =SUM(P21:AA21) -> 6210815.6 | AD21: =AD$18*ASSUMPTIONS!$C13 -> 468453.45 | AE21: =AE$18*ASSUMPTIONS!$C13 -> 411061.01 | AF21: =AF$18*ASSUMPTIONS!$C13 -> 327548.46 | AG21: =AG$18*ASSUMPTIONS!$C13 -> 448455.05 | AH21: =AH$18*ASSUMPTIONS!$C13 -> 528053.19 | AI21: =AI$18*ASSUMPTIONS!$C13 -> 447595.14 | AJ21: =AJ$18*ASSUMPTIONS!$C13 -> 591186.68 | AK21: =AK$18*ASSUMPTIONS!$C13 -> 636791.26 | ... AO21: =AO$18*ASSUMPTIONS!$C13 -> 544810.85 | AP21: =SUM(AD21:AO21) -> 6047924.5 | AR21: =AR$18*ASSUMPTIONS!$C13 -> 584796.74 | AS21: =AS$18*ASSUMPTIONS!$C13 -> 513812.3 | AT21: =AT$18*ASSUMPTIONS!$C13 -> 412421.19 | AU21: =AU$18*ASSUMPTIONS!$C13 -> 550402.29 | AV21: =AV$18*ASSUMPTIONS!$C13 -> 656301.37 | AW21: =AW$18*ASSUMPTIONS!$C13 -> 559093.87 | AX21: =AX$18*ASSUMPTIONS!$C13 -> 728279.88 | AY21: =AY$18*ASSUMPTIONS!$C13 -> 785523.03 | ... BC21: =BC$18*ASSUMPTIONS!$C13 -> 675947.7 | BD21: =SUM(AR21:BC21) -> 7505824.6 | BE21: =BE18*0.025 -> 10934710 | BF21: =BF18*0.025 -> 12793903
B22: NET REVENUE | P22: =P18-P20-P21 -> 17603970 | Q22: =Q18-Q20-Q21 -> 16026811 | R22: =R18-R20-R21 -> 12493879 | S22: =S18-S20-S21 -> 17498853 | T22: =T18-T20-T21 -> 20772285 | U22: =U18-U20-U21 -> 17309214 | V22: =V18-V20-V21 -> 23238749 | W22: =W18-W20-W21 -> 24962217 | ... AA22: =AA18-AA20-AA21 -> 21356585 | AB22: =SUM(P22:AA22) -> 2.3570616e+08 | AD22: =AD18-AD20-AD21 -> 22954219 | AE22: =AE18-AE20-AE21 -> 20141989 | AF22: =AF18-AF20-AF21 -> 16049874 | AG22: =AG18-AG20-AG21 -> 21974298 | AH22: =AH18-AH20-AH21 -> 25874606 | AI22: =AI18-AI20-AI21 -> 21932162 | AJ22: =AJ18-AJ20-AJ21 -> 28968147 | AK22: =AK18-AK20-AK21 -> 31202772 | ... AO22: =AO18-AO20-AO21 -> 26695732 | AP22: =SUM(AD22:AO22) -> 2.963483e+08 | AR22: =AR18-AR20-AR21 -> 28655040 | AS22: =AS18-AS20-AS21 -> 25176803 | AT22: =AT18-AT20-AT21 -> 20208638 | AU22: =AU18-AU20-AU21 -> 26969712 | AV22: =AV18-AV20-AV21 -> 32158767 | AW22: =AW18-AW20-AW21 -> 27395599 | AX22: =AX18-AX20-AX21 -> 35685714 | AY22: =AY18-AY20-AY21 -> 38490629 | ... BC22: =BC18-BC20-BC21 -> 33121437 | BD22: =SUM(AR22:BC22) -> 3.677854e+08 | BE22: =BE18-BE21 -> 4.264537e+08 | BF22: =BF18-BF21 -> 4.989622e+08
B23: NET REVENUE | P23: =P22/P$22 -> 1 | Q23: =Q22/Q$22 -> 1 | R23: =R22/R$22 -> 1 | S23: =S22/S$22 -> 1 | T23: =T22/T$22 -> 1 | U23: =U22/U$22 -> 1 | V23: =V22/V$22 -> 1 | W23: =W22/W$22 -> 1 | ... AB23: =AB22/AB$22 -> 1 | AP23: =AP22/AP$22 -> 1 | BD23: =BD22/BD$22 -> 1 | BE23: =BE22/BE$22 -> 1 | BF23: =BF22/BF$22 -> 1
B24: MP/ME | P24: 6973324.6 | Q24: 5955783.1 | R24: 4892619.5 | S24: 6630608.8 | T24: 8870567.4 | U24: 7136545.2 | V24: 9963239.7 | W24: =SUM(W14:W16)*0.5+W17*0.34 -> 11492517 | X24: =SUM(X14:X16)*0.5+X17*0.34 -> 10265355 | Y24: =SUM(Y14:Y16)*0.5+Y17*0.34 -> 9897419 | Z24: =SUM(Z14:Z16)*0.5+Z17*0.34 -> 8825316.9 | AA24: =SUM(AA14:AA16)*0.5+AA17*0.34 -> 9598814.6 | AB24: =SUM(P24:AA24) -> 1.0050211e+08 | AD24: =SUM(AD14:AD16)*0.5+AD17*0.34 -> 9899128.8 | AE24: =SUM(AE14:AE16)*0.5+AE17*0.34 -> 8633397.7 | AF24: =SUM(AF14:AF16)*0.5+AF17*0.34 -> 6639667.8 | AG24: =SUM(AG14:AG16)*0.5+AG17*0.34 -> 10230878 | AH24: =SUM(AH14:AH16)*0.5+AH17*0.34 -> 11463613 | AI24: =SUM(AI14:AI16)*0.5+AI17*0.34 -> 9516779.2 | AJ24: =SUM(AJ14:AJ16)*0.5+AJ17*0.34 -> 13389622 | AK24: =SUM(AK14:AK16)*0.5+AK17*0.34 -> 14365646 | ... AO24: =SUM(AO14:AO16)*0.5+AO17*0.34 -> 11998518 | AP24: =SUM(AD24:AO24) -> 1.3237237e+08 | AR24: =SUM(AR14:AR16)*0.5+AR17*0.34 -> 12264049 | AS24: =SUM(AS14:AS16)*0.5+AS17*0.34 -> 10709242 | AT24: =SUM(AT14:AT16)*0.5+AT17*0.34 -> 8296773.1 | AU24: =SUM(AU14:AU16)*0.5+AU17*0.34 -> 12485410 | AV24: =SUM(AV14:AV16)*0.5+AV17*0.34 -> 14148503 | AW24: =SUM(AW14:AW16)*0.5+AW17*0.34 -> 11802317 | AX24: =SUM(AX14:AX16)*0.5+AX17*0.34 -> 16399939 | AY24: =SUM(AY14:AY16)*0.5+AY17*0.34 -> 17617699 | ... BC24: =SUM(BC14:BC16)*0.5+BC17*0.34 -> 14790414 | BD24: =SUM(AR24:BC24) -> 1.6317214e+08 | BE24: =SUM(BE14:BE16)*0.5+BE17*0.34 -> 1.8810237e+08 | BF24: =SUM(BF14:BF16)*0.5+BF17*0.34 -> 2.1763826e+08
B25: MARGEN MATERIAL DIRECTO | P25: =P22-P24 -> 10630645 | Q25: =Q22-Q24 -> 10071028 | R25: =R22-R24 -> 7601259.1 | S25: =S22-S24 -> 10868244 | T25: =T22-T24 -> 11901718 | U25: =U22-U24 -> 10172669 | V25: =V22-V24 -> 13275509 | W25: =W22-W24 -> 13469701 | ... AA25: =AA22-AA24 -> 11757771 | AB25: =1-AB24/AB$22 -> 0.57361271 | AD25: =AD22-AD24 -> 13055090 | AE25: =AE22-AE24 -> 11508592 | AF25: =AF22-AF24 -> 9410206.5 | AG25: =AG22-AG24 -> 11743420 | AH25: =AH22-AH24 -> 14410993 | AI25: =AI22-AI24 -> 12415383 | AJ25: =AJ22-AJ24 -> 15578525 | AK25: =AK22-AK24 -> 16837126 | ... AO25: =AO22-AO24 -> 14697213 | AP25: =1-AP24/AP$22 -> 0.55332166 | AR25: =AR22-AR24 -> 16390991 | AS25: =AS22-AS24 -> 14467561 | AT25: =AT22-AT24 -> 11911865 | AU25: =AU22-AU24 -> 14484303 | AV25: =AV22-AV24 -> 18010264 | AW25: =AW22-AW24 -> 15593282 | AX25: =AX22-AX24 -> 19285775 | AY25: =AY22-AY24 -> 20872929 | ... BC25: =BC22-BC24 -> 18331024 | BD25: =BD18-BD24 -> 2.1211908e+08 | BE25: =BE18-BE24 -> 2.4928604e+08 | BF25: =BF18-BF24 -> 2.9411785e+08
B26: MARGEN MATERIAL DIRECTO | P26: =P25/P$22 -> 0.60387772 | Q26: =Q25/Q$22 -> 0.62838626 | R26: =R25/R$22 -> 0.60839867 | S26: =S25/S$22 -> 0.62108323 | T26: =T25/T$22 -> 0.57296141 | U26: =U25/U$22 -> 0.58770253 | V26: =V25/V$22 -> 0.57126608 | W26: =W25/W$22 -> 0.53960354 | ... AA26: =AA25/AA$22 -> 0.55054544 | AB26: =AVERAGE(P26:AA26) -> 0.57791496 | AD26: =AD25/AD$22 -> 0.56874469 | AE26: =AE25/AE$22 -> 0.57137314 | AF26: =AF25/AF$22 -> 0.5863103 | AG26: =AG25/AG$22 -> 0.53441615 | AH26: =AH25/AH$22 -> 0.55695506 | AI26: =AI25/AI$22 -> 0.56608112 | AJ26: =AJ25/AJ$22 -> 0.5377812 | AK26: =AK25/AK$22 -> 0.53960354 | ... AO26: =AO25/AO$22 -> 0.55054544 | AP26: =AVERAGE(AD26:AO26) -> 0.5552471 | AR26: =AR25/AR$22 -> 0.57201077 | AS26: =AS25/AS$22 -> 0.57463853 | AT26: =AT25/AT$22 -> 0.58944423 | AU26: =AU25/AU$22 -> 0.53705811 | AV26: =AV25/AV$22 -> 0.56004212 | AW26: =AW25/AW$22 -> 0.5691893 | AX26: =AX25/AX$22 -> 0.54043405 | AY26: =AY25/AY$22 -> 0.54228601 | ... BC26: =BC25/BC$22 -> 0.55344892 | BD26: =AVERAGE(AR26:BC26) -> 0.55819619 | BE26: =AVERAGE(AS26:BD26) -> 0.55704497 | BF26: =AVERAGE(AT26:BE26) -> 0.55557884
B27: Indirectos | P27: 47984.8 | Q27: 59373.29 | R27: 108693.8 | S27: 116944.3 | T27: 142308.6 | U27: 125983 | V27: 197435.75 | W27: =W22*ASSUMPTIONS!$C$17 -> 249622.17 | X27: =X22*ASSUMPTIONS!$C$17 -> 224307.79 | Y27: =Y22*ASSUMPTIONS!$C$17 -> 221722.9 | Z27: =Z22*ASSUMPTIONS!$C$17 -> 198405.3 | AA27: =AA22*ASSUMPTIONS!$C$17 -> 213565.85 | AB27: =SUM(P27:AA27) -> 1906347.6 | AD27: =AD22*ASSUMPTIONS!$C$17 -> 229542.19 | AE27: =AE22*ASSUMPTIONS!$C$17 -> 201419.89 | AF27: =AF22*ASSUMPTIONS!$C$17 -> 160498.74 | AG27: =AG22*ASSUMPTIONS!$C$17 -> 219742.98 | AH27: =AH22*ASSUMPTIONS!$C$17 -> 258746.06 | AI27: =AI22*ASSUMPTIONS!$C$17 -> 219321.62 | AJ27: =AJ22*ASSUMPTIONS!$C$17 -> 289681.47 | AK27: =AK22*ASSUMPTIONS!$C$17 -> 312027.72 | ... AO27: =AO22*ASSUMPTIONS!$C$17 -> 266957.32 | AP27: =SUM(AD27:AO27) -> 2963483 | AR27: =AR22*ASSUMPTIONS!$C$17 -> 286550.4 | AS27: =AS22*ASSUMPTIONS!$C$17 -> 251768.03 | AT27: =AT22*ASSUMPTIONS!$C$17 -> 202086.38 | AU27: =AU22*ASSUMPTIONS!$C$17 -> 269697.12 | AV27: =AV22*ASSUMPTIONS!$C$17 -> 321587.67 | AW27: =AW22*ASSUMPTIONS!$C$17 -> 273955.99 | AX27: =AX22*ASSUMPTIONS!$C$17 -> 356857.14 | AY27: =AY22*ASSUMPTIONS!$C$17 -> 384906.29 | ... BC27: =BC22*ASSUMPTIONS!$C$17 -> 331214.37 | BD27: =SUM(AR27:BC27) -> 3677854 | BE27: =BE22*ASSUMPTIONS!$C$17 -> 4264537 | BF27: =BF22*ASSUMPTIONS!$C$17 -> 4989622
B28: Logistica MP/ME | AB28: =SUM(P28:AA28) -> 0 | AP28: =SUM(AD28:AO28) -> 0 | BD28: =SUM(AR28:BC28) -> 0
B29: Nomina Produccion | P29: 3242912.5 | Q29: 2305460.2 | R29: 1787305.3 | S29: 2025486 | T29: 2081617.5 | U29: 2047912.4 | V29: 1940260.9 | W29: =1795060.87177475 -> 1795060.9 | X29: =1795060.87177475-ASSUMPTIONS!$C48 -> 1388185.9 | Y29: =1795060.87177475-ASSUMPTIONS!$C48 -> 1388185.9 | Z29: =1795060.87177475-ASSUMPTIONS!$C48 -> 1388185.9 | AA29: =1795060.87177475-ASSUMPTIONS!$C48 -> 1388185.9 | AB29: =SUM(P29:AA29) -> 22778759 | AD29: =1795060.87177475-ASSUMPTIONS!$C48 -> 1388185.9 | AE29: =1795060.87177475-ASSUMPTIONS!$C48 -> 1388185.9 | AF29: =1795060.87177475-ASSUMPTIONS!$C48 -> 1388185.9 | AG29: =1795060.87177475-ASSUMPTIONS!$C48 -> 1388185.9 | AH29: =1795060.87177475-ASSUMPTIONS!$C48 -> 1388185.9 | AI29: =1795060.87177475-ASSUMPTIONS!$C48 -> 1388185.9 | AJ29: =1795060.87177475-ASSUMPTIONS!$C48 -> 1388185.9 | AK29: =1795060.87177475-ASSUMPTIONS!$C48 -> 1388185.9 | ... AO29: =1795060.87177475-ASSUMPTIONS!$C48 -> 1388185.9 | AP29: =SUM(AD29:AO29) -> 16658230 | AR29: =1795060.87177475-ASSUMPTIONS!$C48 -> 1388185.9 | AS29: =1795060.87177475-ASSUMPTIONS!$C48 -> 1388185.9 | AT29: =1795060.87177475-ASSUMPTIONS!$C48 -> 1388185.9 | AU29: =1795060.87177475-ASSUMPTIONS!$C48 -> 1388185.9 | AV29: =1795060.87177475-ASSUMPTIONS!$C48 -> 1388185.9 | AW29: =1795060.87177475-ASSUMPTIONS!$C48 -> 1388185.9 | AX29: =1795060.87177475-ASSUMPTIONS!$C48 -> 1388185.9 | AY29: =1795060.87177475-ASSUMPTIONS!$C48 -> 1388185.9 | ... BC29: =1795060.87177475-ASSUMPTIONS!$C48 -> 1388185.9 | BD29: =SUM(AR29:BC29) -> 16658230 | BE29: =BD29*1.07 -> 17824307 | BF29: =BE29*1.07 -> 19072008
B30: Tesistán | P30: 687435.81 | Q30: 539876.45 | R30: 545472.55 | S30: 387511.65 | T30: 597519.94 | U30: 599209.07 | V30: 689160.68 | W30: =SUM(Gastos!AA7:AA10) -> 551800 | X30: =SUM(Gastos!AB7:AB10) -> 551800 | Y30: =SUM(Gastos!AC7:AC10) -> 551800 | Z30: =SUM(Gastos!AD7:AD10) -> 551800 | AA30: =SUM(Gastos!AE7:AE10) -> 551800 | AB30: =SUM(P30:AA30) -> 6805186.1 | AD30: =SUM(Gastos!AG7:AG10) -> 560283 | AE30: =SUM(Gastos!AH7:AH10) -> 560283 | AF30: =SUM(Gastos!AI7:AI10) -> 560283 | AG30: =SUM(Gastos!AJ7:AJ10) -> 560283 | AH30: =SUM(Gastos!AK7:AK10) -> 591958 | AI30: =SUM(Gastos!AL7:AL10) -> 604234 | AJ30: =SUM(Gastos!AM7:AM10) -> 604234 | AK30: =SUM(Gastos!AN7:AN10) -> 604234 | ... AO30: =SUM(Gastos!AR7:AR10) -> 591958 | AP30: =SUM(AD30:AO30) -> 7013624 | AR30: =SUM(Gastos!AT7:AT10) -> 601258.01 | AS30: =SUM(Gastos!AU7:AU10) -> 601258.01 | AT30: =SUM(Gastos!AV7:AV10) -> 601258.01 | AU30: =SUM(Gastos!AW7:AW10) -> 601258.01 | AV30: =SUM(Gastos!AX7:AX10) -> 635150.26 | AW30: =SUM(Gastos!AY7:AY10) -> 648653.86 | AX30: =SUM(Gastos!AZ7:AZ10) -> 648653.86 | AY30: =SUM(Gastos!BA7:BA10) -> 648653.86 | ... BC30: =SUM(Gastos!BE7:BE10) -> 635150.26 | BD30: =SUM(AR30:BC30) -> 7526744.9 | BE30: =BD30*1.07 -> 8053617.1 | BF30: =BE30*1.07 -> 8617370.3
B31: Argentina | W31: =SUM(Gastos!AA13:AA18) -> 77650.69 | X31: =SUM(Gastos!AB13:AB18) -> 77650.69 | Y31: =SUM(Gastos!AC13:AC18) -> 77650.69 | Z31: =SUM(Gastos!AD13:AD18) -> 77650.69 | AA31: =SUM(Gastos!AE13:AE18) -> 77650.69 | AB31: =SUM(P31:AA31) -> 388253.45 | AD31: =SUM(Gastos!AG13:AG18) -> 77650.69 | AE31: =SUM(Gastos!AH13:AH18) -> 77650.69 | AF31: =SUM(Gastos!AI13:AI18) -> 77650.69 | AG31: =SUM(Gastos!AJ13:AJ18) -> 77650.69 | AH31: =SUM(Gastos!AK13:AK18) -> 77650.69 | AI31: =SUM(Gastos!AL13:AL18) -> 0 | AJ31: =SUM(Gastos!AM13:AM18) -> 0 | AK31: =SUM(Gastos!AN13:AN18) -> 0 | ... AO31: =SUM(Gastos!AR13:AR18) -> 0 | AP31: =SUM(AD31:AO31) -> 388253.45 | AR31: =SUM(Gastos!AT13:AT18) -> 0 | AS31: =SUM(Gastos!AU13:AU18) -> 0 | AT31: =SUM(Gastos!AV13:AV18) -> 0 | AU31: =SUM(Gastos!AW13:AW18) -> 0 | AV31: =SUM(Gastos!AX13:AX18) -> 0 | AW31: =SUM(Gastos!AY13:AY18) -> 0 | AX31: =SUM(Gastos!AZ13:AZ18) -> 0 | AY31: =SUM(Gastos!BA13:BA18) -> 0 | ... BC31: =SUM(Gastos!BE13:BE18) -> 0 | BD31: =SUM(AR31:BC31) -> 0 | BE31: =SUM(Gastos!BG13:BG18) -> 0 | BF31: =SUM(Gastos!BH13:BH18) -> 0
B32: Otros Gastos Producción (Rentas Equipos) | P32: 71000 | Q32: 51000 | R32: 51000 | S32: 51000 | T32: 51000 | U32: 51000 | V32: 51000
B33: Mantenimiento | P33: 183449.01 | Q33: 153041.74 | R33: 120779.55 | S33: 203199.63 | T33: 120903.89 | U33: 218826.81 | V33: 81559.6 | W33: =W18*ASSUMPTIONS!$C$24 -> 216509.03 | X33: =X18*ASSUMPTIONS!$C$24 -> 194552.68 | Y33: =Y18*ASSUMPTIONS!$C$24 -> 192310.68 | Z33: =Z18*ASSUMPTIONS!$C$24 -> 172086.23 | AA33: =AA18*ASSUMPTIONS!$C$24 -> 185235.69 | AB33: =SUM(P33:AA33) -> 2042454.5 | AD33: =AD18*ASSUMPTIONS!$C$24 -> 199092.72 | AE33: =AE18*ASSUMPTIONS!$C$24 -> 174700.93 | AF33: =AF18*ASSUMPTIONS!$C$24 -> 139208.09 | AG33: =AG18*ASSUMPTIONS!$C$24 -> 190593.4 | AH33: =AH18*ASSUMPTIONS!$C$24 -> 224422.61 | AI33: =AI18*ASSUMPTIONS!$C$24 -> 190227.94 | AJ33: =AJ18*ASSUMPTIONS!$C$24 -> 251254.34 | AK33: =AK18*ASSUMPTIONS!$C$24 -> 270636.29 | ... AO33: =AO18*ASSUMPTIONS!$C$24 -> 231544.61 | AP33: =SUM(AD33:AO33) -> 2570367.9 | AR33: =AR18*ASSUMPTIONS!$C$24 -> 248538.61 | AS33: =AS18*ASSUMPTIONS!$C$24 -> 218370.23 | AT33: =AT18*ASSUMPTIONS!$C$24 -> 175279.01 | AU33: =AU18*ASSUMPTIONS!$C$24 -> 233920.97 | AV33: =AV18*ASSUMPTIONS!$C$24 -> 278928.08 | AW33: =AW18*ASSUMPTIONS!$C$24 -> 237614.89 | AX33: =AX18*ASSUMPTIONS!$C$24 -> 309518.95 | AY33: =AY18*ASSUMPTIONS!$C$24 -> 333847.29 | ... BC33: =BC18*ASSUMPTIONS!$C$24 -> 287277.77 | BD33: =SUM(AR33:BC33) -> 3189975.4 | BE33: =BE18*ASSUMPTIONS!$C$24 -> 3717801.5 | BF33: =BF18*ASSUMPTIONS!$C$24 -> 4349926.9
B34: TOTAL COGS | P34: =SUM(P27:P33)+P24 -> 11206107 | Q34: =SUM(Q27:Q33)+Q24 -> 9064534.8 | R34: =SUM(R27:R33)+R24 -> 7505870.8 | S34: =SUM(S27:S33)+S24 -> 9414750.4 | T34: =SUM(T27:T33)+T24 -> 11863917 | U34: =SUM(U27:U33)+U24 -> 10179476 | V34: =SUM(V27:V33)+V24 -> 12922657 | W34: =SUM(W27:W33)+W24 -> 14383159 | ... AB34: =SUM(AB27:AB33)+AB24 -> 1.3442311e+08 | AD34: =SUM(AD27:AD33)+AD24 -> 12353883 | AE34: =SUM(AE27:AE33)+AE24 -> 11035638 | AF34: =SUM(AF27:AF33)+AF24 -> 8965494.2 | AG34: =SUM(AG27:AG33)+AG24 -> 12667334 | AH34: =SUM(AH27:AH33)+AH24 -> 14004577 | AI34: =SUM(AI27:AI33)+AI24 -> 11918749 | AJ34: =SUM(AJ27:AJ33)+AJ24 -> 15922978 | AK34: =SUM(AK27:AK33)+AK24 -> 16940730 | ... AP34: =SUM(AP27:AP33)+AP24 -> 1.6196632e+08 | AR34: =SUM(AR27:AR33)+AR24 -> 14788582 | AS34: =SUM(AS27:AS33)+AS24 -> 13168824 | AT34: =SUM(AT27:AT33)+AT24 -> 10663582 | AU34: =SUM(AU27:AU33)+AU24 -> 14978472 | AV34: =SUM(AV27:AV33)+AV24 -> 16772355 | AW34: =SUM(AW27:AW33)+AW24 -> 14350728 | AX34: =SUM(AX27:AX33)+AX24 -> 19103155 | AY34: =SUM(AY27:AY33)+AY24 -> 20373293 | ... BF34: =SUM(BF27:BF33)+BF24 -> 2.5466718e+08
B35: TOTAL COGS | P35: =P34/P18 -> 0.59803736 | Q35: =Q34/Q18 -> 0.5512889 | R35: =R34/R18 -> 0.57288247 | S35: =S34/S18 -> 0.52484359 | T35: =T34/T18 -> 0.56168193 | U35: =U34/U18 -> 0.56856495 | V35: =V34/V18 -> 0.54647107 | W35: =W34/W18 -> 0.56467324 | ... AB35: =AB34/AB18 -> 0.55565803 | AD35: =AD34/AD18 -> 0.52743269 | AE35: =AE34/AE18 -> 0.53693432 | AF35: =AF34/AF18 -> 0.5474301 | AG35: =AG34/AG18 -> 0.56493216 | AH35: =AH34/AH18 -> 0.53042296 | AI35: =AI34/AI18 -> 0.53256827 | AJ35: =AJ34/AJ18 -> 0.53867851 | AK35: =AK34/AK18 -> 0.53206539 | ... AP35: =AP34/AP18 -> 0.53560961 | AR35: =AR34/AR18 -> 0.50576827 | AS35: =AS34/AS18 -> 0.51259279 | AT35: =AT34/AT18 -> 0.51712097 | AU35: =AU34/AU18 -> 0.54427359 | AV35: =AV34/AV18 -> 0.51111748 | AW35: =AW34/AW18 -> 0.51335666 | AX35: =AX34/AX18 -> 0.52461026 | AY35: =AY34/AY18 -> 0.51871916 | ... BF35: =BF34/BF18 -> 0.49763389
B36: UTILIDAD DE PRODUCCION | P36: =P25-SUM(P27:P33) -> 6397863.1 | Q36: =Q25-SUM(Q27:Q31) -> 7166317.9 | R36: =R25-SUM(R27:R31) -> 5159787.4 | S36: =S25-SUM(S27:S33) -> 8084102.7 | T36: =T25-SUM(T27:T33) -> 8908368 | U36: =U25-SUM(U27:U33) -> 7129737.8 | V36: =V25-SUM(V27:V33) -> 10316092 | W36: =W25-SUM(W27:W33) -> 10579058 | X36: =X25-SUM(X27:X33) -> 9728926.9 | Y36: =Y25-SUM(Y27:Y33) -> 9843201 | Z36: =Z25-SUM(Z27:Z33) -> 8627084.8 | AA36: =AA25-SUM(AA27:AA33) -> 9341332.6 | AB36: =SUM(P36:AA36) -> 1.0128187e+08 | AD36: =AD25-SUM(AD27:AD33) -> 10600336 | AE36: =AE25-SUM(AE27:AE33) -> 9106351.2 | AF36: =AF25-SUM(AF27:AF33) -> 7084380.1 | AG36: =AG25-SUM(AG27:AG33) -> 9306963.6 | AH36: =AH25-SUM(AH27:AH33) -> 11870030 | AI36: =AI25-SUM(AI27:AI33) -> 10013413 | AJ36: =AJ25-SUM(AJ27:AJ33) -> 13045169 | AK36: =AK25-SUM(AK27:AK33) -> 14262042 | ... AO36: =AO25-SUM(AO27:AO33) -> 12218568 | AP36: =SUM(AD36:AO36) -> 1.3438197e+08 | AR36: =AR25-SUM(AR27:AR33) -> 13866459 | AS36: =AS25-SUM(AS27:AS33) -> 12007979 | AT36: =AT25-SUM(AT27:AT33) -> 9545056 | AU36: =AU25-SUM(AU27:AU33) -> 11991241 | AV36: =AV25-SUM(AV27:AV33) -> 15386412 | AW36: =AW25-SUM(AW27:AW33) -> 13044871 | AX36: =AX25-SUM(AX27:AX33) -> 16582559 | AY36: =AY25-SUM(AY27:AY33) -> 18117336 | ... BC36: =BC25-SUM(BC27:BC33) -> 15689195 | BD36: =SUM(AR36:BC36) -> 1.7356046e+08 | BE36: =BE25-SUM(BE27:BE33) -> 2.1542578e+08 | BF36: =BF25-SUM(BF27:BF33) -> 2.5708892e+08
B37: UTILIDAD DE PRODUCCION | P37: =P36/P$22 -> 0.36343297 | Q37: =Q36/Q$22 -> 0.44714559 | R37: =R36/R$22 -> 0.41298524 | S37: =S36/S$22 -> 0.461979 | T37: =T36/T$22 -> 0.42885835 | U37: =U36/U$22 -> 0.41190418 | V37: =V36/V$22 -> 0.4439177 | W37: =W36/W$22 -> 0.42380282 | ... AB37: =AB36/AB$22 -> 0.42969548 | AD37: =AD36/AD$22 -> 0.46180338 | AE37: =AE36/AE$22 -> 0.45210784 | AF37: =AF36/AF$22 -> 0.44139786 | AG37: =AG36/AG$22 -> 0.42353862 | AH37: =AH36/AH$22 -> 0.45875208 | AI37: =AI36/AI$22 -> 0.45656299 | AJ37: =AJ36/AJ$22 -> 0.45032805 | AK37: =AK36/AK$22 -> 0.45707613 | ... AP37: =AP36/AP$22 -> 0.45345958 | AR37: =AR36/AR$22 -> 0.48390993 | AS37: =AS36/AS$22 -> 0.47694614 | AT37: =AT36/AT$22 -> 0.47232554 | AU37: =AU36/AU$22 -> 0.44461879 | AV37: =AV36/AV$22 -> 0.47845155 | AW37: =AW36/AW$22 -> 0.47616667 | AX37: =AX36/AX$22 -> 0.46468341 | AY37: =AY36/AY$22 -> 0.47069473 | ... BF37: =BF36/BF$22 -> 0.51524729
B38: Nomina Calidad | P38: 169679.14 | Q38: 195139.32 | R38: 201944.44 | S38: 260585.16 | T38: 223951.13 | U38: 271308.24 | V38: 346862.92 | W38: 238079.16 | X38: 238079.16 | Y38: 238079.16 | Z38: 238079.16 | AA38: 238079.16 | AB38: =SUM(P38:AA38) -> 2859866.1 | AD38: =238079.155439036+75000 -> 313079.16 | AE38: =238079.155439036+75000 -> 313079.16 | AF38: =238079.155439036+75000 -> 313079.16 | AG38: =238079.155439036+75000 -> 313079.16 | AH38: =238079.155439036+75000 -> 313079.16 | AI38: =238079.155439036+75000 -> 313079.16 | AJ38: =238079.155439036+75000 -> 313079.16 | AK38: =238079.155439036+75000 -> 313079.16 | ... AO38: =238079.155439036+75000 -> 313079.16 | AP38: =SUM(AD38:AO38) -> 3756949.9 | AR38: =238079.155439036+75000 -> 313079.16 | AS38: =238079.155439036+75000 -> 313079.16 | AT38: =238079.155439036+75000 -> 313079.16 | AU38: =238079.155439036+75000 -> 313079.16 | AV38: =238079.155439036+75000 -> 313079.16 | AW38: =238079.155439036+75000 -> 313079.16 | AX38: =238079.155439036+75000 -> 313079.16 | AY38: =238079.155439036+75000 -> 313079.16 | ... BC38: =238079.155439036+75000 -> 313079.16 | BD38: =SUM(AR38:BC38) -> 3756949.9 | BE38: =BD38*1.07 -> 4019936.4 | BF38: =BE38*1.07 -> 4301331.9
B39: Gastos Generales Calidad | P39: 74300 | Q39: 87735 | R39: 83190 | S39: 72545 | T39: 124125 | U39: 110105 | V39: 110695 | W39: =W18*ASSUMPTIONS!$C26 -> 254716.5 | X39: =X18*ASSUMPTIONS!$C26 -> 228885.5 | Y39: =Y18*ASSUMPTIONS!$C26 -> 226247.86 | Z39: =Z18*ASSUMPTIONS!$C26 -> 202454.38 | AA39: =AA18*ASSUMPTIONS!$C26 -> 217924.34 | AB39: =SUM(P39:AA39) -> 1792923.6 | AD39: =AD18*ASSUMPTIONS!$C26 -> 234226.73 | AE39: =AE18*ASSUMPTIONS!$C26 -> 205530.5 | AF39: =AF18*ASSUMPTIONS!$C26 -> 163774.23 | AG39: =AG18*ASSUMPTIONS!$C26 -> 224227.53 | AH39: =AH18*ASSUMPTIONS!$C26 -> 264026.59 | AI39: =AI18*ASSUMPTIONS!$C26 -> 223797.57 | AJ39: =AJ18*ASSUMPTIONS!$C26 -> 295593.34 | AK39: =AK18*ASSUMPTIONS!$C26 -> 318395.63 | ... AO39: =AO18*ASSUMPTIONS!$C26 -> 272405.42 | AP39: =SUM(AD39:AO39) -> 3023962.2 | AR39: =AR18*ASSUMPTIONS!$C26 -> 292398.37 | AS39: =AS18*ASSUMPTIONS!$C26 -> 256906.15 | AT39: =AT18*ASSUMPTIONS!$C26 -> 206210.6 | AU39: =AU18*ASSUMPTIONS!$C26 -> 275201.15 | AV39: =AV18*ASSUMPTIONS!$C26 -> 328150.68 | AW39: =AW18*ASSUMPTIONS!$C26 -> 279546.93 | AX39: =AX18*ASSUMPTIONS!$C26 -> 364139.94 | AY39: =AY18*ASSUMPTIONS!$C26 -> 392761.52 | ... BC39: =BC18*ASSUMPTIONS!$C26 -> 337973.85 | BD39: =SUM(AR39:BC39) -> 3752912.3 | BE39: =BE18*ASSUMPTIONS!$C26 -> 4373884.1 | BF39: =BF18*ASSUMPTIONS!$C26 -> 5117561.1
B40: Shrink | W40: =W18*ASSUMPTIONS!$C28 -> 63679.126 | X40: =X18*ASSUMPTIONS!$C28 -> 57221.376 | Y40: =Y18*ASSUMPTIONS!$C28 -> 56561.965 | Z40: =Z18*ASSUMPTIONS!$C28 -> 50613.596 | AA40: =AA18*ASSUMPTIONS!$C28 -> 54481.085 | AB40: =SUM(P40:AA40) -> 282557.15 | AD40: =AD18*ASSUMPTIONS!$C28 -> 58556.682 | AE40: =AE18*ASSUMPTIONS!$C28 -> 51382.626 | AF40: =AF18*ASSUMPTIONS!$C28 -> 40943.557 | AG40: =AG18*ASSUMPTIONS!$C28 -> 56056.882 | AH40: =AH18*ASSUMPTIONS!$C28 -> 66006.649 | AI40: =AI18*ASSUMPTIONS!$C28 -> 55949.393 | AJ40: =AJ18*ASSUMPTIONS!$C28 -> 73898.335 | AK40: =AK18*ASSUMPTIONS!$C28 -> 79598.908 | ... AO40: =AO18*ASSUMPTIONS!$C28 -> 68101.356 | AP40: =SUM(AD40:AO40) -> 755990.56 | AR40: =AR18*ASSUMPTIONS!$C28 -> 73099.592 | AS40: =AS18*ASSUMPTIONS!$C28 -> 64226.537 | AT40: =AT18*ASSUMPTIONS!$C28 -> 51552.649 | AU40: =AU18*ASSUMPTIONS!$C28 -> 68800.287 | AV40: =AV18*ASSUMPTIONS!$C28 -> 82037.671 | AW40: =AW18*ASSUMPTIONS!$C28 -> 69886.733 | AX40: =AX18*ASSUMPTIONS!$C28 -> 91034.985 | AY40: =AY18*ASSUMPTIONS!$C28 -> 98190.379 | ... BC40: =BC18*ASSUMPTIONS!$C28 -> 84493.463 | BD40: =SUM(AR40:BC40) -> 938228.07 | BE40: =BE18*ASSUMPTIONS!$C28 -> 1093471 | BF40: =BF18*ASSUMPTIONS!$C28 -> 1279390.3
B41: UTILIDAD BRUTA | P41: =P36-SUM(P38:P40) -> 6153884 | Q41: =Q36-SUM(Q38:Q40) -> 6883443.6 | R41: =R36-SUM(R38:R40) -> 4874653 | S41: =S36-SUM(S38:S40) -> 7750972.6 | T41: =T36-SUM(T38:T40) -> 8560291.9 | U41: =U36-SUM(U38:U40) -> 6748324.6 | V41: =V36-SUM(V38:V40) -> 9858534 | W41: =W36-SUM(W38:W40) -> 10022583 | ... AA41: =AA36-SUM(AA38:AA40) -> 8830848 | AB41: =SUM(P41:AA41) -> 96346525 | AD41: =AD36-SUM(AD38:AD40) -> 9994473.4 | AE41: =AE36-SUM(AE38:AE40) -> 8536358.9 | AF41: =AF36-SUM(AF38:AF40) -> 6566583.2 | AG41: =AG36-SUM(AG38:AG40) -> 8713600.1 | AH41: =AH36-SUM(AH38:AH40) -> 11226917 | AI41: =AI36-SUM(AI38:AI40) -> 9420587.3 | AJ41: =AJ36-SUM(AJ38:AJ40) -> 12362598 | AK41: =AK36-SUM(AK38:AK40) -> 13550969 | ... AO41: =AO36-SUM(AO38:AO40) -> 11564982 | AP41: =SUM(AD41:AO41) -> 1.2684507e+08 | AR41: =AR36-SUM(AR38:AR40) -> 13187881 | AS41: =AS36-SUM(AS38:AS40) -> 11373767 | AT41: =AT36-SUM(AT38:AT40) -> 8974213.6 | AU41: =AU36-SUM(AU38:AU40) -> 11334160 | AV41: =AV36-SUM(AV38:AV40) -> 14663145 | AW41: =AW36-SUM(AW38:AW40) -> 12382359 | AX41: =AX36-SUM(AX38:AX40) -> 15814305 | AY41: =AY36-SUM(AY38:AY40) -> 17313305 | ... BC41: =BC36-SUM(BC38:BC40) -> 14953649 | BD41: =SUM(AR41:BC41) -> 1.6511236e+08 | BE41: =BE36-SUM(BE38:BE40) -> 2.0593849e+08 | BF41: =BF36-SUM(BF38:BF40) -> 2.4639064e+08
B42: UTILIDAD BRUTA | P42: =P41/P$22 -> 0.34957365 | Q42: =Q41/Q$22 -> 0.42949553 | R42: =R41/R$22 -> 0.39016331 | S42: =S41/S$22 -> 0.44294175 | T42: =T41/T$22 -> 0.41210159 | U42: =U41/U$22 -> 0.38986891 | V42: =V41/V$22 -> 0.42422826 | W42: =W41/W$22 -> 0.40151014 | ... AB42: =AB41/AB$22 -> 0.40875692 | AD42: =AD41/AD$22 -> 0.43540899 | AE42: =AE41/AE$22 -> 0.42380913 | AF42: =AF41/AF$22 -> 0.40913611 | AG42: =AG41/AG$22 -> 0.396536 | AH42: =AH41/AH$22 -> 0.43389712 | AI42: =AI41/AI$22 -> 0.429533 | AJ42: =AJ41/AJ$22 -> 0.42676524 | AK42: =AK41/AK$22 -> 0.43428733 | ... AP42: =AP41/AP$22 -> 0.42802699 | AR42: =AR41/AR$22 -> 0.46022903 | AS42: =AS41/AS$22 -> 0.45175581 | AT42: =AT41/AT$22 -> 0.44407809 | AU42: =AU41/AU$22 -> 0.42025514 | AV42: =AV41/AV$22 -> 0.45596103 | AW42: =AW41/AW$22 -> 0.45198349 | AX42: =AX41/AX$22 -> 0.44315507 | AY42: =AY41/AY$22 -> 0.44980572 | ... BF42: =BF41/BF$22 -> 0.49380622
B43: Nomina Soporte Produccion | P43: 474620.72 | Q43: 402759.34 | R43: 356971.49 | S43: 423860.67 | T43: 361715.01 | U43: 420335.46 | V43: 719782.8 | W43: =375227.519850061+160000 -> 535227.52 | X43: =375227.519850061+160000 -> 535227.52 | Y43: =375227.519850061+160000 -> 535227.52 | Z43: =375227.519850061+160000 -> 535227.52 | AA43: =375227.519850061+160000 -> 535227.52 | AB43: =SUM(P43:AA43) -> 5836183.1 | AD43: =AA43*1.07 -> 572693.45 | AE43: =AD43 -> 572693.45 | AF43: =AE43 -> 572693.45 | AG43: =AF43 -> 572693.45 | AH43: =AG43 -> 572693.45 | AI43: =AH43 -> 572693.45 | AJ43: =AI43 -> 572693.45 | AK43: =AJ43 -> 572693.45 | AL43: =AK43 -> 572693.45 | ... AO43: =AN43 -> 572693.45 | AP43: =SUM(AD43:AO43) -> 6872321.4 | AR43: =AO43*1.07 -> 612781.99 | AS43: =AR43 -> 612781.99 | AT43: =AS43 -> 612781.99 | AU43: =AT43 -> 612781.99 | AV43: =AU43 -> 612781.99 | AW43: =AV43 -> 612781.99 | AX43: =AW43 -> 612781.99 | AY43: =AX43 -> 612781.99 | AZ43: =AY43 -> 612781.99 | ... BC43: =BB43 -> 612781.99 | BD43: =SUM(AR43:BC43) -> 7353383.8 | BE43: =BD43*1.07 -> 7868120.7 | BF43: =BE43*1.07 -> 8418889.2
B44: Nomina Almacen | P44: 0 | Q44: 106941.66 | R44: 186736.5 | S44: 198804.96 | T44: 225735.04 | U44: 212132.17 | V44: 202403.54 | W44: 191005.54 | X44: 191005.54 | Y44: 191005.54 | Z44: 191005.54 | AA44: 191005.54 | AB44: =SUM(Q44:AA44) -> 2087781.5 | AD44: =AA44*1.07 -> 204375.92 | AE44: =AD44 -> 204375.92 | AF44: =AE44 -> 204375.92 | AG44: =AF44 -> 204375.92 | AH44: =AG44 -> 204375.92 | AI44: =AH44 -> 204375.92 | AJ44: =AI44 -> 204375.92 | AK44: =AJ44 -> 204375.92 | AL44: =AK44 -> 204375.92 | ... AO44: =AN44 -> 204375.92 | AP44: =SUM(AD44:AO44) -> 2452511.1 | AR44: =AO44*1.07 -> 218682.24 | AS44: =AR44 -> 218682.24 | AT44: =AS44 -> 218682.24 | AU44: =AT44 -> 218682.24 | AV44: =AU44 -> 218682.24 | AW44: =AV44 -> 218682.24 | AX44: =AW44 -> 218682.24 | AY44: =AX44 -> 218682.24 | AZ44: =AY44 -> 218682.24 | ... BC44: =BB44 -> 218682.24 | BD44: =SUM(AR44:BC44) -> 2624186.9 | BE44: =BD44*1.07 -> 2807879.9 | BF44: =BE44*1.07 -> 3004431.5
B45: Nomina Mantenimiento | P45: 0 | Q45: 39996.18 | R45: 84495.36 | S45: 97627.88 | T45: 96956.31 | U45: 99350.38 | V45: 88231.51 | W45: 87622.044 | X45: 87622.044 | Y45: 87622.044 | Z45: 87622.044 | AA45: 87622.044 | AB45: =SUM(P45:AA45) -> 944767.84 | AD45: =AA45*1.07 -> 93755.588 | AE45: =AD45 -> 93755.588 | AF45: =AE45 -> 93755.588 | AG45: =AF45 -> 93755.588 | AH45: =AG45 -> 93755.588 | AI45: =AH45 -> 93755.588 | AJ45: =AI45 -> 93755.588 | AK45: =AJ45 -> 93755.588 | AL45: =AK45 -> 93755.588 | ... AO45: =AN45 -> 93755.588 | AP45: =SUM(AD45:AO45) -> 1125067.1 | AR45: =AO45*1.07 -> 100318.48 | AS45: =AR45 -> 100318.48 | AT45: =AS45 -> 100318.48 | AU45: =AT45 -> 100318.48 | AV45: =AU45 -> 100318.48 | AW45: =AV45 -> 100318.48 | AX45: =AW45 -> 100318.48 | AY45: =AX45 -> 100318.48 | AZ45: =AY45 -> 100318.48 | ... BC45: =BB45 -> 100318.48 | BD45: =SUM(AR45:BC45) -> 1203821.7 | BE45: =BD45*1.07 -> 1288089.3 | BF45: =BE45*1.07 -> 1378255.5
B46: Nomina Servicios Generales | P46: 0 | Q46: 114374.86 | R46: 137949.88 | S46: 141275.22 | T46: 148836.01 | U46: 178275.37 | V46: 125448.78 | W46: =130519.684320294+'Subtotal Nom_Enero'!$E4 -> 321525.22 | X46: =130519.684320294+'Subtotal Nom_Enero'!$E4 -> 321525.22 | Y46: =130519.684320294+'Subtotal Nom_Enero'!$E4 -> 321525.22 | Z46: =130519.684320294+'Subtotal Nom_Enero'!$E4 -> 321525.22 | AA46: =130519.684320294+'Subtotal Nom_Enero'!$E4 -> 321525.22 | AB46: =SUM(P46:AA46) -> 2453786.2 | AD46: =AA46*1.07 -> 344031.99 | AE46: =AD46 -> 344031.99 | AF46: =AE46 -> 344031.99 | AG46: =AF46 -> 344031.99 | AH46: =AG46 -> 344031.99 | AI46: =AH46 -> 344031.99 | AJ46: =AI46 -> 344031.99 | AK46: =AJ46 -> 344031.99 | AL46: =AK46 -> 344031.99 | ... AO46: =AN46 -> 344031.99 | AP46: =SUM(AD46:AO46) -> 4128383.8 | AR46: =AO46*1.07 -> 368114.22 | AS46: =AR46 -> 368114.22 | AT46: =AS46 -> 368114.22 | AU46: =AT46 -> 368114.22 | AV46: =AU46 -> 368114.22 | AW46: =AV46 -> 368114.22 | AX46: =AW46 -> 368114.22 | AY46: =AX46 -> 368114.22 | AZ46: =AY46 -> 368114.22 | ... BC46: =BB46 -> 368114.22 | BD46: =SUM(AR46:BC46) -> 4417370.7 | BE46: =BD46*1.07 -> 4726586.6 | BF46: =BE46*1.07 -> 5057447.7
B47: Nomina Ventas | P47: 573424.24 | Q47: 617838.75 | R47: 637815.98 | S47: 741184.14 | T47: 693351.94 | U47: 725965.01 | V47: 1009479 | W47: 468529.3 | X47: 468529.3 | Y47: 468529.3 | Z47: 468529.3 | AA47: 468529.3 | AB47: =SUM(P47:AA47) -> 7341705.6 | AD47: =AA47*1.07 -> 501326.36 | AE47: =AD47 -> 501326.36 | AF47: =AE47 -> 501326.36 | AG47: =AF47 -> 501326.36 | AH47: =AG47 -> 501326.36 | AI47: =AH47 -> 501326.36 | AJ47: =AI47 -> 501326.36 | AK47: =AJ47 -> 501326.36 | AL47: =AK47 -> 501326.36 | ... AO47: =AN47 -> 501326.36 | AP47: =SUM(AD47:AO47) -> 6015916.3 | AR47: =AO47*1.07 -> 536419.2 | AS47: =AR47 -> 536419.2 | AT47: =AS47 -> 536419.2 | AU47: =AT47 -> 536419.2 | AV47: =AU47 -> 536419.2 | AW47: =AV47 -> 536419.2 | AX47: =AW47 -> 536419.2 | AY47: =AX47 -> 536419.2 | AZ47: =AY47 -> 536419.2 | ... BC47: =BB47 -> 536419.2 | BD47: =SUM(AR47:BC47) -> 6437030.4 | BE47: =BD47*1.07 -> 6887622.5 | BF47: =BE47*1.07 -> 7369756.1
B48: Trade Mktg | P48: 219729.14 | Q48: 127931.18 | R48: 488164.32 | S48: 470080.06 | T48: 482232.72 | U48: 224881 | V48: 908978.41 | W48: =OFFSET(INDEX(BIOMIRAL_PVT_LBL[], MATCH("TOTAL INC NUEVOS CANALES", BIOMIRAL_PVT_LBL[Column3], 0), MATCH("TMI - TRADE MARKETING INVESTMENT-ENE", 'BIOMIRAL PVT LBL'!2:2, 0)),0,V11) -> 547297.74 | X48: =OFFSET(INDEX(BIOMIRAL_PVT_LBL[], MATCH("TOTAL INC NUEVOS CANALES", BIOMIRAL_PVT_LBL[Column3], 0), MATCH("TMI - TRADE MARKETING INVESTMENT-ENE", 'BIOMIRAL PVT LBL'!2:2, 0)),0,W11) -> 503181.56 | Y48: =OFFSET(INDEX(BIOMIRAL_PVT_LBL[], MATCH("TOTAL INC NUEVOS CANALES", BIOMIRAL_PVT_LBL[Column3], 0), MATCH("TMI - TRADE MARKETING INVESTMENT-ENE", 'BIOMIRAL PVT LBL'!2:2, 0)),0,X11) -> 614386.91 | Z48: =OFFSET(INDEX(BIOMIRAL_PVT_LBL[], MATCH("TOTAL INC NUEVOS CANALES", BIOMIRAL_PVT_LBL[Column3], 0), MATCH("TMI - TRADE MARKETING INVESTMENT-ENE", 'BIOMIRAL PVT LBL'!2:2, 0)),0,Y11) -> 578804.63 | AA48: =OFFSET(INDEX(BIOMIRAL_PVT_LBL[], MATCH("TOTAL INC NUEVOS CANALES", BIOMIRAL_PVT_LBL[Column3], 0), MATCH("TMI - TRADE MARKETING INVESTMENT-ENE", 'BIOMIRAL PVT LBL'!2:2, 0)),0,Z11) -> 657419.39 | AB48: =SUM(P48:AA48) -> 5823087 | AD48: =ASSUMPTIONS!$C$31*(AD17+AD16) -> 566314.85 | AE48: =ASSUMPTIONS!$C$31*(AE17+AE16) -> 513477.33 | AF48: =ASSUMPTIONS!$C$31*(AF17+AF16) -> 484076.13 | AG48: =ASSUMPTIONS!$C$31*(AG17+AG16) -> 306405.7 | AH48: =ASSUMPTIONS!$C$31*(AH17+AH16) -> 588840.78 | AI48: =ASSUMPTIONS!$C$31*(AI17+AI16) -> 576141.11 | AJ48: =ASSUMPTIONS!$C$31*(AJ17+AJ16) -> 508404.55 | AK48: =ASSUMPTIONS!$C$31*(AK17+AK16) -> 583008.63 | ... AO48: =ASSUMPTIONS!$C$31*(AO17+AO16) -> 601936.36 | AP48: =SUM(AD48:AO48) -> 6532716.4 | AR48: =ASSUMPTIONS!$C$31*(AR17+AR16) -> 736209.3 | AS48: =ASSUMPTIONS!$C$31*(AS17+AS16) -> 667520.53 | AT48: =ASSUMPTIONS!$C$31*(AT17+AT16) -> 629298.97 | AU48: =ASSUMPTIONS!$C$31*(AU17+AU16) -> 398327.41 | AV48: =ASSUMPTIONS!$C$31*(AV17+AV16) -> 763202.79 | AW48: =ASSUMPTIONS!$C$31*(AW17+AW16) -> 746318.57 | AX48: =ASSUMPTIONS!$C$31*(AX17+AX16) -> 657225.14 | AY48: =ASSUMPTIONS!$C$31*(AY17+AY16) -> 753044.16 | ... BC48: =ASSUMPTIONS!$C$31*(BC17+BC16) -> 777760.34 | BD48: =SUM(AR48:BC48) -> 8460047.8 | BE48: =ASSUMPTIONS!$C$31*(BE17+BE16) -> 10534455 | BF48: =ASSUMPTIONS!$C$31*(BF17+BF16) -> 13119344
B49: Presupuesto Mktg | P49: 367779.02 | Q49: 559363.51 | R49: 494981.97 | S49: 507835.16 | T49: 802292.79 | U49: 779976.06 | V49: 434504.82 | W49: =ASSUMPTIONS!$C$31*(W16+W17) -> 466406.9 | X49: =ASSUMPTIONS!$C$31*(X16+X17) -> 434582.34 | Y49: =ASSUMPTIONS!$C$31*(Y16+Y17) -> 516061.55 | Z49: =ASSUMPTIONS!$C$31*(Z16+Z17) -> 492644.89 | AA49: =ASSUMPTIONS!$C$31*(AA16+AA17) -> 481549.09 | AB49: =SUM(P49:AA49) -> 6337978.1 | AD49: =ASSUMPTIONS!$C$32*(AD16+AD17) -> 679577.82 | AE49: =ASSUMPTIONS!$C$32*(AE16+AE17) -> 616172.8 | AF49: =ASSUMPTIONS!$C$32*(AF16+AF17) -> 580891.36 | AG49: =ASSUMPTIONS!$C$32*(AG16+AG17) -> 367686.84 | AH49: =ASSUMPTIONS!$C$32*(AH16+AH17) -> 706608.94 | AI49: =ASSUMPTIONS!$C$32*(AI16+AI17) -> 691369.33 | AJ49: =ASSUMPTIONS!$C$32*(AJ16+AJ17) -> 610085.46 | AK49: =ASSUMPTIONS!$C$32*(AK16+AK17) -> 699610.35 | ... AO49: =ASSUMPTIONS!$C$32*(AO16+AO17) -> 722323.63 | AP49: =SUM(AD49:AO49) -> 7839259.7 | AR49: =ASSUMPTIONS!$C$32*(AR16+AR17) -> 883451.16 | AS49: =ASSUMPTIONS!$C$32*(AS16+AS17) -> 801024.64 | AT49: =ASSUMPTIONS!$C$32*(AT16+AT17) -> 755158.76 | AU49: =ASSUMPTIONS!$C$32*(AU16+AU17) -> 477992.89 | AV49: =ASSUMPTIONS!$C$32*(AV16+AV17) -> 915843.35 | AW49: =ASSUMPTIONS!$C$32*(AW16+AW17) -> 895582.28 | AX49: =ASSUMPTIONS!$C$32*(AX16+AX17) -> 788670.16 | AY49: =ASSUMPTIONS!$C$32*(AY16+AY17) -> 903652.99 | ... BC49: =ASSUMPTIONS!$C$32*(BC16+BC17) -> 933312.41 | BD49: =SUM(AR49:BC49) -> 10152057 | BE49: =ASSUMPTIONS!$C$32*(BE16+BE17) -> 12641346 | BF49: =ASSUMPTIONS!$C$32*(BF16+BF17) -> 15743213
B50: Viáticos Ventas | P50: 51.71 | Q50: 9668.9 | R50: 9311.94 | S50: 25446.08 | T50: 140999.14 | U50: 42612.35 | V50: 62727.45 | W50: =Gastos!AA49 -> 25000 | X50: =Gastos!AB49 -> 25000 | Y50: =Gastos!AC49 -> 25000 | Z50: =Gastos!AD49 -> 25000 | AA50: =Gastos!AE49 -> 25000 | AB50: =SUM(P50:AA50) -> 415817.57 | AD50: =Gastos!AG49 -> 50000 | AE50: =Gastos!AH49 -> 50000 | AF50: =Gastos!AI49 -> 50000 | AG50: =Gastos!AJ49 -> 50000 | AH50: =Gastos!AK49 -> 50000 | AI50: =Gastos!AL49 -> 50000 | AJ50: =Gastos!AM49 -> 50000 | AK50: =Gastos!AN49 -> 50000 | ... AO50: =Gastos!AR49 -> 50000 | AP50: =SUM(AD50:AO50) -> 600000 | AR50: =Gastos!AT49 -> 75000 | AS50: =Gastos!AU49 -> 75000 | AT50: =Gastos!AV49 -> 75000 | AU50: =Gastos!AW49 -> 75000 | AV50: =Gastos!AX49 -> 75000 | AW50: =Gastos!AY49 -> 75000 | AX50: =Gastos!AZ49 -> 75000 | AY50: =Gastos!BA49 -> 75000 | ... BC50: =Gastos!BE49 -> 75000 | BD50: =SUM(AR50:BC50) -> 900000 | BE50: =BD50*1.1 -> 990000 | BF50: =BE50*1.1 -> 1089000
B51: Nomina Desarrollo | P51: 253774.22 | Q51: 227874.52 | R51: 213692.45 | S51: 252577.28 | T51: 213980.06 | U51: 254145.77 | V51: 349520.38 | W51: =224607.710972195+70000 -> 294607.71 | X51: =224607.710972195+70000 -> 294607.71 | Y51: =224607.710972195+70000 -> 294607.71 | Z51: =224607.710972195+70000 -> 294607.71 | AA51: =224607.710972195+70000 -> 294607.71 | AB51: =SUM(P51:AA51) -> 3238603.2 | AD51: =AA51*1.07 -> 315230.25 | AE51: =AD51 -> 315230.25 | AF51: =AE51 -> 315230.25 | AG51: =AF51 -> 315230.25 | AH51: =AG51 -> 315230.25 | AI51: =AH51 -> 315230.25 | AJ51: =AI51 -> 315230.25 | AK51: =AJ51 -> 315230.25 | AL51: =AK51 -> 315230.25 | ... AO51: =AN51 -> 315230.25 | AP51: =SUM(AD51:AO51) -> 3782763 | AR51: =AO51*1.07 -> 337296.37 | AS51: =AR51 -> 337296.37 | AT51: =AS51 -> 337296.37 | AU51: =AT51 -> 337296.37 | AV51: =AU51 -> 337296.37 | AW51: =AV51 -> 337296.37 | AX51: =AW51 -> 337296.37 | AY51: =AX51 -> 337296.37 | AZ51: =AY51 -> 337296.37 | ... BC51: =BB51 -> 337296.37 | BD51: =SUM(AR51:BC51) -> 4047556.4 | BE51: =BD51*1.07 -> 4330885.4 | BF51: =BE51*1.07 -> 4634047.3
B52: Gastos Desarrollo | P52: 2905 | Q52: 20754.01 | R52: 24463.53 | S52: 25600 | T52: 58424.29 | U52: 61787.45 | V52: 19081 | W52: =W$18*ASSUMPTIONS!$C34 -> 127358.25 | X52: =X$18*ASSUMPTIONS!$C34 -> 114442.75 | Y52: =Y$18*ASSUMPTIONS!$C34 -> 113123.93 | Z52: =Z$18*ASSUMPTIONS!$C34 -> 101227.19 | AA52: =AA$18*ASSUMPTIONS!$C34 -> 108962.17 | AB52: =SUM(P52:AA52) -> 778129.58 | AD52: =AD$18*ASSUMPTIONS!$C34 -> 117113.36 | AE52: =AE$18*ASSUMPTIONS!$C34 -> 102765.25 | AF52: =AF$18*ASSUMPTIONS!$C34 -> 81887.114 | AG52: =AG$18*ASSUMPTIONS!$C34 -> 112113.76 | AH52: =AH$18*ASSUMPTIONS!$C34 -> 132013.3 | AI52: =AI$18*ASSUMPTIONS!$C34 -> 111898.79 | AJ52: =AJ$18*ASSUMPTIONS!$C34 -> 147796.67 | AK52: =AK$18*ASSUMPTIONS!$C34 -> 159197.82 | ... AO52: =AO$18*ASSUMPTIONS!$C34 -> 136202.71 | AP52: =SUM(AD52:AO52) -> 1511981.1 | AR52: =AR$18*ASSUMPTIONS!$C34 -> 146199.18 | AS52: =AS$18*ASSUMPTIONS!$C34 -> 128453.07 | AT52: =AT$18*ASSUMPTIONS!$C34 -> 103105.3 | AU52: =AU$18*ASSUMPTIONS!$C34 -> 137600.57 | AV52: =AV$18*ASSUMPTIONS!$C34 -> 164075.34 | AW52: =AW$18*ASSUMPTIONS!$C34 -> 139773.47 | AX52: =AX$18*ASSUMPTIONS!$C34 -> 182069.97 | AY52: =AY$18*ASSUMPTIONS!$C34 -> 196380.76 | ... BC52: =BC$18*ASSUMPTIONS!$C34 -> 168986.93 | BD52: =SUM(AR52:BC52) -> 1876456.1 | BE52: =BE$18*ASSUMPTIONS!$C34 -> 2186942 | BF52: =BF$18*ASSUMPTIONS!$C34 -> 2558780.5
B53: Nomina Admin | P53: 567507 | Q53: 435800.3 | R53: 338511.97 | S53: 381355.3 | T53: 367277.47 | U53: 420721.28 | V53: 524248.01 | W53: 323102.11 | X53: 323102.11 | Y53: 323102.11 | Z53: 323102.11 | AA53: 323102.11 | AB53: =SUM(P53:AA53) -> 4650931.9 | AD53: =AA53*1.07 -> 345719.25 | AE53: =AD53 -> 345719.25 | AF53: =AE53 -> 345719.25 | AG53: =AF53 -> 345719.25 | AH53: =AG53 -> 345719.25 | AI53: =AH53 -> 345719.25 | AJ53: =AI53 -> 345719.25 | AK53: =AJ53 -> 345719.25 | AL53: =AK53 -> 345719.25 | ... AO53: =AN53 -> 345719.25 | AP53: =SUM(AD53:AO53) -> 4148631.1 | AR53: =AO53*1.07 -> 369919.6 | AS53: =AR53 -> 369919.6 | AT53: =AS53 -> 369919.6 | AU53: =AT53 -> 369919.6 | AV53: =AU53 -> 369919.6 | AW53: =AV53 -> 369919.6 | AX53: =AW53 -> 369919.6 | AY53: =AX53 -> 369919.6 | AZ53: =AY53 -> 369919.6 | ... BC53: =BB53 -> 369919.6 | BD53: =SUM(AR53:BC53) -> 4439035.2 | BE53: =BD53*1.07 -> 4749767.7 | BF53: =BE53*1.07 -> 5082251.4
B54: Nomina Direccion | P54: 531888.62 | Q54: 690493.27 | R54: 350910.07 | S54: 680404.13 | T54: 637496.56 | U54: 761675.36 | V54: 842897.89 | W54: ='Subtotal Nom_Enero'!$E7 -> 679204.68 | X54: ='Subtotal Nom_Enero'!$E7 -> 679204.68 | Y54: ='Subtotal Nom_Enero'!$E7 -> 679204.68 | Z54: ='Subtotal Nom_Enero'!$E7 -> 679204.68 | AA54: ='Subtotal Nom_Enero'!$E7 -> 679204.68 | AB54: =SUM(P54:AA54) -> 7891789.3 | AD54: ='Subtotal Nom_Enero'!$E7 -> 679204.68 | AE54: ='Subtotal Nom_Enero'!$E7 -> 679204.68 | AF54: ='Subtotal Nom_Enero'!$E7 -> 679204.68 | AG54: ='Subtotal Nom_Enero'!$E7 -> 679204.68 | AH54: ='Subtotal Nom_Enero'!$E7 -> 679204.68 | AI54: ='Subtotal Nom_Enero'!$E7 -> 679204.68 | AJ54: ='Subtotal Nom_Enero'!$E7 -> 679204.68 | AK54: ='Subtotal Nom_Enero'!$E7 -> 679204.68 | ... AO54: ='Subtotal Nom_Enero'!$E7 -> 679204.68 | AP54: =SUM(AD54:AO54) -> 8150456.2 | AR54: ='Subtotal Nom_Enero'!$E7 -> 679204.68 | AS54: ='Subtotal Nom_Enero'!$E7 -> 679204.68 | AT54: ='Subtotal Nom_Enero'!$E7 -> 679204.68 | AU54: ='Subtotal Nom_Enero'!$E7 -> 679204.68 | AV54: ='Subtotal Nom_Enero'!$E7 -> 679204.68 | AW54: ='Subtotal Nom_Enero'!$E7 -> 679204.68 | AX54: ='Subtotal Nom_Enero'!$E7 -> 679204.68 | AY54: ='Subtotal Nom_Enero'!$E7 -> 679204.68 | ... BC54: ='Subtotal Nom_Enero'!$E7 -> 679204.68 | BD54: =SUM(AR54:BC54) -> 8150456.2 | BE54: =BD54*1.07 -> 8720988.1 | BF54: =BE54*1.07 -> 9331457.3
B55: Gastos Generales | P55: 3329777.7 | Q55: 2120848 | R55: 3698640.5 | S55: 1221806.7 | T55: 1774086 | U55: 420899.59 | V55: 820157.03 | W55: =SUM(Gastos!AA22:AA34) -> 178921.87 | X55: =SUM(Gastos!AB22:AB34) -> 178921.87 | Y55: =SUM(Gastos!AC22:AC34) -> 178921.87 | Z55: =SUM(Gastos!AD22:AD34) -> 178921.87 | AA55: =SUM(Gastos!AE22:AE34) -> 178921.87 | AB55: =SUM(P55:AA55) -> 14280825 | AD55: =SUM(Gastos!AG22:AG34) -> 315042.56 | AE55: =SUM(Gastos!AH22:AH34) -> 315042.56 | AF55: =SUM(Gastos!AI22:AI34) -> 315042.56 | AG55: =SUM(Gastos!AJ22:AJ34) -> 315042.56 | AH55: =SUM(Gastos!AK22:AK34) -> 315042.56 | AI55: =SUM(Gastos!AL22:AL34) -> 315042.56 | AJ55: =SUM(Gastos!AM22:AM34) -> 315042.56 | AK55: =SUM(Gastos!AN22:AN34) -> 315042.56 | ... AO55: =SUM(Gastos!AR22:AR34) -> 315042.56 | AP55: =SUM(AD55:AO55) -> 3780510.8 | AR55: =SUM(Gastos!AT22:AT34) -> 336771.7 | AS55: =SUM(Gastos!AU22:AU34) -> 336771.7 | AT55: =SUM(Gastos!AV22:AV34) -> 336771.7 | AU55: =SUM(Gastos!AW22:AW34) -> 336771.7 | AV55: =SUM(Gastos!AX22:AX34) -> 336771.7 | AW55: =SUM(Gastos!AY22:AY34) -> 336771.7 | AX55: =SUM(Gastos!AZ22:AZ34) -> 336771.7 | AY55: =SUM(Gastos!BA22:BA34) -> 336771.7 | ... BC55: =SUM(Gastos!BE22:BE34) -> 336771.7 | BD55: =SUM(AR55:BC55) -> 4041260.4 | BE55: =BD55*1.1 -> 4445386.4 | BF55: =BE55*1.1 -> 4889925.1
B56: Logistica | P56: 494367.56 | Q56: 396171.07 | R56: 343227.86 | S56: 535156.62 | T56: 519993.99 | U56: 560717.72 | V56: 570275.01 | W56: =W$18*ASSUMPTIONS!$C$37 -> 764149.51 | X56: =X$18*ASSUMPTIONS!$C$37 -> 686656.51 | Y56: =Y$18*ASSUMPTIONS!$C$37 -> 678743.58 | Z56: =Z$18*ASSUMPTIONS!$C$37 -> 607363.15 | AA56: =AA$18*ASSUMPTIONS!$C$37 -> 653773.02 | AB56: =SUM(P56:AA56) -> 6810595.6 | AD56: =AD$18*ASSUMPTIONS!$C$37 -> 702680.18 | AE56: =AE$18*ASSUMPTIONS!$C$37 -> 616591.51 | AF56: =AF$18*ASSUMPTIONS!$C$37 -> 491322.68 | AG56: =AG$18*ASSUMPTIONS!$C$37 -> 672682.58 | AH56: =AH$18*ASSUMPTIONS!$C$37 -> 792079.78 | AI56: =AI$18*ASSUMPTIONS!$C$37 -> 671392.71 | AJ56: =AJ$18*ASSUMPTIONS!$C$37 -> 886780.02 | AK56: =AK$18*ASSUMPTIONS!$C$37 -> 955186.89 | ... AO56: =AO$18*ASSUMPTIONS!$C$37 -> 817216.27 | AP56: =SUM(AD56:AO56) -> 9071886.7 | AR56: =AR$18*ASSUMPTIONS!$C$37 -> 877195.11 | AS56: =AS$18*ASSUMPTIONS!$C$37 -> 770718.45 | AT56: =AT$18*ASSUMPTIONS!$C$37 -> 618631.79 | AU56: =AU$18*ASSUMPTIONS!$C$37 -> 825603.44 | AV56: =AV$18*ASSUMPTIONS!$C$37 -> 984452.05 | AW56: =AW$18*ASSUMPTIONS!$C$37 -> 838640.8 | AX56: =AX$18*ASSUMPTIONS!$C$37 -> 1092419.8 | AY56: =AY$18*ASSUMPTIONS!$C$37 -> 1178284.6 | ... BC56: =BC$18*ASSUMPTIONS!$C$37 -> 1013921.6 | BD56: =SUM(AR56:BC56) -> 11258737 | BE56: =BE$18*ASSUMPTIONS!$C$37 -> 13121652 | BF56: =BF$18*ASSUMPTIONS!$C$37 -> 15352683
B57: Vales Gasolina (ex. Prestaciones) | P57: 22751.33 | Q57: 44615.91 | R57: 29533.49 | S57: 42890.43 | T57: 69844.77 | U57: 23806.94 | V57: 11521.21 | W57: =Gastos!AA33 -> 27000 | X57: =Gastos!AB33 -> 27000 | Y57: =Gastos!AC33 -> 27000 | Z57: =Gastos!AD33 -> 27000 | AA57: =Gastos!AE33 -> 27000 | AB57: =SUM(P57:AA57) -> 379964.08 | AD57: =Gastos!AG33 -> 27000 | AE57: =Gastos!AH33 -> 27000 | AF57: =Gastos!AI33 -> 27000 | AG57: =Gastos!AJ33 -> 27000 | AH57: =Gastos!AK33 -> 27000 | AI57: =Gastos!AL33 -> 27000 | AJ57: =Gastos!AM33 -> 27000 | AK57: =Gastos!AN33 -> 27000 | ... AO57: =Gastos!AR33 -> 27000 | AP57: =SUM(AD57:AO57) -> 324000 | AR57: =Gastos!AT33 -> 27000 | AS57: =Gastos!AU33 -> 27000 | AT57: =Gastos!AV33 -> 27000 | AU57: =Gastos!AW33 -> 27000 | AV57: =Gastos!AX33 -> 27000 | AW57: =Gastos!AY33 -> 27000 | AX57: =Gastos!AZ33 -> 27000 | AY57: =Gastos!BA33 -> 27000 | ... BC57: =Gastos!BE33 -> 27000 | BD57: =SUM(AR57:BC57) -> 324000 | BE57: =BD57*1.1 -> 356400 | BF57: =BE57*1.1 -> 392040
B58: Servicios Profesionales | P58: 17956.28 | Q58: 12766.69 | R58: 17048.96 | S58: 87039.85 | T58: 64575.39 | U58: 115361.26 | V58: 72816.01 | W58: =SUM(Gastos!AA39:AA45) -> 175000 | X58: =SUM(Gastos!AB39:AB45) -> 175000 | Y58: =SUM(Gastos!AC39:AC45) -> 175000 | Z58: =SUM(Gastos!AD39:AD45) -> 175000 | AA58: =SUM(Gastos!AE39:AE45) -> 175000 | AB58: =SUM(P58:AA58) -> 1262564.4 | AD58: =SUM(Gastos!AG39:AG45) -> 175000 | AE58: =SUM(Gastos!AH39:AH45) -> 175000 | AF58: =SUM(Gastos!AI39:AI45) -> 175000 | AG58: =SUM(Gastos!AJ39:AJ45) -> 175000 | AH58: =SUM(Gastos!AK39:AK45) -> 175000 | AI58: =SUM(Gastos!AL39:AL45) -> 175000 | AJ58: =SUM(Gastos!AM39:AM45) -> 15000 | AK58: =SUM(Gastos!AN39:AN45) -> 15000 | ... AO58: =SUM(Gastos!AR39:AR45) -> 15000 | AP58: =SUM(AD58:AO58) -> 1140000 | AR58: =SUM(Gastos!AT39:AT45) -> 15000 | AS58: =SUM(Gastos!AU39:AU45) -> 15000 | AT58: =SUM(Gastos!AV39:AV45) -> 15000 | AU58: =SUM(Gastos!AW39:AW45) -> 15000 | AV58: =SUM(Gastos!AX39:AX45) -> 15000 | AW58: =SUM(Gastos!AY39:AY45) -> 15000 | AX58: =SUM(Gastos!AZ39:AZ45) -> 15000 | AY58: =SUM(Gastos!BA39:BA45) -> 15000 | ... BC58: =SUM(Gastos!BE39:BE45) -> 15000 | BD58: =SUM(AR58:BC58) -> 180000 | BE58: =BD58 -> 180000 | BF58: =BE58 -> 180000
B59: Seguros | P59: 176752.89 | Q59: 206716.76 | R59: 81329.9 | S59: 178085.96 | T59: 88176.58 | U59: 29074.4 | V59: -60784.16 | W59: =SUM(Gastos!AA55:AA62) -> 98690.106 | X59: =SUM(Gastos!AB55:AB62) -> 98690.106 | Y59: =SUM(Gastos!AC55:AC62) -> 98690.106 | Z59: =SUM(Gastos!AD55:AD62) -> 98690.106 | AA59: =SUM(Gastos!AE55:AE62) -> 98690.106 | AB59: =SUM(P59:AA59) -> 1192802.9 | AD59: =SUM(Gastos!AG55:AG62) -> 98690.106 | AE59: =SUM(Gastos!AH55:AH62) -> 98690.106 | AF59: =SUM(Gastos!AI55:AI62) -> 98690.106 | AG59: =SUM(Gastos!AJ55:AJ62) -> 98690.106 | AH59: =SUM(Gastos!AK55:AK62) -> 98690.106 | AI59: =SUM(Gastos!AL55:AL62) -> 98690.106 | AJ59: =SUM(Gastos!AM55:AM62) -> 98690.106 | AK59: =SUM(Gastos!AN55:AN62) -> 98690.106 | ... AO59: =SUM(Gastos!AR55:AR62) -> 98690.106 | AP59: =SUM(AD59:AO59) -> 1184281.3 | AR59: =SUM(Gastos!AT55:AT62) -> 98690.106 | AS59: =SUM(Gastos!AU55:AU62) -> 98690.106 | AT59: =SUM(Gastos!AV55:AV62) -> 98690.106 | AU59: =SUM(Gastos!AW55:AW62) -> 98690.106 | AV59: =SUM(Gastos!AX55:AX62) -> 98690.106 | AW59: =SUM(Gastos!AY55:AY62) -> 98690.106 | AX59: =SUM(Gastos!AZ55:AZ62) -> 98690.106 | AY59: =SUM(Gastos!BA55:BA62) -> 98690.106 | ... BC59: =SUM(Gastos!BE55:BE62) -> 98690.106 | BD59: =SUM(AR59:BC59) -> 1184281.3 | BE59: =BD59*1.1 -> 1302709.4 | BF59: =BE59*1.1 -> 1432980.3
B60: Amortizacion (Arrendamientos) | P60: 556984.4 | Q60: 574355.51 | R60: 551743.55 | S60: 658037.47 | T60: 455677.03 | U60: 762389.9 | V60: 131356.17 | W60: 238809.71 | X60: 243402.5 | Y60: 277247.12 | Z60: 249398.02 | AA60: 254239.06 | AB60: =SUM(P60:AA60) -> 4953640.4 | AD60: 254239.06 | AE60: 254239.06 | AF60: 254239.06 | AG60: 254239.06 | AH60: 254239.06 | AI60: 254239.06 | AJ60: 254239.06 | AK60: 254239.06 | AL60: 254239.06 | AM60: 254239.06 | AN60: 254239.06 | AO60: 254239.06 | AP60: =SUM(AD60:AO60) -> 3050868.7 | AR60: 254239.06 | AS60: 254239.06 | AT60: 254239.06 | AU60: 254239.06 | AV60: 254239.06 | AW60: 254239.06 | AX60: 254239.06 | AY60: 254239.06 | AZ60: 254239.06 | BA60: 254239.06 | BB60: 254239.06 | BC60: 254239.06 | BD60: =SUM(AR60:BC60) -> 3050868.7 | BE60: =BD60 -> 3050868.7 | BF60: =BE60 -> 3050868.7
B61: UTILIDAD OPERATIVA | P61: =P41-SUM(P43:P60) -> -1436385.9 | Q61: =Q41-SUM(Q43:Q60) -> 174173.11 | R61: =R41-SUM(R43:R60) -> -3170876.7 | S61: =S41-SUM(S43:S60) -> 1081904.6 | T61: =T41-SUM(T43:T60) -> 1358640.8 | U61: =U41-SUM(U43:U60) -> 654217.09 | V61: =V41-SUM(V43:V60) -> 3025889.1 | W61: =W41-SUM(W43:W60) -> 4473125.1 | ... AB61: =AB41-SUM(AB43:AB60) -> 19665572 | AD61: =AD41-SUM(AD43:AD60) -> 3952477.9 | AE61: =AE41-SUM(AE43:AE60) -> 2711042.8 | AF61: =AF41-SUM(AF43:AF60) -> 952096.71 | AG61: =AG41-SUM(AG43:AG60) -> 3278401.9 | AH61: =AH41-SUM(AH43:AH60) -> 5031065.1 | AI61: =AI41-SUM(AI43:AI60) -> 3393476.2 | AJ61: =AJ41-SUM(AJ43:AJ60) -> 6393222.5 | AK61: =AK41-SUM(AK43:AK60) -> 7337655.6 | ... AP61: =AP41-SUM(AP43:AP60) -> 55133517 | AR61: =AR41-SUM(AR43:AR60) -> 6515389.1 | AS61: =AS41-SUM(AS43:AS60) -> 4976612.6 | AT61: =AT41-SUM(AT43:AT60) -> 2838581.2 | AU61: =AU41-SUM(AU43:AU60) -> 5465198.2 | AV61: =AV41-SUM(AV43:AV60) -> 7806133.4 | AW61: =AW41-SUM(AW43:AW60) -> 5732605.8 | AX61: =AX41-SUM(AX43:AX60) -> 9064482.5 | AY61: =AY41-SUM(AY43:AY60) -> 10252505 | ... BF61: =BF41-SUM(BF43:BF60) -> 1.4430527e+08
B62: UTILIDAD OPERATIVA | P62: =P61/P$22 -> -0.081594431 | Q62: =Q61/Q$22 -> 0.010867609 | R62: =R61/R$22 -> -0.25379442 | S62: =S61/S$22 -> 0.061827174 | T62: =T61/T$22 -> 0.065406421 | U62: =U61/U$22 -> 0.037795886 | V62: =V61/V$22 -> 0.13020878 | W62: =W61/W$22 -> 0.17919582 | ... AB62: =AB61/AB$22 -> 0.083432575 | AD62: =AD61/AD$22 -> 0.1721896 | AE62: =AE61/AE$22 -> 0.13459658 | AF62: =AF61/AF$22 -> 0.059321132 | AG62: =AG61/AG$22 -> 0.14919257 | AH62: =AH61/AH$22 -> 0.19444026 | AI62: =AI61/AI$22 -> 0.15472602 | AJ62: =AJ61/AJ$22 -> 0.22069836 | AK62: =AK61/AK$22 -> 0.23516038 | ... AP62: =AP61/AP$22 -> 0.18604297 | AR62: =AR61/AR$22 -> 0.22737323 | AS62: =AS61/AS$22 -> 0.19766658 | AT62: =AT61/AT$22 -> 0.14046375 | AU62: =AU61/AU$22 -> 0.20264207 | AV62: =AV61/AV$22 -> 0.24273733 | AW62: =AW61/AW$22 -> 0.2092528 | AX62: =AX61/AX$22 -> 0.25400872 | AY62: =AY61/AY$22 -> 0.26636366 | ... BF62: =BF61/BF$22 -> 0.28921082
B63: Depreciacion | P63: 182040.33 | Q63: 185015.34 | R63: 188217.45 | S63: 205396.93 | T63: 208858 | U63: 216813.35 | V63: 219917.39 | AB63: =SUM(P63:AA63) -> 1406258.8 | AP63: =SUM(AD63:AO63) -> 0 | BD63: =SUM(AR63:BC63) -> 0 | BE63: =SUM(AS63:BD63) -> 0 | BF63: =SUM(AT63:BE63) -> 0
B64: Intereses | P64: 1125368.9 | Q64: 1176022.9 | R64: 1028103.3 | S64: 1330732.1 | T64: 1150136.9 | U64: 784790.69 | V64: 1032556.8 | W64: ='Interest Expense'!S31 -> 1267197.2 | X64: ='Interest Expense'!T31 -> 1435839.3 | Y64: ='Interest Expense'!U31 -> 1503784.3 | Z64: ='Interest Expense'!V31 -> 1497283.3 | AA64: ='Interest Expense'!W31 -> 1490677.2 | AB64: =SUM(P64:AA64) -> 14822493 | AD64: ='Interest Expense'!Y31 -> 1483963.4 | AE64: ='Interest Expense'!Z31 -> 1477139.7 | AF64: ='Interest Expense'!AA31 -> 1456401.4 | AG64: ='Interest Expense'!AB31 -> 1430517.1 | AH64: ='Interest Expense'!AC31 -> 1409802 | AI64: ='Interest Expense'!AD31 -> 1385909.2 | AJ64: ='Interest Expense'!AE31 -> 1365318.4 | AK64: ='Interest Expense'!AF31 -> 1341888.3 | ... AO64: ='Interest Expense'!AJ31 -> 1258523.4 | AP64: =SUM(AD64:AO64) -> 16508198 | AR64: ='Interest Expense'!AL31 -> 725835.34 | AS64: ='Interest Expense'!AM31 -> 705709.12 | AT64: ='Interest Expense'!AN31 -> 685472.38 | AU64: ='Interest Expense'!AO31 -> 665122.74 | AV64: ='Interest Expense'!AP31 -> 644657.74 | AW64: ='Interest Expense'!AQ31 -> 624074.88 | AX64: ='Interest Expense'!AR31 -> 603371.62 | AY64: ='Interest Expense'!AS31 -> 582545.34 | ... BC64: ='Interest Expense'!AW31 -> 501626.27 | BD64: =SUM(AR64:BC64) -> 7363493.7 | BE64: =SUM('Interest Expense'!AY31:'Interest Expense'!BJ31) -> 4397043.5 | BF64: =SUM('Interest Expense'!AZ31:'Interest Expense'!BK31) -> 3915676.3
B65: Intereses (% of EBITDA) | P65: =P64/P61 -> -0.78347252 | Q65: =Q64/Q61 -> 6.7520347 | R65: =R64/R61 -> -0.32423314 | S65: =S64/S61 -> 1.2299902 | T65: =T64/T61 -> 0.84653489 | U65: =U64/U61 -> 1.1995876 | V65: =V64/V61 -> 0.34124081 | W65: =W64/W61 -> 0.28329125 | ... AB65: =AB64/AB61 -> 0.75372803 | AD65: =AD64/AD61 -> 0.37545141 | AE65: =AE64/AE61 -> 0.54486032 | AF65: =AF64/AF61 -> 1.529678 | AG65: =AG64/AG61 -> 0.43634584 | AH65: =AH64/AH61 -> 0.28021939 | AI65: =AI64/AI61 -> 0.40840399 | AJ65: =AJ64/AJ61 -> 0.21355716 | AK65: =AK64/AK61 -> 0.18287698 | ... AP65: =AP64/AP61 -> 0.29942219 | AR65: =AR64/AR61 -> 0.11140322 | AS65: =AS64/AS61 -> 0.14180512 | AT65: =AT64/AT61 -> 0.24148416 | AU65: =AU64/AU61 -> 0.12170148 | AV65: =AV64/AV61 -> 0.08258349 | AW65: =AW64/AW61 -> 0.10886408 | AX65: =AX64/AX61 -> 0.066564375 | AY65: =AY64/AY61 -> 0.056819806 | ... BF65: =BF64/BF61 -> 0.027134673
B66: Impuestos | V66: =IF((V61-V64)>0,(V61-V64)*0.3,0) -> 597999.68 | W66: =IF((W61-W64)>0,(W61-W64)*0.3,0) -> 961778.36 | X66: =IF((X61-X64)>0,(X61-X64)*0.3,0) -> 714359.95 | Y66: =IF((Y61-Y64)>0,(Y61-Y64)*0.3,0) -> 664058.55 | Z66: =IF((Z61-Z64)>0,(Z61-Z64)*0.3,0) -> 361134.09 | AA66: =IF((AA61-AA64)>0,(AA61-AA64)*0.3,0) -> 533637.6 | AB66: =SUM(P66:AA66) -> 3832968.2 | AD66: =IF((AD61-AD64)>0,(AD61-AD64)*0.3,0) -> 740554.36 | AE66: =IF((AE61-AE64)>0,(AE61-AE64)*0.3,0) -> 370170.95 | AF66: =IF((AF61-AF64)>0,(AF61-AF64)*0.3,0) -> 0 | AG66: =IF((AG61-AG64)>0,(AG61-AG64)*0.3,0) -> 554365.47 | AH66: =IF((AH61-AH64)>0,(AH61-AH64)*0.3,0) -> 1086378.9 | AI66: =IF((AI61-AI64)>0,(AI61-AI64)*0.3,0) -> 602270.09 | AJ66: =IF((AJ61-AJ64)>0,(AJ61-AJ64)*0.3,0) -> 1508371.2 | AK66: =IF((AK61-AK64)>0,(AK61-AK64)*0.3,0) -> 1798730.2 | ... AO66: =IF((AO61-AO64)>0,(AO61-AO64)*0.3,0) -> 1263741 | AP66: =SUM(AD66:AO66) -> 11738887 | BD66: =SUM(AR66:BC66) -> 0 | BE66: =SUM(AS66:BD66) -> 0 | BF66: =SUM(AT66:BE66) -> 0
B67: TOTAL OP EXPENSES | P67: =SUM(P38:P40)+SUM(P43:P59) -> 7277264.6 | Q67: =SUM(Q38:Q40)+SUM(Q43:Q59) -> 6417789.3 | R67: =SUM(R38:R40)+SUM(R43:R59) -> 7778920.6 | S67: =SUM(S38:S40)+SUM(S43:S59) -> 6344160.6 | T67: =SUM(T38:T40)+SUM(T43:T59) -> 7094050.2 | U67: =SUM(U38:U40)+SUM(U43:U59) -> 5713130.8 | V67: =SUM(V38:V40)+SUM(V43:V59) -> 7158846.6 | W67: =SUM(W38:W40)+SUM(W43:W59) -> 5867123.3 | ... AA67: =SUM(AA38:AA40)+SUM(AA43:AA59) -> 5817624.3 | AB67: =SUM(P67:AA67) -> 76662660 | AD67: =SUM(AD38:AD40)+SUM(AD43:AD59) -> 6393618.9 | AE67: =SUM(AE38:AE40)+SUM(AE43:AE59) -> 6141069.3 | AF67: =SUM(AF38:AF40)+SUM(AF43:AF59) -> 5878044.4 | AG67: =SUM(AG38:AG40)+SUM(AG43:AG59) -> 5774322.6 | AH67: =SUM(AH38:AH40)+SUM(AH43:AH59) -> 6584725.4 | AI67: =SUM(AI38:AI40)+SUM(AI43:AI59) -> 6365698.2 | AJ67: =SUM(AJ38:AJ40)+SUM(AJ43:AJ59) -> 6397707.7 | AK67: =SUM(AK38:AK40)+SUM(AK43:AK59) -> 6670147.5 | ... AO67: =SUM(AO38:AO40)+SUM(AO43:AO59) -> 6493335.1 | AP67: =SUM(AD67:AO67) -> 76197588 | AR67: =SUM(AR38:AR40)+SUM(AR43:AR59) -> 7096830.5 | AS67: =SUM(AS38:AS40)+SUM(AS43:AS59) -> 6777127.1 | AT67: =SUM(AT38:AT40)+SUM(AT43:AT59) -> 6452235.8 | AU67: =SUM(AU38:AU40)+SUM(AU43:AU59) -> 6271803.5 | AV67: =SUM(AV38:AV40)+SUM(AV43:AV59) -> 7326039.6 | AW67: =SUM(AW38:AW40)+SUM(AW43:AW59) -> 7058026.5 | AX67: =SUM(AX38:AX40)+SUM(AX43:AX59) -> 7263837.8 | AY67: =SUM(AY38:AY40)+SUM(AY43:AY59) -> 7610592.1 | ... BF67: =SUM(BF38:BF40)+SUM(BF43:BF59) -> 1.0973279e+08
B68: TOTAL OP EXPENSES | P68: =P67/P18 -> 0.38836647 | Q68: =Q67/Q18 -> 0.39031854 | R68: =R67/R18 -> 0.59372289 | S68: =S67/S18 -> 0.35366758 | T68: =T67/T18 -> 0.33585869 | U68: =U67/U18 -> 0.31910147 | V68: =V67/V18 -> 0.30273207 | W68: =W67/W18 -> 0.23033935 | ... AB68: =AB67/AB18 -> 0.31689657 | AD68: =AD67/AD18 -> 0.2729671 | AE68: =AE67/AE18 -> 0.29879114 | AF68: =AF67/AF18 -> 0.35891144 | AG68: =AG67/AG18 -> 0.25752068 | AH68: =AH67/AH18 -> 0.24939629 | AI68: =AI67/AI18 -> 0.28444 | AJ68: =AJ67/AJ18 -> 0.21643613 | AK68: =AK67/AK18 -> 0.20949243 | ... AP68: =AP67/AP18 -> 0.2519793 | AR68: =AR67/AR18 -> 0.24271101 | AS68: =AS67/AS18 -> 0.26379778 | AT68: =AT67/AT18 -> 0.31289545 | AU68: =AU67/AU18 -> 0.22789889 | AV68: =AV67/AV18 -> 0.2232523 | AW68: =AW67/AW18 -> 0.25248091 | AX68: =AX67/AX18 -> 0.19947929 | AY68: =AY67/AY18 -> 0.19377133 | ... BF68: =BF67/BF18 -> 0.21442399
B69: TOTAL EXPENSES | P69: =P67+P34+SUM(P63:P64) -> 19790780 | Q69: =Q67+Q34+SUM(Q63:Q64) -> 16843362 | R69: =R67+R34+SUM(R63:R64) -> 16501112 | S69: =S67+S34+SUM(S63:S64) -> 17295040 | T69: =T67+T34+SUM(T63:T64) -> 20316962 | U69: =U67+U34+SUM(U63:U64) -> 16894211 | V69: =V67+V34+SUM(V63:V64) -> 21333977 | W69: =W67+W34+SUM(W63:W64) -> 21517480 | ... AA69: =AA67+AA34+SUM(AA63:AA64) -> 19323554 | AB69: =SUM(P69:AA69) -> 2.2769152e+08 | AD69: =AD67+AD34+SUM(AD63:AD64) -> 20231466 | AE69: =AE67+AE34+SUM(AE63:AE64) -> 18653847 | AF69: =AF67+AF34+SUM(AF63:AF64) -> 16299940 | AG69: =AG67+AG34+SUM(AG63:AG64) -> 19872174 | AH69: =AH67+AH34+SUM(AH63:AH64) -> 21999104 | AI69: =AI67+AI34+SUM(AI63:AI64) -> 19670356 | AJ69: =AJ67+AJ34+SUM(AJ63:AJ64) -> 23686004 | AK69: =AK67+AK34+SUM(AK63:AK64) -> 24952765 | ... AO69: =AO67+AO34+SUM(AO63:AO64) -> 22229023 | AP69: =SUM(AD69:AO69) -> 2.5467211e+08 | AR69: =AR67+AR34+SUM(AR63:AR64) -> 22611247 | AS69: =AS67+AS34+SUM(AS63:AS64) -> 20651660 | AT69: =AT67+AT34+SUM(AT63:AT64) -> 17801291 | AU69: =AU67+AU34+SUM(AU63:AU64) -> 21915398 | AV69: =AV67+AV34+SUM(AV63:AV64) -> 24743052 | AW69: =AW67+AW34+SUM(AW63:AW64) -> 22032829 | AX69: =AX67+AX34+SUM(AX63:AX64) -> 26970364 | AY69: =AY67+AY34+SUM(AY63:AY64) -> 28566430 | ... BF69: =BF67+BF34+SUM(BF63:BF64) -> 3.6831565e+08
B70: TOTAL EXPENSES | P70: =P69/P22 -> 1.1242226 | Q70: =Q69/Q22 -> 1.0509491 | R70: =R69/R22 -> 1.3207357 | S70: =S69/S22 -> 0.98835277 | T70: =T69/T22 -> 0.97808027 | U70: =U69/U22 -> 0.97602416 | V70: =V69/V22 -> 0.9180347 | W70: =W69/W22 -> 0.86200194 | ... AB70: =AB69/AB22 -> 0.96599733 | AD70: =AD69/AD22 -> 0.88138331 | AE70: =AE69/AE22 -> 0.92611741 | AF70: =AF69/AF22 -> 1.0155805 | AG70: =AG69/AG22 -> 0.90433715 | AH70: =AH69/AH22 -> 0.85021986 | AI70: =AI69/AI22 -> 0.89687264 | AJ70: =AJ69/AJ22 -> 0.81765685 | AK70: =AK69/AK22 -> 0.79969708 | ... AP70: =AP69/AP22 -> 0.85936755 | AR70: =AR69/AR22 -> 0.78908448 | AS70: =AS69/AS22 -> 0.8202654 | AT70: =AT69/AT22 -> 0.88087531 | AU70: =AU69/AU22 -> 0.81259294 | AV70: =AV69/AV22 -> 0.76940302 | AW70: =AW69/AW22 -> 0.80424703 | AX70: =AX69/AX22 -> 0.75577482 | AY70: =AY69/AY22 -> 0.74216585 | ... BF70: =BF69/BF22 -> 0.73816342
B71: UTILIDAD NETA | P71: =P61-SUM(P63:P64) -> -2743795.1 | Q71: =Q61-SUM(Q63:Q64) -> -1186865.1 | R71: =R61-SUM(R63:R64) -> -4387197.5 | S71: =S61-SUM(S63:S64) -> -454224.36 | T71: =T61-SUM(T63:T64) -> -354.04 | U71: =U61-SUM(U63:U66) -> -347388.15 | V71: =V61-SUM(V63:V66) -> 1175414.9 | W71: =W61-SUM(W63:W66) -> 2244149.2 | X71: =X61-SUM(X63:X66) -> 1666839.5 | Y71: =Y61-SUM(Y63:Y66) -> 1549469.6 | Z71: =Z61-SUM(Z63:Z66) -> 842645.65 | AA71: =AA61-SUM(AA63:AA66) -> 1245153.9 | AB71: =SUM(P71:AA71) -> -396151.48 | AD71: =AD61-SUM(AD63:AD66) -> 1727959.8 | AE71: =AE61-SUM(AE63:AE66) -> 863731.68 | AF71: =AF61-SUM(AF63:AF66) -> -504306.18 | AG71: =AG61-SUM(AG63:AG66) -> 1293519 | AH71: =AH61-SUM(AH63:AH66) -> 2534883.9 | AI71: =AI61-SUM(AI63:AI66) -> 1405296.5 | AJ71: =AJ61-SUM(AJ63:AJ66) -> 3519532.6 | AK71: =AK61-SUM(AK63:AK66) -> 4197036.9 | ... AO71: =AO61-SUM(AO63:AO66) -> 2948728.8 | AP71: =SUM(AD71:AO71) -> 26886427 | AR71: =AR61-SUM(AR63:AR66) -> 5789553.6 | AS71: =AS61-SUM(AS63:AS66) -> 4270903.3 | AT71: =AT61-SUM(AT63:AT66) -> 2153108.5 | AU71: =AU61-SUM(AU63:AU66) -> 4800075.4 | AV71: =AV61-SUM(AV63:AV66) -> 7161475.5 | AW71: =AW61-SUM(AW63:AW66) -> 5108530.8 | AX71: =AX61-SUM(AX63:AX66) -> 8461110.9 | AY71: =AY61-SUM(AY63:AY66) -> 9669959.5 | ... BF71: =BF61-SUM(BF63:BF66) -> 1.4038959e+08
B72: UTILIDAD NETA | P72: =P71/P$22 -> -0.15586229 | Q72: =Q71/Q$22 -> -0.074054977 | R72: =R71/R$22 -> -0.35114776 | S72: =S71/S$22 -> -0.025957379 | T72: =T71/T$22 -> -1.7043864e-05 | U72: =U71/U$22 -> -0.02006955 | V72: =V71/V$22 -> 0.050579955 | W72: =W71/W$22 -> 0.089901838 | ... AB72: =AB71/AB$22 -> -0.0016807005 | AD72: =AD71/AD$22 -> 0.075278527 | AE72: =AE71/AE$22 -> 0.042882144 | AF72: =AF71/AF$22 -> -0.031421192 | AG72: =AG71/AG$22 -> 0.058865089 | AH72: =AH71/AH$22 -> 0.097968019 | AI72: =AI71/AI$22 -> 0.064074689 | AJ72: =AJ71/AJ$22 -> 0.12149664 | AK72: =AK71/AK$22 -> 0.13450846 | ... AP72: =AP71/AP$22 -> 0.090725768 | AR72: =AR71/AR$22 -> 0.20204312 | AS72: =AS71/AS$22 -> 0.16963645 | AT72: =AT71/AT$22 -> 0.10654397 | AU72: =AU71/AU$22 -> 0.17798022 | AV72: =AV71/AV$22 -> 0.22269123 | AW72: =AW71/AW$22 -> 0.18647268 | AX72: =AX71/AX$22 -> 0.23710079 | AY72: =AY71/AY$22 -> 0.25122893 | ... BF72: =BF71/BF$22 -> 0.28136318
S74: =S67+SUM(S27:S33) -> 9128302.2 | T74: =T67+SUM(T27:T33) -> 10087400 | U74: =U67+SUM(U27:U33) -> 8756062.1 | V74: =V67+SUM(V27:V33) -> 10118264 | W74: =W67+SUM(W27:W33) -> 8757766.1 | X74: =X67+SUM(X27:X33) -> 8104982.3 | Y74: =Y67+SUM(Y27:Y33) -> 8280311.2 | Z74: =Z67+SUM(Z27:Z33) -> 8064751.2 | AA74: =AA67+SUM(AA27:AA33) -> 8234062.5
S75: =S74/S18 -> 0.50887497 | T75: =T74/T18 -> 0.477575 | U75: =U74/U18 -> 0.4890615 | V75: =V74/V18 -> 0.42787938 | W75: =W74/W18 -> 0.34382405 | X75: =X74/X18 -> 0.35410641 | Y75: =Y74/Y18 -> 0.36598407 | Z75: =Z74/Z18 -> 0.39834905 | AA75: =AA74/AA18 -> 0.37784042
P78: -2646016.6 | Q78: -1418262.6 | R78: -4558114.9 | S78: -375338.21 | T78: 11240 | U78: -307420.95 | V78: 1774466.3

Sheet BEAR V. ROLLING
D7: PPTO DIC 24 | F7: ROLLING FCST | G7: % | H7: FCST BEAR CASE | I7: % | J7: BEAR V. ROLLING
C8: NET REVENUE | D8: =IS!AA18 -> 2.3278528e+08 | F8: ='IS (ROLLING)'!AB18 -> 2.4191698e+08 | G8: =F8/F$8 -> 1 | H8: ='IS (BEAR)'!AA18 -> 2.2150807e+08 | I8: =H8/H$8 -> 1 | J8: =H8/F8-1 -> -0.084363292
C9: UTILIDAD BRUTA | D9: =IS!AA35 -> 94673025 | F9: ='IS (ROLLING)'!AB36 -> 1.0128187e+08 | G9: =F9/F$8 -> 0.41866376 | H9: ='IS (BEAR)'!AA35 -> 86404582 | I9: =H9/H$8 -> 0.3900742 | J9: =H9/F9-1 -> -0.14688996
C10: UTILIDAD OPERATIVA | D10: =IS!AA59 -> 32130402 | F10: ='IS (ROLLING)'!AB61 -> 19665572 | G10: =F10/F$8 -> 0.081290582 | H10: ='IS (BEAR)'!AA59 -> 28371218 | I10: =H10/H$8 -> 0.1280821 | J10: =H10/F10-1 -> 0.44268459
C11: UTILIDAD NETA | D11: =IS!AA70 -> 7005782.9 | F11: ='IS (ROLLING)'!AB71 -> -396151.48 | G11: =F11/F$8 -> -0.0016375514 | H11: ='IS (BEAR)'!AA70 -> 5189922.1 | I11: =H11/H$8 -> 0.023429946 | J11: =H11/F11-1 -> -14.100853

Sheet Interest Expense
B2: Interest Expense
L3: 1 | M3: 2 | N3: 3 | O3: 4 | P3: 5 | Q3: 6 | R3: 7 | S3: 8 | T3: 9 | U3: 10 | V3: 11 | W3: 12 | Y3: 1 | Z3: 2 | AA3: 3 | AB3: 4 | AC3: 5 | AD3: 6 | AE3: 7 | AF3: 8 | AG3: 9 | AH3: 10 | AI3: 11 | AJ3: 12
L4: 1 | M4: 1 | N4: 1 | O4: 2 | P4: 2 | Q4: 2 | R4: 3 | S4: 3 | T4: 3 | U4: 4 | V4: 4 | W4: 4
B5: Acreedor | C5: Monto Capital BOP | D5: Tasa Annual | H5: PROPUESTA | L5: 2025 | M5: 2025 | N5: 2025 | O5: 2025 | P5: 2025 | Q5: 2025 | R5: 2025 | S5: 2025 | T5: 2025 | U5: 2025 | V5: 2025 | W5: 2025 | Y5: 2026 | Z5: 2026 | AA5: 2026 | AB5: 2026 | AC5: 2026 | AD5: 2026 | AE5: 2026 | AF5: 2026 | AG5: 2026 | AH5: 2026 | AI5: 2026 | AJ5: 2026 | AL5: 2027 | AM5: 2027 | AN5: 2027 | AO5: 2027 | AP5: 2027 | AQ5: 2027 | AR5: 2027 | AS5: 2027 | AT5: 2027 | AU5: 2027 | AV5: 2027 | AW5: 2027 | AY5: 2028 | AZ5: 2028 | BA5: 2028 | BB5: 2028 | BC5: 2028 | BD5: 2028 | BE5: 2028 | BF5: 2028 | BG5: 2028 | BH5: 2028 | BI5: 2028 | BJ5: 2028
B6: CAPIX | C6: =18248000+5000000+2000000+1500000 -> 26748000 | D6: 0.23 | E6: =C6/SUM(C$6:C$13) -> 0.25921801 | F6: =E6*D6 -> 0.059620143 | H6: 22500000 | I6: =H6/SUM(H$6:H$16) -> 0.24892885 | J6: =I6*D6 -> 0.057253635 | K6: =H6*(D6/12) -> 431250 | L6: =$C6*($D6/12) -> 512670 | M6: =$C6*($D6/12) -> 512670 | N6: =$C6*($D6/12) -> 512670 | O6: =$C6*($D6/12) -> 512670 | P6: =($C6+3248000)*($D6/12) -> 574923.33 | Q6: =($C6+3248000)*($D6/12) -> 574923.33 | R6: =($C6+3248000)*($D6/12) -> 574923.33 | S6: =($C6+3248000)*($D6/12) -> 574923.33 | T6: =($C6+3248000)*($D6/12) -> 574923.33 | U6: =($C6+3248000)*($D6/12) -> 574923.33 | V6: =($C6+3248000)*($D6/12) -> 574923.33 | W6: =($C6+3248000)*($D6/12) -> 574923.33 | Y6: =($C6+3248000)*($D6/12) -> 574923.33 | Z6: =($C6+3248000)*($D6/12) -> 574923.33 | AA6: =($C6+3248000)*($D6/12) -> 574923.33 | AB6: =($C6+3248000)*($D6/12) -> 574923.33 | AC6: =($C6+3248000)*($D6/12) -> 574923.33 | AD6: =($C6+3248000)*($D6/12) -> 574923.33 | AE6: =($C6+3248000)*($D6/12) -> 574923.33 | AF6: =($C6+3248000)*($D6/12) -> 574923.33 | ... AJ6: =($C6+3248000)*($D6/12) -> 574923.33
B7: Capital X | C7: 26000000 | D7: 0.275 | E7: =C7/SUM(C$6:C$13) -> 0.25196906 | F7: =E7*D7 -> 0.06929149 | I7: =H7/SUM(H$6:H$16) -> 0 | J7: =I7*D7 -> 0 | K7: =H7*(D7/12) -> 0 | L7: =$C7*($D7/12) -> 595833.33 | M7: =$C7*($D7/12) -> 595833.33 | N7: =$C7*($D7/12) -> 595833.33 | O7: =$C7*($D7/12) -> 595833.33 | P7: =$C7*($D7/12) -> 595833.33 | Q7: =$C7*($D7/12) -> 595833.33 | R7: =$C7*($D7/12) -> 595833.33 | S7: =$C7*($D7/12) -> 595833.33 | ... W7: =$C7*($D7/12) -> 595833.33 | Y7: =$C7*($D7/12) -> 595833.33 | Z7: =$C7*($D7/12) -> 595833.33 | AA7: =$C7*($D7/12) -> 595833.33 | AB7: =$C7*($D7/12) -> 595833.33 | AC7: =$C7*($D7/12) -> 595833.33 | AD7: =$C7*($D7/12) -> 595833.33 | AE7: =$C7*($D7/12) -> 595833.33 | AF7: =$C7*($D7/12) -> 595833.33 | ... AJ7: =$C7*($D7/12) -> 595833.33
B8: Arrendamientos | C8: 15645232 | D8: 0.27 | E8: =C8/SUM(C$6:C$13) -> 0.15161978 | F8: =E8*D8 -> 0.040937341 | I8: =H8/SUM(H$6:H$16) -> 0 | J8: =I8*D8 -> 0 | K8: =H8*(D8/12) -> 0 | L8: 338929.63 | M8: 333802.95 | N8: 325250.28 | O8: 321066.42 | P8: 316790.21 | Q8: 312419.6 | R8: 307267 | S8: 302773.73 | T8: 298180.94 | U8: 292891.11 | V8: 288155.28 | W8: 283314.24 | Y8: 278365.62 | Z8: 273307.01 | AA8: 268135.94 | AB8: 257818.86 | AC8: 252671.01 | AD8: 244345.44 | AE8: 239321.9 | AF8: 231459.01 | AG8: 225281.19 | AH8: 220319.96 | AI8: 215249.6 | AJ8: 210362.98 | AL8: 205370.48 | AM8: 200269.81 | AN8: 195058.63 | AO8: 189734.54 | AP8: 184295.1 | AQ8: 178737.8 | AR8: 173060.09 | AS8: 167259.36 | AT8: 161332.95 | AU8: 155278.14 | AV8: 149092.14 | AW8: 142772.11 | AY8: 136315.14 | AZ8: 129718.28 | BA8: 122978.48 | BB8: 116092.65 | BC8: 109057.63 | BD8: 101870.18 | BE8: 94527.011 | BF8: 87024.735 | BG8: 79359.91 | BH8: 71529.014 | BI8: 63528.448 | BJ8: 55354.537 | BL8: 47003.524 | BM8: 38471.573 | BN8: 29754.763 | BO8: 20849.089
B9: Banorte-5,750,000 | C9: ='CREDITOS'!G49 -> 3641666.7 | D9: 0.15 | E9: =C9/SUM(C$6:C$13) -> 0.03529182 | F9: =E9*D9 -> 0.005293773 | I9: =H9/SUM(H$6:H$16) -> 0 | J9: =I9*D9 -> 0 | K9: =H9*(D9/12) -> 0 | L9: 39151.112 | M9: 37927.64 | N9: 36704.168 | O9: 35480.696 | P9: 34257.224 | Q9: 33033.751 | R9: 31810.279 | S9: 30586.807 | T9: 29363.335 | U9: 28139.863 | V9: 26916.391 | W9: 25692.918 | Y9: 24469.446 | Z9: 23245.974 | AA9: 22022.502 | AB9: 20799.03 | AC9: 19575.557 | AD9: 18352.085 | AE9: 17128.613 | AF9: 15905.141 | AG9: 14681.669 | AH9: 13458.197 | AI9: 12234.724 | AJ9: 11011.252 | AL9: 9787.78 | AM9: 8564.3078 | AN9: 7340.8356 | AO9: 6117.3635 | AP9: 4893.8913 | AQ9: 3670.4191 | AR9: 2446.9469 | AS9: 1223.4747
B10: Banorte-3,000,000 | C10: ='CREDITOS'!O49 -> 1450000 | D10: 0.15 | E10: =C10/SUM(C$6:C$13) -> 0.01405212 | F10: =E10*D10 -> 0.0021078181 | I10: =H10/SUM(H$6:H$16) -> 0 | J10: =I10*D10 -> 0 | K10: =H10*(D10/12) -> 0 | L10: 12458.333 | M10: 11916.667 | N10: 11375 | O10: 10833.333 | P10: 10291.667 | Q10: 9750 | R10: 9208.3333 | S10: 8666.6667 | T10: 8125 | U10: 7583.3333 | V10: 7041.6667 | W10: 6500 | Y10: 5958.3333 | Z10: 5416.6667 | AA10: 4875 | AB10: 4333.3333 | AC10: 3791.6667 | AD10: 3250 | AE10: 2708.3333 | AF10: 2166.6667 | AG10: 1625 | AH10: 1083.3333 | AI10: 541.66667
B11: Santander | C11: ='CREDITOS'!W58 -> 104166.51 | D11: 0.15 | F11: =E11*D11 -> 0 | I11: =H11/SUM(H$6:H$16) -> 0 | J11: =I11*D11 -> 0 | K11: =H11*(D11/12) -> 0 | L11: 4513.8873 | M11: 3385.415 | N11: 2256.9428 | O11: 1128.4705
B12: Arrendamas Xanalab | C12: ='CREDITOS'!BP57 -> 0 | E12: =C12/SUM(C$6:C$13) -> 0 | F12: =E12*D12 -> 0 | I12: =H12/SUM(H$6:H$16) -> 0 | J12: =I12*D12 -> 0 | K12: =H12*(D12/12) -> 0 | L12: 7857.1495 | M12: 7731.7023 | N12: 7603.5371 | O12: 7472.5949 | P12: 7338.8157 | Q12: 7202.138 | R12: 7062.4988 | S12: 6919.8342 | T12: 6774.0785 | U12: 6625.1648 | V12: 6473.0246 | W12: 6317.588 | Y12: 6158.7836 | Z12: 5996.5385 | AA12: 5830.7781 | AB12: 5661.4261 | AC12: 5488.4049 | AD12: 5311.6349 | AE12: 5131.0349 | AF12: 4946.5219 | AG12: 4758.0111 | AH12: 4565.4159 | AI12: 4368.6478 | AJ12: 4167.6164 | AL12: 3962.2293 | AM12: 3752.3922 | AN12: 3538.0086 | AO12: 3318.98 | AP12: 3095.2058 | AQ12: 2866.5831 | AR12: 2633.007 | AS12: 2394.3701 | AT12: 2150.5626 | AU12: 1901.4727 | AV12: 1646.9858 | AW12: 1386.9851 | AY12: 1121.351 | AZ12: 849.96151 | BA12: 572.6919 | BB12: 289.41479
B13: NUVARI | C13: 29598209 | D13: 0.13 | E13: =C13/SUM(C$6:C$13) -> 0.28683972 | F13: =E13*D13 -> 0.037289164 | I13: =H13/SUM(H$6:H$16) -> 0 | J13: =I13*D13 -> 0 | K13: =H13*(D13/12) -> 0 | L13: =$C13*($D13/12) -> 320647.26 | M13: =$C13*($D13/12) -> 320647.26 | N13: =$C13*($D13/12) -> 320647.26 | O13: =$C13*($D13/12) -> 320647.26 | P13: =$C13*($D13/12) -> 320647.26 | Q13: =$C13*($D13/12) -> 320647.26 | R13: =$C13*($D13/12) -> 320647.26 | S13: =$C13*($D13/12) -> 320647.26 | ... W13: =$C13*($D13/12) -> 320647.26 | Y13: =$C13*($D13/12) -> 320647.26 | Z13: =$C13*($D13/12) -> 320647.26 | AA13: =$C13*($D13/12) -> 320647.26 | AB13: =$C13*($D13/12) -> 320647.26 | AC13: =$C13*($D13/12) -> 320647.26 | AD13: =$C13*($D13/12) -> 320647.26 | AE13: =$C13*($D13/12) -> 320647.26 | AF13: =$C13*($D13/12) -> 320647.26 | ... AJ13: =$C13*($D13/12) -> 320647.26
B14: NUVARI (2) | D14: 0.16 | H14: 13000000 | I14: =H14/SUM(H$6:H$16) -> 0.14382556 | J14: =I14*D14 -> 0.023012089 | K14: =H14*(D14/12) -> 173333.33 | L14: =$C14*($D14/12) -> 0 | M14: =$C14*($D14/12) -> 0 | N14: =$C14*($D14/12) -> 0 | O14: =$C14*($D14/12) -> 0 | P14: =$C14*($D14/12) -> 0 | Q14: =$C14*($D14/12) -> 0 | R14: =$C14*($D14/12) -> 0 | S14: =$C14*($D14/12) -> 0 | ... W14: =$C14*($D14/12) -> 0
F15: =SUM(F6:F13) -> 0.21453973 | I15: =H15/SUM(H$6:H$16) -> 0 | J15: =I15*D15 -> 0 | K15: =H15*(D15/12) -> 0
B16: NUEVA LINEA SESAJAL | D16: 0.15 | H16: =SUM(C6:C16)-SUM(H6:H15)-H17 -> 54887274 | I16: =H16/SUM(H$6:H$16) -> 0.6072456 | J16: =I16*D16 -> 0.091086839 | K16: =H16*(D16/12) -> 686090.93
B17: Capitalizacion | H17: 12800000 | K17: =H17*(D17/12) -> 0
C18: =SUM(C6:C15) -> 1.0318727e+08 | H18: =SUM(H6:H16) -> 90387274 | K18: =SUM(K6:K17) -> 1290674.3 | L18: =SUM(L6:L17) -> 1832060.7
B21: ESCENARIO SESAJAL
B22: Acreedor | C22: Monto | D22: Tasa Annual
B23: CAPIX | C23: =18248000+5000000+2000000+1500000 -> 26748000 | D23: 0.23 | L23: =$C23*($D23/12) -> 512670 | M23: =$C23*($D23/12) -> 512670 | N23: =$C23*($D23/12) -> 512670 | O23: =$C23*($D23/12) -> 512670 | P23: =$C23*($D23/12) -> 512670 | Q23: =$C23*($D23/12) -> 512670 | R23: =$C23*($D23/12) -> 512670 | S23: =$C23*($D23/12) -> 512670 | ... W23: =$C23*($D23/12) -> 512670 | Y23: =$C23*($D23/12) -> 512670 | Z23: =$C23*($D23/12) -> 512670 | AA23: =$C23*($D23/12) -> 512670 | AB23: =$C23*($D23/12) -> 512670 | AC23: =$C23*($D23/12) -> 512670 | AD23: =$C23*($D23/12) -> 512670 | AE23: =$C23*($D23/12) -> 512670 | AF23: =$C23*($D23/12) -> 512670 | ... AJ23: =$C23*($D23/12) -> 512670
B24: Arrendamas | C24: =C8-'Linea Sesajal'!E44 -> 15645232 | D24: 0.27 | L24: =($C24/$C8)*L8 -> 338929.63 | M24: =($C24/$C8)*M8 -> 333802.95 | N24: =($C24/$C8)*N8 -> 325250.28 | O24: =($C24/$C8)*O8 -> 321066.42 | P24: =($C24/$C8)*P8 -> 316790.21 | Q24: =($C24/$C8)*Q8 -> 312419.6 | R24: =($C24/$C8)*R8 -> 307267 | S24: =($C24/$C8)*S8 -> 302773.73 | ... W24: =($C24/$C8)*W8 -> 283314.24 | Y24: =($C24/$C8)*Y8 -> 278365.62 | Z24: =($C24/$C8)*Z8 -> 273307.01 | AA24: =($C24/$C8)*AA8 -> 268135.94 | AB24: =($C24/$C8)*AB8 -> 257818.86 | AC24: =($C24/$C8)*AC8 -> 252671.01 | AD24: =($C24/$C8)*AD8 -> 244345.44 | AE24: =($C24/$C8)*AE8 -> 239321.9 | AF24: =($C24/$C8)*AF8 -> 231459.01 | ... AJ24: =($C24/$C8)*AJ8 -> 210362.98 | AL24: =($C24/$C8)*AL8 -> 205370.48 | AM24: =($C24/$C8)*AM8 -> 200269.81 | AN24: =($C24/$C8)*AN8 -> 195058.63 | AO24: =($C24/$C8)*AO8 -> 189734.54 | AP24: =($C24/$C8)*AP8 -> 184295.1 | AQ24: =($C24/$C8)*AQ8 -> 178737.8 | AR24: =($C24/$C8)*AR8 -> 173060.09 | AS24: =($C24/$C8)*AS8 -> 167259.36 | ... AW24: =($C24/$C8)*AW8 -> 142772.11 | AY24: =($C24/$C8)*AY8 -> 136315.14 | AZ24: =($C24/$C8)*AZ8 -> 129718.28 | BA24: =($C24/$C8)*BA8 -> 122978.48 | BB24: =($C24/$C8)*BB8 -> 116092.65 | BC24: =($C24/$C8)*BC8 -> 109057.63 | BD24: =($C24/$C8)*BD8 -> 101870.18 | BE24: =($C24/$C8)*BE8 -> 94527.011 | BF24: =($C24/$C8)*BF8 -> 87024.735 | ... BJ24: =($C24/$C8)*BJ8 -> 55354.537 | BL24: =($C24/$C8)*BL8 -> 47003.524 | BM24: =($C24/$C8)*BM8 -> 38471.573 | BN24: =($C24/$C8)*BN8 -> 29754.763 | BO24: =($C24/$C8)*BO8 -> 20849.089
B25: Banorte-5,750,000 | C25: 3641666.7 | D25: 0.15 | E25: 0.036699509 | F25: 0.0055049264 | I25: 0 | J25: 0 | K25: 0 | L25: 39151.112 | M25: 37927.64 | N25: 36704.168 | O25: 35480.696 | P25: 34257.224 | Q25: 33033.751 | R25: 31810.279 | S25: 30586.807 | T25: 29363.335 | U25: 28139.863 | V25: 26916.391 | W25: 25692.918 | Y25: 24469.446 | Z25: 23245.974 | AA25: 22022.502 | AB25: 20799.03 | AC25: 19575.557 | AD25: 18352.085 | AE25: 17128.613 | AF25: 15905.141 | AG25: 14681.669 | AH25: 13458.197 | AI25: 12234.724 | AJ25: 11011.252 | AL25: 9787.78 | AM25: 8564.3078 | AN25: 7340.8356 | AO25: 6117.3635 | AP25: 4893.8913 | AQ25: 3670.4191 | AR25: 2446.9469 | AS25: 1223.4747
B26: Banorte-3,000,000 | C26: 1450000 | D26: 0.15 | E26: 0.014612619 | F26: 0.0021918928 | I26: 0 | J26: 0 | K26: 0 | L26: 12458.333 | M26: 11916.667 | N26: 11375 | O26: 10833.333 | P26: 10291.667 | Q26: 9750 | R26: 9208.3333 | S26: 8666.6667 | T26: 8125 | U26: 7583.3333 | V26: 7041.6667 | W26: 6500 | Y26: 5958.3333 | Z26: 5416.6667 | AA26: 4875 | AB26: 4333.3333 | AC26: 3791.6667 | AD26: 3250 | AE26: 2708.3333 | AF26: 2166.6667 | AG26: 1625 | AH26: 1083.3333 | AI26: 541.66667
B27: Santander | C27: 0 | D27: 0.15
B28: NUVARI | C28: =C13-H14-6500000 -> 10098209 | D28: 0.13
B29: NUEVA LINEA SESAJAL | D29: 0.15 | S29: 412500 | T29: 587500 | U29: 662500 | V29: 662500 | W29: 662500 | Y29: 662500 | Z29: 662500 | AA29: 648697.92 | AB29: 634895.83 | AC29: 621093.75 | AD29: 607291.67 | AE29: 593489.58 | AF29: 579687.5 | AG29: 565885.42 | AH29: 552083.33 | AI29: 538281.25 | AJ29: 524479.17 | AL29: 510677.08 | AM29: 496875 | AN29: 483072.92 | AO29: 469270.83 | AP29: 455468.75 | AQ29: 441666.67 | AR29: 427864.58 | AS29: 414062.5 | AT29: 400260.42 | AU29: 386458.33 | AV29: 372656.25 | AW29: 358854.17 | AY29: 345052.08 | AZ29: 331250 | BA29: 317447.92 | BB29: 303645.83 | BC29: 289843.75 | BD29: 276041.67 | BE29: 262239.58 | BF29: 248437.5 | BG29: 234635.42 | BH29: 220833.33 | BI29: 207031.25 | BJ29: 193229.17 | BL29: 179427.08 | BM29: 165625 | BN29: 151822.92 | BO29: 138020.83 | BP29: 124218.75 | BQ29: 110416.67 | BR29: 96614.583 | BS29: 82812.5 | BT29: 69010.417 | BU29: 55208.333 | BV29: 41406.25 | BW29: 27604.167 | BX29: 13802.083
L31: =SUM(L23:L30) -> 903209.08 | M31: =SUM(M23:M30) -> 896317.26 | N31: =SUM(N23:N30) -> 885999.45 | O31: =SUM(O23:O30) -> 880050.45 | P31: =SUM(P23:P30) -> 874009.1 | Q31: =SUM(Q23:Q30) -> 867873.35 | R31: =SUM(R23:R30) -> 860955.61 | S31: =SUM(S23:S30) -> 1267197.2 | ... W31: =SUM(W23:W30) -> 1490677.2 | Y31: =SUM(Y23:Y30) -> 1483963.4 | Z31: =SUM(Z23:Z30) -> 1477139.7 | AA31: =SUM(AA23:AA30) -> 1456401.4 | AB31: =SUM(AB23:AB30) -> 1430517.1 | AC31: =SUM(AC23:AC30) -> 1409802 | AD31: =SUM(AD23:AD30) -> 1385909.2 | AE31: =SUM(AE23:AE30) -> 1365318.4 | AF31: =SUM(AF23:AF30) -> 1341888.3 | ... AJ31: =SUM(AJ23:AJ30) -> 1258523.4 | AL31: =SUM(AL23:AL30) -> 725835.34 | AM31: =SUM(AM23:AM30) -> 705709.12 | AN31: =SUM(AN23:AN30) -> 685472.38 | AO31: =SUM(AO23:AO30) -> 665122.74 | AP31: =SUM(AP23:AP30) -> 644657.74 | AQ31: =SUM(AQ23:AQ30) -> 624074.88 | AR31: =SUM(AR23:AR30) -> 603371.62 | AS31: =SUM(AS23:AS30) -> 582545.34 | ... AW31: =SUM(AW23:AW30) -> 501626.27 | AY31: =SUM(AY23:AY30) -> 481367.22 | AZ31: =SUM(AZ23:AZ30) -> 460968.28 | BA31: =SUM(BA23:BA30) -> 440426.39 | BB31: =SUM(BB23:BB30) -> 419738.48 | BC31: =SUM(BC23:BC30) -> 398901.38 | BD31: =SUM(BD23:BD30) -> 377911.85 | BE31: =SUM(BE23:BE30) -> 356766.59 | BF31: =SUM(BF23:BF30) -> 335462.23 | ... BJ31: =SUM(BJ23:BJ30) -> 248583.7 | BL31: =SUM(BL23:BL30) -> 226430.61 | BM31: =SUM(BM23:BM30) -> 204096.57 | BN31: =SUM(BN23:BN30) -> 181577.68 | BO31: =SUM(BO23:BO30) -> 158869.92 | BP31: =SUM(BP23:BP30) -> 124218.75 | BQ31: =SUM(BQ23:BQ30) -> 110416.67 | BR31: =SUM(BR23:BR30) -> 96614.583 | BS31: =SUM(BS23:BS30) -> 82812.5 | ... BX31: =SUM(BX23:BX30) -> 13802.083
B33: ESCENARIO NUVARI
B34: Acreedor | C34: Monto | D34: Tasa Annual
B35: CAPIX | C35: =18248000+5000000+2000000+1500000 -> 26748000 | D35: 0.23 | L35: =$C35*($D35/12) -> 512670 | M35: =$C35*($D35/12) -> 512670 | N35: =$C35*($D35/12) -> 512670 | O35: =$C35*($D35/12) -> 512670 | P35: =$C35*($D35/12) -> 512670 | Q35: =$C35*($D35/12) -> 512670 | R35: =$C35*($D35/12) -> 512670 | S35: =$C35*($D35/12) -> 512670 | ... W35: =$C35*($D35/12) -> 512670 | Y35: =$C35*($D35/12) -> 512670 | Z35: =$C35*($D35/12) -> 512670 | AA35: =$C35*($D35/12) -> 512670 | AB35: =$C35*($D35/12) -> 512670 | AC35: =$C35*($D35/12) -> 512670 | AD35: =$C35*($D35/12) -> 512670 | AE35: =$C35*($D35/12) -> 512670 | AF35: =$C35*($D35/12) -> 512670 | ... AJ35: =$C35*($D35/12) -> 512670
B36: Arrendamientos | C36: 15645232 | D36: 0.27 | E36: =C36/SUM(C$6:C$13) -> 0.15161978 | F36: =E36*D36 -> 0.040937341 | I36: =H36/SUM(H$6:H$16) -> 0 | J36: =I36*D36 -> 0 | K36: =H36*(D36/12) -> 0 | L36: 338929.63 | M36: 333802.95 | N36: 325250.28 | O36: 321066.42 | P36: 316790.21 | Q36: 312419.6 | R36: 307267 | S36: 302773.73 | T36: 298180.94 | U36: 292891.11 | V36: 288155.28 | W36: 283314.24 | Y36: 278365.62 | Z36: 273307.01 | AA36: 268135.94 | AB36: 257818.86 | AC36: 252671.01 | AD36: 244345.44 | AE36: 239321.9 | AF36: 231459.01 | AG36: 225281.19 | AH36: 220319.96 | AI36: 215249.6 | AJ36: 210362.98 | AL36: 205370.48 | AM36: 200269.81 | AN36: 195058.63 | AO36: 189734.54 | AP36: 184295.1 | AQ36: 178737.8 | AR36: 173060.09 | AS36: 167259.36 | AT36: 161332.95 | AU36: 155278.14 | AV36: 149092.14 | AW36: 142772.11 | AY36: 136315.14 | AZ36: 129718.28 | BA36: 122978.48 | BB36: 116092.65 | BC36: 109057.63 | BD36: 101870.18 | BE36: 94527.011 | BF36: 87024.735 | BG36: 79359.91 | BH36: 71529.014 | BI36: 63528.448 | BJ36: 55354.537 | BL36: 47003.524 | BM36: 38471.573 | BN36: 29754.763 | BO36: 20849.089
B37: Banorte-5,750,000 | C37: 3641666.7 | D37: 0.15 | E37: 0.036699509 | F37: 0.0055049264 | I37: 0 | J37: 0 | K37: 0 | L37: 39151.112 | M37: 37927.64 | N37: 36704.168 | O37: 35480.696 | P37: 34257.224 | Q37: 33033.751 | R37: 31810.279 | S37: 30586.807 | T37: 29363.335 | U37: 28139.863 | V37: 26916.391 | W37: 25692.918 | Y37: 24469.446 | Z37: 23245.974 | AA37: 22022.502 | AB37: 20799.03 | AC37: 19575.557 | AD37: 18352.085 | AE37: 17128.613 | AF37: 15905.141 | AG37: 14681.669 | AH37: 13458.197 | AI37: 12234.724 | AJ37: 11011.252 | AL37: 9787.78 | AM37: 8564.3078 | AN37: 7340.8356 | AO37: 6117.3635 | AP37: 4893.8913 | AQ37: 3670.4191 | AR37: 2446.9469 | AS37: 1223.4747
B38: Banorte-3,000,000 | C38: 1450000 | D38: 0.15 | E38: 0.014612619 | F38: 0.0021918928 | I38: 0 | J38: 0 | K38: 0 | L38: 12458.333 | M38: 11916.667 | N38: 11375 | O38: 10833.333 | P38: 10291.667 | Q38: 9750 | R38: 9208.3333 | S38: 8666.6667 | T38: 8125 | U38: 7583.3333 | V38: 7041.6667 | W38: 6500 | Y38: 5958.3333 | Z38: 5416.6667 | AA38: 4875 | AB38: 4333.3333 | AC38: 3791.6667 | AD38: 3250 | AE38: 2708.3333 | AF38: 2166.6667 | AG38: 1625 | AH38: 1083.3333 | AI38: 541.66667
B39: Santander | C39: 0 | D39: 0.15
B40: NUVARI | C40: =C13 -> 29598209 | D40: 0.13 | L40: =$C40*($D40/12) -> 320647.26 | M40: =$C40*($D40/12) -> 320647.26 | N40: =$C40*($D40/12) -> 320647.26 | O40: =$C40*($D40/12) -> 320647.26 | P40: =$C40*($D40/12) -> 320647.26 | Q40: =$C40*($D40/12) -> 320647.26 | R40: =$C40*($D40/12) -> 320647.26 | S40: =$C40*($D40/12) -> 320647.26 | ... W40: =$C40*($D40/12) -> 320647.26 | Y40: =$C40*($D40/12) -> 320647.26 | Z40: =$C40*($D40/12) -> 320647.26 | AA40: =$C40*($D40/12) -> 320647.26 | AB40: =$C40*($D40/12) -> 320647.26 | AC40: =$C40*($D40/12) -> 320647.26 | AD40: =$C40*($D40/12) -> 320647.26 | AE40: =$C40*($D40/12) -> 320647.26 | AF40: =$C40*($D40/12) -> 320647.26 | ... AJ40: =$C40*($D40/12) -> 320647.26
B41: NUVARI NUEVA LINEA | C41: ='Linea Sesajal'!G48-'Linea Sesajal'!$E44+'Linea Sesajal'!F37 -> 41653778 | D41: 0.2 | R41: =($D41/12)*('Linea Sesajal'!E48-'Linea Sesajal'!$E44+'Linea Sesajal'!D37+'Linea Sesajal'!D40) -> 531143.79 | S41: =($D41/12)*('Linea Sesajal'!F48-'Linea Sesajal'!$E44+'Linea Sesajal'!E37+'Linea Sesajal'!E40) -> 711345.02 | T41: =($D41/12)*('Linea Sesajal'!G48-'Linea Sesajal'!$E44+'Linea Sesajal'!F37+'Linea Sesajal'!F40) -> 795146.73 | U41: =($D41/12)*('Linea Sesajal'!H48-'Linea Sesajal'!$E44+'Linea Sesajal'!G37+'Linea Sesajal'!G40) -> 867966.7 | V41: =($D41/12)*('Linea Sesajal'!I48-'Linea Sesajal'!$E44+'Linea Sesajal'!H37+'Linea Sesajal'!H40) -> 848952.87 | W41: =($D41/12)*('Linea Sesajal'!J48-'Linea Sesajal'!$E44+'Linea Sesajal'!I37+'Linea Sesajal'!I40) -> 861452.87 | Y41: =W41 -> 861452.87 | Z41: =Y41 -> 861452.87 | AA41: =Z41 -> 861452.87 | AB41: =AA41 -> 861452.87 | AC41: =AB41 -> 861452.87 | AD41: =AC41 -> 861452.87 | AE41: =AD41 -> 861452.87 | AF41: =AE41 -> 861452.87 | AG41: =AF41 -> 861452.87 | ... AJ41: =AI41 -> 861452.87 | AL41: =AJ41 -> 861452.87 | AM41: =AL41 -> 861452.87 | AN41: =AM41 -> 861452.87 | AO41: =AN41 -> 861452.87 | AP41: =AO41 -> 861452.87 | AQ41: =AP41 -> 861452.87 | AR41: =AQ41 -> 861452.87 | AS41: =AR41 -> 861452.87 | AT41: =AS41 -> 861452.87 | ... AW41: =AV41 -> 861452.87 | AY41: =AW41 -> 861452.87 | AZ41: =AY41 -> 861452.87 | BA41: =AZ41 -> 861452.87 | BB41: =BA41 -> 861452.87 | BC41: =BB41 -> 861452.87 | BD41: =BC41 -> 861452.87 | BE41: =BD41 -> 861452.87 | BF41: =BE41 -> 861452.87 | BG41: =BF41 -> 861452.87 | ... BJ41: =BI41 -> 861452.87 | BL41: =BJ41 -> 861452.87 | BM41: =BL41 -> 861452.87 | BN41: =BM41 -> 861452.87 | BO41: =BN41 -> 861452.87
L43: =SUM(L35:L42) -> 1223856.3 | M43: =SUM(M35:M42) -> 1216964.5 | N43: =SUM(N35:N42) -> 1206646.7 | O43: =SUM(O35:O42) -> 1200697.7 | P43: =SUM(P35:P42) -> 1194656.4 | Q43: =SUM(Q35:Q42) -> 1188520.6 | R43: =SUM(R35:R42) -> 1712746.7 | S43: =SUM(S35:S42) -> 1886689.5 | ... W43: =SUM(W35:W42) -> 2010277.3 | Y43: =SUM(Y35:Y42) -> 2003563.5 | Z43: =SUM(Z35:Z42) -> 1996739.8 | AA43: =SUM(AA35:AA42) -> 1989803.6 | AB43: =SUM(AB35:AB42) -> 1977721.4 | AC43: =SUM(AC35:AC42) -> 1970808.4 | AD43: =SUM(AD35:AD42) -> 1960717.7 | AE43: =SUM(AE35:AE42) -> 1953929 | AF43: =SUM(AF35:AF42) -> 1944300.9 | ... AJ43: =SUM(AJ35:AJ42) -> 1916144.4 | AL43: =SUM(AL35:AL42) -> 1076611.1 | AM43: =SUM(AM35:AM42) -> 1070287 | AN43: =SUM(AN35:AN42) -> 1063852.3 | AO43: =SUM(AO35:AO42) -> 1057304.8 | AP43: =SUM(AP35:AP42) -> 1050641.9 | AQ43: =SUM(AQ35:AQ42) -> 1043861.1 | AR43: =SUM(AR35:AR42) -> 1036959.9

Sheet KPIs SEP 2024 V. MAY
C4: WC | D4: 45536 | E4: 45778 | F4: Change
C5: CXC | D5: 32980000 | E5: =26046315.78+10000000 -> 36046316 | F5: =E5-D5 -> 3066315.8
C6: CXP | D6: 45424000 | E6: 24000000 | F6: =E6-D6 -> -21424000
C7: Inv | D7: 25459878 | E7: 24500000 | F7: =E7-D7 -> -959877.96
C8: Net WC | D8: =D7+D5-D6 -> 13015878 | E8: =E7+E5-E6 -> 36546316 | F8: =E8-D8 -> 23530438
C10: FORECAST 1H 25
D11: 45627 | E11: 45778 | F11: Change
C12: NET REVENUE | D12: =SUM(IS!O18:T18) -> 1.0399444e+08 | E12: =SUM('IS (ROLLING)'!P18:U18) -> 1.0524665e+08 | F12: =E12/D12-1 -> 0.012041162

Sheet IS (BRIEF)
B8: BRIEF INCOME STATEMENT
B10: PERIODO | C10: enero | D10: febrero | E10: marzo | F10: abril | G10: mayo | H10: junio | I10: julio | J10: agosto | K10: septiembre | L10: octubre | M10: noviembre | N10: diciembre | O10: Acumulado
C11: real | D11: real | E11: real | F11: preliminar | G11: fcst | H11: fcst | I11: fcst | J11: fcst | K11: fcst | L11: fcst | M11: fcst | N11: fcst | P11: Acumulado
B12: Maquila | C12: ='IS (ROLLING)'!P15 -> 9677100.6 | D12: ='IS (ROLLING)'!Q15 -> 8226802.9 | E12: ='IS (ROLLING)'!R15 -> 5356720.1 | F12: ='IS (ROLLING)'!S15 -> 13035711 | G12: ='IS (ROLLING)'!T15 -> 11700675 | H12: ='IS (ROLLING)'!U15 -> 8685547.9 | I12: ='IS (ROLLING)'!V15 -> 15512994 | J12: ='IS (ROLLING)'!W15 -> 16143512 | ... N12: ='IS (ROLLING)'!AA15 -> 12161452 | O12: =SUM(C12:N12) -> 1.3739352e+08 | P12: =SUM(C12:E12) -> 23260624
B13: Private Label | C13: ='IS (ROLLING)'!P16 -> 0 | D13: ='IS (ROLLING)'!Q16 -> 0 | E13: ='IS (ROLLING)'!R16 -> 0 | F13: ='IS (ROLLING)'!S16 -> 0 | G13: ='IS (ROLLING)'!T16 -> 732871.29 | H13: ='IS (ROLLING)'!U16 -> 852760.66 | I13: ='IS (ROLLING)'!V16 -> 1184249.6 | J13: ='IS (ROLLING)'!W16 -> 1557459 | ... N13: ='IS (ROLLING)'!AA16 -> 1522217 | O13: =SUM(C13:N13) -> 10394733 | P13: =SUM(C13:E13) -> 0
B14: Biomiral | C14: ='IS (ROLLING)'!P17 -> 9061037.6 | D14: ='IS (ROLLING)'!Q17 -> 8215637.3 | E14: ='IS (ROLLING)'!R17 -> 7745218.1 | F14: ='IS (ROLLING)'!S17 -> 4902491.2 | G14: ='IS (ROLLING)'!T17 -> 8688581.2 | H14: ='IS (ROLLING)'!U17 -> 8365497.1 | I14: ='IS (ROLLING)'!V17 -> 6950223.2 | J14: ='IS (ROLLING)'!W17 -> 7770679 | ... N14: ='IS (ROLLING)'!AA17 -> 8108764.8 | O14: =SUM(C14:N14) -> 94128730 | P14: =SUM(C14:E14) -> 25021893
B15: GROSS REVENUE | C15: ='1Q Consolidado'!B18 -> 16930425 | D15: ='1Q Consolidado'!D18 -> 15998744 | E15: ='1Q Consolidado'!F18 -> 13102800 | F15: ='IS (ROLLING)'!S18 -> 17938202 | G15: ='IS (ROLLING)'!T18 -> 21122128 | H15: ='IS (ROLLING)'!U18 -> 17903806 | I15: ='IS (ROLLING)'!V18 -> 23647467 | J15: ='IS (ROLLING)'!W18 -> 25471650 | K15: ='IS (ROLLING)'!X18 -> 22888550 | L15: ='IS (ROLLING)'!Y18 -> 22624786 | M15: ='IS (ROLLING)'!Z18 -> 20245438 | N15: ='IS (ROLLING)'!AA18 -> 21792434 | O15: =SUM(C15:N15) -> 2.3966643e+08 | P15: =SUM(C15:E15) -> 46031970
B16: GROSS REVENUE | C16: =C15/C18 -> 1.0668829 | D16: =D15/D18 -> 1.0266718 | E16: =E15/E18 -> 1.0486652 | F16: =F15/F18 -> 1.0251073 | G16: =G15/G18 -> 1.0168418 | H16: =H15/H18 -> 1.0343512 | I16: =I15/I18 -> 1.0175878 | J16: =J15/J18 -> 1.0204082 | ... P16: =P15/P18 -> 1.0474449
B17: Descuentos & Devoluciones | C17: ='IS (ROLLING)'!P21-'1Q Consolidado'!B35 -> 1061368.4 | D17: ='IS (ROLLING)'!Q21 -> 415629.29 | E17: ='IS (ROLLING)'!R21 -> 608059.55 | F17: ='IS (ROLLING)'!S21 -> 439349.09 | G17: ='IS (ROLLING)'!T21 -> 349842.16 | H17: ='IS (ROLLING)'!U21 -> 594591.44 | I17: ='IS (ROLLING)'!V21 -> 408718.56 | J17: ='IS (ROLLING)'!W21 -> 509433.01 | K17: ='IS (ROLLING)'!X21 -> 457771.01 | ... N17: ='IS (ROLLING)'!AA21 -> 435848.68 | O17: =SUM(C17:N17) -> 6138015.6 | P17: =SUM(C17:E17) -> 2085057.2
B18: NET REVENUE | C18: =C15-C17 -> 15869057 | D18: =D15-D17 -> 15583115 | E18: =E15-E17 -> 12494741 | F18: =F15-F17 -> 17498853 | G18: =G15-G17 -> 20772285 | H18: =H15-H17 -> 17309214 | I18: =I15-I17 -> 23238749 | J18: =J15-J17 -> 24962217 | ... N18: =N15-N17 -> 21356585 | O18: =SUM(C18:N18) -> 2.3352842e+08 | P18: =SUM(C18:E18) -> 43946913
B19: MP/ME | C19: ='1Q Consolidado'!B45 -> 6374777.3 | D19: ='1Q Consolidado'!D45 -> 6554330.4 | E19: ='1Q Consolidado'!F45 -> 4958570.6 | F19: ='IS (ROLLING)'!S24 -> 6630608.8 | G19: ='IS (ROLLING)'!T24 -> 8870567.4 | H19: ='IS (ROLLING)'!U24 -> 7136545.2 | I19: ='IS (ROLLING)'!V24 -> 9963239.7 | J19: ='IS (ROLLING)'!W24 -> 11492517 | K19: ='IS (ROLLING)'!X24 -> 10265355 | L19: ='IS (ROLLING)'!Y24 -> 9897419 | M19: ='IS (ROLLING)'!Z24 -> 8825316.9 | N19: ='IS (ROLLING)'!AA24 -> 9598814.6 | O19: =SUM(C19:N19) -> 1.0056806e+08 | P19: =SUM(C19:E19) -> 17887678
B20: Otros costos directos | C20: ='1Q Consolidado'!B53 -> 3390431.5 | D20: ='1Q Consolidado'!D53 -> 2440860.5 | E20: ='1Q Consolidado'!F53 -> 1928559.7 | F20: ='IS (ROLLING)'!S29 -> 2025486 | G20: ='IS (ROLLING)'!T29 -> 2081617.5 | H20: ='IS (ROLLING)'!U29 -> 2047912.4 | I20: ='IS (ROLLING)'!V29 -> 1940260.9 | J20: ='IS (ROLLING)'!W29 -> 1795060.9 | K20: ='IS (ROLLING)'!X29 -> 1388185.9 | L20: ='IS (ROLLING)'!Y29 -> 1388185.9 | M20: ='IS (ROLLING)'!Z29 -> 1388185.9 | N20: ='IS (ROLLING)'!AA29 -> 1388185.9 | O20: =SUM(C20:N20) -> 23202933 | P20: =SUM(C20:E20) -> 7759851.6
B21: Costos indirectos | C21: ='1Q Consolidado'!B67 -> 1394621.1 | D21: ='1Q Consolidado'!D67 -> 1695025.5 | E21: ='1Q Consolidado'!F67 -> 1817295.8 | F21: ='IS (ROLLING)'!S27+'IS (ROLLING)'!S30+'IS (ROLLING)'!S31+'IS (ROLLING)'!S33 -> 707655.58 | G21: ='IS (ROLLING)'!T27+'IS (ROLLING)'!T30+'IS (ROLLING)'!T31+'IS (ROLLING)'!T33 -> 860732.43 | H21: ='IS (ROLLING)'!U27+'IS (ROLLING)'!U30+'IS (ROLLING)'!U31+'IS (ROLLING)'!U33 -> 944018.88 | I21: ='IS (ROLLING)'!V27+'IS (ROLLING)'!V30+'IS (ROLLING)'!V31+'IS (ROLLING)'!V33 -> 968156.03 | J21: ='IS (ROLLING)'!W27+'IS (ROLLING)'!W30+'IS (ROLLING)'!W31+'IS (ROLLING)'!W33 -> 1095581.9 | K21: ='IS (ROLLING)'!X27+'IS (ROLLING)'!X30+'IS (ROLLING)'!X31+'IS (ROLLING)'!X33 -> 1048311.2 | L21: ='IS (ROLLING)'!Y27+'IS (ROLLING)'!Y30+'IS (ROLLING)'!Y31+'IS (ROLLING)'!Y33 -> 1043484.3 | M21: ='IS (ROLLING)'!Z27+'IS (ROLLING)'!Z30+'IS (ROLLING)'!Z31+'IS (ROLLING)'!Z33 -> 999942.21 | N21: ='IS (ROLLING)'!AA27+'IS (ROLLING)'!AA30+'IS (ROLLING)'!AA31+'IS (ROLLING)'!AA33 -> 1028252.2 | O21: =SUM(C21:N21) -> 13603077 | P21: =SUM(C21:E21) -> 4906942.5
B22: UTILIDAD BRUTA | C22: =C18-SUM(C19:C21) -> 4709227.2 | D22: =D18-SUM(D19:D21) -> 4892898.8 | E22: =E18-SUM(E19:E21) -> 3790314.6 | F22: =F18-SUM(F19:F21) -> 8135102.7 | G22: =G18-SUM(G19:G21) -> 8959368 | H22: =H18-SUM(H19:H21) -> 7180737.8 | I22: =I18-SUM(I19:I21) -> 10367092 | J22: =J18-SUM(J19:J21) -> 10579058 | ... N22: =N18-SUM(N19:N21) -> 9341332.6 | O22: =SUM(C22:N22) -> 96154344 | P22: =SUM(C22:E22) -> 13392441
B23: UTILIDAD BRUTA | C23: =C22/C18 -> 0.29675532 | D23: =D22/D18 -> 0.31398721 | E23: =E22/E18 -> 0.3033528 | F23: =F22/F18 -> 0.46489348 | G23: =G22/G18 -> 0.43131354 | H23: =H22/H18 -> 0.41485059 | I23: =I22/I18 -> 0.44611231 | J23: =J22/J18 -> 0.42380282 | ... N23: =N22/N18 -> 0.43739823 | O23: =O22/O$18 -> 0.4117458 | P23: =P22/P$18 -> 0.30474133
B24: Total Gastos | C24: =SUM('1Q Consolidado'!B71:B83) -> 4415253.8 | D24: =SUM('1Q Consolidado'!D71:D83) -> 4108257.2 | E24: =SUM('1Q Consolidado'!F71:F83) -> 4214679.7 | F24: =SUM('IS (ROLLING)'!S38:S40)+SUM('IS (ROLLING)'!S43:S60) -> 7002198.1 | G24: =SUM('IS (ROLLING)'!T38:T40)+SUM('IS (ROLLING)'!T43:T60) -> 7549727.2 | H24: =SUM('IS (ROLLING)'!U38:U40)+SUM('IS (ROLLING)'!U43:U60) -> 6475520.7 | I24: =SUM('IS (ROLLING)'!V38:V40)+SUM('IS (ROLLING)'!V43:V60) -> 7290202.8 | J24: =SUM('IS (ROLLING)'!W38:W40)+SUM('IS (ROLLING)'!W43:W60) -> 6105933 | K24: =SUM('IS (ROLLING)'!X38:X40)+SUM('IS (ROLLING)'!X43:X60) -> 5911887.8 | L24: =SUM('IS (ROLLING)'!Y38:Y40)+SUM('IS (ROLLING)'!Y43:Y60) -> 6125888.2 | M24: =SUM('IS (ROLLING)'!Z38:Z40)+SUM('IS (ROLLING)'!Z43:Z60) -> 5926021.1 | N24: =SUM('IS (ROLLING)'!AA38:AA40)+SUM('IS (ROLLING)'!AA43:AA60) -> 6071863.4 | O24: =SUM(C24:N24) -> 71197433 | P24: =SUM(C24:E24) -> 12738191
B25: UTILIDAD OPERATIVA | C25: =C22-C24 -> 293973.38 | D25: =D22-D24 -> 784641.62 | E25: =E22-E24 -> -424365.14 | F25: =F22-F24 -> 1132904.6 | G25: =G22-G24 -> 1409640.8 | H25: =H22-H24 -> 705217.09 | I25: =I22-I24 -> 3076889.1 | J25: =J22-J24 -> 4473125.1 | ... N25: =N22-N24 -> 3269469.2 | O25: =SUM(C25:N25) -> 24956911 | P25: =SUM(C25:E25) -> 654249.86
B26: UTILIDAD OPERATIVA | C26: =C25/C18 -> 0.018524943 | D26: =D25/D18 -> 0.050352039 | E26: =E25/E18 -> -0.033963501 | F26: =F25/F18 -> 0.064741651 | G26: =G25/G18 -> 0.067861615 | H26: =H25/H18 -> 0.040742294 | I26: =I25/I18 -> 0.13240339 | J26: =J25/J18 -> 0.17919582 | ... N26: =N25/N18 -> 0.15308951 | O26: =O25/O$18 -> 0.10686884 | P26: =P25/P$18 -> 0.014887277
B27: Intereses & Arrendamientos | C27: ='1Q Consolidado'!B88 -> 1344504 | D27: ='1Q Consolidado'!D88 -> 1290476.5 | E27: ='1Q Consolidado'!F88 -> 1077858 | F27: ='IS (ROLLING)'!S64 -> 1330732.1 | G27: ='IS (ROLLING)'!T64 -> 1150136.9 | H27: ='IS (ROLLING)'!U64 -> 784790.69 | I27: ='IS (ROLLING)'!V64 -> 1032556.8 | J27: ='IS (ROLLING)'!W64 -> 1267197.2 | K27: ='IS (ROLLING)'!X64 -> 1435839.3 | L27: ='IS (ROLLING)'!Y64 -> 1503784.3 | M27: ='IS (ROLLING)'!Z64 -> 1497283.3 | N27: ='IS (ROLLING)'!AA64 -> 1490677.2 | O27: =SUM(C27:N27) -> 15205836 | P27: =SUM(C27:E27) -> 3712838.4
B28: Impuestos
B29: UTILIDAD NETA | C29: =C25-C27 -> -1050530.6 | D29: =D25-D27 -> -505834.88 | E29: =E25-E27 -> -1502223.1 | F29: =F25-F27 -> -197827.43 | G29: =G25-G27 -> 259503.96 | H29: =H25-H27 -> -79573.6 | I29: =I25-I27 -> 2044332.3 | J29: =J25-J27 -> 3205927.9 | ... N29: =N25-N27 -> 1778792 | O29: =SUM(C29:N29) -> 9751075.1 | P29: =SUM(C29:E29) -> -3058588.6
B30: UTILIDAD NETA | C30: =C29/C18 -> -0.066199939 | D30: =D29/D18 -> -0.032460447 | E30: =E29/E18 -> -0.12022843 | F30: =F29/F18 -> -0.011305165 | G30: =G29/G18 -> 0.012492798 | H30: =H29/H18 -> -0.0045971815 | I30: =I29/I18 -> 0.087970841 | J30: =J29/J18 -> 0.12843121 | ... N30: =N29/N18 -> 0.083290094 | O30: =O29/O$18 -> 0.041755412 | P30: =P29/P$18 -> -0.069597348
B32: Gastos Ej Anteriores | C32: ='1Q Consolidado'!B105 -> 2957032.8 | D32: ='1Q Consolidado'!D105 -> 2300445.1 | E32: ='1Q Consolidado'!F105 -> 2506004.9 | P32: =SUM(C32:E32) -> 7763482.8
B33: Resultado Inc. Ej Anteriores | C33: =C29-C32 -> -4007563.4 | D33: =D29-D32 -> -2806280 | E33: =E29-E32 -> -4008228 | P33: =SUM(C33:E33) -> -10822071
B35: PPTO DIC 2024 | C35: =IS!O$18 -> 21880937 | D35: =IS!P$18 -> 16336216 | E35: =IS!Q$18 -> 15159887 | F35: =IS!R$18 -> 16142972 | G35: =IS!S$18 -> 16250542 | H35: =IS!T$18 -> 18223883 | I35: =IS!U$18 -> 18810588 | J35: =IS!V$18 -> 18543472 | ... O35: =IS!AA$18 -> 2.3278528e+08
B36: Diferencia Periodo | C36: =C$15-C35 -> -4950511.9 | D36: =D$15-D35 -> -337471.77 | E36: =E$15-E35 -> -2057087 | F36: =F$15-F35 -> 1795229.7 | G36: =G$15-G35 -> 4871585.3 | H36: =H$15-H35 -> -320076.93 | I36: =I$15-I35 -> 4836879.3 | J36: =J$15-J35 -> 6928178.1 | ... O36: =O$15-O35 -> 6881152.4
B37: Diferencia Acumulada | C37: =C36 -> -4950511.9 | D37: =C37+D36 -> -5287983.6 | E37: =D37+E36 -> -7345070.7 | F37: =E37+F36 -> -5549840.9 | G37: =F37+G36 -> -678255.68 | H37: =G37+H36 -> -998332.61 | I37: =H37+I36 -> 3838546.7 | J37: =I37+J36 -> 10766725 | K37: =J37+K36 -> 13375342 | ... N37: =M37+N36 -> 6881152.4
B38: % Cumplimiento Ppto | C38: =C37/SUM(C35:$C35) -> -0.22624771 | D38: =D37/SUM($C35:D35) -> -0.13836676 | E38: =E37/SUM($C35:E35) -> -0.1376073 | F38: =F37/SUM($C35:F35) -> -0.079830838 | G38: =G37/SUM($C35:G35) -> -0.0079077916 | H38: =H37/SUM($C35:H35) -> -0.0095998654 | I38: =I37/SUM($C35:I35) -> 0.031257244 | J38: =J37/SUM($C35:J35) -> 0.076171484 | K38: =K37/SUM($C35:K35) -> 0.082753646 | ... N38: =N37/SUM($C35:N35) -> 0.029560084

Sheet IS (SCENARIO CAP)
B7: SCENARIO CAPITALIZACIÓN | AB7: 19683312 | BG7: 14603982 | BH7: 8000000 | BI7: 8000000 | BJ7: 8000000 | BK7: 8000000 | BL7: 8000000 | BM7: 8000000 | BN7: 8000000 | BO7: 8000000 | BP7: 8000000 | BQ7: 23085702 | BR7: 8000000 | BS7: 8000000 | BT7: 8000000 | BU7: 8000000 | BV7: 8000000 | BW7: 8000000 | BX7: 8000000 | BY7: 8000000 | BZ7: 8000000 | CA7: 19370357 | CB7: 8000000 | CC7: 8000000 | CD7: 8000000 | CE7: 8000000 | CF7: 8000000 | CG7: 8000000 | CH7: 8000000 | CI7: 8000000 | CJ7: 8000000 | CK7: 23764811 | CL7: 8000000 | CM7: 8000000 | CN7: 8000000 | CO7: 8000000 | CP7: 8000000 | CQ7: 8000000 | CR7: 8000000 | CS7: 8000000 | CT7: 8000000 | CU7: 22053812
B8: INCOME STATEMENT (ROLLING FCST)
B10: PERIODO
B11: MES | C11: 1 | D11: 2 | E11: 3 | F11: 4 | G11: 5 | H11: 6 | I11: 7 | J11: 8 | K11: 9 | L11: 10 | M11: 11 | N11: 12 | O11: 1 | P11: 2 | Q11: 3 | R11: 4 | S11: 5 | T11: 6 | U11: 7 | V11: 8 | W11: 9 | X11: 10 | Y11: 11 | Z11: 12 | AA11: 2025 | AB11: 1 | AC11: 2 | AD11: 3 | AE11: 4 | AF11: 5 | AG11: 6 | AH11: 7 | AI11: 8 | AJ11: 9 | AK11: 10 | AL11: 11 | AM11: 12 | AN11: 2026 | AO11: 1 | AP11: 2 | AQ11: 3 | AR11: 4 | AS11: 5 | AT11: 6 | AU11: 7 | AV11: 8 | AW11: 9 | AX11: 10 | AY11: 11 | AZ11: 12 | BA11: 2027
B12: QTR | C12: 1 | D12: 1 | E12: 1 | F12: 2 | G12: 2 | H12: 2 | I12: 3 | J12: 3 | K12: 3 | L12: 4 | M12: 4 | N12: 4 | O12: 1 | P12: 1 | Q12: 1 | R12: 2 | S12: 2 | T12: 2 | U12: 3 | V12: 3 | W12: 3 | X12: 4 | Y12: 4 | Z12: 4 | AB12: 1 | AC12: 1 | AD12: 1 | AE12: 2 | AF12: 2 | AG12: 2 | AH12: 3 | AI12: 3 | AJ12: 3 | AK12: 4 | AL12: 4 | AM12: 4 | AO12: 1 | AP12: 1 | AQ12: 1 | AR12: 2 | AS12: 2 | AT12: 2 | AU12: 3 | AV12: 3 | AW12: 3 | AX12: 4 | AY12: 4 | AZ12: 4
