Workbook

Sheet REPORTE_CORTOS
A1: CODIGO | B1: 51CBLO01 | C1: 51CBOM04 | D1: 51CBOM05 | E1: 51CPAM01 | F1: 51CPAZ03 | G1: 51CPAZ04 | H1: 51CPAZ05 | I1: 51CPBD01 | J1: 51CPBD02 | K1: 51CPBR01 | L1: 51CPBW01 | M1: 51CPCA01 | N1: 51CPCB01 | O1: 51CPCD01 | P1: 51CPCS01 | Q1: 51CPCS02 | R1: 51CPCV01 | S1: 51CPDG05 | T1: 51CPDG06 | U1: 51CPDL01 | V1: 51CPDN01 | W1: 51CPFB01 | X1: 51CPFBB01 | Y1: 51CPFIT01 | Z1: 51CPFIT02 | AA1: 51CPFIT03 | AB1: 51CPFP01 | AC1: 51CPFP02 | AD1: 51CPGBS01 | AE1: 51CPGM01 | AF1: 51CPGM02 | AG1: 51CPGMFA01 | AH1: 51CPKM01 | AI1: 51CPKM02 | AJ1: 51CPLM01 | AK1: 51CPLP01 | AL1: 51CPLR01 | AM1: 51CPMB01 | AN1: 51CPMM01 | AO1: 51CPMM02 | AP1: 51CPMS01 | AQ1: 51CPOM01 | AR1: 51CPOM02 | AS1: 51CPOM03 | AT1: 51CPPBS01 | AU1: 51CPPH01 | AV1: 51CPPMS01 | AW1: 51CPRM01 | AX1: 51CPRM02 | AY1: 51CPVAF01 | AZ1: 51CPVB01 | BA1: 51CPVB02 | BB1: 51CPVF01 | BC1: 51CPVT03 | BD1: 51CPVT05 | BE1: 51CPWB01 | BF1: 51CPWP01 | BG1: 51CPWQU01 | BH1: 51CPWR01 | BI1: 51GLVA04 | BJ1: 51JBMP01 | BK1: 51JBNC01 | BL1: 51PLAB01 | BM1: 51PLAB02 | BN1: 51PLBC01 | BO1: 51PLBC02 | BP1: 51PLBCL01 | BQ1: 51PLBCL02 | BR1: 51PLBCL03 | BS1: 51PLBCS01 | BT1: 51PLBFK01 | BU1: 51PLBFK02 | BV1: 51PLBK01 | BW1: 51PLBMF01 | BX1: 51PLBMF03 | BY1: 51PLBMF04 | BZ1: 51PLBMM01 | CA1: 51PLBMM03 | CB1: 51PLBMM04 | CC1: 51PLBMY01 | CD1: 51PLBVP01 | CE1: 51PLC201 | CF1: 51PLC202 | CG1: 51PLC203 | CH1: 51PLCB03 | CI1: 51PLCB04 | CJ1: 51PLCB06 | CK1: 51PLCCDS01 | CL1: 51PLCHS01 | CM1: 51PLCL01 | CN1: 51PLCM01 | CO1: 51PLCN01 | CP1: 51PLCOH01 | CQ1: 51PLCR01 | CR1: 51PLCR02 | CS1: 51PLCRH01 | CT1: 51PLCV01 | CU1: 51PLCV03 | CV1: 51PLCX01 | CW1: 51PLCXA01 | CX1: 51PLCXA02 | CY1: 51PLCXM01 | CZ1: 51PLDL01 | DA1: 51PLDL02 | DB1: 51PLDL03 | DC1: 51PLDL04 | DD1: 51PLDL05 | DE1: 51PLEF01 | DF1: 51PLEL01 | DG1: 51PLFC01 | DH1: 51PLFP01 | DI1: 51PLFP02 | DJ1: 51PLFX01 | DK1: 51PLFX02 | DL1: 51PLFX04 | DM1: 51PLGRH01 | DN1: 51PLGS01 | DO1: 51PLGY01 | DP1: 51PLHG01 | DQ1: 51PLHG02 | DR1: 51PLHG03 | DS1: 51PLHG07 | DT1: 51PLHG09 | DU1: 51PLHG10 | DV1: 51PLHG11 | DW1: 51PLHG12 | DX1: 51PLHG18 | DY1: 51PLHG20 | DZ1: 51PLHG21 | EA1: 51PLHG23 | EB1: 51PLHG24 | EC1: 51PLHG25 | ED1: 51PLHG26 | EE1: 51PLHG27 | EF1: 51PLHG28 | EG1: 51PLHG29 | EH1: 51PLHG30 | EI1: 51PLHG31 | EJ1: 51PLHG32 | EK1: 51PLHG33 | EL1: 51PLHG34 | EM1: 51PLHG35 | EN1: 51PLHG36 | EO1: 51PLHK01 | EP1: 51PLHK02 | EQ1: 51PLHK03 | ER1: 51PLKL01 | ES1: 51PLLC01 | ET1: 51PLPC01 | EU1: 51PLPW01 | EV1: 51PLPW02 | EW1: 51PLPW03 | EX1: 51PLSF01 | EY1: 51PLTF01 | EZ1: 51PLVC01 | FA1: 51TBAC01 | FB1: 51TBAFS01 | FC1: 51TBAP01 | FD1: 51TBBCS01 | FE1: 51TBBF02 | FF1: 51TBBH01 | FG1: 51TBBM01 | FH1: 51TBCA05 | FI1: 51TBCB01 | FJ1: 51TBCBS01 | FK1: 51TBCG01 | FL1: 51TBCMZS01 | FM1: 51TBCR01 | FN1: 51TBCV01 | FO1: 51TBECBA01 | FP1: 51TBECGA01 | FQ1: 51TBEKDA01 | FR1: 51TBEMKA01 | FS1: 51TBEVCS01 | FT1: 51TBEX01 | FU1: 51TBEX03 | FV1: 51TBKY01 | FW1: 51TBLC01 | FX1: 51TBMC01 | FY1: 51TBME01 | FZ1: 51TBME03 | GA1: 51TBMF01 | GB1: 51TBML01 | GC1: 51TBMM01 | GD1: 51TBMN01 | GE1: 51TBMVA01 | GF1: 51TBMZ01 | GG1: 51TBPF01 | GH1: 51TBTM01 | GI1: 51TBTM05 | GJ1: 51TBVB01 | GK1: 51TBVCA01 | GL1: 51TBVCS01 | GM1: 51TBVDS01 | GN1: 51TBVK01 | GO1: 51TBVRS01 | GP1: 51TBZA01 | GQ1: 51TBZN01 | GR1: Descripción | GS1: LT | GT1: Proveedor | GU1: Tipo | GV1: A1 | GW1: A2 | GX1: A3 | GY1: Type | GZ1: 45887 | HA1: =WORKDAY.INTL(GZ1,1,11) -> 45888 | HB1: =WORKDAY.INTL(HA1,1,11) -> 45889 | HC1: =WORKDAY.INTL(HB1,1,11) -> 45890 | HD1: =WORKDAY.INTL(HC1,1,11) -> 45891 | HE1: =WORKDAY.INTL(HD1,1,11) -> 45892 | HF1: =WORKDAY.INTL(HE1,1,11) -> 45894 | HG1: =HF1+7-WEEKDAY(HF1-1)+1 -> 45901 | HH1: =HG1+7-WEEKDAY(HG1-1)+1 -> 45908 | HI1: =HH1+7-WEEKDAY(HH1-1)+1 -> 45915 | HJ1: =HI1+7-WEEKDAY(HI1-1)+1 -> 45922 | HK1: =HJ1+7-WEEKDAY(HJ1-1)+1 -> 45929 | HL1: =HK1+7-WEEKDAY(HK1-1)+1 -> 45936 | HM1: =HL1+7-WEEKDAY(HL1-1)+1 -> 45943 | HN1: =HM1+7-WEEKDAY(HM1-1)+1 -> 45950 | ... HT1: =HS1+7-WEEKDAY(HS1-1)+1 -> 45992 | HU1: Semanas de corto | HV1: Comentarios | HW1: Tipo
A2: 41CPAM01 | E2: 30 | GR2: AMBROTOSE AO CAPSULAS MANNATECH | GS2: 2 | GV2: =SUMIF(FACT_A1[cve_prod],DIM_BILL[[#This Row],[CODIGO]],FACT_A1[Existencia]) -> 0 | GW2: =SUMIF(FACT_A2[cve_prod],DIM_BILL[[#This Row],[CODIGO]],FACT_A2[Existencia]) -> 0 | GY2: Por Surtir & Parcial | GZ2: =SUMIFS(POs[saldo],POs[cve_prod],DIM_BILL[[#This Row],[CODIGO]],POs[status],$GY2,POs[f_ent],GZ$1) -> 0 | HA2: =SUMIFS(POs[saldo],POs[cve_prod],DIM_BILL[[#This Row],[CODIGO]],POs[status],$GY2,POs[f_ent],HA$1) -> 0 | HB2: =SUMIFS(POs[saldo],POs[cve_prod],DIM_BILL[[#This Row],[CODIGO]],POs[status],$GY2,POs[f_ent],HB$1) -> 0 | HC2: =SUMIFS(POs[saldo],POs[cve_prod],DIM_BILL[[#This Row],[CODIGO]],POs[status],$GY2,POs[f_ent],HC$1) -> 0 | HD2: =SUMIFS(POs[saldo],POs[cve_prod],DIM_BILL[[#This Row],[CODIGO]],POs[status],$GY2,POs[f_ent],HD$1) -> 0 | HE2: =SUMIFS(POs[saldo],POs[cve_prod],DIM_BILL[[#This Row],[CODIGO]],POs[status],$GY2,POs[f_ent],HE$1) -> 0 | HF2: =SUMIFS(POs[saldo],POs[cve_prod],DIM_BILL[[#This Row],[CODIGO]],POs[status],$GY2,POs[Semana],WEEKNUM(HF$1)) -> 0 | HG2: =SUMIFS(POs[saldo],POs[cve_prod],DIM_BILL[[#This Row],[CODIGO]],POs[status],$GY2,POs[Semana],WEEKNUM(HG$1)) -> 0 | HH2: =SUMIFS(POs[saldo],POs[cve_prod],DIM_BILL[[#This Row],[CODIGO]],POs[status],$GY2,POs[Semana],WEEKNUM(HH$1)) -> 0 | HI2: =SUMIFS(POs[saldo],POs[cve_prod],DIM_BILL[[#This Row],[CODIGO]],POs[status],$GY2,POs[Semana],WEEKNUM(HI$1)) -> 0 | HJ2: =SUMIFS(POs[saldo],POs[cve_prod],DIM_BILL[[#This Row],[CODIGO]],POs[status],$GY2,POs[Semana],WEEKNUM(HJ$1)) -> 0 | HK2: =SUMIFS(POs[saldo],POs[cve_prod],DIM_BILL[[#This Row],[CODIGO]],POs[status],$GY2,POs[Semana],WEEKNUM(HK$1)) -> 0 | HL2: =SUMIFS(POs[saldo],POs[cve_prod],DIM_BILL[[#This Row],[CODIGO]],POs[status],$GY2,POs[Semana],WEEKNUM(HL$1)) -> 0 | HM2: =SUMIFS(POs[saldo],POs[cve_prod],DIM_BILL[[#This Row],[CODIGO]],POs[status],$GY2,POs[Semana],WEEKNUM(HM$1)) -> 0 | ... HT2: =SUMIFS(POs[saldo],POs[cve_prod],DIM_BILL[[#This Row],[CODIGO]],POs[status],$GY2,POs[Semana],WEEKNUM(HT$1)) -> 0 | HW2: =DIM_BILL[[#This Row],[Tipo]]
A3: 41CPAM01 | E3: 30 | GR3: AMBROTOSE AO CAPSULAS MANNATECH | GS3: 2 | GV3: =SUMIF(FACT_A1[cve_prod],DIM_BILL[[#This Row],[CODIGO]],FACT_A1[Existencia]) -> 0 | GW3: =SUMIF(FACT_A2[cve_prod],DIM_BILL[[#This Row],[CODIGO]],FACT_A2[Existencia]) -> 0 | GY3: Demanda | GZ3: =SUMPRODUCT($B3:$GQ3,INDEX(PLAN_PRODUCCION!$B$4:$GQ$24,COLUMN()-COLUMN($GZ$1)+1,0)) -> 60000 | HA3: =SUMPRODUCT($B3:$GQ3,INDEX(PLAN_PRODUCCION!$B$4:$GQ$24,COLUMN()-COLUMN($GZ$1)+1,0)) -> 0 | HB3: =SUMPRODUCT($B3:$GQ3,INDEX(PLAN_PRODUCCION!$B$4:$GQ$24,COLUMN()-COLUMN($GZ$1)+1,0)) -> 0 | HC3: =SUMPRODUCT($B3:$GQ3,INDEX(PLAN_PRODUCCION!$B$4:$GQ$24,COLUMN()-COLUMN($GZ$1)+1,0)) -> 0 | HD3: =SUMPRODUCT($B3:$GQ3,INDEX(PLAN_PRODUCCION!$B$4:$GQ$24,COLUMN()-COLUMN($GZ$1)+1,0)) -> 0 | HE3: =SUMPRODUCT($B3:$GQ3,INDEX(PLAN_PRODUCCION!$B$4:$GQ$24,COLUMN()-COLUMN($GZ$1)+1,0)) -> 0 | HF3: =SUMPRODUCT($B3:$GQ3,INDEX(PLAN_PRODUCCION!$B$4:$GQ$24,COLUMN()-COLUMN($GZ$1)+1,0)) -> 0 | HG3: =SUMPRODUCT($B3:$GQ3,INDEX(PLAN_PRODUCCION!$B$4:$GQ$24,COLUMN()-COLUMN($GZ$1)+1,0)) -> 0 | ... HT3: =SUMPRODUCT($B3:$GQ3,INDEX(PLAN_PRODUCCION!$B$4:$GQ$24,COLUMN()-COLUMN($GZ$1)+1,0)) -> 0 | HW3: =DIM_BILL[[#This Row],[Tipo]]
A4: 41CPAM01 | E4: 30 | GR4: AMBROTOSE AO CAPSULAS MANNATECH | GS4: 2 | GV4: =SUMIF(FACT_A1[cve_prod],DIM_BILL[[#This Row],[CODIGO]],FACT_A1[Existencia]) -> 0 | GW4: =SUMIF(FACT_A2[cve_prod],DIM_BILL[[#This Row],[CODIGO]],FACT_A2[Existencia]) -> 0 | GY4: Cortos + PO's Confirmadas | GZ4: =GV4+GW4+GX4+GZ2-GZ3 -> -60000 | HA4: =GZ4+HA2-HA3 -> -60000 | HB4: =HA4+HB2-HB3 -> -60000 | HC4: =HB4+HC2-HC3 -> -60000 | HD4: =HC4+HD2-HD3 -> -60000 | HE4: =HD4+HE2-HE3 -> -60000 | HF4: =HE4+HF2-HF3 -> -60000 | HG4: =HF4+HG2-HG3 -> -60000 | HH4: =HG4+HH2-HH3 -> -60000 | ... HT4: =HS4+HT2-HT3 -> -60000 | HU4: =COUNTIF(GZ4:HT4,"<0") -> 21 | HW4: =DIM_BILL[[#This Row],[Tipo]]
A5: 41PRAB02 | BL5: 0.0013331765 | BM5: 4.4439216e-05 | GR5: PREMEZCLA COLAGENO PEPTAN P 5000 LD + D3 | GS5: 2 | GT5: Aspen Labs | GU5: MATERIA PRIMA | GV5: =SUMIF(FACT_A1[cve_prod],DIM_BILL[[#This Row],[CODIGO]],FACT_A1[Existencia]) -> 0 | GW5: =SUMIF(FACT_A2[cve_prod],DIM_BILL[[#This Row],[CODIGO]],FACT_A2[Existencia]) -> 37.731 | GY5: Por Surtir & Parcial | GZ5: =SUMIFS(POs[saldo],POs[cve_prod],DIM_BILL[[#This Row],[CODIGO]],POs[status],$GY5,POs[f_ent],GZ$1) -> 0 | HA5: =SUMIFS(POs[saldo],POs[cve_prod],DIM_BILL[[#This Row],[CODIGO]],POs[status],$GY5,POs[f_ent],HA$1) -> 0 | HB5: =SUMIFS(POs[saldo],POs[cve_prod],DIM_BILL[[#This Row],[CODIGO]],POs[status],$GY5,POs[f_ent],HB$1) -> 0 | HC5: =SUMIFS(POs[saldo],POs[cve_prod],DIM_BILL[[#This Row],[CODIGO]],POs[status],$GY5,POs[f_ent],HC$1) -> 0 | HD5: =SUMIFS(POs[saldo],POs[cve_prod],DIM_BILL[[#This Row],[CODIGO]],POs[status],$GY5,POs[f_ent],HD$1) -> 0 | HE5: =SUMIFS(POs[saldo],POs[cve_prod],DIM_BILL[[#This Row],[CODIGO]],POs[status],$GY5,POs[f_ent],HE$1) -> 0 | HF5: =SUMIFS(POs[saldo],POs[cve_prod],DIM_BILL[[#This Row],[CODIGO]],POs[status],$GY5,POs[Semana],WEEKNUM(HF$1)) -> 0 | HG5: =SUMIFS(POs[saldo],POs[cve_prod],DIM_BILL[[#This Row],[CODIGO]],POs[status],$GY5,POs[Semana],WEEKNUM(HG$1)) -> 0 | HH5: =SUMIFS(POs[saldo],POs[cve_prod],DIM_BILL[[#This Row],[CODIGO]],POs[status],$GY5,POs[Semana],WEEKNUM(HH$1)) -> 0 | HI5: =SUMIFS(POs[saldo],POs[cve_prod],DIM_BILL[[#This Row],[CODIGO]],POs[status],$GY5,POs[Semana],WEEKNUM(HI$1)) -> 0 | HJ5: =SUMIFS(POs[saldo],POs[cve_prod],DIM_BILL[[#This Row],[CODIGO]],POs[status],$GY5,POs[Semana],WEEKNUM(HJ$1)) -> 0 | HK5: =SUMIFS(POs[saldo],POs[cve_prod],DIM_BILL[[#This Row],[CODIGO]],POs[status],$GY5,POs[Semana],WEEKNUM(HK$1)) -> 0 | HL5: =SUMIFS(POs[saldo],POs[cve_prod],DIM_BILL[[#This Row],[CODIGO]],POs[status],$GY5,POs[Semana],WEEKNUM(HL$1)) -> 0 | HM5: =SUMIFS(POs[saldo],POs[cve_prod],DIM_BILL[[#This Row],[CODIGO]],POs[status],$GY5,POs[Semana],WEEKNUM(HM$1)) -> 0 | ... HT5: =SUMIFS(POs[saldo],POs[cve_prod],DIM_BILL[[#This Row],[CODIGO]],POs[status],$GY5,POs[Semana],WEEKNUM(HT$1)) -> 0 | HW5: =DIM_BILL[[#This Row],[Tipo]] -> MATERIA PRIMA
A6: 41PRAB02 | BL6: 0.0013331765 | BM6: 4.4439216e-05 | GR6: PREMEZCLA COLAGENO PEPTAN P 5000 LD + D3 | GS6: 2 | GT6: Aspen Labs | GU6: MATERIA PRIMA | GV6: =SUMIF(FACT_A1[cve_prod],DIM_BILL[[#This Row],[CODIGO]],FACT_A1[Existencia]) -> 0 | GW6: =SUMIF(FACT_A2[cve_prod],DIM_BILL[[#This Row],[CODIGO]],FACT_A2[Existencia]) -> 37.731 | GY6: Demanda | GZ6: =SUMPRODUCT($B6:$GQ6,INDEX(PLAN_PRODUCCION!$B$4:$GQ$24,COLUMN()-COLUMN($GZ$1)+1,0)) -> 7.683096 | HA6: =SUMPRODUCT($B6:$GQ6,INDEX(PLAN_PRODUCCION!$B$4:$GQ$24,COLUMN()-COLUMN($GZ$1)+1,0)) -> 0 | HB6: =SUMPRODUCT($B6:$GQ6,INDEX(PLAN_PRODUCCION!$B$4:$GQ$24,COLUMN()-COLUMN($GZ$1)+1,0)) -> 0 | HC6: =SUMPRODUCT($B6:$GQ6,INDEX(PLAN_PRODUCCION!$B$4:$GQ$24,COLUMN()-COLUMN($GZ$1)+1,0)) -> 0 | HD6: =SUMPRODUCT($B6:$GQ6,INDEX(PLAN_PRODUCCION!$B$4:$GQ$24,COLUMN()-COLUMN($GZ$1)+1,0)) -> 0 | HE6: =SUMPRODUCT($B6:$GQ6,INDEX(PLAN_PRODUCCION!$B$4:$GQ$24,COLUMN()-COLUMN($GZ$1)+1,0)) -> 0 | HF6: =SUMPRODUCT($B6:$GQ6,INDEX(PLAN_PRODUCCION!$B$4:$GQ$24,COLUMN()-COLUMN($GZ$1)+1,0)) -> 9.0656 | HG6: =SUMPRODUCT($B6:$GQ6,INDEX(PLAN_PRODUCCION!$B$4:$GQ$24,COLUMN()-COLUMN($GZ$1)+1,0)) -> 9.0656 | ... HT6: =SUMPRODUCT($B6:$GQ6,INDEX(PLAN_PRODUCCION!$B$4:$GQ$24,COLUMN()-COLUMN($GZ$1)+1,0)) -> 0 | HW6: =DIM_BILL[[#This Row],[Tipo]] -> MATERIA PRIMA
A7: 41PRAB02 | BL7: 0.0013331765 | BM7: 4.4439216e-05 | GR7: PREMEZCLA COLAGENO PEPTAN P 5000 LD + D3 | GS7: 2 | GT7: Aspen Labs | GU7: MATERIA PRIMA | GV7: =SUMIF(FACT_A1[cve_prod],DIM_BILL[[#This Row],[CODIGO]],FACT_A1[Existencia]) -> 0 | GW7: =SUMIF(FACT_A2[cve_prod],DIM_BILL[[#This Row],[CODIGO]],FACT_A2[Existencia]) -> 37.731 | GY7: Cortos + PO's Confirmadas | GZ7: =GV7+GW7+GX7+GZ5-GZ6 -> 30.047904 | HA7: =GZ7+HA5-HA6 -> 30.047904 | HB7: =HA7+HB5-HB6 -> 30.047904 | HC7: =HB7+HC5-HC6 -> 30.047904 | HD7: =HC7+HD5-HD6 -> 30.047904 | HE7: =HD7+HE5-HE6 -> 30.047904 | HF7: =HE7+HF5-HF6 -> 20.982304 | HG7: =HF7+HG5-HG6 -> 11.916704 | HH7: =HG7+HH5-HH6 -> 11.916704 | ... HT7: =HS7+HT5-HT6 -> 11.916704 | HU7: =COUNTIF(GZ7:HT7,"<0") -> 0 | HW7: =DIM_BILL[[#This Row],[Tipo]] -> MATERIA PRIMA
A8: 51PLHG17 | DX8: 10 | GR8: HIDRA2GO UVA SOBRES 6g ST | GS8: 2 | GV8: =SUMIF(FACT_A1[cve_prod],DIM_BILL[[#This Row],[CODIGO]],FACT_A1[Existencia]) -> 0 | GY8: Por Surtir & Parcial | GZ8: =SUMIFS(POs[saldo],POs[cve_prod],DIM_BILL[[#This Row],[CODIGO]],POs[status],$GY8,POs[f_ent],GZ$1) -> 0 | HA8: =SUMIFS(POs[saldo],POs[cve_prod],DIM_BILL[[#This Row],[CODIGO]],POs[status],$GY8,POs[f_ent],HA$1) -> 0 | HB8: =SUMIFS(POs[saldo],POs[cve_prod],DIM_BILL[[#This Row],[CODIGO]],POs[status],$GY8,POs[f_ent],HB$1) -> 0 | HC8: =SUMIFS(POs[saldo],POs[cve_prod],DIM_BILL[[#This Row],[CODIGO]],POs[status],$GY8,POs[f_ent],HC$1) -> 0 | HD8: =SUMIFS(POs[saldo],POs[cve_prod],DIM_BILL[[#This Row],[CODIGO]],POs[status],$GY8,POs[f_ent],HD$1) -> 0 | HE8: =SUMIFS(POs[saldo],POs[cve_prod],DIM_BILL[[#This Row],[CODIGO]],POs[status],$GY8,POs[f_ent],HE$1) -> 0 | HF8: =SUMIFS(POs[saldo],POs[cve_prod],DIM_BILL[[#This Row],[CODIGO]],POs[status],$GY8,POs[Semana],WEEKNUM(HF$1)) -> 0 | HG8: =SUMIFS(POs[saldo],POs[cve_prod],DIM_BILL[[#This Row],[CODIGO]],POs[status],$GY8,POs[Semana],WEEKNUM(HG$1)) -> 0 | HH8: =SUMIFS(POs[saldo],POs[cve_prod],DIM_BILL[[#This Row],[CODIGO]],POs[status],$GY8,POs[Semana],WEEKNUM(HH$1)) -> 0 | HI8: =SUMIFS(POs[saldo],POs[cve_prod],DIM_BILL[[#This Row],[CODIGO]],POs[status],$GY8,POs[Semana],WEEKNUM(HI$1)) -> 0 | HJ8: =SUMIFS(POs[saldo],POs[cve_prod],DIM_BILL[[#This Row],[CODIGO]],POs[status],$GY8,POs[Semana],WEEKNUM(HJ$1)) -> 0 | HK8: =SUMIFS(POs[saldo],POs[cve_prod],DIM_BILL[[#This Row],[CODIGO]],POs[status],$GY8,POs[Semana],WEEKNUM(HK$1)) -> 0 | HL8: =SUMIFS(POs[saldo],POs[cve_prod],DIM_BILL[[#This Row],[CODIGO]],POs[status],$GY8,POs[Semana],WEEKNUM(HL$1)) -> 0 | HM8: =SUMIFS(POs[saldo],POs[cve_prod],DIM_BILL[[#This Row],[CODIGO]],POs[status],$GY8,POs[Semana],WEEKNUM(HM$1)) -> 0 | ... HT8: =SUMIFS(POs[saldo],POs[cve_prod],DIM_BILL[[#This Row],[CODIGO]],POs[status],$GY8,POs[Semana],WEEKNUM(HT$1)) -> 0 | HW8: =DIM_BILL[[#This Row],[Tipo]]
A9: 51PLHG17 | DX9: 10 | GR9: HIDRA2GO UVA SOBRES 6g ST | GS9: 2 | GV9: =SUMIF(FACT_A1[cve_prod],DIM_BILL[[#This Row],[CODIGO]],FACT_A1[Existencia]) -> 0 | GW9: =SUMIF(FACT_A2[cve_prod],DIM_BILL[[#This Row],[CODIGO]],FACT_A2[Existencia]) -> 0 | GY9: Demanda | GZ9: =SUMPRODUCT($B9:$GQ9,INDEX(PLAN_PRODUCCION!$B$4:$GQ$24,COLUMN()-COLUMN($GZ$1)+1,0)) -> 0 | HA9: =SUMPRODUCT($B9:$GQ9,INDEX(PLAN_PRODUCCION!$B$4:$GQ$24,COLUMN()-COLUMN($GZ$1)+1,0)) -> 0 | HB9: =SUMPRODUCT($B9:$GQ9,INDEX(PLAN_PRODUCCION!$B$4:$GQ$24,COLUMN()-COLUMN($GZ$1)+1,0)) -> 0 | HC9: =SUMPRODUCT($B9:$GQ9,INDEX(PLAN_PRODUCCION!$B$4:$GQ$24,COLUMN()-COLUMN($GZ$1)+1,0)) -> 0 | HD9: =SUMPRODUCT($B9:$GQ9,INDEX(PLAN_PRODUCCION!$B$4:$GQ$24,COLUMN()-COLUMN($GZ$1)+1,0)) -> 0 | HE9: =SUMPRODUCT($B9:$GQ9,INDEX(PLAN_PRODUCCION!$B$4:$GQ$24,COLUMN()-COLUMN($GZ$1)+1,0)) -> 0 | HF9: =SUMPRODUCT($B9:$GQ9,INDEX(PLAN_PRODUCCION!$B$4:$GQ$24,COLUMN()-COLUMN($GZ$1)+1,0)) -> 0 | HG9: =SUMPRODUCT($B9:$GQ9,INDEX(PLAN_PRODUCCION!$B$4:$GQ$24,COLUMN()-COLUMN($GZ$1)+1,0)) -> 0 | ... HT9: =SUMPRODUCT($B9:$GQ9,INDEX(PLAN_PRODUCCION!$B$4:$GQ$24,COLUMN()-COLUMN($GZ$1)+1,0)) -> 0 | HW9: =DIM_BILL[[#This Row],[Tipo]]
A10: 51PLHG17 | DX10: 10 | GR10: HIDRA2GO UVA SOBRES 6g ST | GS10: 2 | GV10: =SUMIF(FACT_A1[cve_prod],DIM_BILL[[#This Row],[CODIGO]],FACT_A1[Existencia]) -> 0 | GW10: =SUMIF(FACT_A2[cve_prod],DIM_BILL[[#This Row],[CODIGO]],FACT_A2[Existencia]) -> 0 | GY10: Cortos + PO's Confirmadas | GZ10: =GV10+GW10+GX10+GZ8-GZ9 -> 0 | HA10: =GZ10+HA8-HA9 -> 0 | HB10: =HA10+HB8-HB9 -> 0 | HC10: =HB10+HC8-HC9 -> 0 | HD10: =HC10+HD8-HD9 -> 0 | HE10: =HD10+HE8-HE9 -> 0 | HF10: =HE10+HF8-HF9 -> 0 | HG10: =HF10+HG8-HG9 -> 0 | HH10: =HG10+HH8-HH9 -> 0 | ... HT10: =HS10+HT8-HT9 -> 0 | HU10: =COUNTIF(GZ10:HT10,"<0") -> 0 | HW10: =DIM_BILL[[#This Row],[Tipo]]
A11: 51PLHG19 | DY11: 25.75 | GR11: HIDRA2GO MORA AZUL SOBRES 6g ST | GS11: 2 | GV11: =SUMIF(FACT_A1[cve_prod],DIM_BILL[[#This Row],[CODIGO]],FACT_A1[Existencia]) -> 0 | GW11: =SUMIF(FACT_A2[cve_prod],DIM_BILL[[#This Row],[CODIGO]],FACT_A2[Existencia]) -> 0 | GY11: Por Surtir & Parcial | GZ11: =SUMIFS(POs[saldo],POs[cve_prod],DIM_BILL[[#This Row],[CODIGO]],POs[status],$GY11,POs[f_ent],GZ$1) -> 0 | HA11: =SUMIFS(POs[saldo],POs[cve_prod],DIM_BILL[[#This Row],[CODIGO]],POs[status],$GY11,POs[f_ent],HA$1) -> 0 | HB11: =SUMIFS(POs[saldo],POs[cve_prod],DIM_BILL[[#This Row],[CODIGO]],POs[status],$GY11,POs[f_ent],HB$1) -> 0 | HC11: =SUMIFS(POs[saldo],POs[cve_prod],DIM_BILL[[#This Row],[CODIGO]],POs[status],$GY11,POs[f_ent],HC$1) -> 0 | HD11: =SUMIFS(POs[saldo],POs[cve_prod],DIM_BILL[[#This Row],[CODIGO]],POs[status],$GY11,POs[f_ent],HD$1) -> 0 | HE11: =SUMIFS(POs[saldo],POs[cve_prod],DIM_BILL[[#This Row],[CODIGO]],POs[status],$GY11,POs[f_ent],HE$1) -> 0 | HF11: =SUMIFS(POs[saldo],POs[cve_prod],DIM_BILL[[#This Row],[CODIGO]],POs[status],$GY11,POs[Semana],WEEKNUM(HF$1)) -> 0 | HG11: =SUMIFS(POs[saldo],POs[cve_prod],DIM_BILL[[#This Row],[CODIGO]],POs[status],$GY11,POs[Semana],WEEKNUM(HG$1)) -> 0 | HH11: =SUMIFS(POs[saldo],POs[cve_prod],DIM_BILL[[#This Row],[CODIGO]],POs[status],$GY11,POs[Semana],WEEKNUM(HH$1)) -> 0 | HI11: =SUMIFS(POs[saldo],POs[cve_prod],DIM_BILL[[#This Row],[CODIGO]],POs[status],$GY11,POs[Semana],WEEKNUM(HI$1)) -> 0 | HJ11: =SUMIFS(POs[saldo],POs[cve_prod],DIM_BILL[[#This Row],[CODIGO]],POs[status],$GY11,POs[Semana],WEEKNUM(HJ$1)) -> 0 | HK11: =SUMIFS(POs[saldo],POs[cve_prod],DIM_BILL[[#This Row],[CODIGO]],POs[status],$GY11,POs[Semana],WEEKNUM(HK$1)) -> 0 | HL11: =SUMIFS(POs[saldo],POs[cve_prod],DIM_BILL[[#This Row],[CODIGO]],POs[status],$GY11,POs[Semana],WEEKNUM(HL$1)) -> 0 | HM11: =SUMIFS(POs[saldo],POs[cve_prod],DIM_BILL[[#This Row],[CODIGO]],POs[status],$GY11,POs[Semana],WEEKNUM(HM$1)) -> 0 | ... HT11: =SUMIFS(POs[saldo],POs[cve_prod],DIM_BILL[[#This Row],[CODIGO]],POs[status],$GY11,POs[Semana],WEEKNUM(HT$1)) -> 0 | HW11: =DIM_BILL[[#This Row],[Tipo]]
A12: 51PLHG19 | DY12: 25.75 | GR12: HIDRA2GO MORA AZUL SOBRES 6g ST | GS12: 2 | GV12: =SUMIF(FACT_A1[cve_prod],DIM_BILL[[#This Row],[CODIGO]],FACT_A1[Existencia]) -> 0 | GW12: =SUMIF(FACT_A2[cve_prod],DIM_BILL[[#This Row],[CODIGO]],FACT_A2[Existencia]) -> 0 | GY12: Demanda | GZ12: =SUMPRODUCT($B12:$GQ12,INDEX(PLAN_PRODUCCION!$B$4:$GQ$24,COLUMN()-COLUMN($GZ$1)+1,0)) -> 92700 | HA12: =SUMPRODUCT($B12:$GQ12,INDEX(PLAN_PRODUCCION!$B$4:$GQ$24,COLUMN()-COLUMN($GZ$1)+1,0)) -> 0 | HB12: =SUMPRODUCT($B12:$GQ12,INDEX(PLAN_PRODUCCION!$B$4:$GQ$24,COLUMN()-COLUMN($GZ$1)+1,0)) -> 0 | HC12: =SUMPRODUCT($B12:$GQ12,INDEX(PLAN_PRODUCCION!$B$4:$GQ$24,COLUMN()-COLUMN($GZ$1)+1,0)) -> 0 | HD12: =SUMPRODUCT($B12:$GQ12,INDEX(PLAN_PRODUCCION!$B$4:$GQ$24,COLUMN()-COLUMN($GZ$1)+1,0)) -> 0 | HE12: =SUMPRODUCT($B12:$GQ12,INDEX(PLAN_PRODUCCION!$B$4:$GQ$24,COLUMN()-COLUMN($GZ$1)+1,0)) -> 0 | HF12: =SUMPRODUCT($B12:$GQ12,INDEX(PLAN_PRODUCCION!$B$4:$GQ$24,COLUMN()-COLUMN($GZ$1)+1,0)) -> 0 | HG12: =SUMPRODUCT($B12:$GQ12,INDEX(PLAN_PRODUCCION!$B$4:$GQ$24,COLUMN()-COLUMN($GZ$1)+1,0)) -> 0 | ... HT12: =SUMPRODUCT($B12:$GQ12,INDEX(PLAN_PRODUCCION!$B$4:$GQ$24,COLUMN()-COLUMN($GZ$1)+1,0)) -> 0 | HW12: =DIM_BILL[[#This Row],[Tipo]]
A13: 51PLHG19 | DY13: 25.75 | GR13: HIDRA2GO MORA AZUL SOBRES 6g ST | GS13: 2 | GV13: =SUMIF(FACT_A1[cve_prod],DIM_BILL[[#This Row],[CODIGO]],FACT_A1[Existencia]) -> 0 | GW13: =SUMIF(FACT_A2[cve_prod],DIM_BILL[[#This Row],[CODIGO]],FACT_A2[Existencia]) -> 0 | GY13: Cortos + PO's Confirmadas | GZ13: =GV13+GW13+GX13+GZ11-GZ12 -> -92700 | HA13: =GZ13+HA11-HA12 -> -92700 | HB13: =HA13+HB11-HB12 -> -92700 | HC13: =HB13+HC11-HC12 -> -92700 | HD13: =HC13+HD11-HD12 -> -92700 | HE13: =HD13+HE11-HE12 -> -92700 | HF13: =HE13+HF11-HF12 -> -92700 | HG13: =HF13+HG11-HG12 -> -92700 | HH13: =HG13+HH11-HH12 -> -92700 | ... HT13: =HS13+HT11-HT12 -> -92700 | HU13: =COUNTIF(GZ13:HT13,"<0") -> 21 | HW13: =DIM_BILL[[#This Row],[Tipo]]
A14: 51PLHG22 | EA14: 10 | GR14: HIDRA2GO FRESA-KIWI SOBRES 6g ST | GS14: 2 | GV14: =SUMIF(FACT_A1[cve_prod],DIM_BILL[[#This Row],[CODIGO]],FACT_A1[Existencia]) -> 0 | GW14: =SUMIF(FACT_A2[cve_prod],DIM_BILL[[#This Row],[CODIGO]],FACT_A2[Existencia]) -> 0 | GY14: Por Surtir & Parcial | GZ14: =SUMIFS(POs[saldo],POs[cve_prod],DIM_BILL[[#This Row],[CODIGO]],POs[status],$GY14,POs[f_ent],GZ$1) -> 0 | HA14: =SUMIFS(POs[saldo],POs[cve_prod],DIM_BILL[[#This Row],[CODIGO]],POs[status],$GY14,POs[f_ent],HA$1) -> 0 | HB14: =SUMIFS(POs[saldo],POs[cve_prod],DIM_BILL[[#This Row],[CODIGO]],POs[status],$GY14,POs[f_ent],HB$1) -> 0 | HC14: =SUMIFS(POs[saldo],POs[cve_prod],DIM_BILL[[#This Row],[CODIGO]],POs[status],$GY14,POs[f_ent],HC$1) -> 0 | HD14: =SUMIFS(POs[saldo],POs[cve_prod],DIM_BILL[[#This Row],[CODIGO]],POs[status],$GY14,POs[f_ent],HD$1) -> 0 | HE14: =SUMIFS(POs[saldo],POs[cve_prod],DIM_BILL[[#This Row],[CODIGO]],POs[status],$GY14,POs[f_ent],HE$1) -> 0 | HF14: =SUMIFS(POs[saldo],POs[cve_prod],DIM_BILL[[#This Row],[CODIGO]],POs[status],$GY14,POs[Semana],WEEKNUM(HF$1)) -> 0 | HG14: =SUMIFS(POs[saldo],POs[cve_prod],DIM_BILL[[#This Row],[CODIGO]],POs[status],$GY14,POs[Semana],WEEKNUM(HG$1)) -> 0 | HH14: =SUMIFS(POs[saldo],POs[cve_prod],DIM_BILL[[#This Row],[CODIGO]],POs[status],$GY14,POs[Semana],WEEKNUM(HH$1)) -> 0 | HI14: =SUMIFS(POs[saldo],POs[cve_prod],DIM_BILL[[#This Row],[CODIGO]],POs[status],$GY14,POs[Semana],WEEKNUM(HI$1)) -> 0 | HJ14: =SUMIFS(POs[saldo],POs[cve_prod],DIM_BILL[[#This Row],[CODIGO]],POs[status],$GY14,POs[Semana],WEEKNUM(HJ$1)) -> 0 | HK14: =SUMIFS(POs[saldo],POs[cve_prod],DIM_BILL[[#This Row],[CODIGO]],POs[status],$GY14,POs[Semana],WEEKNUM(HK$1)) -> 0 | HL14: =SUMIFS(POs[saldo],POs[cve_prod],DIM_BILL[[#This Row],[CODIGO]],POs[status],$GY14,POs[Semana],WEEKNUM(HL$1)) -> 0 | HM14: =SUMIFS(POs[saldo],POs[cve_prod],DIM_BILL[[#This Row],[CODIGO]],POs[status],$GY14,POs[Semana],WEEKNUM(HM$1)) -> 0 | ... HT14: =SUMIFS(POs[saldo],POs[cve_prod],DIM_BILL[[#This Row],[CODIGO]],POs[status],$GY14,POs[Semana],WEEKNUM(HT$1)) -> 0 | HW14: =DIM_BILL[[#This Row],[Tipo]]
A15: 51PLHG22 | EA15: 10 | GR15: HIDRA2GO FRESA-KIWI SOBRES 6g ST | GS15: 2 | GV15: =SUMIF(FACT_A1[cve_prod],DIM_BILL[[#This Row],[CODIGO]],FACT_A1[Existencia]) -> 0 | GW15: =SUMIF(FACT_A2[cve_prod],DIM_BILL[[#This Row],[CODIGO]],FACT_A2[Existencia]) -> 0 | GY15: Demanda | GZ15: =SUMPRODUCT($B15:$GQ15,INDEX(PLAN_PRODUCCION!$B$4:$GQ$24,COLUMN()-COLUMN($GZ$1)+1,0)) -> 0 | HA15: =SUMPRODUCT($B15:$GQ15,INDEX(PLAN_PRODUCCION!$B$4:$GQ$24,COLUMN()-COLUMN($GZ$1)+1,0)) -> 0 | HB15: =SUMPRODUCT($B15:$GQ15,INDEX(PLAN_PRODUCCION!$B$4:$GQ$24,COLUMN()-COLUMN($GZ$1)+1,0)) -> 0 | HC15: =SUMPRODUCT($B15:$GQ15,INDEX(PLAN_PRODUCCION!$B$4:$GQ$24,COLUMN()-COLUMN($GZ$1)+1,0)) -> 0 | HD15: =SUMPRODUCT($B15:$GQ15,INDEX(PLAN_PRODUCCION!$B$4:$GQ$24,COLUMN()-COLUMN($GZ$1)+1,0)) -> 0 | HE15: =SUMPRODUCT($B15:$GQ15,INDEX(PLAN_PRODUCCION!$B$4:$GQ$24,COLUMN()-COLUMN($GZ$1)+1,0)) -> 0 | HF15: =SUMPRODUCT($B15:$GQ15,INDEX(PLAN_PRODUCCION!$B$4:$GQ$24,COLUMN()-COLUMN($GZ$1)+1,0)) -> 0 | HG15: =SUMPRODUCT($B15:$GQ15,INDEX(PLAN_PRODUCCION!$B$4:$GQ$24,COLUMN()-COLUMN($GZ$1)+1,0)) -> 0 | ... HT15: =SUMPRODUCT($B15:$GQ15,INDEX(PLAN_PRODUCCION!$B$4:$GQ$24,COLUMN()-COLUMN($GZ$1)+1,0)) -> 0 | HW15: =DIM_BILL[[#This Row],[Tipo]]
A16: 51PLHG22 | EA16: 10 | GR16: HIDRA2GO FRESA-KIWI SOBRES 6g ST | GS16: 2 | GV16: =SUMIF(FACT_A1[cve_prod],DIM_BILL[[#This Row],[CODIGO]],FACT_A1[Existencia]) -> 0 | GW16: =SUMIF(FACT_A2[cve_prod],DIM_BILL[[#This Row],[CODIGO]],FACT_A2[Existencia]) -> 0 | GY16: Cortos + PO's Confirmadas | GZ16: =GV16+GW16+GX16+GZ14-GZ15 -> 0 | HA16: =GZ16+HA14-HA15 -> 0 | HB16: =HA16+HB14-HB15 -> 0 | HC16: =HB16+HC14-HC15 -> 0 | HD16: =HC16+HD14-HD15 -> 0 | HE16: =HD16+HE14-HE15 -> 0 | HF16: =HE16+HF14-HF15 -> 0 | HG16: =HF16+HG14-HG15 -> 0 | HH16: =HG16+HH14-HH15 -> 0 | ... HT16: =HS16+HT14-HT15 -> 0 | HU16: =COUNTIF(GZ16:HT16,"<0") -> 0 | HW16: =DIM_BILL[[#This Row],[Tipo]]
A17: 51TBMC02 | GC17: 1 | GR17: MULTILYTE COCO C/20 TABS EFER MIX ST | GS17: 2 | GV17: =SUMIF(FACT_A1[cve_prod],DIM_BILL[[#This Row],[CODIGO]],FACT_A1[Existencia]) -> 0 | GW17: =SUMIF(FACT_A2[cve_prod],DIM_BILL[[#This Row],[CODIGO]],FACT_A2[Existencia]) -> 0 | GY17: Por Surtir & Parcial | GZ17: =SUMIFS(POs[saldo],POs[cve_prod],DIM_BILL[[#This Row],[CODIGO]],POs[status],$GY17,POs[f_ent],GZ$1) -> 0 | HA17: =SUMIFS(POs[saldo],POs[cve_prod],DIM_BILL[[#This Row],[CODIGO]],POs[status],$GY17,POs[f_ent],HA$1) -> 0 | HB17: =SUMIFS(POs[saldo],POs[cve_prod],DIM_BILL[[#This Row],[CODIGO]],POs[status],$GY17,POs[f_ent],HB$1) -> 0 | HC17: =SUMIFS(POs[saldo],POs[cve_prod],DIM_BILL[[#This Row],[CODIGO]],POs[status],$GY17,POs[f_ent],HC$1) -> 0 | HD17: =SUMIFS(POs[saldo],POs[cve_prod],DIM_BILL[[#This Row],[CODIGO]],POs[status],$GY17,POs[f_ent],HD$1) -> 0 | HE17: =SUMIFS(POs[saldo],POs[cve_prod],DIM_BILL[[#This Row],[CODIGO]],POs[status],$GY17,POs[f_ent],HE$1) -> 0 | HF17: =SUMIFS(POs[saldo],POs[cve_prod],DIM_BILL[[#This Row],[CODIGO]],POs[status],$GY17,POs[Semana],WEEKNUM(HF$1)) -> 0 | HG17: =SUMIFS(POs[saldo],POs[cve_prod],DIM_BILL[[#This Row],[CODIGO]],POs[status],$GY17,POs[Semana],WEEKNUM(HG$1)) -> 0 | HH17: =SUMIFS(POs[saldo],POs[cve_prod],DIM_BILL[[#This Row],[CODIGO]],POs[status],$GY17,POs[Semana],WEEKNUM(HH$1)) -> 0 | HI17: =SUMIFS(POs[saldo],POs[cve_prod],DIM_BILL[[#This Row],[CODIGO]],POs[status],$GY17,POs[Semana],WEEKNUM(HI$1)) -> 0 | HJ17: =SUMIFS(POs[saldo],POs[cve_prod],DIM_BILL[[#This Row],[CODIGO]],POs[status],$GY17,POs[Semana],WEEKNUM(HJ$1)) -> 0 | HK17: =SUMIFS(POs[saldo],POs[cve_prod],DIM_BILL[[#This Row],[CODIGO]],POs[status],$GY17,POs[Semana],WEEKNUM(HK$1)) -> 0 | HL17: =SUMIFS(POs[saldo],POs[cve_prod],DIM_BILL[[#This Row],[CODIGO]],POs[status],$GY17,POs[Semana],WEEKNUM(HL$1)) -> 0 | HM17: =SUMIFS(POs[saldo],POs[cve_prod],DIM_BILL[[#This Row],[CODIGO]],POs[status],$GY17,POs[Semana],WEEKNUM(HM$1)) -> 0 | ... HT17: =SUMIFS(POs[saldo],POs[cve_prod],DIM_BILL[[#This Row],[CODIGO]],POs[status],$GY17,POs[Semana],WEEKNUM(HT$1)) -> 0 | HW17: =DIM_BILL[[#This Row],[Tipo]]
A18: 51TBMC02 | GC18: 1 | GR18: MULTILYTE COCO C/20 TABS EFER MIX ST | GS18: 2 | GV18: =SUMIF(FACT_A1[cve_prod],DIM_BILL[[#This Row],[CODIGO]],FACT_A1[Existencia]) -> 0 | GW18: =SUMIF(FACT_A2[cve_prod],DIM_BILL[[#This Row],[CODIGO]],FACT_A2[Existencia]) -> 0 | GY18: Demanda | GZ18: =SUMPRODUCT($B18:$GQ18,INDEX(PLAN_PRODUCCION!$B$4:$GQ$24,COLUMN()-COLUMN($GZ$1)+1,0)) -> 7000 | HA18: =SUMPRODUCT($B18:$GQ18,INDEX(PLAN_PRODUCCION!$B$4:$GQ$24,COLUMN()-COLUMN($GZ$1)+1,0)) -> 0 | HB18: =SUMPRODUCT($B18:$GQ18,INDEX(PLAN_PRODUCCION!$B$4:$GQ$24,COLUMN()-COLUMN($GZ$1)+1,0)) -> 0 | HC18: =SUMPRODUCT($B18:$GQ18,INDEX(PLAN_PRODUCCION!$B$4:$GQ$24,COLUMN()-COLUMN($GZ$1)+1,0)) -> 0 | HD18: =SUMPRODUCT($B18:$GQ18,INDEX(PLAN_PRODUCCION!$B$4:$GQ$24,COLUMN()-COLUMN($GZ$1)+1,0)) -> 0 | HE18: =SUMPRODUCT($B18:$GQ18,INDEX(PLAN_PRODUCCION!$B$4:$GQ$24,COLUMN()-COLUMN($GZ$1)+1,0)) -> 0 | HF18: =SUMPRODUCT($B18:$GQ18,INDEX(PLAN_PRODUCCION!$B$4:$GQ$24,COLUMN()-COLUMN($GZ$1)+1,0)) -> 0 | HG18: =SUMPRODUCT($B18:$GQ18,INDEX(PLAN_PRODUCCION!$B$4:$GQ$24,COLUMN()-COLUMN($GZ$1)+1,0)) -> 0 | ... HT18: =SUMPRODUCT($B18:$GQ18,INDEX(PLAN_PRODUCCION!$B$4:$GQ$24,COLUMN()-COLUMN($GZ$1)+1,0)) -> 0 | HW18: =DIM_BILL[[#This Row],[Tipo]]
A19: 51TBMC02 | GC19: 1 | GR19: MULTILYTE COCO C/20 TABS EFER MIX ST | GS19: 2 | GV19: =SUMIF(FACT_A1[cve_prod],DIM_BILL[[#This Row],[CODIGO]],FACT_A1[Existencia]) -> 0 | GW19: =SUMIF(FACT_A2[cve_prod],DIM_BILL[[#This Row],[CODIGO]],FACT_A2[Existencia]) -> 0 | GY19: Cortos + PO's Confirmadas | GZ19: =GV19+GW19+GX19+GZ17-GZ18 -> -7000 | HA19: =GZ19+HA17-HA18 -> -7000 | HB19: =HA19+HB17-HB18 -> -7000 | HC19: =HB19+HC17-HC18 -> -7000 | HD19: =HC19+HD17-HD18 -> -7000 | HE19: =HD19+HE17-HE18 -> -7000 | HF19: =HE19+HF17-HF18 -> -7000 | HG19: =HF19+HG17-HG18 -> -7000 | HH19: =HG19+HH17-HH18 -> -7000 | ... HT19: =HS19+HT17-HT18 -> -7000 | HU19: =COUNTIF(GZ19:HT19,"<0") -> 21 | HW19: =DIM_BILL[[#This Row],[Tipo]]
A20: 51TBMF02 | GC20: 1 | GR20: MULTILYTE FRESA KIWI 20 TABS EFER MIX ST | GS20: 2 | GV20: =SUMIF(FACT_A1[cve_prod],DIM_BILL[[#This Row],[CODIGO]],FACT_A1[Existencia]) -> 0 | GW20: =SUMIF(FACT_A2[cve_prod],DIM_BILL[[#This Row],[CODIGO]],FACT_A2[Existencia]) -> 0 | GY20: Por Surtir & Parcial | GZ20: =SUMIFS(POs[saldo],POs[cve_prod],DIM_BILL[[#This Row],[CODIGO]],POs[status],$GY20,POs[f_ent],GZ$1) -> 0 | HA20: =SUMIFS(POs[saldo],POs[cve_prod],DIM_BILL[[#This Row],[CODIGO]],POs[status],$GY20,POs[f_ent],HA$1) -> 0 | HB20: =SUMIFS(POs[saldo],POs[cve_prod],DIM_BILL[[#This Row],[CODIGO]],POs[status],$GY20,POs[f_ent],HB$1) -> 0 | HC20: =SUMIFS(POs[saldo],POs[cve_prod],DIM_BILL[[#This Row],[CODIGO]],POs[status],$GY20,POs[f_ent],HC$1) -> 0 | HD20: =SUMIFS(POs[saldo],POs[cve_prod],DIM_BILL[[#This Row],[CODIGO]],POs[status],$GY20,POs[f_ent],HD$1) -> 0 | HE20: =SUMIFS(POs[saldo],POs[cve_prod],DIM_BILL[[#This Row],[CODIGO]],POs[status],$GY20,POs[f_ent],HE$1) -> 0 | HF20: =SUMIFS(POs[saldo],POs[cve_prod],DIM_BILL[[#This Row],[CODIGO]],POs[status],$GY20,POs[Semana],WEEKNUM(HF$1)) -> 0 | HG20: =SUMIFS(POs[saldo],POs[cve_prod],DIM_BILL[[#This Row],[CODIGO]],POs[status],$GY20,POs[Semana],WEEKNUM(HG$1)) -> 0 | HH20: =SUMIFS(POs[saldo],POs[cve_prod],DIM_BILL[[#This Row],[CODIGO]],POs[status],$GY20,POs[Semana],WEEKNUM(HH$1)) -> 0 | HI20: =SUMIFS(POs[saldo],POs[cve_prod],DIM_BILL[[#This Row],[CODIGO]],POs[status],$GY20,POs[Semana],WEEKNUM(HI$1)) -> 0 | HJ20: =SUMIFS(POs[saldo],POs[cve_prod],DIM_BILL[[#This Row],[CODIGO]],POs[status],$GY20,POs[Semana],WEEKNUM(HJ$1)) -> 0 | HK20: =SUMIFS(POs[saldo],POs[cve_prod],DIM_BILL[[#This Row],[CODIGO]],POs[status],$GY20,POs[Semana],WEEKNUM(HK$1)) -> 0 | HL20: =SUMIFS(POs[saldo],POs[cve_prod],DIM_BILL[[#This Row],[CODIGO]],POs[status],$GY20,POs[Semana],WEEKNUM(HL$1)) -> 0 | HM20: =SUMIFS(POs[saldo],POs[cve_prod],DIM_BILL[[#This Row],[CODIGO]],POs[status],$GY20,POs[Semana],WEEKNUM(HM$1)) -> 0 | ... HT20: =SUMIFS(POs[saldo],POs[cve_prod],DIM_BILL[[#This Row],[CODIGO]],POs[status],$GY20,POs[Semana],WEEKNUM(HT$1)) -> 0 | HW20: =DIM_BILL[[#This Row],[Tipo]]
A21: 51TBMF02 | GC21: 1 | GR21: MULTILYTE FRESA KIWI 20 TABS EFER MIX ST | GS21: 2 | GV21: =SUMIF(FACT_A1[cve_prod],DIM_BILL[[#This Row],[CODIGO]],FACT_A1[Existencia]) -> 0 | GW21: =SUMIF(FACT_A2[cve_prod],DIM_BILL[[#This Row],[CODIGO]],FACT_A2[Existencia]) -> 0 | GY21: Demanda | GZ21: =SUMPRODUCT($B21:$GQ21,INDEX(PLAN_PRODUCCION!$B$4:$GQ$24,COLUMN()-COLUMN($GZ$1)+1,0)) -> 7000 | HA21: =SUMPRODUCT($B21:$GQ21,INDEX(PLAN_PRODUCCION!$B$4:$GQ$24,COLUMN()-COLUMN($GZ$1)+1,0)) -> 0 | HB21: =SUMPRODUCT($B21:$GQ21,INDEX(PLAN_PRODUCCION!$B$4:$GQ$24,COLUMN()-COLUMN($GZ$1)+1,0)) -> 0 | HC21: =SUMPRODUCT($B21:$GQ21,INDEX(PLAN_PRODUCCION!$B$4:$GQ$24,COLUMN()-COLUMN($GZ$1)+1,0)) -> 0 | HD21: =SUMPRODUCT($B21:$GQ21,INDEX(PLAN_PRODUCCION!$B$4:$GQ$24,COLUMN()-COLUMN($GZ$1)+1,0)) -> 0 | HE21: =SUMPRODUCT($B21:$GQ21,INDEX(PLAN_PRODUCCION!$B$4:$GQ$24,COLUMN()-COLUMN($GZ$1)+1,0)) -> 0 | HF21: =SUMPRODUCT($B21:$GQ21,INDEX(PLAN_PRODUCCION!$B$4:$GQ$24,COLUMN()-COLUMN($GZ$1)+1,0)) -> 0 | HG21: =SUMPRODUCT($B21:$GQ21,INDEX(PLAN_PRODUCCION!$B$4:$GQ$24,COLUMN()-COLUMN($GZ$1)+1,0)) -> 0 | ... HT21: =SUMPRODUCT($B21:$GQ21,INDEX(PLAN_PRODUCCION!$B$4:$GQ$24,COLUMN()-COLUMN($GZ$1)+1,0)) -> 0 | HW21: =DIM_BILL[[#This Row],[Tipo]]
A22: 51TBMF02 | GC22: 1 | GR22: MULTILYTE FRESA KIWI 20 TABS EFER MIX ST | GS22: 2 | GV22: =SUMIF(FACT_A1[cve_prod],DIM_BILL[[#This Row],[CODIGO]],FACT_A1[Existencia]) -> 0 | GW22: =SUMIF(FACT_A2[cve_prod],DIM_BILL[[#This Row],[CODIGO]],FACT_A2[Existencia]) -> 0 | GY22: Cortos + PO's Confirmadas | GZ22: =GV22+GW22+GX22+GZ20-GZ21 -> -7000 | HA22: =GZ22+HA20-HA21 -> -7000 | HB22: =HA22+HB20-HB21 -> -7000 | HC22: =HB22+HC20-HC21 -> -7000 | HD22: =HC22+HD20-HD21 -> -7000 | HE22: =HD22+HE20-HE21 -> -7000 | HF22: =HE22+HF20-HF21 -> -7000 | HG22: =HF22+HG20-HG21 -> -7000 | HH22: =HG22+HH20-HH21 -> -7000 | ... HT22: =HS22+HT20-HT21 -> -7000 | HU22: =COUNTIF(GZ22:HT22,"<0") -> 21 | HW22: =DIM_BILL[[#This Row],[Tipo]]
A23: 51TBML02 | GC23: 1 | GR23: MULTILYTE LIMONADA C/20 TABS EFER MIX ST | GS23: 2 | GV23: =SUMIF(FACT_A1[cve_prod],DIM_BILL[[#This Row],[CODIGO]],FACT_A1[Existencia]) -> 0 | GW23: =SUMIF(FACT_A2[cve_prod],DIM_BILL[[#This Row],[CODIGO]],FACT_A2[Existencia]) -> 0 | GY23: Por Surtir & Parcial | GZ23: =SUMIFS(POs[saldo],POs[cve_prod],DIM_BILL[[#This Row],[CODIGO]],POs[status],$GY23,POs[f_ent],GZ$1) -> 0 | HA23: =SUMIFS(POs[saldo],POs[cve_prod],DIM_BILL[[#This Row],[CODIGO]],POs[status],$GY23,POs[f_ent],HA$1) -> 0 | HB23: =SUMIFS(POs[saldo],POs[cve_prod],DIM_BILL[[#This Row],[CODIGO]],POs[status],$GY23,POs[f_ent],HB$1) -> 0 | HC23: =SUMIFS(POs[saldo],POs[cve_prod],DIM_BILL[[#This Row],[CODIGO]],POs[status],$GY23,POs[f_ent],HC$1) -> 0 | HD23: =SUMIFS(POs[saldo],POs[cve_prod],DIM_BILL[[#This Row],[CODIGO]],POs[status],$GY23,POs[f_ent],HD$1) -> 0 | HE23: =SUMIFS(POs[saldo],POs[cve_prod],DIM_BILL[[#This Row],[CODIGO]],POs[status],$GY23,POs[f_ent],HE$1) -> 0 | HF23: =SUMIFS(POs[saldo],POs[cve_prod],DIM_BILL[[#This Row],[CODIGO]],POs[status],$GY23,POs[Semana],WEEKNUM(HF$1)) -> 0 | HG23: =SUMIFS(POs[saldo],POs[cve_prod],DIM_BILL[[#This Row],[CODIGO]],POs[status],$GY23,POs[Semana],WEEKNUM(HG$1)) -> 0 | HH23: =SUMIFS(POs[saldo],POs[cve_prod],DIM_BILL[[#This Row],[CODIGO]],POs[status],$GY23,POs[Semana],WEEKNUM(HH$1)) -> 0 | HI23: =SUMIFS(POs[saldo],POs[cve_prod],DIM_BILL[[#This Row],[CODIGO]],POs[status],$GY23,POs[Semana],WEEKNUM(HI$1)) -> 0 | HJ23: =SUMIFS(POs[saldo],POs[cve_prod],DIM_BILL[[#This Row],[CODIGO]],POs[status],$GY23,POs[Semana],WEEKNUM(HJ$1)) -> 0 | HK23: =SUMIFS(POs[saldo],POs[cve_prod],DIM_BILL[[#This Row],[CODIGO]],POs[status],$GY23,POs[Semana],WEEKNUM(HK$1)) -> 0 | HL23: =SUMIFS(POs[saldo],POs[cve_prod],DIM_BILL[[#This Row],[CODIGO]],POs[status],$GY23,POs[Semana],WEEKNUM(HL$1)) -> 0 | HM23: =SUMIFS(POs[saldo],POs[cve_prod],DIM_BILL[[#This Row],[CODIGO]],POs[status],$GY23,POs[Semana],WEEKNUM(HM$1)) -> 0 | ... HT23: =SUMIFS(POs[saldo],POs[cve_prod],DIM_BILL[[#This Row],[CODIGO]],POs[status],$GY23,POs[Semana],WEEKNUM(HT$1)) -> 0 | HW23: =DIM_BILL[[#This Row],[Tipo]]
A24: 51TBML02 | GC24: 1 | GR24: MULTILYTE LIMONADA C/20 TABS EFER MIX ST | GS24: 2 | GV24: =SUMIF(FACT_A1[cve_prod],DIM_BILL[[#This Row],[CODIGO]],FACT_A1[Existencia]) -> 0 | GW24: =SUMIF(FACT_A2[cve_prod],DIM_BILL[[#This Row],[CODIGO]],FACT_A2[Existencia]) -> 0 | GY24: Demanda | GZ24: =SUMPRODUCT($B24:$GQ24,INDEX(PLAN_PRODUCCION!$B$4:$GQ$24,COLUMN()-COLUMN($GZ$1)+1,0)) -> 7000 | HA24: =SUMPRODUCT($B24:$GQ24,INDEX(PLAN_PRODUCCION!$B$4:$GQ$24,COLUMN()-COLUMN($GZ$1)+1,0)) -> 0 | HB24: =SUMPRODUCT($B24:$GQ24,INDEX(PLAN_PRODUCCION!$B$4:$GQ$24,COLUMN()-COLUMN($GZ$1)+1,0)) -> 0 | HC24: =SUMPRODUCT($B24:$GQ24,INDEX(PLAN_PRODUCCION!$B$4:$GQ$24,COLUMN()-COLUMN($GZ$1)+1,0)) -> 0 | HD24: =SUMPRODUCT($B24:$GQ24,INDEX(PLAN_PRODUCCION!$B$4:$GQ$24,COLUMN()-COLUMN($GZ$1)+1,0)) -> 0 | HE24: =SUMPRODUCT($B24:$GQ24,INDEX(PLAN_PRODUCCION!$B$4:$GQ$24,COLUMN()-COLUMN($GZ$1)+1,0)) -> 0 | HF24: =SUMPRODUCT($B24:$GQ24,INDEX(PLAN_PRODUCCION!$B$4:$GQ$24,COLUMN()-COLUMN($GZ$1)+1,0)) -> 0 | HG24: =SUMPRODUCT($B24:$GQ24,INDEX(PLAN_PRODUCCION!$B$4:$GQ$24,COLUMN()-COLUMN($GZ$1)+1,0)) -> 0 | ... HT24: =SUMPRODUCT($B24:$GQ24,INDEX(PLAN_PRODUCCION!$B$4:$GQ$24,COLUMN()-COLUMN($GZ$1)+1,0)) -> 0 | HW24: =DIM_BILL[[#This Row],[Tipo]]
A25: 51TBML02 | GC25: 1 | GR25: MULTILYTE LIMONADA C/20 TABS EFER MIX ST | GS25: 2 | GV25: =SUMIF(FACT_A1[cve_prod],DIM_BILL[[#This Row],[CODIGO]],FACT_A1[Existencia]) -> 0 | GW25: =SUMIF(FACT_A2[cve_prod],DIM_BILL[[#This Row],[CODIGO]],FACT_A2[Existencia]) -> 0 | GY25: Cortos + PO's Confirmadas | GZ25: =GV25+GW25+GX25+GZ23-GZ24 -> -7000 | HA25: =GZ25+HA23-HA24 -> -7000 | HB25: =HA25+HB23-HB24 -> -7000 | HC25: =HB25+HC23-HC24 -> -7000 | HD25: =HC25+HD23-HD24 -> -7000 | HE25: =HD25+HE23-HE24 -> -7000 | HF25: =HE25+HF23-HF24 -> -7000 | HG25: =HF25+HG23-HG24 -> -7000 | HH25: =HG25+HH23-HH24 -> -7000 | ... HT25: =HS25+HT23-HT24 -> -7000 | HU25: =COUNTIF(GZ25:HT25,"<0") -> 21 | HW25: =DIM_BILL[[#This Row],[Tipo]]
A26: 51TBMN02 | GC26: 1 | GR26: MULTILYTE NARANJA C/20 TABS EFER MIX ST | GS26: 2 | GV26: =SUMIF(FACT_A1[cve_prod],DIM_BILL[[#This Row],[CODIGO]],FACT_A1[Existencia]) -> 0 | GW26: =SUMIF(FACT_A2[cve_prod],DIM_BILL[[#This Row],[CODIGO]],FACT_A2[Existencia]) -> 0 | GY26: Por Surtir & Parcial | GZ26: =SUMIFS(POs[saldo],POs[cve_prod],DIM_BILL[[#This Row],[CODIGO]],POs[status],$GY26,POs[f_ent],GZ$1) -> 0 | HA26: =SUMIFS(POs[saldo],POs[cve_prod],DIM_BILL[[#This Row],[CODIGO]],POs[status],$GY26,POs[f_ent],HA$1) -> 0 | HB26: =SUMIFS(POs[saldo],POs[cve_prod],DIM_BILL[[#This Row],[CODIGO]],POs[status],$GY26,POs[f_ent],HB$1) -> 0 | HC26: =SUMIFS(POs[saldo],POs[cve_prod],DIM_BILL[[#This Row],[CODIGO]],POs[status],$GY26,POs[f_ent],HC$1) -> 0 | HD26: =SUMIFS(POs[saldo],POs[cve_prod],DIM_BILL[[#This Row],[CODIGO]],POs[status],$GY26,POs[f_ent],HD$1) -> 0 | HE26: =SUMIFS(POs[saldo],POs[cve_prod],DIM_BILL[[#This Row],[CODIGO]],POs[status],$GY26,POs[f_ent],HE$1) -> 0 | HF26: =SUMIFS(POs[saldo],POs[cve_prod],DIM_BILL[[#This Row],[CODIGO]],POs[status],$GY26,POs[Semana],WEEKNUM(HF$1)) -> 0 | HG26: =SUMIFS(POs[saldo],POs[cve_prod],DIM_BILL[[#This Row],[CODIGO]],POs[status],$GY26,POs[Semana],WEEKNUM(HG$1)) -> 0 | HH26: =SUMIFS(POs[saldo],POs[cve_prod],DIM_BILL[[#This Row],[CODIGO]],POs[status],$GY26,POs[Semana],WEEKNUM(HH$1)) -> 0 | HI26: =SUMIFS(POs[saldo],POs[cve_prod],DIM_BILL[[#This Row],[CODIGO]],POs[status],$GY26,POs[Semana],WEEKNUM(HI$1)) -> 0 | HJ26: =SUMIFS(POs[saldo],POs[cve_prod],DIM_BILL[[#This Row],[CODIGO]],POs[status],$GY26,POs[Semana],WEEKNUM(HJ$1)) -> 0 | HK26: =SUMIFS(POs[saldo],POs[cve_prod],DIM_BILL[[#This Row],[CODIGO]],POs[status],$GY26,POs[Semana],WEEKNUM(HK$1)) -> 0 | HL26: =SUMIFS(POs[saldo],POs[cve_prod],DIM_BILL[[#This Row],[CODIGO]],POs[status],$GY26,POs[Semana],WEEKNUM(HL$1)) -> 0 | HM26: =SUMIFS(POs[saldo],POs[cve_prod],DIM_BILL[[#This Row],[CODIGO]],POs[status],$GY26,POs[Semana],WEEKNUM(HM$1)) -> 0 | ... HT26: =SUMIFS(POs[saldo],POs[cve_prod],DIM_BILL[[#This Row],[CODIGO]],POs[status],$GY26,POs[Semana],WEEKNUM(HT$1)) -> 0 | HW26: =DIM_BILL[[#This Row],[Tipo]]
A27: 51TBMN02 | GC27: 1 | GR27: MULTILYTE NARANJA C/20 TABS EFER MIX ST | GS27: 2 | GV27: =SUMIF(FACT_A1[cve_prod],DIM_BILL[[#This Row],[CODIGO]],FACT_A1[Existencia]) -> 0 | GW27: =SUMIF(FACT_A2[cve_prod],DIM_BILL[[#This Row],[CODIGO]],FACT_A2[Existencia]) -> 0 | GY27: Demanda | GZ27: =SUMPRODUCT($B27:$GQ27,INDEX(PLAN_PRODUCCION!$B$4:$GQ$24,COLUMN()-COLUMN($GZ$1)+1,0)) -> 7000 | HA27: =SUMPRODUCT($B27:$GQ27,INDEX(PLAN_PRODUCCION!$B$4:$GQ$24,COLUMN()-COLUMN($GZ$1)+1,0)) -> 0 | HB27: =SUMPRODUCT($B27:$GQ27,INDEX(PLAN_PRODUCCION!$B$4:$GQ$24,COLUMN()-COLUMN($GZ$1)+1,0)) -> 0 | HC27: =SUMPRODUCT($B27:$GQ27,INDEX(PLAN_PRODUCCION!$B$4:$GQ$24,COLUMN()-COLUMN($GZ$1)+1,0)) -> 0 | HD27: =SUMPRODUCT($B27:$GQ27,INDEX(PLAN_PRODUCCION!$B$4:$GQ$24,COLUMN()-COLUMN($GZ$1)+1,0)) -> 0 | HE27: =SUMPRODUCT($B27:$GQ27,INDEX(PLAN_PRODUCCION!$B$4:$GQ$24,COLUMN()-COLUMN($GZ$1)+1,0)) -> 0 | HF27: =SUMPRODUCT($B27:$GQ27,INDEX(PLAN_PRODUCCION!$B$4:$GQ$24,COLUMN()-COLUMN($GZ$1)+1,0)) -> 0 | HG27: =SUMPRODUCT($B27:$GQ27,INDEX(PLAN_PRODUCCION!$B$4:$GQ$24,COLUMN()-COLUMN($GZ$1)+1,0)) -> 0 | ... HT27: =SUMPRODUCT($B27:$GQ27,INDEX(PLAN_PRODUCCION!$B$4:$GQ$24,COLUMN()-COLUMN($GZ$1)+1,0)) -> 0 | HW27: =DIM_BILL[[#This Row],[Tipo]]
A28: 51TBMN02 | GC28: 1 | GR28: MULTILYTE NARANJA C/20 TABS EFER MIX ST | GS28: 2 | GV28: =SUMIF(FACT_A1[cve_prod],DIM_BILL[[#This Row],[CODIGO]],FACT_A1[Existencia]) -> 0 | GW28: =SUMIF(FACT_A2[cve_prod],DIM_BILL[[#This Row],[CODIGO]],FACT_A2[Existencia]) -> 0 | GY28: Cortos + PO's Confirmadas | GZ28: =GV28+GW28+GX28+GZ26-GZ27 -> -7000 | HA28: =GZ28+HA26-HA27 -> -7000 | HB28: =HA28+HB26-HB27 -> -7000 | HC28: =HB28+HC26-HC27 -> -7000 | HD28: =HC28+HD26-HD27 -> -7000 | HE28: =HD28+HE26-HE27 -> -7000 | HF28: =HE28+HF26-HF27 -> -7000 | HG28: =HF28+HG26-HG27 -> -7000 | HH28: =HG28+HH26-HH27 -> -7000 | ... HT28: =HS28+HT26-HT27 -> -7000 | HU28: =COUNTIF(GZ28:HT28,"<0") -> 21 | HW28: =DIM_BILL[[#This Row],[Tipo]]
A29: DES-0032 | BT29: 0.00063454545 | BU29: 0.0011168 | BW29: 0.0011168 | BX29: 0.00063454545 | BY29: 0.0022336 | BZ29: 0.0011168 | CA29: 0.00063454545 | CB29: 0.0022336 | CC29: 0.00093066667 | CD29: 0.002792 | CQ29: 0.0019008 | CT29: 0.0019 | GR29: FOSFATO DICALCICO ANHIDRO | GS29: 1 | GT29: HCQ INGREDIENTES PARA LA INDUSTRIA ALIMENTICIA, S.A. DE C.V. | GU29: MATERIA PRIMA | GV29: =SUMIF(FACT_A1[cve_prod],DIM_BILL[[#This Row],[CODIGO]],FACT_A1[Existencia]) -> 0 | GW29: =SUMIF(FACT_A2[cve_prod],DIM_BILL[[#This Row],[CODIGO]],FACT_A2[Existencia]) -> 39.27902 | GY29: Por Surtir & Parcial | GZ29: =SUMIFS(POs[saldo],POs[cve_prod],DIM_BILL[[#This Row],[CODIGO]],POs[status],$GY29,POs[f_ent],GZ$1) -> 0 | HA29: =SUMIFS(POs[saldo],POs[cve_prod],DIM_BILL[[#This Row],[CODIGO]],POs[status],$GY29,POs[f_ent],HA$1) -> 0 | HB29: =SUMIFS(POs[saldo],POs[cve_prod],DIM_BILL[[#This Row],[CODIGO]],POs[status],$GY29,POs[f_ent],HB$1) -> 0 | HC29: =SUMIFS(POs[saldo],POs[cve_prod],DIM_BILL[[#This Row],[CODIGO]],POs[status],$GY29,POs[f_ent],HC$1) -> 0 | HD29: =SUMIFS(POs[saldo],POs[cve_prod],DIM_BILL[[#This Row],[CODIGO]],POs[status],$GY29,POs[f_ent],HD$1) -> 0 | HE29: =SUMIFS(POs[saldo],POs[cve_prod],DIM_BILL[[#This Row],[CODIGO]],POs[status],$GY29,POs[f_ent],HE$1) -> 0 | HF29: =SUMIFS(POs[saldo],POs[cve_prod],DIM_BILL[[#This Row],[CODIGO]],POs[status],$GY29,POs[Semana],WEEKNUM(HF$1)) -> 0 | HG29: =SUMIFS(POs[saldo],POs[cve_prod],DIM_BILL[[#This Row],[CODIGO]],POs[status],$GY29,POs[Semana],WEEKNUM(HG$1)) -> 0 | HH29: =SUMIFS(POs[saldo],POs[cve_prod],DIM_BILL[[#This Row],[CODIGO]],POs[status],$GY29,POs[Semana],WEEKNUM(HH$1)) -> 0 | HI29: =SUMIFS(POs[saldo],POs[cve_prod],DIM_BILL[[#This Row],[CODIGO]],POs[status],$GY29,POs[Semana],WEEKNUM(HI$1)) -> 0 | HJ29: =SUMIFS(POs[saldo],POs[cve_prod],DIM_BILL[[#This Row],[CODIGO]],POs[status],$GY29,POs[Semana],WEEKNUM(HJ$1)) -> 0 | HK29: =SUMIFS(POs[saldo],POs[cve_prod],DIM_BILL[[#This Row],[CODIGO]],POs[status],$GY29,POs[Semana],WEEKNUM(HK$1)) -> 0 | HL29: =SUMIFS(POs[saldo],POs[cve_prod],DIM_BILL[[#This Row],[CODIGO]],POs[status],$GY29,POs[Semana],WEEKNUM(HL$1)) -> 0 | HM29: =SUMIFS(POs[saldo],POs[cve_prod],DIM_BILL[[#This Row],[CODIGO]],POs[status],$GY29,POs[Semana],WEEKNUM(HM$1)) -> 0 | ... HT29: =SUMIFS(POs[saldo],POs[cve_prod],DIM_BILL[[#This Row],[CODIGO]],POs[status],$GY29,POs[Semana],WEEKNUM(HT$1)) -> 0 | HW29: =DIM_BILL[[#This Row],[Tipo]] -> MATERIA PRIMA
A30: DES-0032 | BT30: 0.00063454545 | BU30: 0.0011168 | BW30: 0.0011168 | BX30: 0.00063454545 | BY30: 0.0022336 | BZ30: 0.0011168 | CA30: 0.00063454545 | CB30: 0.0022336 | CC30: 0.00093066667 | CD30: 0.002792 | CQ30: 0.0019008 | CT30: 0.0019 | GR30: FOSFATO DICALCICO ANHIDRO | GS30: 1 | GT30: HCQ INGREDIENTES PARA LA INDUSTRIA ALIMENTICIA, S.A. DE C.V. | GU30: MATERIA PRIMA | GV30: =SUMIF(FACT_A1[cve_prod],DIM_BILL[[#This Row],[CODIGO]],FACT_A1[Existencia]) -> 0 | GW30: =SUMIF(FACT_A2[cve_prod],DIM_BILL[[#This Row],[CODIGO]],FACT_A2[Existencia]) -> 39.27902 | GY30: Demanda | GZ30: =SUMPRODUCT($B30:$GQ30,INDEX(PLAN_PRODUCCION!$B$4:$GQ$24,COLUMN()-COLUMN($GZ$1)+1,0)) -> 77.3375 | HA30: =SUMPRODUCT($B30:$GQ30,INDEX(PLAN_PRODUCCION!$B$4:$GQ$24,COLUMN()-COLUMN($GZ$1)+1,0)) -> 0 | HB30: =SUMPRODUCT($B30:$GQ30,INDEX(PLAN_PRODUCCION!$B$4:$GQ$24,COLUMN()-COLUMN($GZ$1)+1,0)) -> 0 | HC30: =SUMPRODUCT($B30:$GQ30,INDEX(PLAN_PRODUCCION!$B$4:$GQ$24,COLUMN()-COLUMN($GZ$1)+1,0)) -> 0 | HD30: =SUMPRODUCT($B30:$GQ30,INDEX(PLAN_PRODUCCION!$B$4:$GQ$24,COLUMN()-COLUMN($GZ$1)+1,0)) -> 0 | HE30: =SUMPRODUCT($B30:$GQ30,INDEX(PLAN_PRODUCCION!$B$4:$GQ$24,COLUMN()-COLUMN($GZ$1)+1,0)) -> 0 | HF30: =SUMPRODUCT($B30:$GQ30,INDEX(PLAN_PRODUCCION!$B$4:$GQ$24,COLUMN()-COLUMN($GZ$1)+1,0)) -> 0 | HG30: =SUMPRODUCT($B30:$GQ30,INDEX(PLAN_PRODUCCION!$B$4:$GQ$24,COLUMN()-COLUMN($GZ$1)+1,0)) -> 0 | ... HT30: =SUMPRODUCT($B30:$GQ30,INDEX(PLAN_PRODUCCION!$B$4:$GQ$24,COLUMN()-COLUMN($GZ$1)+1,0)) -> 0 | HW30: =DIM_BILL[[#This Row],[Tipo]] -> MATERIA PRIMA
A31: DES-0032 | BT31: 0.00063454545 | BU31: 0.0011168 | BW31: 0.0011168 | BX31: 0.00063454545 | BY31: 0.0022336 | BZ31: 0.0011168 | CA31: 0.00063454545 | CB31: 0.0022336 | CC31: 0.00093066667 | CD31: 0.002792 | CQ31: 0.0019008 | CT31: 0.0019 | GR31: FOSFATO DICALCICO ANHIDRO | GS31: 1 | GT31: HCQ INGREDIENTES PARA LA INDUSTRIA ALIMENTICIA, S.A. DE C.V. | GU31: MATERIA PRIMA | GV31: =SUMIF(FACT_A1[cve_prod],DIM_BILL[[#This Row],[CODIGO]],FACT_A1[Existencia]) -> 0 | GW31: =SUMIF(FACT_A2[cve_prod],DIM_BILL[[#This Row],[CODIGO]],FACT_A2[Existencia]) -> 39.27902 | GY31: Cortos + PO's Confirmadas | GZ31: =GV31+GW31+GX31+GZ29-GZ30 -> -38.05848 | HA31: =GZ31+HA29-HA30 -> -38.05848 | HB31: =HA31+HB29-HB30 -> -38.05848 | HC31: =HB31+HC29-HC30 -> -38.05848 | HD31: =HC31+HD29-HD30 -> -38.05848 | HE31: =HD31+HE29-HE30 -> -38.05848 | HF31: =HE31+HF29-HF30 -> -38.05848 | HG31: =HF31+HG29-HG30 -> -38.05848 | HH31: =HG31+HH29-HH30 -> -38.05848 | ... HT31: =HS31+HT29-HT30 -> -38.05848 | HU31: =COUNTIF(GZ31:HT31,"<0") -> 21 | HW31: =DIM_BILL[[#This Row],[Tipo]] -> MATERIA PRIMA
A32: M | FH32: 0.78 | FK32: 0.0063333333 | FW32: 0.063333333 | GG32: 0.0018888889 | GR32: MANO DE O. | GS32: 2 | GV32: =SUMIF(FACT_A1[cve_prod],DIM_BILL[[#This Row],[CODIGO]],FACT_A1[Existencia]) -> 0 | GW32: =SUMIF(FACT_A2[cve_prod],DIM_BILL[[#This Row],[CODIGO]],FACT_A2[Existencia]) -> 0 | GY32: Por Surtir & Parcial | GZ32: =SUMIFS(POs[saldo],POs[cve_prod],DIM_BILL[[#This Row],[CODIGO]],POs[status],$GY32,POs[f_ent],GZ$1) -> 0 | HA32: =SUMIFS(POs[saldo],POs[cve_prod],DIM_BILL[[#This Row],[CODIGO]],POs[status],$GY32,POs[f_ent],HA$1) -> 0 | HB32: =SUMIFS(POs[saldo],POs[cve_prod],DIM_BILL[[#This Row],[CODIGO]],POs[status],$GY32,POs[f_ent],HB$1) -> 0 | HC32: =SUMIFS(POs[saldo],POs[cve_prod],DIM_BILL[[#This Row],[CODIGO]],POs[status],$GY32,POs[f_ent],HC$1) -> 0 | HD32: =SUMIFS(POs[saldo],POs[cve_prod],DIM_BILL[[#This Row],[CODIGO]],POs[status],$GY32,POs[f_ent],HD$1) -> 0 | HE32: =SUMIFS(POs[saldo],POs[cve_prod],DIM_BILL[[#This Row],[CODIGO]],POs[status],$GY32,POs[f_ent],HE$1) -> 0 | HF32: =SUMIFS(POs[saldo],POs[cve_prod],DIM_BILL[[#This Row],[CODIGO]],POs[status],$GY32,POs[Semana],WEEKNUM(HF$1)) -> 0 | HG32: =SUMIFS(POs[saldo],POs[cve_prod],DIM_BILL[[#This Row],[CODIGO]],POs[status],$GY32,POs[Semana],WEEKNUM(HG$1)) -> 0 | HH32: =SUMIFS(POs[saldo],POs[cve_prod],DIM_BILL[[#This Row],[CODIGO]],POs[status],$GY32,POs[Semana],WEEKNUM(HH$1)) -> 0 | HI32: =SUMIFS(POs[saldo],POs[cve_prod],DIM_BILL[[#This Row],[CODIGO]],POs[status],$GY32,POs[Semana],WEEKNUM(HI$1)) -> 0 | HJ32: =SUMIFS(POs[saldo],POs[cve_prod],DIM_BILL[[#This Row],[CODIGO]],POs[status],$GY32,POs[Semana],WEEKNUM(HJ$1)) -> 0 | HK32: =SUMIFS(POs[saldo],POs[cve_prod],DIM_BILL[[#This Row],[CODIGO]],POs[status],$GY32,POs[Semana],WEEKNUM(HK$1)) -> 0 | HL32: =SUMIFS(POs[saldo],POs[cve_prod],DIM_BILL[[#This Row],[CODIGO]],POs[status],$GY32,POs[Semana],WEEKNUM(HL$1)) -> 0 | HM32: =SUMIFS(POs[saldo],POs[cve_prod],DIM_BILL[[#This Row],[CODIGO]],POs[status],$GY32,POs[Semana],WEEKNUM(HM$1)) -> 0 | ... HT32: =SUMIFS(POs[saldo],POs[cve_prod],DIM_BILL[[#This Row],[CODIGO]],POs[status],$GY32,POs[Semana],WEEKNUM(HT$1)) -> 0 | HW32: =DIM_BILL[[#This Row],[Tipo]]
A33: M | FH33: 0.78 | FK33: 0.0063333333 | FW33: 0.063333333 | GG33: 0.0018888889 | GR33: MANO DE O. | GS33: 2 | GV33: =SUMIF(FACT_A1[cve_prod],DIM_BILL[[#This Row],[CODIGO]],FACT_A1[Existencia]) -> 0 | GW33: =SUMIF(FACT_A2[cve_prod],DIM_BILL[[#This Row],[CODIGO]],FACT_A2[Existencia]) -> 0 | GY33: Demanda | GZ33: =SUMPRODUCT($B33:$GQ33,INDEX(PLAN_PRODUCCION!$B$4:$GQ$24,COLUMN()-COLUMN($GZ$1)+1,0)) -> 108 | HA33: =SUMPRODUCT($B33:$GQ33,INDEX(PLAN_PRODUCCION!$B$4:$GQ$24,COLUMN()-COLUMN($GZ$1)+1,0)) -> 0 | HB33: =SUMPRODUCT($B33:$GQ33,INDEX(PLAN_PRODUCCION!$B$4:$GQ$24,COLUMN()-COLUMN($GZ$1)+1,0)) -> 0 | HC33: =SUMPRODUCT($B33:$GQ33,INDEX(PLAN_PRODUCCION!$B$4:$GQ$24,COLUMN()-COLUMN($GZ$1)+1,0)) -> 0 | HD33: =SUMPRODUCT($B33:$GQ33,INDEX(PLAN_PRODUCCION!$B$4:$GQ$24,COLUMN()-COLUMN($GZ$1)+1,0)) -> 0 | HE33: =SUMPRODUCT($B33:$GQ33,INDEX(PLAN_PRODUCCION!$B$4:$GQ$24,COLUMN()-COLUMN($GZ$1)+1,0)) -> 0 | HF33: =SUMPRODUCT($B33:$GQ33,INDEX(PLAN_PRODUCCION!$B$4:$GQ$24,COLUMN()-COLUMN($GZ$1)+1,0)) -> 0 | HG33: =SUMPRODUCT($B33:$GQ33,INDEX(PLAN_PRODUCCION!$B$4:$GQ$24,COLUMN()-COLUMN($GZ$1)+1,0)) -> 0 | ... HT33: =SUMPRODUCT($B33:$GQ33,INDEX(PLAN_PRODUCCION!$B$4:$GQ$24,COLUMN()-COLUMN($GZ$1)+1,0)) -> 0 | HW33: =DIM_BILL[[#This Row],[Tipo]]
A34: M | FH34: 0.78 | FK34: 0.0063333333 | FW34: 0.063333333 | GG34: 0.0018888889 | GR34: MANO DE O. | GS34: 2 | GV34: =SUMIF(FACT_A1[cve_prod],DIM_BILL[[#This Row],[CODIGO]],FACT_A1[Existencia]) -> 0 | GW34: =SUMIF(FACT_A2[cve_prod],DIM_BILL[[#This Row],[CODIGO]],FACT_A2[Existencia]) -> 0 | GY34: Cortos + PO's Confirmadas | GZ34: =GV34+GW34+GX34+GZ32-GZ33 -> -108 | HA34: =GZ34+HA32-HA33 -> -108 | HB34: =HA34+HB32-HB33 -> -108 | HC34: =HB34+HC32-HC33 -> -108 | HD34: =HC34+HD32-HD33 -> -108 | HE34: =HD34+HE32-HE33 -> -108 | HF34: =HE34+HF32-HF33 -> -108 | HG34: =HF34+HG32-HG33 -> -108 | HH34: =HG34+HH32-HH33 -> -108 | ... HT34: =HS34+HT32-HT33 -> -108 | HU34: =COUNTIF(GZ34:HT34,"<0") -> 21 | HW34: =DIM_BILL[[#This Row],[Tipo]]
A35: M1CBOM02 | AQ35: 60.034305 | GR35: OMEGA 3, 6 y 9 CÁPSULA BLANDA | GS35: 4 | GT35: BIOCAPS DE MEXICO SA DE CV | GU35: MATERIA PRIMA | GV35: =SUMIF(FACT_A1[cve_prod],DIM_BILL[[#This Row],[CODIGO]],FACT_A1[Existencia]) -> 191371 | GW35: =SUMIF(FACT_A2[cve_prod],DIM_BILL[[#This Row],[CODIGO]],FACT_A2[Existencia]) -> 220000 | GY35: Por Surtir & Parcial | GZ35: =SUMIFS(POs[saldo],POs[cve_prod],DIM_BILL[[#This Row],[CODIGO]],POs[status],$GY35,POs[f_ent],GZ$1) -> 0 | HA35: =SUMIFS(POs[saldo],POs[cve_prod],DIM_BILL[[#This Row],[CODIGO]],POs[status],$GY35,POs[f_ent],HA$1) -> 0 | HB35: =SUMIFS(POs[saldo],POs[cve_prod],DIM_BILL[[#This Row],[CODIGO]],POs[status],$GY35,POs[f_ent],HB$1) -> 0 | HC35: =SUMIFS(POs[saldo],POs[cve_prod],DIM_BILL[[#This Row],[CODIGO]],POs[status],$GY35,POs[f_ent],HC$1) -> 0 | HD35: =SUMIFS(POs[saldo],POs[cve_prod],DIM_BILL[[#This Row],[CODIGO]],POs[status],$GY35,POs[f_ent],HD$1) -> 0 | HE35: =SUMIFS(POs[saldo],POs[cve_prod],DIM_BILL[[#This Row],[CODIGO]],POs[status],$GY35,POs[f_ent],HE$1) -> 0 | HF35: =SUMIFS(POs[saldo],POs[cve_prod],DIM_BILL[[#This Row],[CODIGO]],POs[status],$GY35,POs[Semana],WEEKNUM(HF$1)) -> 0 | HG35: =SUMIFS(POs[saldo],POs[cve_prod],DIM_BILL[[#This Row],[CODIGO]],POs[status],$GY35,POs[Semana],WEEKNUM(HG$1)) -> 0 | HH35: =SUMIFS(POs[saldo],POs[cve_prod],DIM_BILL[[#This Row],[CODIGO]],POs[status],$GY35,POs[Semana],WEEKNUM(HH$1)) -> 350000 | HI35: =SUMIFS(POs[saldo],POs[cve_prod],DIM_BILL[[#This Row],[CODIGO]],POs[status],$GY35,POs[Semana],WEEKNUM(HI$1)) -> 0 | HJ35: =SUMIFS(POs[saldo],POs[cve_prod],DIM_BILL[[#This Row],[CODIGO]],POs[status],$GY35,POs[Semana],WEEKNUM(HJ$1)) -> 0 | HK35: =SUMIFS(POs[saldo],POs[cve_prod],DIM_BILL[[#This Row],[CODIGO]],POs[status],$GY35,POs[Semana],WEEKNUM(HK$1)) -> 0 | HL35: =SUMIFS(POs[saldo],POs[cve_prod],DIM_BILL[[#This Row],[CODIGO]],POs[status],$GY35,POs[Semana],WEEKNUM(HL$1)) -> 0 | HM35: =SUMIFS(POs[saldo],POs[cve_prod],DIM_BILL[[#This Row],[CODIGO]],POs[status],$GY35,POs[Semana],WEEKNUM(HM$1)) -> 0 | ... HT35: =SUMIFS(POs[saldo],POs[cve_prod],DIM_BILL[[#This Row],[CODIGO]],POs[status],$GY35,POs[Semana],WEEKNUM(HT$1)) -> 0 | HW35: =DIM_BILL[[#This Row],[Tipo]] -> MATERIA PRIMA
A36: M1CBOM02 | AQ36: 60.034305 | GR36: OMEGA 3, 6 y 9 CÁPSULA BLANDA | GS36: 4 | GT36: BIOCAPS DE MEXICO SA DE CV | GU36: MATERIA PRIMA | GV36: =SUMIF(FACT_A1[cve_prod],DIM_BILL[[#This Row],[CODIGO]],FACT_A1[Existencia]) -> 191371 | GW36: =SUMIF(FACT_A2[cve_prod],DIM_BILL[[#This Row],[CODIGO]],FACT_A2[Existencia]) -> 220000 | GY36: Demanda | GZ36: =SUMPRODUCT($B36:$GQ36,INDEX(PLAN_PRODUCCION!$B$4:$GQ$24,COLUMN()-COLUMN($GZ$1)+1,0)) -> 289965.69 | HA36: =SUMPRODUCT($B36:$GQ36,INDEX(PLAN_PRODUCCION!$B$4:$GQ$24,COLUMN()-COLUMN($GZ$1)+1,0)) -> 0 | HB36: =SUMPRODUCT($B36:$GQ36,INDEX(PLAN_PRODUCCION!$B$4:$GQ$24,COLUMN()-COLUMN($GZ$1)+1,0)) -> 0 | HC36: =SUMPRODUCT($B36:$GQ36,INDEX(PLAN_PRODUCCION!$B$4:$GQ$24,COLUMN()-COLUMN($GZ$1)+1,0)) -> 0 | HD36: =SUMPRODUCT($B36:$GQ36,INDEX(PLAN_PRODUCCION!$B$4:$GQ$24,COLUMN()-COLUMN($GZ$1)+1,0)) -> 0 | HE36: =SUMPRODUCT($B36:$GQ36,INDEX(PLAN_PRODUCCION!$B$4:$GQ$24,COLUMN()-COLUMN($GZ$1)+1,0)) -> 0 | HF36: =SUMPRODUCT($B36:$GQ36,INDEX(PLAN_PRODUCCION!$B$4:$GQ$24,COLUMN()-COLUMN($GZ$1)+1,0)) -> 0 | HG36: =SUMPRODUCT($B36:$GQ36,INDEX(PLAN_PRODUCCION!$B$4:$GQ$24,COLUMN()-COLUMN($GZ$1)+1,0)) -> 60034.305 | ... HT36: =SUMPRODUCT($B36:$GQ36,INDEX(PLAN_PRODUCCION!$B$4:$GQ$24,COLUMN()-COLUMN($GZ$1)+1,0)) -> 0 | HW36: =DIM_BILL[[#This Row],[Tipo]] -> MATERIA PRIMA
A37: M1CBOM02 | AQ37: 60.034305 | GR37: OMEGA 3, 6 y 9 CÁPSULA BLANDA | GS37: 4 | GT37: BIOCAPS DE MEXICO SA DE CV | GU37: MATERIA PRIMA | GV37: =SUMIF(FACT_A1[cve_prod],DIM_BILL[[#This Row],[CODIGO]],FACT_A1[Existencia]) -> 191371 | GW37: =SUMIF(FACT_A2[cve_prod],DIM_BILL[[#This Row],[CODIGO]],FACT_A2[Existencia]) -> 220000 | GY37: Cortos + PO's Confirmadas | GZ37: =GV37+GW37+GX37+GZ35-GZ36 -> 121405.31 | HA37: =GZ37+HA35-HA36 -> 121405.31 | HB37: =HA37+HB35-HB36 -> 121405.31 | HC37: =HB37+HC35-HC36 -> 121405.31 | HD37: =HC37+HD35-HD36 -> 121405.31 | HE37: =HD37+HE35-HE36 -> 121405.31 | HF37: =HE37+HF35-HF36 -> 121405.31 | HG37: =HF37+HG35-HG36 -> 61371 | HH37: =HG37+HH35-HH36 -> 411371 | ... HT37: =HS37+HT35-HT36 -> 351336.69 | HU37: =COUNTIF(GZ37:HT37,"<0") -> 0 | HV37: Descuadre de inventario y parcial pendiente por ingresar | HW37: =DIM_BILL[[#This Row],[Tipo]] -> MATERIA PRIMA
A38: M1CBOM03 | B38: 60 | AR38: 60.030875 | AS38: 30 | GR38: OMEGA 3 CÁPSULA BLANDA EPA 33/ DHA 22 | GS38: 3 | GT38: LINDY PHARMA | GU38: MATERIA PRIMA | GV38: =SUMIF(FACT_A1[cve_prod],DIM_BILL[[#This Row],[CODIGO]],FACT_A1[Existencia]) -> 0 | GW38: =SUMIF(FACT_A2[cve_prod],DIM_BILL[[#This Row],[CODIGO]],FACT_A2[Existencia]) -> 271166.8 | GY38: Por Surtir & Parcial | GZ38: =SUMIFS(POs[saldo],POs[cve_prod],DIM_BILL[[#This Row],[CODIGO]],POs[status],$GY38,POs[f_ent],GZ$1) -> 0 | HA38: =SUMIFS(POs[saldo],POs[cve_prod],DIM_BILL[[#This Row],[CODIGO]],POs[status],$GY38,POs[f_ent],HA$1) -> 0 | HB38: =SUMIFS(POs[saldo],POs[cve_prod],DIM_BILL[[#This Row],[CODIGO]],POs[status],$GY38,POs[f_ent],HB$1) -> 0 | HC38: =SUMIFS(POs[saldo],POs[cve_prod],DIM_BILL[[#This Row],[CODIGO]],POs[status],$GY38,POs[f_ent],HC$1) -> 0 | HD38: =SUMIFS(POs[saldo],POs[cve_prod],DIM_BILL[[#This Row],[CODIGO]],POs[status],$GY38,POs[f_ent],HD$1) -> 0 | HE38: =SUMIFS(POs[saldo],POs[cve_prod],DIM_BILL[[#This Row],[CODIGO]],POs[status],$GY38,POs[f_ent],HE$1) -> 0 | HF38: =SUMIFS(POs[saldo],POs[cve_prod],DIM_BILL[[#This Row],[CODIGO]],POs[status],$GY38,POs[Semana],WEEKNUM(HF$1)) -> 0 | HG38: =SUMIFS(POs[saldo],POs[cve_prod],DIM_BILL[[#This Row],[CODIGO]],POs[status],$GY38,POs[Semana],WEEKNUM(HG$1)) -> 750000 | HH38: =SUMIFS(POs[saldo],POs[cve_prod],DIM_BILL[[#This Row],[CODIGO]],POs[status],$GY38,POs[Semana],WEEKNUM(HH$1)) -> 0 | HI38: =SUMIFS(POs[saldo],POs[cve_prod],DIM_BILL[[#This Row],[CODIGO]],POs[status],$GY38,POs[Semana],WEEKNUM(HI$1)) -> 0 | HJ38: =SUMIFS(POs[saldo],POs[cve_prod],DIM_BILL[[#This Row],[CODIGO]],POs[status],$GY38,POs[Semana],WEEKNUM(HJ$1)) -> 0 | HK38: =SUMIFS(POs[saldo],POs[cve_prod],DIM_BILL[[#This Row],[CODIGO]],POs[status],$GY38,POs[Semana],WEEKNUM(HK$1)) -> 0 | HL38: =SUMIFS(POs[saldo],POs[cve_prod],DIM_BILL[[#This Row],[CODIGO]],POs[status],$GY38,POs[Semana],WEEKNUM(HL$1)) -> 0 | HM38: =SUMIFS(POs[saldo],POs[cve_prod],DIM_BILL[[#This Row],[CODIGO]],POs[status],$GY38,POs[Semana],WEEKNUM(HM$1)) -> 0 | ... HT38: =SUMIFS(POs[saldo],POs[cve_prod],DIM_BILL[[#This Row],[CODIGO]],POs[status],$GY38,POs[Semana],WEEKNUM(HT$1)) -> 0 | HW38: =DIM_BILL[[#This Row],[Tipo]] -> MATERIA PRIMA
A39: M1CBOM03 | B39: 60 | AR39: 60.030875 | AS39: 30 | GR39: OMEGA 3 CÁPSULA BLANDA EPA 33/ DHA 22 | GS39: 3 | GT39: LINDY PHARMA | GU39: MATERIA PRIMA | GV39: =SUMIF(FACT_A1[cve_prod],DIM_BILL[[#This Row],[CODIGO]],FACT_A1[Existencia]) -> 0 | GW39: =SUMIF(FACT_A2[cve_prod],DIM_BILL[[#This Row],[CODIGO]],FACT_A2[Existencia]) -> 271166.8 | GY39: Demanda | GZ39: =SUMPRODUCT($B39:$GQ39,INDEX(PLAN_PRODUCCION!$B$4:$GQ$24,COLUMN()-COLUMN($GZ$1)+1,0)) -> 694443.97 | HA39: =SUMPRODUCT($B39:$GQ39,INDEX(PLAN_PRODUCCION!$B$4:$GQ$24,COLUMN()-COLUMN($GZ$1)+1,0)) -> 0 | HB39: =SUMPRODUCT($B39:$GQ39,INDEX(PLAN_PRODUCCION!$B$4:$GQ$24,COLUMN()-COLUMN($GZ$1)+1,0)) -> 0 | HC39: =SUMPRODUCT($B39:$GQ39,INDEX(PLAN_PRODUCCION!$B$4:$GQ$24,COLUMN()-COLUMN($GZ$1)+1,0)) -> 0 | HD39: =SUMPRODUCT($B39:$GQ39,INDEX(PLAN_PRODUCCION!$B$4:$GQ$24,COLUMN()-COLUMN($GZ$1)+1,0)) -> 0 | HE39: =SUMPRODUCT($B39:$GQ39,INDEX(PLAN_PRODUCCION!$B$4:$GQ$24,COLUMN()-COLUMN($GZ$1)+1,0)) -> 0 | HF39: =SUMPRODUCT($B39:$GQ39,INDEX(PLAN_PRODUCCION!$B$4:$GQ$24,COLUMN()-COLUMN($GZ$1)+1,0)) -> 0 | HG39: =SUMPRODUCT($B39:$GQ39,INDEX(PLAN_PRODUCCION!$B$4:$GQ$24,COLUMN()-COLUMN($GZ$1)+1,0)) -> 258132.76 | ... HT39: =SUMPRODUCT($B39:$GQ39,INDEX(PLAN_PRODUCCION!$B$4:$GQ$24,COLUMN()-COLUMN($GZ$1)+1,0)) -> 0 | HW39: =DIM_BILL[[#This Row],[Tipo]] -> MATERIA PRIMA
A40: M1CBOM03 | B40: 60 | AR40: 60.030875 | AS40: 30 | GR40: OMEGA 3 CÁPSULA BLANDA EPA 33/ DHA 22 | GS40: 3 | GT40: LINDY PHARMA | GU40: MATERIA PRIMA | GV40: =SUMIF(FACT_A1[cve_prod],DIM_BILL[[#This Row],[CODIGO]],FACT_A1[Existencia]) -> 0 | GW40: =SUMIF(FACT_A2[cve_prod],DIM_BILL[[#This Row],[CODIGO]],FACT_A2[Existencia]) -> 271166.8 | GY40: Cortos + PO's Confirmadas | GZ40: =GV40+GW40+GX40+GZ38-GZ39 -> -423277.17 | HA40: =GZ40+HA38-HA39 -> -423277.17 | HB40: =HA40+HB38-HB39 -> -423277.17 | HC40: =HB40+HC38-HC39 -> -423277.17 | HD40: =HC40+HD38-HD39 -> -423277.17 | HE40: =HD40+HE38-HE39 -> -423277.17 | HF40: =HE40+HF38-HF39 -> -423277.17 | HG40: =HF40+HG38-HG39 -> 68590.066 | HH40: =HG40+HH38-HH39 -> 68590.066 | ... HT40: =HS40+HT38-HT39 -> -651780.43 | HU40: =COUNTIF(GZ40:HT40,"<0") -> 17 | HW40: =DIM_BILL[[#This Row],[Tipo]] -> MATERIA PRIMA
A41: M1CBOM04 | C41: 60 | GR41: OMEGA 3 KRILL CÁPSULA BLANDA | GS41: 2 | GV41: =SUMIF(FACT_A1[cve_prod],DIM_BILL[[#This Row],[CODIGO]],FACT_A1[Existencia]) -> 0 | GW41: =SUMIF(FACT_A2[cve_prod],DIM_BILL[[#This Row],[CODIGO]],FACT_A2[Existencia]) -> 21340 | GY41: Por Surtir & Parcial | GZ41: =SUMIFS(POs[saldo],POs[cve_prod],DIM_BILL[[#This Row],[CODIGO]],POs[status],$GY41,POs[f_ent],GZ$1) -> 0 | HA41: =SUMIFS(POs[saldo],POs[cve_prod],DIM_BILL[[#This Row],[CODIGO]],POs[status],$GY41,POs[f_ent],HA$1) -> 0 | HB41: =SUMIFS(POs[saldo],POs[cve_prod],DIM_BILL[[#This Row],[CODIGO]],POs[status],$GY41,POs[f_ent],HB$1) -> 0 | HC41: =SUMIFS(POs[saldo],POs[cve_prod],DIM_BILL[[#This Row],[CODIGO]],POs[status],$GY41,POs[f_ent],HC$1) -> 0 | HD41: =SUMIFS(POs[saldo],POs[cve_prod],DIM_BILL[[#This Row],[CODIGO]],POs[status],$GY41,POs[f_ent],HD$1) -> 0 | HE41: =SUMIFS(POs[saldo],POs[cve_prod],DIM_BILL[[#This Row],[CODIGO]],POs[status],$GY41,POs[f_ent],HE$1) -> 0 | HF41: =SUMIFS(POs[saldo],POs[cve_prod],DIM_BILL[[#This Row],[CODIGO]],POs[status],$GY41,POs[Semana],WEEKNUM(HF$1)) -> 0 | HG41: =SUMIFS(POs[saldo],POs[cve_prod],DIM_BILL[[#This Row],[CODIGO]],POs[status],$GY41,POs[Semana],WEEKNUM(HG$1)) -> 0 | HH41: =SUMIFS(POs[saldo],POs[cve_prod],DIM_BILL[[#This Row],[CODIGO]],POs[status],$GY41,POs[Semana],WEEKNUM(HH$1)) -> 0 | HI41: =SUMIFS(POs[saldo],POs[cve_prod],DIM_BILL[[#This Row],[CODIGO]],POs[status],$GY41,POs[Semana],WEEKNUM(HI$1)) -> 0 | HJ41: =SUMIFS(POs[saldo],POs[cve_prod],DIM_BILL[[#This Row],[CODIGO]],POs[status],$GY41,POs[Semana],WEEKNUM(HJ$1)) -> 0 | HK41: =SUMIFS(POs[saldo],POs[cve_prod],DIM_BILL[[#This Row],[CODIGO]],POs[status],$GY41,POs[Semana],WEEKNUM(HK$1)) -> 0 | HL41: =SUMIFS(POs[saldo],POs[cve_prod],DIM_BILL[[#This Row],[CODIGO]],POs[status],$GY41,POs[Semana],WEEKNUM(HL$1)) -> 0 | HM41: =SUMIFS(POs[saldo],POs[cve_prod],DIM_BILL[[#This Row],[CODIGO]],POs[status],$GY41,POs[Semana],WEEKNUM(HM$1)) -> 0 | ... HT41: =SUMIFS(POs[saldo],POs[cve_prod],DIM_BILL[[#This Row],[CODIGO]],POs[status],$GY41,POs[Semana],WEEKNUM(HT$1)) -> 0 | HW41: =DIM_BILL[[#This Row],[Tipo]]
A42: M1CBOM04 | C42: 60 | GR42: OMEGA 3 KRILL CÁPSULA BLANDA | GS42: 2 | GV42: =SUMIF(FACT_A1[cve_prod],DIM_BILL[[#This Row],[CODIGO]],FACT_A1[Existencia]) -> 0 | GW42: =SUMIF(FACT_A2[cve_prod],DIM_BILL[[#This Row],[CODIGO]],FACT_A2[Existencia]) -> 21340 | GY42: Demanda | GZ42: =SUMPRODUCT($B42:$GQ42,INDEX(PLAN_PRODUCCION!$B$4:$GQ$24,COLUMN()-COLUMN($GZ$1)+1,0)) -> 0 | HA42: =SUMPRODUCT($B42:$GQ42,INDEX(PLAN_PRODUCCION!$B$4:$GQ$24,COLUMN()-COLUMN($GZ$1)+1,0)) -> 0 | HB42: =SUMPRODUCT($B42:$GQ42,INDEX(PLAN_PRODUCCION!$B$4:$GQ$24,COLUMN()-COLUMN($GZ$1)+1,0)) -> 0 | HC42: =SUMPRODUCT($B42:$GQ42,INDEX(PLAN_PRODUCCION!$B$4:$GQ$24,COLUMN()-COLUMN($GZ$1)+1,0)) -> 0 | HD42: =SUMPRODUCT($B42:$GQ42,INDEX(PLAN_PRODUCCION!$B$4:$GQ$24,COLUMN()-COLUMN($GZ$1)+1,0)) -> 0 | HE42: =SUMPRODUCT($B42:$GQ42,INDEX(PLAN_PRODUCCION!$B$4:$GQ$24,COLUMN()-COLUMN($GZ$1)+1,0)) -> 0 | HF42: =SUMPRODUCT($B42:$GQ42,INDEX(PLAN_PRODUCCION!$B$4:$GQ$24,COLUMN()-COLUMN($GZ$1)+1,0)) -> 0 | HG42: =SUMPRODUCT($B42:$GQ42,INDEX(PLAN_PRODUCCION!$B$4:$GQ$24,COLUMN()-COLUMN($GZ$1)+1,0)) -> 0 | ... HT42: =SUMPRODUCT($B42:$GQ42,INDEX(PLAN_PRODUCCION!$B$4:$GQ$24,COLUMN()-COLUMN($GZ$1)+1,0)) -> 0 | HW42: =DIM_BILL[[#This Row],[Tipo]]
A43: M1CBOM04 | C43: 60 | GR43: OMEGA 3 KRILL CÁPSULA BLANDA | GS43: 2 | GV43: =SUMIF(FACT_A1[cve_prod],DIM_BILL[[#This Row],[CODIGO]],FACT_A1[Existencia]) -> 0 | GW43: =SUMIF(FACT_A2[cve_prod],DIM_BILL[[#This Row],[CODIGO]],FACT_A2[Existencia]) -> 21340 | GY43: Cortos + PO's Confirmadas | GZ43: =GV43+GW43+GX43+GZ41-GZ42 -> 21340 | HA43: =GZ43+HA41-HA42 -> 21340 | HB43: =HA43+HB41-HB42 -> 21340 | HC43: =HB43+HC41-HC42 -> 21340 | HD43: =HC43+HD41-HD42 -> 21340 | HE43: =HD43+HE41-HE42 -> 21340 | HF43: =HE43+HF41-HF42 -> 21340 | HG43: =HF43+HG41-HG42 -> 21340 | HH43: =HG43+HH41-HH42 -> 21340 | ... HT43: =HS43+HT41-HT42 -> 21340 | HU43: =COUNTIF(GZ43:HT43,"<0") -> 0 | HW43: =DIM_BILL[[#This Row],[Tipo]]
A44: M1CBOM05 | D44: 60 | GR44: OMEGA 3 650mg caps blanda oval verde | GS44: 3 | GT44: INDUSTRIAS DE NUTRACEUTICOS | GU44: MAQUILA | GV44: =SUMIF(FACT_A1[cve_prod],DIM_BILL[[#This Row],[CODIGO]],FACT_A1[Existencia]) -> 0 | GW44: =SUMIF(FACT_A2[cve_prod],DIM_BILL[[#This Row],[CODIGO]],FACT_A2[Existencia]) -> 25000 | GY44: Por Surtir & Parcial | GZ44: =SUMIFS(POs[saldo],POs[cve_prod],DIM_BILL[[#This Row],[CODIGO]],POs[status],$GY44,POs[f_ent],GZ$1) -> 0 | HA44: =SUMIFS(POs[saldo],POs[cve_prod],DIM_BILL[[#This Row],[CODIGO]],POs[status],$GY44,POs[f_ent],HA$1) -> 0 | HB44: =SUMIFS(POs[saldo],POs[cve_prod],DIM_BILL[[#This Row],[CODIGO]],POs[status],$GY44,POs[f_ent],HB$1) -> 0 | HC44: =SUMIFS(POs[saldo],POs[cve_prod],DIM_BILL[[#This Row],[CODIGO]],POs[status],$GY44,POs[f_ent],HC$1) -> 0 | HD44: =SUMIFS(POs[saldo],POs[cve_prod],DIM_BILL[[#This Row],[CODIGO]],POs[status],$GY44,POs[f_ent],HD$1) -> 0 | HE44: =SUMIFS(POs[saldo],POs[cve_prod],DIM_BILL[[#This Row],[CODIGO]],POs[status],$GY44,POs[f_ent],HE$1) -> 0 | HF44: =SUMIFS(POs[saldo],POs[cve_prod],DIM_BILL[[#This Row],[CODIGO]],POs[status],$GY44,POs[Semana],WEEKNUM(HF$1)) -> 0 | HG44: =SUMIFS(POs[saldo],POs[cve_prod],DIM_BILL[[#This Row],[CODIGO]],POs[status],$GY44,POs[Semana],WEEKNUM(HG$1)) -> 0 | HH44: =SUMIFS(POs[saldo],POs[cve_prod],DIM_BILL[[#This Row],[CODIGO]],POs[status],$GY44,POs[Semana],WEEKNUM(HH$1)) -> 0 | HI44: =SUMIFS(POs[saldo],POs[cve_prod],DIM_BILL[[#This Row],[CODIGO]],POs[status],$GY44,POs[Semana],WEEKNUM(HI$1)) -> 0 | HJ44: =SUMIFS(POs[saldo],POs[cve_prod],DIM_BILL[[#This Row],[CODIGO]],POs[status],$GY44,POs[Semana],WEEKNUM(HJ$1)) -> 0 | HK44: =SUMIFS(POs[saldo],POs[cve_prod],DIM_BILL[[#This Row],[CODIGO]],POs[status],$GY44,POs[Semana],WEEKNUM(HK$1)) -> 0 | HL44: =SUMIFS(POs[saldo],POs[cve_prod],DIM_BILL[[#This Row],[CODIGO]],POs[status],$GY44,POs[Semana],WEEKNUM(HL$1)) -> 0 | HM44: =SUMIFS(POs[saldo],POs[cve_prod],DIM_BILL[[#This Row],[CODIGO]],POs[status],$GY44,POs[Semana],WEEKNUM(HM$1)) -> 0 | ... HT44: =SUMIFS(POs[saldo],POs[cve_prod],DIM_BILL[[#This Row],[CODIGO]],POs[status],$GY44,POs[Semana],WEEKNUM(HT$1)) -> 0 | HW44: =DIM_BILL[[#This Row],[Tipo]] -> MAQUILA
A45: M1CBOM05 | D45: 60 | GR45: OMEGA 3 650mg caps blanda oval verde | GS45: 3 | GT45: INDUSTRIAS DE NUTRACEUTICOS | GU45: MAQUILA | GV45: =SUMIF(FACT_A1[cve_prod],DIM_BILL[[#This Row],[CODIGO]],FACT_A1[Existencia]) -> 0 | GW45: =SUMIF(FACT_A2[cve_prod],DIM_BILL[[#This Row],[CODIGO]],FACT_A2[Existencia]) -> 25000 | GY45: Demanda | GZ45: =SUMPRODUCT($B45:$GQ45,INDEX(PLAN_PRODUCCION!$B$4:$GQ$24,COLUMN()-COLUMN($GZ$1)+1,0)) -> 600000 | HA45: =SUMPRODUCT($B45:$GQ45,INDEX(PLAN_PRODUCCION!$B$4:$GQ$24,COLUMN()-COLUMN($GZ$1)+1,0)) -> 0 | HB45: =SUMPRODUCT($B45:$GQ45,INDEX(PLAN_PRODUCCION!$B$4:$GQ$24,COLUMN()-COLUMN($GZ$1)+1,0)) -> 0 | HC45: =SUMPRODUCT($B45:$GQ45,INDEX(PLAN_PRODUCCION!$B$4:$GQ$24,COLUMN()-COLUMN($GZ$1)+1,0)) -> 0 | HD45: =SUMPRODUCT($B45:$GQ45,INDEX(PLAN_PRODUCCION!$B$4:$GQ$24,COLUMN()-COLUMN($GZ$1)+1,0)) -> 0 | HE45: =SUMPRODUCT($B45:$GQ45,INDEX(PLAN_PRODUCCION!$B$4:$GQ$24,COLUMN()-COLUMN($GZ$1)+1,0)) -> 0 | HF45: =SUMPRODUCT($B45:$GQ45,INDEX(PLAN_PRODUCCION!$B$4:$GQ$24,COLUMN()-COLUMN($GZ$1)+1,0)) -> 0 | HG45: =SUMPRODUCT($B45:$GQ45,INDEX(PLAN_PRODUCCION!$B$4:$GQ$24,COLUMN()-COLUMN($GZ$1)+1,0)) -> 0 | ... HT45: =SUMPRODUCT($B45:$GQ45,INDEX(PLAN_PRODUCCION!$B$4:$GQ$24,COLUMN()-COLUMN($GZ$1)+1,0)) -> 0 | HW45: =DIM_BILL[[#This Row],[Tipo]] -> MAQUILA
A46: M1CBOM05 | D46: 60 | GR46: OMEGA 3 650mg caps blanda oval verde | GS46: 3 | GT46: INDUSTRIAS DE NUTRACEUTICOS | GU46: MAQUILA | GV46: =SUMIF(FACT_A1[cve_prod],DIM_BILL[[#This Row],[CODIGO]],FACT_A1[Existencia]) -> 0 | GW46: =SUMIF(FACT_A2[cve_prod],DIM_BILL[[#This Row],[CODIGO]],FACT_A2[Existencia]) -> 25000 | GY46: Cortos + PO's Confirmadas | GZ46: =GV46+GW46+GX46+GZ44-GZ45 -> -575000 | HA46: =GZ46+HA44-HA45 -> -575000 | HB46: =HA46+HB44-HB45 -> -575000 | HC46: =HB46+HC44-HC45 -> -575000 | HD46: =HC46+HD44-HD45 -> -575000 | HE46: =HD46+HE44-HE45 -> -575000 | HF46: =HE46+HF44-HF45 -> -575000 | HG46: =HF46+HG44-HG45 -> -575000 | HH46: =HG46+HH44-HH45 -> -575000 | ... HT46: =HS46+HT44-HT45 -> -575000 | HU46: =COUNTIF(GZ46:HT46,"<0") -> 21 | HW46: =DIM_BILL[[#This Row],[Tipo]] -> MAQUILA
A47: M1CBVA01 | AY47: 30 | GR47: VITAMINA A 200mg CÁPSULA BLANDA | GS47: 2 | GV47: =SUMIF(FACT_A1[cve_prod],DIM_BILL[[#This Row],[CODIGO]],FACT_A1[Existencia]) -> 0 | GW47: =SUMIF(FACT_A2[cve_prod],DIM_BILL[[#This Row],[CODIGO]],FACT_A2[Existencia]) -> 60000 | GY47: Por Surtir & Parcial | GZ47: =SUMIFS(POs[saldo],POs[cve_prod],DIM_BILL[[#This Row],[CODIGO]],POs[status],$GY47,POs[f_ent],GZ$1) -> 0 | HA47: =SUMIFS(POs[saldo],POs[cve_prod],DIM_BILL[[#This Row],[CODIGO]],POs[status],$GY47,POs[f_ent],HA$1) -> 0 | HB47: =SUMIFS(POs[saldo],POs[cve_prod],DIM_BILL[[#This Row],[CODIGO]],POs[status],$GY47,POs[f_ent],HB$1) -> 0 | HC47: =SUMIFS(POs[saldo],POs[cve_prod],DIM_BILL[[#This Row],[CODIGO]],POs[status],$GY47,POs[f_ent],HC$1) -> 0 | HD47: =SUMIFS(POs[saldo],POs[cve_prod],DIM_BILL[[#This Row],[CODIGO]],POs[status],$GY47,POs[f_ent],HD$1) -> 0 | HE47: =SUMIFS(POs[saldo],POs[cve_prod],DIM_BILL[[#This Row],[CODIGO]],POs[status],$GY47,POs[f_ent],HE$1) -> 0 | HF47: =SUMIFS(POs[saldo],POs[cve_prod],DIM_BILL[[#This Row],[CODIGO]],POs[status],$GY47,POs[Semana],WEEKNUM(HF$1)) -> 0 | HG47: =SUMIFS(POs[saldo],POs[cve_prod],DIM_BILL[[#This Row],[CODIGO]],POs[status],$GY47,POs[Semana],WEEKNUM(HG$1)) -> 0 | HH47: =SUMIFS(POs[saldo],POs[cve_prod],DIM_BILL[[#This Row],[CODIGO]],POs[status],$GY47,POs[Semana],WEEKNUM(HH$1)) -> 0 | HI47: =SUMIFS(POs[saldo],POs[cve_prod],DIM_BILL[[#This Row],[CODIGO]],POs[status],$GY47,POs[Semana],WEEKNUM(HI$1)) -> 0 | HJ47: =SUMIFS(POs[saldo],POs[cve_prod],DIM_BILL[[#This Row],[CODIGO]],POs[status],$GY47,POs[Semana],WEEKNUM(HJ$1)) -> 0 | HK47: =SUMIFS(POs[saldo],POs[cve_prod],DIM_BILL[[#This Row],[CODIGO]],POs[status],$GY47,POs[Semana],WEEKNUM(HK$1)) -> 0 | HL47: =SUMIFS(POs[saldo],POs[cve_prod],DIM_BILL[[#This Row],[CODIGO]],POs[status],$GY47,POs[Semana],WEEKNUM(HL$1)) -> 0 | HM47: =SUMIFS(POs[saldo],POs[cve_prod],DIM_BILL[[#This Row],[CODIGO]],POs[status],$GY47,POs[Semana],WEEKNUM(HM$1)) -> 0 | ... HT47: =SUMIFS(POs[saldo],POs[cve_prod],DIM_BILL[[#This Row],[CODIGO]],POs[status],$GY47,POs[Semana],WEEKNUM(HT$1)) -> 0 | HW47: =DIM_BILL[[#This Row],[Tipo]]
A48: M1CBVA01 | AY48: 30 | GR48: VITAMINA A 200mg CÁPSULA BLANDA | GS48: 2 | GV48: =SUMIF(FACT_A1[cve_prod],DIM_BILL[[#This Row],[CODIGO]],FACT_A1[Existencia]) -> 0 | GW48: =SUMIF(FACT_A2[cve_prod],DIM_BILL[[#This Row],[CODIGO]],FACT_A2[Existencia]) -> 60000 | GY48: Demanda | GZ48: =SUMPRODUCT($B48:$GQ48,INDEX(PLAN_PRODUCCION!$B$4:$GQ$24,COLUMN()-COLUMN($GZ$1)+1,0)) -> 0 | HA48: =SUMPRODUCT($B48:$GQ48,INDEX(PLAN_PRODUCCION!$B$4:$GQ$24,COLUMN()-COLUMN($GZ$1)+1,0)) -> 0 | HB48: =SUMPRODUCT($B48:$GQ48,INDEX(PLAN_PRODUCCION!$B$4:$GQ$24,COLUMN()-COLUMN($GZ$1)+1,0)) -> 0 | HC48: =SUMPRODUCT($B48:$GQ48,INDEX(PLAN_PRODUCCION!$B$4:$GQ$24,COLUMN()-COLUMN($GZ$1)+1,0)) -> 0 | HD48: =SUMPRODUCT($B48:$GQ48,INDEX(PLAN_PRODUCCION!$B$4:$GQ$24,COLUMN()-COLUMN($GZ$1)+1,0)) -> 0 | HE48: =SUMPRODUCT($B48:$GQ48,INDEX(PLAN_PRODUCCION!$B$4:$GQ$24,COLUMN()-COLUMN($GZ$1)+1,0)) -> 0 | HF48: =SUMPRODUCT($B48:$GQ48,INDEX(PLAN_PRODUCCION!$B$4:$GQ$24,COLUMN()-COLUMN($GZ$1)+1,0)) -> 0 | HG48: =SUMPRODUCT($B48:$GQ48,INDEX(PLAN_PRODUCCION!$B$4:$GQ$24,COLUMN()-COLUMN($GZ$1)+1,0)) -> 0 | ... HT48: =SUMPRODUCT($B48:$GQ48,INDEX(PLAN_PRODUCCION!$B$4:$GQ$24,COLUMN()-COLUMN($GZ$1)+1,0)) -> 0 | HW48: =DIM_BILL[[#This Row],[Tipo]]
A49: M1CBVA01 | AY49: 30 | GR49: VITAMINA A 200mg CÁPSULA BLANDA | GS49: 2 | GV49: =SUMIF(FACT_A1[cve_prod],DIM_BILL[[#This Row],[CODIGO]],FACT_A1[Existencia]) -> 0 | GW49: =SUMIF(FACT_A2[cve_prod],DIM_BILL[[#This Row],[CODIGO]],FACT_A2[Existencia]) -> 60000 | GY49: Cortos + PO's Confirmadas | GZ49: =GV49+GW49+GX49+GZ47-GZ48 -> 60000 | HA49: =GZ49+HA47-HA48 -> 60000 | HB49: =HA49+HB47-HB48 -> 60000 | HC49: =HB49+HC47-HC48 -> 60000 | HD49: =HC49+HD47-HD48 -> 60000 | HE49: =HD49+HE47-HE48 -> 60000 | HF49: =HE49+HF47-HF48 -> 60000 | HG49: =HF49+HG47-HG48 -> 60000 | HH49: =HG49+HH47-HH48 -> 60000 | ... HT49: =HS49+HT47-HT48 -> 60000 | HU49: =COUNTIF(GZ49:HT49,"<0") -> 0 | HW49: =DIM_BILL[[#This Row],[Tipo]]
A50: MEP-0007 | FH50: 0.0036677778 | GR50: BOBINA ALUMINIO CASTAÑO DE INDIAS | GS50: 2 | GT50: COMERCIALIZADORA NEFUR | GU50: MATERIAL DE EMPAQUE | GV50: =SUMIF(FACT_A1[cve_prod],DIM_BILL[[#This Row],[CODIGO]],FACT_A1[Existencia]) -> 0 | GW50: =SUMIF(FACT_A2[cve_prod],DIM_BILL[[#This Row],[CODIGO]],FACT_A2[Existencia]) -> 10.3 | GY50: Por Surtir & Parcial | GZ50: =SUMIFS(POs[saldo],POs[cve_prod],DIM_BILL[[#This Row],[CODIGO]],POs[status],$GY50,POs[f_ent],GZ$1) -> 0 | HA50: =SUMIFS(POs[saldo],POs[cve_prod],DIM_BILL[[#This Row],[CODIGO]],POs[status],$GY50,POs[f_ent],HA$1) -> 0 | HB50: =SUMIFS(POs[saldo],POs[cve_prod],DIM_BILL[[#This Row],[CODIGO]],POs[status],$GY50,POs[f_ent],HB$1) -> 0 | HC50: =SUMIFS(POs[saldo],POs[cve_prod],DIM_BILL[[#This Row],[CODIGO]],POs[status],$GY50,POs[f_ent],HC$1) -> 0 | HD50: =SUMIFS(POs[saldo],POs[cve_prod],DIM_BILL[[#This Row],[CODIGO]],POs[status],$GY50,POs[f_ent],HD$1) -> 0 | HE50: =SUMIFS(POs[saldo],POs[cve_prod],DIM_BILL[[#This Row],[CODIGO]],POs[status],$GY50,POs[f_ent],HE$1) -> 0 | HF50: =SUMIFS(POs[saldo],POs[cve_prod],DIM_BILL[[#This Row],[CODIGO]],POs[status],$GY50,POs[Semana],WEEKNUM(HF$1)) -> 0 | HG50: =SUMIFS(POs[saldo],POs[cve_prod],DIM_BILL[[#This Row],[CODIGO]],POs[status],$GY50,POs[Semana],WEEKNUM(HG$1)) -> 0 | HH50: =SUMIFS(POs[saldo],POs[cve_prod],DIM_BILL[[#This Row],[CODIGO]],POs[status],$GY50,POs[Semana],WEEKNUM(HH$1)) -> 0 | HI50: =SUMIFS(POs[saldo],POs[cve_prod],DIM_BILL[[#This Row],[CODIGO]],POs[status],$GY50,POs[Semana],WEEKNUM(HI$1)) -> 0 | HJ50: =SUMIFS(POs[saldo],POs[cve_prod],DIM_BILL[[#This Row],[CODIGO]],POs[status],$GY50,POs[Semana],WEEKNUM(HJ$1)) -> 0 | HK50: =SUMIFS(POs[saldo],POs[cve_prod],DIM_BILL[[#This Row],[CODIGO]],POs[status],$GY50,POs[Semana],WEEKNUM(HK$1)) -> 0 | HL50: =SUMIFS(POs[saldo],POs[cve_prod],DIM_BILL[[#This Row],[CODIGO]],POs[status],$GY50,POs[Semana],WEEKNUM(HL$1)) -> 0 | HM50: =SUMIFS(POs[saldo],POs[cve_prod],DIM_BILL[[#This Row],[CODIGO]],POs[status],$GY50,POs[Semana],WEEKNUM(HM$1)) -> 0 | ... HT50: =SUMIFS(POs[saldo],POs[cve_prod],DIM_BILL[[#This Row],[CODIGO]],POs[status],$GY50,POs[Semana],WEEKNUM(HT$1)) -> 0 | HW50: =DIM_BILL[[#This Row],[Tipo]] -> MATERIAL DE EMPAQUE
A51: MEP-0007 | FH51: 0.0036677778 | GR51: BOBINA ALUMINIO CASTAÑO DE INDIAS | GS51: 2 | GT51: COMERCIALIZADORA NEFUR | GU51: MATERIAL DE EMPAQUE | GV51: =SUMIF(FACT_A1[cve_prod],DIM_BILL[[#This Row],[CODIGO]],FACT_A1[Existencia]) -> 0 | GW51: =SUMIF(FACT_A2[cve_prod],DIM_BILL[[#This Row],[CODIGO]],FACT_A2[Existencia]) -> 10.3 | GY51: Demanda | GZ51: =SUMPRODUCT($B51:$GQ51,INDEX(PLAN_PRODUCCION!$B$4:$GQ$24,COLUMN()-COLUMN($GZ$1)+1,0)) -> 0 | HA51: =SUMPRODUCT($B51:$GQ51,INDEX(PLAN_PRODUCCION!$B$4:$GQ$24,COLUMN()-COLUMN($GZ$1)+1,0)) -> 0 | HB51: =SUMPRODUCT($B51:$GQ51,INDEX(PLAN_PRODUCCION!$B$4:$GQ$24,COLUMN()-COLUMN($GZ$1)+1,0)) -> 0 | HC51: =SUMPRODUCT($B51:$GQ51,INDEX(PLAN_PRODUCCION!$B$4:$GQ$24,COLUMN()-COLUMN($GZ$1)+1,0)) -> 0 | HD51: =SUMPRODUCT($B51:$GQ51,INDEX(PLAN_PRODUCCION!$B$4:$GQ$24,COLUMN()-COLUMN($GZ$1)+1,0)) -> 0 | HE51: =SUMPRODUCT($B51:$GQ51,INDEX(PLAN_PRODUCCION!$B$4:$GQ$24,COLUMN()-COLUMN($GZ$1)+1,0)) -> 0 | HF51: =SUMPRODUCT($B51:$GQ51,INDEX(PLAN_PRODUCCION!$B$4:$GQ$24,COLUMN()-COLUMN($GZ$1)+1,0)) -> 0 | HG51: =SUMPRODUCT($B51:$GQ51,INDEX(PLAN_PRODUCCION!$B$4:$GQ$24,COLUMN()-COLUMN($GZ$1)+1,0)) -> 0 | ... HT51: =SUMPRODUCT($B51:$GQ51,INDEX(PLAN_PRODUCCION!$B$4:$GQ$24,COLUMN()-COLUMN($GZ$1)+1,0)) -> 0 | HW51: =DIM_BILL[[#This Row],[Tipo]] -> MATERIAL DE EMPAQUE
A52: MEP-0007 | FH52: 0.0036677778 | GR52: BOBINA ALUMINIO CASTAÑO DE INDIAS | GS52: 2 | GT52: COMERCIALIZADORA NEFUR | GU52: MATERIAL DE EMPAQUE | GV52: =SUMIF(FACT_A1[cve_prod],DIM_BILL[[#This Row],[CODIGO]],FACT_A1[Existencia]) -> 0 | GW52: =SUMIF(FACT_A2[cve_prod],DIM_BILL[[#This Row],[CODIGO]],FACT_A2[Existencia]) -> 10.3 | GY52: Cortos + PO's Confirmadas | GZ52: =GV52+GW52+GX52+GZ50-GZ51 -> 10.3 | HA52: =GZ52+HA50-HA51 -> 10.3 | HB52: =HA52+HB50-HB51 -> 10.3 | HC52: =HB52+HC50-HC51 -> 10.3 | HD52: =HC52+HD50-HD51 -> 10.3 | HE52: =HD52+HE50-HE51 -> 10.3 | HF52: =HE52+HF50-HF51 -> 10.3 | HG52: =HF52+HG50-HG51 -> 10.3 | HH52: =HG52+HH50-HH51 -> 10.3 | ... HT52: =HS52+HT50-HT51 -> 10.3 | HU52: =COUNTIF(GZ52:HT52,"<0") -> 0 | HW52: =DIM_BILL[[#This Row],[Tipo]] -> MATERIAL DE EMPAQUE
A53: MEP-0013 | GG53: 0.0016533333 | GR53: BOBINA ALUMINIO PLENIFORM 40 | GS53: 2 | GT53: COMERCIALIZADORA NEFUR | GU53: MATERIAL DE EMPAQUE | GV53: =SUMIF(FACT_A1[cve_prod],DIM_BILL[[#This Row],[CODIGO]],FACT_A1[Existencia]) -> 0 | GW53: =SUMIF(FACT_A2[cve_prod],DIM_BILL[[#This Row],[CODIGO]],FACT_A2[Existencia]) -> 0 | GY53: Por Surtir & Parcial | GZ53: =SUMIFS(POs[saldo],POs[cve_prod],DIM_BILL[[#This Row],[CODIGO]],POs[status],$GY53,POs[f_ent],GZ$1) -> 0 | HA53: =SUMIFS(POs[saldo],POs[cve_prod],DIM_BILL[[#This Row],[CODIGO]],POs[status],$GY53,POs[f_ent],HA$1) -> 0 | HB53: =SUMIFS(POs[saldo],POs[cve_prod],DIM_BILL[[#This Row],[CODIGO]],POs[status],$GY53,POs[f_ent],HB$1) -> 0 | HC53: =SUMIFS(POs[saldo],POs[cve_prod],DIM_BILL[[#This Row],[CODIGO]],POs[status],$GY53,POs[f_ent],HC$1) -> 0 | HD53: =SUMIFS(POs[saldo],POs[cve_prod],DIM_BILL[[#This Row],[CODIGO]],POs[status],$GY53,POs[f_ent],HD$1) -> 0 | HE53: =SUMIFS(POs[saldo],POs[cve_prod],DIM_BILL[[#This Row],[CODIGO]],POs[status],$GY53,POs[f_ent],HE$1) -> 0 | HF53: =SUMIFS(POs[saldo],POs[cve_prod],DIM_BILL[[#This Row],[CODIGO]],POs[status],$GY53,POs[Semana],WEEKNUM(HF$1)) -> 0 | HG53: =SUMIFS(POs[saldo],POs[cve_prod],DIM_BILL[[#This Row],[CODIGO]],POs[status],$GY53,POs[Semana],WEEKNUM(HG$1)) -> 0 | HH53: =SUMIFS(POs[saldo],POs[cve_prod],DIM_BILL[[#This Row],[CODIGO]],POs[status],$GY53,POs[Semana],WEEKNUM(HH$1)) -> 0 | HI53: =SUMIFS(POs[saldo],POs[cve_prod],DIM_BILL[[#This Row],[CODIGO]],POs[status],$GY53,POs[Semana],WEEKNUM(HI$1)) -> 0 | HJ53: =SUMIFS(POs[saldo],POs[cve_prod],DIM_BILL[[#This Row],[CODIGO]],POs[status],$GY53,POs[Semana],WEEKNUM(HJ$1)) -> 0 | HK53: =SUMIFS(POs[saldo],POs[cve_prod],DIM_BILL[[#This Row],[CODIGO]],POs[status],$GY53,POs[Semana],WEEKNUM(HK$1)) -> 0 | HL53: =SUMIFS(POs[saldo],POs[cve_prod],DIM_BILL[[#This Row],[CODIGO]],POs[status],$GY53,POs[Semana],WEEKNUM(HL$1)) -> 0 | HM53: =SUMIFS(POs[saldo],POs[cve_prod],DIM_BILL[[#This Row],[CODIGO]],POs[status],$GY53,POs[Semana],WEEKNUM(HM$1)) -> 0 | ... HT53: =SUMIFS(POs[saldo],POs[cve_prod],DIM_BILL[[#This Row],[CODIGO]],POs[status],$GY53,POs[Semana],WEEKNUM(HT$1)) -> 0 | HW53: =DIM_BILL[[#This Row],[Tipo]] -> MATERIAL DE EMPAQUE
A54: MEP-0013 | GG54: 0.0016533333 | GR54: BOBINA ALUMINIO PLENIFORM 40 | GS54: 2 | GT54: COMERCIALIZADORA NEFUR | GU54: MATERIAL DE EMPAQUE | GV54: =SUMIF(FACT_A1[cve_prod],DIM_BILL[[#This Row],[CODIGO]],FACT_A1[Existencia]) -> 0 | GW54: =SUMIF(FACT_A2[cve_prod],DIM_BILL[[#This Row],[CODIGO]],FACT_A2[Existencia]) -> 0 | GY54: Demanda | GZ54: =SUMPRODUCT($B54:$GQ54,INDEX(PLAN_PRODUCCION!$B$4:$GQ$24,COLUMN()-COLUMN($GZ$1)+1,0)) -> 44.64 | HA54: =SUMPRODUCT($B54:$GQ54,INDEX(PLAN_PRODUCCION!$B$4:$GQ$24,COLUMN()-COLUMN($GZ$1)+1,0)) -> 0 | HB54: =SUMPRODUCT($B54:$GQ54,INDEX(PLAN_PRODUCCION!$B$4:$GQ$24,COLUMN()-COLUMN($GZ$1)+1,0)) -> 0 | HC54: =SUMPRODUCT($B54:$GQ54,INDEX(PLAN_PRODUCCION!$B$4:$GQ$24,COLUMN()-COLUMN($GZ$1)+1,0)) -> 0 | HD54: =SUMPRODUCT($B54:$GQ54,INDEX(PLAN_PRODUCCION!$B$4:$GQ$24,COLUMN()-COLUMN($GZ$1)+1,0)) -> 0 | HE54: =SUMPRODUCT($B54:$GQ54,INDEX(PLAN_PRODUCCION!$B$4:$GQ$24,COLUMN()-COLUMN($GZ$1)+1,0)) -> 0 | HF54: =SUMPRODUCT($B54:$GQ54,INDEX(PLAN_PRODUCCION!$B$4:$GQ$24,COLUMN()-COLUMN($GZ$1)+1,0)) -> 0 | HG54: =SUMPRODUCT($B54:$GQ54,INDEX(PLAN_PRODUCCION!$B$4:$GQ$24,COLUMN()-COLUMN($GZ$1)+1,0)) -> 0 | ... HT54: =SUMPRODUCT($B54:$GQ54,INDEX(PLAN_PRODUCCION!$B$4:$GQ$24,COLUMN()-COLUMN($GZ$1)+1,0)) -> 0 | HW54: =DIM_BILL[[#This Row],[Tipo]] -> MATERIAL DE EMPAQUE
A55: MEP-0013 | GG55: 0.0016533333 | GR55: BOBINA ALUMINIO PLENIFORM 40 | GS55: 2 | GT55: COMERCIALIZADORA NEFUR | GU55: MATERIAL DE EMPAQUE | GV55: =SUMIF(FACT_A1[cve_prod],DIM_BILL[[#This Row],[CODIGO]],FACT_A1[Existencia]) -> 0 | GW55: =SUMIF(FACT_A2[cve_prod],DIM_BILL[[#This Row],[CODIGO]],FACT_A2[Existencia]) -> 0 | GY55: Cortos + PO's Confirmadas | GZ55: =GV55+GW55+GX55+GZ53-GZ54 -> -44.64 | HA55: =GZ55+HA53-HA54 -> -44.64 | HB55: =HA55+HB53-HB54 -> -44.64 | HC55: =HB55+HC53-HC54 -> -44.64 | HD55: =HC55+HD53-HD54 -> -44.64 | HE55: =HD55+HE53-HE54 -> -44.64 | HF55: =HE55+HF53-HF54 -> -44.64 | HG55: =HF55+HG53-HG54 -> -44.64 | HH55: =HG55+HH53-HH54 -> -44.64 | ... HT55: =HS55+HT53-HT54 -> -44.64 | HU55: =COUNTIF(GZ55:HT55,"<0") -> 21 | HW55: =DIM_BILL[[#This Row],[Tipo]] -> MATERIAL DE EMPAQUE
A56: MEP-0045 | U56: 0.00369 | GR56: BOBINA ALUMINIO DIALAVIT Cápsulas | GS56: 2 | GT56: COMERCIALIZADORA NEFUR | GU56: MATERIAL DE EMPAQUE | GV56: =SUMIF(FACT_A1[cve_prod],DIM_BILL[[#This Row],[CODIGO]],FACT_A1[Existencia]) -> 0 | GW56: =SUMIF(FACT_A2[cve_prod],DIM_BILL[[#This Row],[CODIGO]],FACT_A2[Existencia]) -> 10.4 | GY56: Por Surtir & Parcial | GZ56: =SUMIFS(POs[saldo],POs[cve_prod],DIM_BILL[[#This Row],[CODIGO]],POs[status],$GY56,POs[f_ent],GZ$1) -> 0 | HA56: =SUMIFS(POs[saldo],POs[cve_prod],DIM_BILL[[#This Row],[CODIGO]],POs[status],$GY56,POs[f_ent],HA$1) -> 0 | HB56: =SUMIFS(POs[saldo],POs[cve_prod],DIM_BILL[[#This Row],[CODIGO]],POs[status],$GY56,POs[f_ent],HB$1) -> 0 | HC56: =SUMIFS(POs[saldo],POs[cve_prod],DIM_BILL[[#This Row],[CODIGO]],POs[status],$GY56,POs[f_ent],HC$1) -> 0 | HD56: =SUMIFS(POs[saldo],POs[cve_prod],DIM_BILL[[#This Row],[CODIGO]],POs[status],$GY56,POs[f_ent],HD$1) -> 0 | HE56: =SUMIFS(POs[saldo],POs[cve_prod],DIM_BILL[[#This Row],[CODIGO]],POs[status],$GY56,POs[f_ent],HE$1) -> 0 | HF56: =SUMIFS(POs[saldo],POs[cve_prod],DIM_BILL[[#This Row],[CODIGO]],POs[status],$GY56,POs[Semana],WEEKNUM(HF$1)) -> 0 | HG56: =SUMIFS(POs[saldo],POs[cve_prod],DIM_BILL[[#This Row],[CODIGO]],POs[status],$GY56,POs[Semana],WEEKNUM(HG$1)) -> 0 | HH56: =SUMIFS(POs[saldo],POs[cve_prod],DIM_BILL[[#This Row],[CODIGO]],POs[status],$GY56,POs[Semana],WEEKNUM(HH$1)) -> 0 | HI56: =SUMIFS(POs[saldo],POs[cve_prod],DIM_BILL[[#This Row],[CODIGO]],POs[status],$GY56,POs[Semana],WEEKNUM(HI$1)) -> 0 | HJ56: =SUMIFS(POs[saldo],POs[cve_prod],DIM_BILL[[#This Row],[CODIGO]],POs[status],$GY56,POs[Semana],WEEKNUM(HJ$1)) -> 0 | HK56: =SUMIFS(POs[saldo],POs[cve_prod],DIM_BILL[[#This Row],[CODIGO]],POs[status],$GY56,POs[Semana],WEEKNUM(HK$1)) -> 0 | HL56: =SUMIFS(POs[saldo],POs[cve_prod],DIM_BILL[[#This Row],[CODIGO]],POs[status],$GY56,POs[Semana],WEEKNUM(HL$1)) -> 0 | HM56: =SUMIFS(POs[saldo],POs[cve_prod],DIM_BILL[[#This Row],[CODIGO]],POs[status],$GY56,POs[Semana],WEEKNUM(HM$1)) -> 0 | ... HT56: =SUMIFS(POs[saldo],POs[cve_prod],DIM_BILL[[#This Row],[CODIGO]],POs[status],$GY56,POs[Semana],WEEKNUM(HT$1)) -> 0 | HW56: =DIM_BILL[[#This Row],[Tipo]] -> MATERIAL DE EMPAQUE
A57: MEP-0045 | U57: 0.00369 | GR57: BOBINA ALUMINIO DIALAVIT Cápsulas | GS57: 2 | GT57: COMERCIALIZADORA NEFUR | GU57: MATERIAL DE EMPAQUE | GV57: =SUMIF(FACT_A1[cve_prod],DIM_BILL[[#This Row],[CODIGO]],FACT_A1[Existencia]) -> 0 | GW57: =SUMIF(FACT_A2[cve_prod],DIM_BILL[[#This Row],[CODIGO]],FACT_A2[Existencia]) -> 10.4 | GY57: Demanda | GZ57: =SUMPRODUCT($B57:$GQ57,INDEX(PLAN_PRODUCCION!$B$4:$GQ$24,COLUMN()-COLUMN($GZ$1)+1,0)) -> 18.45 | HA57: =SUMPRODUCT($B57:$GQ57,INDEX(PLAN_PRODUCCION!$B$4:$GQ$24,COLUMN()-COLUMN($GZ$1)+1,0)) -> 0 | HB57: =SUMPRODUCT($B57:$GQ57,INDEX(PLAN_PRODUCCION!$B$4:$GQ$24,COLUMN()-COLUMN($GZ$1)+1,0)) -> 0 | HC57: =SUMPRODUCT($B57:$GQ57,INDEX(PLAN_PRODUCCION!$B$4:$GQ$24,COLUMN()-COLUMN($GZ$1)+1,0)) -> 0 | HD57: =SUMPRODUCT($B57:$GQ57,INDEX(PLAN_PRODUCCION!$B$4:$GQ$24,COLUMN()-COLUMN($GZ$1)+1,0)) -> 0 | HE57: =SUMPRODUCT($B57:$GQ57,INDEX(PLAN_PRODUCCION!$B$4:$GQ$24,COLUMN()-COLUMN($GZ$1)+1,0)) -> 0 | HF57: =SUMPRODUCT($B57:$GQ57,INDEX(PLAN_PRODUCCION!$B$4:$GQ$24,COLUMN()-COLUMN($GZ$1)+1,0)) -> 0 | HG57: =SUMPRODUCT($B57:$GQ57,INDEX(PLAN_PRODUCCION!$B$4:$GQ$24,COLUMN()-COLUMN($GZ$1)+1,0)) -> 0 | ... HT57: =SUMPRODUCT($B57:$GQ57,INDEX(PLAN_PRODUCCION!$B$4:$GQ$24,COLUMN()-COLUMN($GZ$1)+1,0)) -> 0 | HW57: =DIM_BILL[[#This Row],[Tipo]] -> MATERIAL DE EMPAQUE
A58: MEP-0045 | U58: 0.00369 | GR58: BOBINA ALUMINIO DIALAVIT Cápsulas | GS58: 2 | GT58: COMERCIALIZADORA NEFUR | GU58: MATERIAL DE EMPAQUE | GV58: =SUMIF(FACT_A1[cve_prod],DIM_BILL[[#This Row],[CODIGO]],FACT_A1[Existencia]) -> 0 | GW58: =SUMIF(FACT_A2[cve_prod],DIM_BILL[[#This Row],[CODIGO]],FACT_A2[Existencia]) -> 10.4 | GY58: Cortos + PO's Confirmadas | GZ58: =GV58+GW58+GX58+GZ56-GZ57 -> -8.05 | HA58: =GZ58+HA56-HA57 -> -8.05 | HB58: =HA58+HB56-HB57 -> -8.05 | HC58: =HB58+HC56-HC57 -> -8.05 | HD58: =HC58+HD56-HD57 -> -8.05 | HE58: =HD58+HE56-HE57 -> -8.05 | HF58: =HE58+HF56-HF57 -> -8.05 | HG58: =HF58+HG56-HG57 -> -8.05 | HH58: =HG58+HH56-HH57 -> -8.05 | ... HT58: =HS58+HT56-HT57 -> -8.05 | HU58: =COUNTIF(GZ58:HT58,"<0") -> 21 | HW58: =DIM_BILL[[#This Row],[Tipo]] -> MATERIAL DE EMPAQUE
A59: MEP-0059 | BJ59: 1 | GR59: FRASCO PET 250 mL R24/410 BLANCO | GS59: 2 | GT59: XIOMARA GONZALEZ LOPEZ | GU59: MATERIAL DE EMPAQUE | GV59: =SUMIF(FACT_A1[cve_prod],DIM_BILL[[#This Row],[CODIGO]],FACT_A1[Existencia]) -> 0 | GW59: =SUMIF(FACT_A2[cve_prod],DIM_BILL[[#This Row],[CODIGO]],FACT_A2[Existencia]) -> 3200 | GY59: Por Surtir & Parcial | GZ59: =SUMIFS(POs[saldo],POs[cve_prod],DIM_BILL[[#This Row],[CODIGO]],POs[status],$GY59,POs[f_ent],GZ$1) -> 0 | HA59: =SUMIFS(POs[saldo],POs[cve_prod],DIM_BILL[[#This Row],[CODIGO]],POs[status],$GY59,POs[f_ent],HA$1) -> 0 | HB59: =SUMIFS(POs[saldo],POs[cve_prod],DIM_BILL[[#This Row],[CODIGO]],POs[status],$GY59,POs[f_ent],HB$1) -> 0 | HC59: =SUMIFS(POs[saldo],POs[cve_prod],DIM_BILL[[#This Row],[CODIGO]],POs[status],$GY59,POs[f_ent],HC$1) -> 0 | HD59: =SUMIFS(POs[saldo],POs[cve_prod],DIM_BILL[[#This Row],[CODIGO]],POs[status],$GY59,POs[f_ent],HD$1) -> 0 | HE59: =SUMIFS(POs[saldo],POs[cve_prod],DIM_BILL[[#This Row],[CODIGO]],POs[status],$GY59,POs[f_ent],HE$1) -> 0 | HF59: =SUMIFS(POs[saldo],POs[cve_prod],DIM_BILL[[#This Row],[CODIGO]],POs[status],$GY59,POs[Semana],WEEKNUM(HF$1)) -> 0 | HG59: =SUMIFS(POs[saldo],POs[cve_prod],DIM_BILL[[#This Row],[CODIGO]],POs[status],$GY59,POs[Semana],WEEKNUM(HG$1)) -> 0 | HH59: =SUMIFS(POs[saldo],POs[cve_prod],DIM_BILL[[#This Row],[CODIGO]],POs[status],$GY59,POs[Semana],WEEKNUM(HH$1)) -> 0 | HI59: =SUMIFS(POs[saldo],POs[cve_prod],DIM_BILL[[#This Row],[CODIGO]],POs[status],$GY59,POs[Semana],WEEKNUM(HI$1)) -> 0 | HJ59: =SUMIFS(POs[saldo],POs[cve_prod],DIM_BILL[[#This Row],[CODIGO]],POs[status],$GY59,POs[Semana],WEEKNUM(HJ$1)) -> 0 | HK59: =SUMIFS(POs[saldo],POs[cve_prod],DIM_BILL[[#This Row],[CODIGO]],POs[status],$GY59,POs[Semana],WEEKNUM(HK$1)) -> 0 | HL59: =SUMIFS(POs[saldo],POs[cve_prod],DIM_BILL[[#This Row],[CODIGO]],POs[status],$GY59,POs[Semana],WEEKNUM(HL$1)) -> 0 | HM59: =SUMIFS(POs[saldo],POs[cve_prod],DIM_BILL[[#This Row],[CODIGO]],POs[status],$GY59,POs[Semana],WEEKNUM(HM$1)) -> 0 | ... HT59: =SUMIFS(POs[saldo],POs[cve_prod],DIM_BILL[[#This Row],[CODIGO]],POs[status],$GY59,POs[Semana],WEEKNUM(HT$1)) -> 0 | HW59: =DIM_BILL[[#This Row],[Tipo]] -> MATERIAL DE EMPAQUE
A60: MEP-0059 | BJ60: 1 | GR60: FRASCO PET 250 mL R24/410 BLANCO | GS60: 2 | GT60: XIOMARA GONZALEZ LOPEZ | GU60: MATERIAL DE EMPAQUE | GV60: =SUMIF(FACT_A1[cve_prod],DIM_BILL[[#This Row],[CODIGO]],FACT_A1[Existencia]) -> 0 | GW60: =SUMIF(FACT_A2[cve_prod],DIM_BILL[[#This Row],[CODIGO]],FACT_A2[Existencia]) -> 3200 | GY60: Demanda | GZ60: =SUMPRODUCT($B60:$GQ60,INDEX(PLAN_PRODUCCION!$B$4:$GQ$24,COLUMN()-COLUMN($GZ$1)+1,0)) -> 2000 | HA60: =SUMPRODUCT($B60:$GQ60,INDEX(PLAN_PRODUCCION!$B$4:$GQ$24,COLUMN()-COLUMN($GZ$1)+1,0)) -> 0 | HB60: =SUMPRODUCT($B60:$GQ60,INDEX(PLAN_PRODUCCION!$B$4:$GQ$24,COLUMN()-COLUMN($GZ$1)+1,0)) -> 0 | HC60: =SUMPRODUCT($B60:$GQ60,INDEX(PLAN_PRODUCCION!$B$4:$GQ$24,COLUMN()-COLUMN($GZ$1)+1,0)) -> 0 | HD60: =SUMPRODUCT($B60:$GQ60,INDEX(PLAN_PRODUCCION!$B$4:$GQ$24,COLUMN()-COLUMN($GZ$1)+1,0)) -> 0 | HE60: =SUMPRODUCT($B60:$GQ60,INDEX(PLAN_PRODUCCION!$B$4:$GQ$24,COLUMN()-COLUMN($GZ$1)+1,0)) -> 0 | HF60: =SUMPRODUCT($B60:$GQ60,INDEX(PLAN_PRODUCCION!$B$4:$GQ$24,COLUMN()-COLUMN($GZ$1)+1,0)) -> 0 | HG60: =SUMPRODUCT($B60:$GQ60,INDEX(PLAN_PRODUCCION!$B$4:$GQ$24,COLUMN()-COLUMN($GZ$1)+1,0)) -> 0 | ... HT60: =SUMPRODUCT($B60:$GQ60,INDEX(PLAN_PRODUCCION!$B$4:$GQ$24,COLUMN()-COLUMN($GZ$1)+1,0)) -> 0 | HW60: =DIM_BILL[[#This Row],[Tipo]] -> MATERIAL DE EMPAQUE
A61: MEP-0059 | BJ61: 1 | GR61: FRASCO PET 250 mL R24/410 BLANCO | GS61: 2 | GT61: XIOMARA GONZALEZ LOPEZ | GU61: MATERIAL DE EMPAQUE | GV61: =SUMIF(FACT_A1[cve_prod],DIM_BILL[[#This Row],[CODIGO]],FACT_A1[Existencia]) -> 0 | GW61: =SUMIF(FACT_A2[cve_prod],DIM_BILL[[#This Row],[CODIGO]],FACT_A2[Existencia]) -> 3200 | GY61: Cortos + PO's Confirmadas | GZ61: =GV61+GW61+GX61+GZ59-GZ60 -> 1200 | HA61: =GZ61+HA59-HA60 -> 1200 | HB61: =HA61+HB59-HB60 -> 1200 | HC61: =HB61+HC59-HC60 -> 1200 | HD61: =HC61+HD59-HD60 -> 1200 | HE61: =HD61+HE59-HE60 -> 1200 | HF61: =HE61+HF59-HF60 -> 1200 | HG61: =HF61+HG59-HG60 -> 1200 | HH61: =HG61+HH59-HH60 -> 1200 | ... HT61: =HS61+HT59-HT60 -> 1200 | HU61: =COUNTIF(GZ61:HT61,"<0") -> 0 | HW61: =DIM_BILL[[#This Row],[Tipo]] -> MATERIAL DE EMPAQUE
A62: MEP-0060 | F62: 99.473684 | G62: 31.4 | H62: 37.8 | I62: 30 | J62: 60 | M62: 60 | U62: 30 | AE62: 34 | AF62: 2 | AH62: 60 | AI62: 30 | AL62: 500 | AT62: 34.285714 | GR62: CAPSULA #00 ESCARLATA / ESCARLATA | GS62: 6 | GT62: CAPSUTEC DE MEXICO SA DE CV | GU62: MATERIAL DE EMPAQUE | GV62: =SUMIF(FACT_A1[cve_prod],DIM_BILL[[#This Row],[CODIGO]],FACT_A1[Existencia]) -> 0 | GW62: =SUMIF(FACT_A2[cve_prod],DIM_BILL[[#This Row],[CODIGO]],FACT_A2[Existencia]) -> 240000 | GY62: Por Surtir & Parcial | GZ62: =SUMIFS(POs[saldo],POs[cve_prod],DIM_BILL[[#This Row],[CODIGO]],POs[status],$GY62,POs[f_ent],GZ$1) -> 0 | HA62: =SUMIFS(POs[saldo],POs[cve_prod],DIM_BILL[[#This Row],[CODIGO]],POs[status],$GY62,POs[f_ent],HA$1) -> 0 | HB62: =SUMIFS(POs[saldo],POs[cve_prod],DIM_BILL[[#This Row],[CODIGO]],POs[status],$GY62,POs[f_ent],HB$1) -> 0 | HC62: =SUMIFS(POs[saldo],POs[cve_prod],DIM_BILL[[#This Row],[CODIGO]],POs[status],$GY62,POs[f_ent],HC$1) -> 0 | HD62: =SUMIFS(POs[saldo],POs[cve_prod],DIM_BILL[[#This Row],[CODIGO]],POs[status],$GY62,POs[f_ent],HD$1) -> 0 | HE62: =SUMIFS(POs[saldo],POs[cve_prod],DIM_BILL[[#This Row],[CODIGO]],POs[status],$GY62,POs[f_ent],HE$1) -> 0 | HF62: =SUMIFS(POs[saldo],POs[cve_prod],DIM_BILL[[#This Row],[CODIGO]],POs[status],$GY62,POs[Semana],WEEKNUM(HF$1)) -> 0 | HG62: =SUMIFS(POs[saldo],POs[cve_prod],DIM_BILL[[#This Row],[CODIGO]],POs[status],$GY62,POs[Semana],WEEKNUM(HG$1)) -> 0 | HH62: =SUMIFS(POs[saldo],POs[cve_prod],DIM_BILL[[#This Row],[CODIGO]],POs[status],$GY62,POs[Semana],WEEKNUM(HH$1)) -> 0 | HI62: =SUMIFS(POs[saldo],POs[cve_prod],DIM_BILL[[#This Row],[CODIGO]],POs[status],$GY62,POs[Semana],WEEKNUM(HI$1)) -> 0 | HJ62: =SUMIFS(POs[saldo],POs[cve_prod],DIM_BILL[[#This Row],[CODIGO]],POs[status],$GY62,POs[Semana],WEEKNUM(HJ$1)) -> 0 | HK62: =SUMIFS(POs[saldo],POs[cve_prod],DIM_BILL[[#This Row],[CODIGO]],POs[status],$GY62,POs[Semana],WEEKNUM(HK$1)) -> 0 | HL62: =SUMIFS(POs[saldo],POs[cve_prod],DIM_BILL[[#This Row],[CODIGO]],POs[status],$GY62,POs[Semana],WEEKNUM(HL$1)) -> 0 | HM62: =SUMIFS(POs[saldo],POs[cve_prod],DIM_BILL[[#This Row],[CODIGO]],POs[status],$GY62,POs[Semana],WEEKNUM(HM$1)) -> 0 | ... HT62: =SUMIFS(POs[saldo],POs[cve_prod],DIM_BILL[[#This Row],[CODIGO]],POs[status],$GY62,POs[Semana],WEEKNUM(HT$1)) -> 0 | HW62: =DIM_BILL[[#This Row],[Tipo]] -> MATERIAL DE EMPAQUE
A63: MEP-0060 | F63: 99.473684 | G63: 31.4 | H63: 37.8 | I63: 30 | J63: 60 | M63: 60 | U63: 30 | AE63: 34 | AF63: 2 | AH63: 60 | AI63: 30 | AL63: 500 | AT63: 34.285714 | GR63: CAPSULA #00 ESCARLATA / ESCARLATA | GS63: 6 | GT63: CAPSUTEC DE MEXICO SA DE CV | GU63: MATERIAL DE EMPAQUE | GV63: =SUMIF(FACT_A1[cve_prod],DIM_BILL[[#This Row],[CODIGO]],FACT_A1[Existencia]) -> 0 | GW63: =SUMIF(FACT_A2[cve_prod],DIM_BILL[[#This Row],[CODIGO]],FACT_A2[Existencia]) -> 240000 | GY63: Demanda | GZ63: =SUMPRODUCT($B63:$GQ63,INDEX(PLAN_PRODUCCION!$B$4:$GQ$24,COLUMN()-COLUMN($GZ$1)+1,0)) -> 2296000 | HA63: =SUMPRODUCT($B63:$GQ63,INDEX(PLAN_PRODUCCION!$B$4:$GQ$24,COLUMN()-COLUMN($GZ$1)+1,0)) -> 0 | HB63: =SUMPRODUCT($B63:$GQ63,INDEX(PLAN_PRODUCCION!$B$4:$GQ$24,COLUMN()-COLUMN($GZ$1)+1,0)) -> 0 | HC63: =SUMPRODUCT($B63:$GQ63,INDEX(PLAN_PRODUCCION!$B$4:$GQ$24,COLUMN()-COLUMN($GZ$1)+1,0)) -> 0 | HD63: =SUMPRODUCT($B63:$GQ63,INDEX(PLAN_PRODUCCION!$B$4:$GQ$24,COLUMN()-COLUMN($GZ$1)+1,0)) -> 0 | HE63: =SUMPRODUCT($B63:$GQ63,INDEX(PLAN_PRODUCCION!$B$4:$GQ$24,COLUMN()-COLUMN($GZ$1)+1,0)) -> 0 | HF63: =SUMPRODUCT($B63:$GQ63,INDEX(PLAN_PRODUCCION!$B$4:$GQ$24,COLUMN()-COLUMN($GZ$1)+1,0)) -> 0 | HG63: =SUMPRODUCT($B63:$GQ63,INDEX(PLAN_PRODUCCION!$B$4:$GQ$24,COLUMN()-COLUMN($GZ$1)+1,0)) -> 0 | ... HT63: =SUMPRODUCT($B63:$GQ63,INDEX(PLAN_PRODUCCION!$B$4:$GQ$24,COLUMN()-COLUMN($GZ$1)+1,0)) -> 0 | HW63: =DIM_BILL[[#This Row],[Tipo]] -> MATERIAL DE EMPAQUE
A64: MEP-0060 | F64: 99.473684 | G64: 31.4 | H64: 37.8 | I64: 30 | J64: 60 | M64: 60 | U64: 30 | AE64: 34 | AF64: 2 | AH64: 60 | AI64: 30 | AL64: 500 | AT64: 34.285714 | GR64: CAPSULA #00 ESCARLATA / ESCARLATA | GS64: 6 | GT64: CAPSUTEC DE MEXICO SA DE CV | GU64: MATERIAL DE EMPAQUE | GV64: =SUMIF(FACT_A1[cve_prod],DIM_BILL[[#This Row],[CODIGO]],FACT_A1[Existencia]) -> 0 | GW64: =SUMIF(FACT_A2[cve_prod],DIM_BILL[[#This Row],[CODIGO]],FACT_A2[Existencia]) -> 240000 | GY64: Cortos + PO's Confirmadas | GZ64: =GV64+GW64+GX64+GZ62-GZ63 -> -2056000 | HA64: =GZ64+HA62-HA63 -> -2056000 | HB64: =HA64+HB62-HB63 -> -2056000 | HC64: =HB64+HC62-HC63 -> -2056000 | HD64: =HC64+HD62-HD63 -> -2056000 | HE64: =HD64+HE62-HE63 -> -2056000 | HF64: =HE64+HF62-HF63 -> -2056000 | HG64: =HF64+HG62-HG63 -> -2056000 | HH64: =HG64+HH62-HH63 -> -2056000 | ... HT64: =HS64+HT62-HT63 -> -2056000 | HU64: =COUNTIF(GZ64:HT64,"<0") -> 21 | HW64: =DIM_BILL[[#This Row],[Tipo]] -> MATERIAL DE EMPAQUE
A65: MEP-0061 | O65: 60 | S65: 31.5 | T65: 63 | AK65: 1050 | AW65: 36.05 | AX65: 14.42 | AZ65: 30 | BE65: 240 | GH65: 30.6 | GI65: 45.897705 | GR65: CAPSULA # 0 NATURAL/ NATURAL | GS65: 6 | GT65: CAPSUTEC DE MEXICO SA DE CV | GU65: MATERIAL DE EMPAQUE | GV65: =SUMIF(FACT_A1[cve_prod],DIM_BILL[[#This Row],[CODIGO]],FACT_A1[Existencia]) -> 894000 | GW65: =SUMIF(FACT_A2[cve_prod],DIM_BILL[[#This Row],[CODIGO]],FACT_A2[Existencia]) -> 0 | GY65: Por Surtir & Parcial | GZ65: =SUMIFS(POs[saldo],POs[cve_prod],DIM_BILL[[#This Row],[CODIGO]],POs[status],$GY65,POs[f_ent],GZ$1) -> 0 | HA65: =SUMIFS(POs[saldo],POs[cve_prod],DIM_BILL[[#This Row],[CODIGO]],POs[status],$GY65,POs[f_ent],HA$1) -> 0 | HB65: =SUMIFS(POs[saldo],POs[cve_prod],DIM_BILL[[#This Row],[CODIGO]],POs[status],$GY65,POs[f_ent],HB$1) -> 0 | HC65: =SUMIFS(POs[saldo],POs[cve_prod],DIM_BILL[[#This Row],[CODIGO]],POs[status],$GY65,POs[f_ent],HC$1) -> 0 | HD65: =SUMIFS(POs[saldo],POs[cve_prod],DIM_BILL[[#This Row],[CODIGO]],POs[status],$GY65,POs[f_ent],HD$1) -> 0 | HE65: =SUMIFS(POs[saldo],POs[cve_prod],DIM_BILL[[#This Row],[CODIGO]],POs[status],$GY65,POs[f_ent],HE$1) -> 0 | HF65: =SUMIFS(POs[saldo],POs[cve_prod],DIM_BILL[[#This Row],[CODIGO]],POs[status],$GY65,POs[Semana],WEEKNUM(HF$1)) -> 0 | HG65: =SUMIFS(POs[saldo],POs[cve_prod],DIM_BILL[[#This Row],[CODIGO]],POs[status],$GY65,POs[Semana],WEEKNUM(HG$1)) -> 0 | HH65: =SUMIFS(POs[saldo],POs[cve_prod],DIM_BILL[[#This Row],[CODIGO]],POs[status],$GY65,POs[Semana],WEEKNUM(HH$1)) -> 0 | HI65: =SUMIFS(POs[saldo],POs[cve_prod],DIM_BILL[[#This Row],[CODIGO]],POs[status],$GY65,POs[Semana],WEEKNUM(HI$1)) -> 0 | HJ65: =SUMIFS(POs[saldo],POs[cve_prod],DIM_BILL[[#This Row],[CODIGO]],POs[status],$GY65,POs[Semana],WEEKNUM(HJ$1)) -> 0 | HK65: =SUMIFS(POs[saldo],POs[cve_prod],DIM_BILL[[#This Row],[CODIGO]],POs[status],$GY65,POs[Semana],WEEKNUM(HK$1)) -> 0 | HL65: =SUMIFS(POs[saldo],POs[cve_prod],DIM_BILL[[#This Row],[CODIGO]],POs[status],$GY65,POs[Semana],WEEKNUM(HL$1)) -> 0 | HM65: =SUMIFS(POs[saldo],POs[cve_prod],DIM_BILL[[#This Row],[CODIGO]],POs[status],$GY65,POs[Semana],WEEKNUM(HM$1)) -> 0 | ... HT65: =SUMIFS(POs[saldo],POs[cve_prod],DIM_BILL[[#This Row],[CODIGO]],POs[status],$GY65,POs[Semana],WEEKNUM(HT$1)) -> 0 | HW65: =DIM_BILL[[#This Row],[Tipo]] -> MATERIAL DE EMPAQUE
A66: MEP-0061 | O66: 60 | S66: 31.5 | T66: 63 | AK66: 1050 | AW66: 36.05 | AX66: 14.42 | AZ66: 30 | BE66: 240 | GH66: 30.6 | GI66: 45.897705 | GR66: CAPSULA # 0 NATURAL/ NATURAL | GS66: 6 | GT66: CAPSUTEC DE MEXICO SA DE CV | GU66: MATERIAL DE EMPAQUE | GV66: =SUMIF(FACT_A1[cve_prod],DIM_BILL[[#This Row],[CODIGO]],FACT_A1[Existencia]) -> 894000 | GW66: =SUMIF(FACT_A2[cve_prod],DIM_BILL[[#This Row],[CODIGO]],FACT_A2[Existencia]) -> 0 | GY66: Demanda | GZ66: =SUMPRODUCT($B66:$GQ66,INDEX(PLAN_PRODUCCION!$B$4:$GQ$24,COLUMN()-COLUMN($GZ$1)+1,0)) -> 3808729.5 | HA66: =SUMPRODUCT($B66:$GQ66,INDEX(PLAN_PRODUCCION!$B$4:$GQ$24,COLUMN()-COLUMN($GZ$1)+1,0)) -> 0 | HB66: =SUMPRODUCT($B66:$GQ66,INDEX(PLAN_PRODUCCION!$B$4:$GQ$24,COLUMN()-COLUMN($GZ$1)+1,0)) -> 0 | HC66: =SUMPRODUCT($B66:$GQ66,INDEX(PLAN_PRODUCCION!$B$4:$GQ$24,COLUMN()-COLUMN($GZ$1)+1,0)) -> 0 | HD66: =SUMPRODUCT($B66:$GQ66,INDEX(PLAN_PRODUCCION!$B$4:$GQ$24,COLUMN()-COLUMN($GZ$1)+1,0)) -> 0 | HE66: =SUMPRODUCT($B66:$GQ66,INDEX(PLAN_PRODUCCION!$B$4:$GQ$24,COLUMN()-COLUMN($GZ$1)+1,0)) -> 0 | HF66: =SUMPRODUCT($B66:$GQ66,INDEX(PLAN_PRODUCCION!$B$4:$GQ$24,COLUMN()-COLUMN($GZ$1)+1,0)) -> 0 | HG66: =SUMPRODUCT($B66:$GQ66,INDEX(PLAN_PRODUCCION!$B$4:$GQ$24,COLUMN()-COLUMN($GZ$1)+1,0)) -> 630000 | ... HT66: =SUMPRODUCT($B66:$GQ66,INDEX(PLAN_PRODUCCION!$B$4:$GQ$24,COLUMN()-COLUMN($GZ$1)+1,0)) -> 0 | HW66: =DIM_BILL[[#This Row],[Tipo]] -> MATERIAL DE EMPAQUE
A67: MEP-0061 | O67: 60 | S67: 31.5 | T67: 63 | AK67: 1050 | AW67: 36.05 | AX67: 14.42 | AZ67: 30 | BE67: 240 | GH67: 30.6 | GI67: 45.897705 | GR67: CAPSULA # 0 NATURAL/ NATURAL | GS67: 6 | GT67: CAPSUTEC DE MEXICO SA DE CV | GU67: MATERIAL DE EMPAQUE | GV67: =SUMIF(FACT_A1[cve_prod],DIM_BILL[[#This Row],[CODIGO]],FACT_A1[Existencia]) -> 894000 | GW67: =SUMIF(FACT_A2[cve_prod],DIM_BILL[[#This Row],[CODIGO]],FACT_A2[Existencia]) -> 0 | GY67: Cortos + PO's Confirmadas | GZ67: =GV67+GW67+GX67+GZ65-GZ66 -> -2914729.5 | HA67: =GZ67+HA65-HA66 -> -2914729.5 | HB67: =HA67+HB65-HB66 -> -2914729.5 | HC67: =HB67+HC65-HC66 -> -2914729.5 | HD67: =HC67+HD65-HD66 -> -2914729.5 | HE67: =HD67+HE65-HE66 -> -2914729.5 | HF67: =HE67+HF65-HF66 -> -2914729.5 | HG67: =HF67+HG65-HG66 -> -3544729.5 | HH67: =HG67+HH65-HH66 -> -3544729.5 | ... HT67: =HS67+HT65-HT66 -> -3544729.5 | HU67: =COUNTIF(GZ67:HT67,"<0") -> 21 | HW67: =DIM_BILL[[#This Row],[Tipo]] -> MATERIAL DE EMPAQUE
A68: MEP-0065 | P68: 30.6 | Q68: 2.04 | GR68: CAPSULA ENTERICA "0" Blan/Blan | GS68: 1 | GT68: CAPSUTEC DE MEXICO SA DE CV | GU68: MATERIAL DE EMPAQUE | GV68: =SUMIF(FACT_A1[cve_prod],DIM_BILL[[#This Row],[CODIGO]],FACT_A1[Existencia]) -> 0 | GW68: =SUMIF(FACT_A2[cve_prod],DIM_BILL[[#This Row],[CODIGO]],FACT_A2[Existencia]) -> 0 | GY68: Por Surtir & Parcial | GZ68: =SUMIFS(POs[saldo],POs[cve_prod],DIM_BILL[[#This Row],[CODIGO]],POs[status],$GY68,POs[f_ent],GZ$1) -> 0 | HA68: =SUMIFS(POs[saldo],POs[cve_prod],DIM_BILL[[#This Row],[CODIGO]],POs[status],$GY68,POs[f_ent],HA$1) -> 0 | HB68: =SUMIFS(POs[saldo],POs[cve_prod],DIM_BILL[[#This Row],[CODIGO]],POs[status],$GY68,POs[f_ent],HB$1) -> 0 | HC68: =SUMIFS(POs[saldo],POs[cve_prod],DIM_BILL[[#This Row],[CODIGO]],POs[status],$GY68,POs[f_ent],HC$1) -> 0 | HD68: =SUMIFS(POs[saldo],POs[cve_prod],DIM_BILL[[#This Row],[CODIGO]],POs[status],$GY68,POs[f_ent],HD$1) -> 0 | HE68: =SUMIFS(POs[saldo],POs[cve_prod],DIM_BILL[[#This Row],[CODIGO]],POs[status],$GY68,POs[f_ent],HE$1) -> 0 | HF68: =SUMIFS(POs[saldo],POs[cve_prod],DIM_BILL[[#This Row],[CODIGO]],POs[status],$GY68,POs[Semana],WEEKNUM(HF$1)) -> 0 | HG68: =SUMIFS(POs[saldo],POs[cve_prod],DIM_BILL[[#This Row],[CODIGO]],POs[status],$GY68,POs[Semana],WEEKNUM(HG$1)) -> 0 | HH68: =SUMIFS(POs[saldo],POs[cve_prod],DIM_BILL[[#This Row],[CODIGO]],POs[status],$GY68,POs[Semana],WEEKNUM(HH$1)) -> 0 | HI68: =SUMIFS(POs[saldo],POs[cve_prod],DIM_BILL[[#This Row],[CODIGO]],POs[status],$GY68,POs[Semana],WEEKNUM(HI$1)) -> 0 | HJ68: =SUMIFS(POs[saldo],POs[cve_prod],DIM_BILL[[#This Row],[CODIGO]],POs[status],$GY68,POs[Semana],WEEKNUM(HJ$1)) -> 0 | HK68: =SUMIFS(POs[saldo],POs[cve_prod],DIM_BILL[[#This Row],[CODIGO]],POs[status],$GY68,POs[Semana],WEEKNUM(HK$1)) -> 0 | HL68: =SUMIFS(POs[saldo],POs[cve_prod],DIM_BILL[[#This Row],[CODIGO]],POs[status],$GY68,POs[Semana],WEEKNUM(HL$1)) -> 0 | HM68: =SUMIFS(POs[saldo],POs[cve_prod],DIM_BILL[[#This Row],[CODIGO]],POs[status],$GY68,POs[Semana],WEEKNUM(HM$1)) -> 0 | ... HT68: =SUMIFS(POs[saldo],POs[cve_prod],DIM_BILL[[#This Row],[CODIGO]],POs[status],$GY68,POs[Semana],WEEKNUM(HT$1)) -> 0 | HW68: =DIM_BILL[[#This Row],[Tipo]] -> MATERIAL DE EMPAQUE
A69: MEP-0065 | P69: 30.6 | Q69: 2.04 | GR69: CAPSULA ENTERICA "0" Blan/Blan | GS69: 1 | GT69: CAPSUTEC DE MEXICO SA DE CV | GU69: MATERIAL DE EMPAQUE | GV69: =SUMIF(FACT_A1[cve_prod],DIM_BILL[[#This Row],[CODIGO]],FACT_A1[Existencia]) -> 0 | GW69: =SUMIF(FACT_A2[cve_prod],DIM_BILL[[#This Row],[CODIGO]],FACT_A2[Existencia]) -> 0 | GY69: Demanda | GZ69: =SUMPRODUCT($B69:$GQ69,INDEX(PLAN_PRODUCCION!$B$4:$GQ$24,COLUMN()-COLUMN($GZ$1)+1,0)) -> 0 | HA69: =SUMPRODUCT($B69:$GQ69,INDEX(PLAN_PRODUCCION!$B$4:$GQ$24,COLUMN()-COLUMN($GZ$1)+1,0)) -> 0 | HB69: =SUMPRODUCT($B69:$GQ69,INDEX(PLAN_PRODUCCION!$B$4:$GQ$24,COLUMN()-COLUMN($GZ$1)+1,0)) -> 0 | HC69: =SUMPRODUCT($B69:$GQ69,INDEX(PLAN_PRODUCCION!$B$4:$GQ$24,COLUMN()-COLUMN($GZ$1)+1,0)) -> 0 | HD69: =SUMPRODUCT($B69:$GQ69,INDEX(PLAN_PRODUCCION!$B$4:$GQ$24,COLUMN()-COLUMN($GZ$1)+1,0)) -> 0 | HE69: =SUMPRODUCT($B69:$GQ69,INDEX(PLAN_PRODUCCION!$B$4:$GQ$24,COLUMN()-COLUMN($GZ$1)+1,0)) -> 0 | HF69: =SUMPRODUCT($B69:$GQ69,INDEX(PLAN_PRODUCCION!$B$4:$GQ$24,COLUMN()-COLUMN($GZ$1)+1,0)) -> 0 | HG69: =SUMPRODUCT($B69:$GQ69,INDEX(PLAN_PRODUCCION!$B$4:$GQ$24,COLUMN()-COLUMN($GZ$1)+1,0)) -> 0 | ... HT69: =SUMPRODUCT($B69:$GQ69,INDEX(PLAN_PRODUCCION!$B$4:$GQ$24,COLUMN()-COLUMN($GZ$1)+1,0)) -> 0 | HW69: =DIM_BILL[[#This Row],[Tipo]] -> MATERIAL DE EMPAQUE
A70: MEP-0065 | P70: 30.6 | Q70: 2.04 | GR70: CAPSULA ENTERICA "0" Blan/Blan | GS70: 1 | GT70: CAPSUTEC DE MEXICO SA DE CV | GU70: MATERIAL DE EMPAQUE | GV70: =SUMIF(FACT_A1[cve_prod],DIM_BILL[[#This Row],[CODIGO]],FACT_A1[Existencia]) -> 0 | GW70: =SUMIF(FACT_A2[cve_prod],DIM_BILL[[#This Row],[CODIGO]],FACT_A2[Existencia]) -> 0 | GY70: Cortos + PO's Confirmadas | GZ70: =GV70+GW70+GX70+GZ68-GZ69 -> 0 | HA70: =GZ70+HA68-HA69 -> 0 | HB70: =HA70+HB68-HB69 -> 0 | HC70: =HB70+HC68-HC69 -> 0 | HD70: =HC70+HD68-HD69 -> 0 | HE70: =HD70+HE68-HE69 -> 0 | HF70: =HE70+HF68-HF69 -> 0 | HG70: =HF70+HG68-HG69 -> 0 | HH70: =HG70+HH68-HH69 -> 0 | ... HT70: =HS70+HT68-HT69 -> 0 | HU70: =COUNTIF(GZ70:HT70,"<0") -> 0 | HW70: =DIM_BILL[[#This Row],[Tipo]] -> MATERIAL DE EMPAQUE
A71: MEP-0069 | BL71: 0.082505882 | GR71: Petpolifoil MB 300 ABLAZOR p.t. | GS71: 8 | GT71: BEMIS PACKAGING MÉXICO SA DE CV | GU71: MATERIAL DE EMPAQUE | GV71: =SUMIF(FACT_A1[cve_prod],DIM_BILL[[#This Row],[CODIGO]],FACT_A1[Existencia]) -> 1907.61 | GW71: =SUMIF(FACT_A2[cve_prod],DIM_BILL[[#This Row],[CODIGO]],FACT_A2[Existencia]) -> 305.96 | GY71: Por Surtir & Parcial | GZ71: =SUMIFS(POs[saldo],POs[cve_prod],DIM_BILL[[#This Row],[CODIGO]],POs[status],$GY71,POs[f_ent],GZ$1) -> 0 | HA71: =SUMIFS(POs[saldo],POs[cve_prod],DIM_BILL[[#This Row],[CODIGO]],POs[status],$GY71,POs[f_ent],HA$1) -> 0 | HB71: =SUMIFS(POs[saldo],POs[cve_prod],DIM_BILL[[#This Row],[CODIGO]],POs[status],$GY71,POs[f_ent],HB$1) -> 0 | HC71: =SUMIFS(POs[saldo],POs[cve_prod],DIM_BILL[[#This Row],[CODIGO]],POs[status],$GY71,POs[f_ent],HC$1) -> 0 | HD71: =SUMIFS(POs[saldo],POs[cve_prod],DIM_BILL[[#This Row],[CODIGO]],POs[status],$GY71,POs[f_ent],HD$1) -> 0 | HE71: =SUMIFS(POs[saldo],POs[cve_prod],DIM_BILL[[#This Row],[CODIGO]],POs[status],$GY71,POs[f_ent],HE$1) -> 0 | HF71: =SUMIFS(POs[saldo],POs[cve_prod],DIM_BILL[[#This Row],[CODIGO]],POs[status],$GY71,POs[Semana],WEEKNUM(HF$1)) -> 0 | HG71: =SUMIFS(POs[saldo],POs[cve_prod],DIM_BILL[[#This Row],[CODIGO]],POs[status],$GY71,POs[Semana],WEEKNUM(HG$1)) -> 0 | HH71: =SUMIFS(POs[saldo],POs[cve_prod],DIM_BILL[[#This Row],[CODIGO]],POs[status],$GY71,POs[Semana],WEEKNUM(HH$1)) -> 0 | HI71: =SUMIFS(POs[saldo],POs[cve_prod],DIM_BILL[[#This Row],[CODIGO]],POs[status],$GY71,POs[Semana],WEEKNUM(HI$1)) -> 0 | HJ71: =SUMIFS(POs[saldo],POs[cve_prod],DIM_BILL[[#This Row],[CODIGO]],POs[status],$GY71,POs[Semana],WEEKNUM(HJ$1)) -> 0 | HK71: =SUMIFS(POs[saldo],POs[cve_prod],DIM_BILL[[#This Row],[CODIGO]],POs[status],$GY71,POs[Semana],WEEKNUM(HK$1)) -> 0 | HL71: =SUMIFS(POs[saldo],POs[cve_prod],DIM_BILL[[#This Row],[CODIGO]],POs[status],$GY71,POs[Semana],WEEKNUM(HL$1)) -> 0 | HM71: =SUMIFS(POs[saldo],POs[cve_prod],DIM_BILL[[#This Row],[CODIGO]],POs[status],$GY71,POs[Semana],WEEKNUM(HM$1)) -> 0 | ... HT71: =SUMIFS(POs[saldo],POs[cve_prod],DIM_BILL[[#This Row],[CODIGO]],POs[status],$GY71,POs[Semana],WEEKNUM(HT$1)) -> 0 | HW71: =DIM_BILL[[#This Row],[Tipo]] -> MATERIAL DE EMPAQUE
A72: MEP-0069 | BL72: 0.082505882 | GR72: Petpolifoil MB 300 ABLAZOR p.t. | GS72: 8 | GT72: BEMIS PACKAGING MÉXICO SA DE CV | GU72: MATERIAL DE EMPAQUE | GV72: =SUMIF(FACT_A1[cve_prod],DIM_BILL[[#This Row],[CODIGO]],FACT_A1[Existencia]) -> 1907.61 | GW72: =SUMIF(FACT_A2[cve_prod],DIM_BILL[[#This Row],[CODIGO]],FACT_A2[Existencia]) -> 305.96 | GY72: Demanda | GZ72: =SUMPRODUCT($B72:$GQ72,INDEX(PLAN_PRODUCCION!$B$4:$GQ$24,COLUMN()-COLUMN($GZ$1)+1,0)) -> 475.4814 | HA72: =SUMPRODUCT($B72:$GQ72,INDEX(PLAN_PRODUCCION!$B$4:$GQ$24,COLUMN()-COLUMN($GZ$1)+1,0)) -> 0 | HB72: =SUMPRODUCT($B72:$GQ72,INDEX(PLAN_PRODUCCION!$B$4:$GQ$24,COLUMN()-COLUMN($GZ$1)+1,0)) -> 0 | HC72: =SUMPRODUCT($B72:$GQ72,INDEX(PLAN_PRODUCCION!$B$4:$GQ$24,COLUMN()-COLUMN($GZ$1)+1,0)) -> 0 | HD72: =SUMPRODUCT($B72:$GQ72,INDEX(PLAN_PRODUCCION!$B$4:$GQ$24,COLUMN()-COLUMN($GZ$1)+1,0)) -> 0 | HE72: =SUMPRODUCT($B72:$GQ72,INDEX(PLAN_PRODUCCION!$B$4:$GQ$24,COLUMN()-COLUMN($GZ$1)+1,0)) -> 0 | HF72: =SUMPRODUCT($B72:$GQ72,INDEX(PLAN_PRODUCCION!$B$4:$GQ$24,COLUMN()-COLUMN($GZ$1)+1,0)) -> 561.04 | HG72: =SUMPRODUCT($B72:$GQ72,INDEX(PLAN_PRODUCCION!$B$4:$GQ$24,COLUMN()-COLUMN($GZ$1)+1,0)) -> 561.04 | ... HT72: =SUMPRODUCT($B72:$GQ72,INDEX(PLAN_PRODUCCION!$B$4:$GQ$24,COLUMN()-COLUMN($GZ$1)+1,0)) -> 0 | HW72: =DIM_BILL[[#This Row],[Tipo]] -> MATERIAL DE EMPAQUE
A73: MEP-0069 | BL73: 0.082505882 | GR73: Petpolifoil MB 300 ABLAZOR p.t. | GS73: 8 | GT73: BEMIS PACKAGING MÉXICO SA DE CV | GU73: MATERIAL DE EMPAQUE | GV73: =SUMIF(FACT_A1[cve_prod],DIM_BILL[[#This Row],[CODIGO]],FACT_A1[Existencia]) -> 1907.61 | GW73: =SUMIF(FACT_A2[cve_prod],DIM_BILL[[#This Row],[CODIGO]],FACT_A2[Existencia]) -> 305.96 | GY73: Cortos + PO's Confirmadas | GZ73: =GV73+GW73+GX73+GZ71-GZ72 -> 1738.0886 | HA73: =GZ73+HA71-HA72 -> 1738.0886 | HB73: =HA73+HB71-HB72 -> 1738.0886 | HC73: =HB73+HC71-HC72 -> 1738.0886 | HD73: =HC73+HD71-HD72 -> 1738.0886 | HE73: =HD73+HE71-HE72 -> 1738.0886 | HF73: =HE73+HF71-HF72 -> 1177.0486 | HG73: =HF73+HG71-HG72 -> 616.0086 | HH73: =HG73+HH71-HH72 -> 616.0086 | ... HT73: =HS73+HT71-HT72 -> 616.0086 | HU73: =COUNTIF(GZ73:HT73,"<0") -> 0 | HW73: =DIM_BILL[[#This Row],[Tipo]] -> MATERIAL DE EMPAQUE
A74: MEP-0070 | BM74: 0.0027501961 | GR74: Petpolifoil MB 300 ABLAZOR Obsequio | GS74: 8 | GT74: BEMIS PACKAGING MÉXICO SA DE CV | GU74: MATERIAL DE EMPAQUE | GV74: =SUMIF(FACT_A1[cve_prod],DIM_BILL[[#This Row],[CODIGO]],FACT_A1[Existencia]) -> 0 | GW74: =SUMIF(FACT_A2[cve_prod],DIM_BILL[[#This Row],[CODIGO]],FACT_A2[Existencia]) -> 452.86 | GY74: Por Surtir & Parcial | GZ74: =SUMIFS(POs[saldo],POs[cve_prod],DIM_BILL[[#This Row],[CODIGO]],POs[status],$GY74,POs[f_ent],GZ$1) -> 0 | HA74: =SUMIFS(POs[saldo],POs[cve_prod],DIM_BILL[[#This Row],[CODIGO]],POs[status],$GY74,POs[f_ent],HA$1) -> 0 | HB74: =SUMIFS(POs[saldo],POs[cve_prod],DIM_BILL[[#This Row],[CODIGO]],POs[status],$GY74,POs[f_ent],HB$1) -> 0 | HC74: =SUMIFS(POs[saldo],POs[cve_prod],DIM_BILL[[#This Row],[CODIGO]],POs[status],$GY74,POs[f_ent],HC$1) -> 0 | HD74: =SUMIFS(POs[saldo],POs[cve_prod],DIM_BILL[[#This Row],[CODIGO]],POs[status],$GY74,POs[f_ent],HD$1) -> 0 | HE74: =SUMIFS(POs[saldo],POs[cve_prod],DIM_BILL[[#This Row],[CODIGO]],POs[status],$GY74,POs[f_ent],HE$1) -> 0 | HF74: =SUMIFS(POs[saldo],POs[cve_prod],DIM_BILL[[#This Row],[CODIGO]],POs[status],$GY74,POs[Semana],WEEKNUM(HF$1)) -> 0 | HG74: =SUMIFS(POs[saldo],POs[cve_prod],DIM_BILL[[#This Row],[CODIGO]],POs[status],$GY74,POs[Semana],WEEKNUM(HG$1)) -> 0 | HH74: =SUMIFS(POs[saldo],POs[cve_prod],DIM_BILL[[#This Row],[CODIGO]],POs[status],$GY74,POs[Semana],WEEKNUM(HH$1)) -> 0 | HI74: =SUMIFS(POs[saldo],POs[cve_prod],DIM_BILL[[#This Row],[CODIGO]],POs[status],$GY74,POs[Semana],WEEKNUM(HI$1)) -> 0 | HJ74: =SUMIFS(POs[saldo],POs[cve_prod],DIM_BILL[[#This Row],[CODIGO]],POs[status],$GY74,POs[Semana],WEEKNUM(HJ$1)) -> 0 | HK74: =SUMIFS(POs[saldo],POs[cve_prod],DIM_BILL[[#This Row],[CODIGO]],POs[status],$GY74,POs[Semana],WEEKNUM(HK$1)) -> 0 | HL74: =SUMIFS(POs[saldo],POs[cve_prod],DIM_BILL[[#This Row],[CODIGO]],POs[status],$GY74,POs[Semana],WEEKNUM(HL$1)) -> 0 | HM74: =SUMIFS(POs[saldo],POs[cve_prod],DIM_BILL[[#This Row],[CODIGO]],POs[status],$GY74,POs[Semana],WEEKNUM(HM$1)) -> 0 | ... HT74: =SUMIFS(POs[saldo],POs[cve_prod],DIM_BILL[[#This Row],[CODIGO]],POs[status],$GY74,POs[Semana],WEEKNUM(HT$1)) -> 0 | HW74: =DIM_BILL[[#This Row],[Tipo]] -> MATERIAL DE EMPAQUE
A75: MEP-0070 | BM75: 0.0027501961 | GR75: Petpolifoil MB 300 ABLAZOR Obsequio | GS75: 8 | GT75: BEMIS PACKAGING MÉXICO SA DE CV | GU75: MATERIAL DE EMPAQUE | GV75: =SUMIF(FACT_A1[cve_prod],DIM_BILL[[#This Row],[CODIGO]],FACT_A1[Existencia]) -> 0 | GW75: =SUMIF(FACT_A2[cve_prod],DIM_BILL[[#This Row],[CODIGO]],FACT_A2[Existencia]) -> 452.86 | GY75: Demanda | GZ75: =SUMPRODUCT($B75:$GQ75,INDEX(PLAN_PRODUCCION!$B$4:$GQ$24,COLUMN()-COLUMN($GZ$1)+1,0)) -> 0 | HA75: =SUMPRODUCT($B75:$GQ75,INDEX(PLAN_PRODUCCION!$B$4:$GQ$24,COLUMN()-COLUMN($GZ$1)+1,0)) -> 0 | HB75: =SUMPRODUCT($B75:$GQ75,INDEX(PLAN_PRODUCCION!$B$4:$GQ$24,COLUMN()-COLUMN($GZ$1)+1,0)) -> 0 | HC75: =SUMPRODUCT($B75:$GQ75,INDEX(PLAN_PRODUCCION!$B$4:$GQ$24,COLUMN()-COLUMN($GZ$1)+1,0)) -> 0 | HD75: =SUMPRODUCT($B75:$GQ75,INDEX(PLAN_PRODUCCION!$B$4:$GQ$24,COLUMN()-COLUMN($GZ$1)+1,0)) -> 0 | HE75: =SUMPRODUCT($B75:$GQ75,INDEX(PLAN_PRODUCCION!$B$4:$GQ$24,COLUMN()-COLUMN($GZ$1)+1,0)) -> 0 | HF75: =SUMPRODUCT($B75:$GQ75,INDEX(PLAN_PRODUCCION!$B$4:$GQ$24,COLUMN()-COLUMN($GZ$1)+1,0)) -> 0 | HG75: =SUMPRODUCT($B75:$GQ75,INDEX(PLAN_PRODUCCION!$B$4:$GQ$24,COLUMN()-COLUMN($GZ$1)+1,0)) -> 0 | ... HT75: =SUMPRODUCT($B75:$GQ75,INDEX(PLAN_PRODUCCION!$B$4:$GQ$24,COLUMN()-COLUMN($GZ$1)+1,0)) -> 0 | HW75: =DIM_BILL[[#This Row],[Tipo]] -> MATERIAL DE EMPAQUE
A76: MEP-0070 | BM76: 0.0027501961 | GR76: Petpolifoil MB 300 ABLAZOR Obsequio | GS76: 8 | GT76: BEMIS PACKAGING MÉXICO SA DE CV | GU76: MATERIAL DE EMPAQUE | GV76: =SUMIF(FACT_A1[cve_prod],DIM_BILL[[#This Row],[CODIGO]],FACT_A1[Existencia]) -> 0 | GW76: =SUMIF(FACT_A2[cve_prod],DIM_BILL[[#This Row],[CODIGO]],FACT_A2[Existencia]) -> 452.86 | GY76: Cortos + PO's Confirmadas | GZ76: =GV76+GW76+GX76+GZ74-GZ75 -> 452.86 | HA76: =GZ76+HA74-HA75 -> 452.86 | HB76: =HA76+HB74-HB75 -> 452.86 | HC76: =HB76+HC74-HC75 -> 452.86 | HD76: =HC76+HD74-HD75 -> 452.86 | HE76: =HD76+HE74-HE75 -> 452.86 | HF76: =HE76+HF74-HF75 -> 452.86 | HG76: =HF76+HG74-HG75 -> 452.86 | HH76: =HG76+HH74-HH75 -> 452.86 | ... HT76: =HS76+HT74-HT75 -> 452.86 | HU76: =COUNTIF(GZ76:HT76,"<0") -> 0 | HW76: =DIM_BILL[[#This Row],[Tipo]] -> MATERIAL DE EMPAQUE
A77: MEP-0071 | CU77: 0.01782 | GR77: GLASSPOLIFOIL CVYM 0 AZÚCAR 1 CAIDA | GS77: 3 | GT77: EXTRUPACK SA DE CV | GU77: MATERIAL DE EMPAQUE | GV77: =SUMIF(FACT_A1[cve_prod],DIM_BILL[[#This Row],[CODIGO]],FACT_A1[Existencia]) -> 0 | GW77: =SUMIF(FACT_A2[cve_prod],DIM_BILL[[#This Row],[CODIGO]],FACT_A2[Existencia]) -> 496.98 | GY77: Por Surtir & Parcial | GZ77: =SUMIFS(POs[saldo],POs[cve_prod],DIM_BILL[[#This Row],[CODIGO]],POs[status],$GY77,POs[f_ent],GZ$1) -> 0 | HA77: =SUMIFS(POs[saldo],POs[cve_prod],DIM_BILL[[#This Row],[CODIGO]],POs[status],$GY77,POs[f_ent],HA$1) -> 0 | HB77: =SUMIFS(POs[saldo],POs[cve_prod],DIM_BILL[[#This Row],[CODIGO]],POs[status],$GY77,POs[f_ent],HB$1) -> 0 | HC77: =SUMIFS(POs[saldo],POs[cve_prod],DIM_BILL[[#This Row],[CODIGO]],POs[status],$GY77,POs[f_ent],HC$1) -> 0 | HD77: =SUMIFS(POs[saldo],POs[cve_prod],DIM_BILL[[#This Row],[CODIGO]],POs[status],$GY77,POs[f_ent],HD$1) -> 0 | HE77: =SUMIFS(POs[saldo],POs[cve_prod],DIM_BILL[[#This Row],[CODIGO]],POs[status],$GY77,POs[f_ent],HE$1) -> 0 | HF77: =SUMIFS(POs[saldo],POs[cve_prod],DIM_BILL[[#This Row],[CODIGO]],POs[status],$GY77,POs[Semana],WEEKNUM(HF$1)) -> 0 | HG77: =SUMIFS(POs[saldo],POs[cve_prod],DIM_BILL[[#This Row],[CODIGO]],POs[status],$GY77,POs[Semana],WEEKNUM(HG$1)) -> 0 | HH77: =SUMIFS(POs[saldo],POs[cve_prod],DIM_BILL[[#This Row],[CODIGO]],POs[status],$GY77,POs[Semana],WEEKNUM(HH$1)) -> 0 | HI77: =SUMIFS(POs[saldo],POs[cve_prod],DIM_BILL[[#This Row],[CODIGO]],POs[status],$GY77,POs[Semana],WEEKNUM(HI$1)) -> 0 | HJ77: =SUMIFS(POs[saldo],POs[cve_prod],DIM_BILL[[#This Row],[CODIGO]],POs[status],$GY77,POs[Semana],WEEKNUM(HJ$1)) -> 0 | HK77: =SUMIFS(POs[saldo],POs[cve_prod],DIM_BILL[[#This Row],[CODIGO]],POs[status],$GY77,POs[Semana],WEEKNUM(HK$1)) -> 0 | HL77: =SUMIFS(POs[saldo],POs[cve_prod],DIM_BILL[[#This Row],[CODIGO]],POs[status],$GY77,POs[Semana],WEEKNUM(HL$1)) -> 0 | HM77: =SUMIFS(POs[saldo],POs[cve_prod],DIM_BILL[[#This Row],[CODIGO]],POs[status],$GY77,POs[Semana],WEEKNUM(HM$1)) -> 0 | ... HT77: =SUMIFS(POs[saldo],POs[cve_prod],DIM_BILL[[#This Row],[CODIGO]],POs[status],$GY77,POs[Semana],WEEKNUM(HT$1)) -> 0 | HW77: =DIM_BILL[[#This Row],[Tipo]] -> MATERIAL DE EMPAQUE
A78: MEP-0071 | CU78: 0.01782 | GR78: GLASSPOLIFOIL CVYM 0 AZÚCAR 1 CAIDA | GS78: 3 | GT78: EXTRUPACK SA DE CV | GU78: MATERIAL DE EMPAQUE | GV78: =SUMIF(FACT_A1[cve_prod],DIM_BILL[[#This Row],[CODIGO]],FACT_A1[Existencia]) -> 0 | GW78: =SUMIF(FACT_A2[cve_prod],DIM_BILL[[#This Row],[CODIGO]],FACT_A2[Existencia]) -> 496.98 | GY78: Demanda | GZ78: =SUMPRODUCT($B78:$GQ78,INDEX(PLAN_PRODUCCION!$B$4:$GQ$24,COLUMN()-COLUMN($GZ$1)+1,0)) -> 178.2 | HA78: =SUMPRODUCT($B78:$GQ78,INDEX(PLAN_PRODUCCION!$B$4:$GQ$24,COLUMN()-COLUMN($GZ$1)+1,0)) -> 0 | HB78: =SUMPRODUCT($B78:$GQ78,INDEX(PLAN_PRODUCCION!$B$4:$GQ$24,COLUMN()-COLUMN($GZ$1)+1,0)) -> 0 | HC78: =SUMPRODUCT($B78:$GQ78,INDEX(PLAN_PRODUCCION!$B$4:$GQ$24,COLUMN()-COLUMN($GZ$1)+1,0)) -> 0 | HD78: =SUMPRODUCT($B78:$GQ78,INDEX(PLAN_PRODUCCION!$B$4:$GQ$24,COLUMN()-COLUMN($GZ$1)+1,0)) -> 0 | HE78: =SUMPRODUCT($B78:$GQ78,INDEX(PLAN_PRODUCCION!$B$4:$GQ$24,COLUMN()-COLUMN($GZ$1)+1,0)) -> 0 | HF78: =SUMPRODUCT($B78:$GQ78,INDEX(PLAN_PRODUCCION!$B$4:$GQ$24,COLUMN()-COLUMN($GZ$1)+1,0)) -> 0 | HG78: =SUMPRODUCT($B78:$GQ78,INDEX(PLAN_PRODUCCION!$B$4:$GQ$24,COLUMN()-COLUMN($GZ$1)+1,0)) -> 0 | ... HT78: =SUMPRODUCT($B78:$GQ78,INDEX(PLAN_PRODUCCION!$B$4:$GQ$24,COLUMN()-COLUMN($GZ$1)+1,0)) -> 0 | HW78: =DIM_BILL[[#This Row],[Tipo]] -> MATERIAL DE EMPAQUE
A79: MEP-0071 | CU79: 0.01782 | GR79: GLASSPOLIFOIL CVYM 0 AZÚCAR 1 CAIDA | GS79: 3 | GT79: EXTRUPACK SA DE CV | GU79: MATERIAL DE EMPAQUE | GV79: =SUMIF(FACT_A1[cve_prod],DIM_BILL[[#This Row],[CODIGO]],FACT_A1[Existencia]) -> 0 | GW79: =SUMIF(FACT_A2[cve_prod],DIM_BILL[[#This Row],[CODIGO]],FACT_A2[Existencia]) -> 496.98 | GY79: Cortos + PO's Confirmadas | GZ79: =GV79+GW79+GX79+GZ77-GZ78 -> 318.78 | HA79: =GZ79+HA77-HA78 -> 318.78 | HB79: =HA79+HB77-HB78 -> 318.78 | HC79: =HB79+HC77-HC78 -> 318.78 | HD79: =HC79+HD77-HD78 -> 318.78 | HE79: =HD79+HE77-HE78 -> 318.78 | HF79: =HE79+HF77-HF78 -> 318.78 | HG79: =HF79+HG77-HG78 -> 318.78 | HH79: =HG79+HH77-HH78 -> 318.78 | ... HT79: =HS79+HT77-HT78 -> 318.78 | HU79: =COUNTIF(GZ79:HT79,"<0") -> 0 | HW79: =DIM_BILL[[#This Row],[Tipo]] -> MATERIAL DE EMPAQUE
A80: MEP-0086 | E80: 1 | AU80: 1.02 | GR80: TAPA BLANCA R-38 BLANCA CHILD PROOF | GS80: 2 | GT80: XIOMARA GONZALEZ LOPEZ | GU80: MATERIAL DE EMPAQUE | GV80: =SUMIF(FACT_A1[cve_prod],DIM_BILL[[#This Row],[CODIGO]],FACT_A1[Existencia]) -> 0 | GW80: =SUMIF(FACT_A2[cve_prod],DIM_BILL[[#This Row],[CODIGO]],FACT_A2[Existencia]) -> 0 | GY80: Por Surtir & Parcial | GZ80: =SUMIFS(POs[saldo],POs[cve_prod],DIM_BILL[[#This Row],[CODIGO]],POs[status],$GY80,POs[f_ent],GZ$1) -> 0 | HA80: =SUMIFS(POs[saldo],POs[cve_prod],DIM_BILL[[#This Row],[CODIGO]],POs[status],$GY80,POs[f_ent],HA$1) -> 0 | HB80: =SUMIFS(POs[saldo],POs[cve_prod],DIM_BILL[[#This Row],[CODIGO]],POs[status],$GY80,POs[f_ent],HB$1) -> 0 | HC80: =SUMIFS(POs[saldo],POs[cve_prod],DIM_BILL[[#This Row],[CODIGO]],POs[status],$GY80,POs[f_ent],HC$1) -> 0 | HD80: =SUMIFS(POs[saldo],POs[cve_prod],DIM_BILL[[#This Row],[CODIGO]],POs[status],$GY80,POs[f_ent],HD$1) -> 0 | HE80: =SUMIFS(POs[saldo],POs[cve_prod],DIM_BILL[[#This Row],[CODIGO]],POs[status],$GY80,POs[f_ent],HE$1) -> 0 | HF80: =SUMIFS(POs[saldo],POs[cve_prod],DIM_BILL[[#This Row],[CODIGO]],POs[status],$GY80,POs[Semana],WEEKNUM(HF$1)) -> 0 | HG80: =SUMIFS(POs[saldo],POs[cve_prod],DIM_BILL[[#This Row],[CODIGO]],POs[status],$GY80,POs[Semana],WEEKNUM(HG$1)) -> 0 | HH80: =SUMIFS(POs[saldo],POs[cve_prod],DIM_BILL[[#This Row],[CODIGO]],POs[status],$GY80,POs[Semana],WEEKNUM(HH$1)) -> 0 | HI80: =SUMIFS(POs[saldo],POs[cve_prod],DIM_BILL[[#This Row],[CODIGO]],POs[status],$GY80,POs[Semana],WEEKNUM(HI$1)) -> 0 | HJ80: =SUMIFS(POs[saldo],POs[cve_prod],DIM_BILL[[#This Row],[CODIGO]],POs[status],$GY80,POs[Semana],WEEKNUM(HJ$1)) -> 0 | HK80: =SUMIFS(POs[saldo],POs[cve_prod],DIM_BILL[[#This Row],[CODIGO]],POs[status],$GY80,POs[Semana],WEEKNUM(HK$1)) -> 0 | HL80: =SUMIFS(POs[saldo],POs[cve_prod],DIM_BILL[[#This Row],[CODIGO]],POs[status],$GY80,POs[Semana],WEEKNUM(HL$1)) -> 0 | HM80: =SUMIFS(POs[saldo],POs[cve_prod],DIM_BILL[[#This Row],[CODIGO]],POs[status],$GY80,POs[Semana],WEEKNUM(HM$1)) -> 0 | ... HT80: =SUMIFS(POs[saldo],POs[cve_prod],DIM_BILL[[#This Row],[CODIGO]],POs[status],$GY80,POs[Semana],WEEKNUM(HT$1)) -> 0 | HW80: =DIM_BILL[[#This Row],[Tipo]] -> MATERIAL DE EMPAQUE
A81: MEP-0086 | E81: 1 | AU81: 1.02 | GR81: TAPA BLANCA R-38 BLANCA CHILD PROOF | GS81: 2 | GT81: XIOMARA GONZALEZ LOPEZ | GU81: MATERIAL DE EMPAQUE | GV81: =SUMIF(FACT_A1[cve_prod],DIM_BILL[[#This Row],[CODIGO]],FACT_A1[Existencia]) -> 0 | GW81: =SUMIF(FACT_A2[cve_prod],DIM_BILL[[#This Row],[CODIGO]],FACT_A2[Existencia]) -> 0 | GY81: Demanda | GZ81: =SUMPRODUCT($B81:$GQ81,INDEX(PLAN_PRODUCCION!$B$4:$GQ$24,COLUMN()-COLUMN($GZ$1)+1,0)) -> 2000 | HA81: =SUMPRODUCT($B81:$GQ81,INDEX(PLAN_PRODUCCION!$B$4:$GQ$24,COLUMN()-COLUMN($GZ$1)+1,0)) -> 0 | HB81: =SUMPRODUCT($B81:$GQ81,INDEX(PLAN_PRODUCCION!$B$4:$GQ$24,COLUMN()-COLUMN($GZ$1)+1,0)) -> 0 | HC81: =SUMPRODUCT($B81:$GQ81,INDEX(PLAN_PRODUCCION!$B$4:$GQ$24,COLUMN()-COLUMN($GZ$1)+1,0)) -> 0 | HD81: =SUMPRODUCT($B81:$GQ81,INDEX(PLAN_PRODUCCION!$B$4:$GQ$24,COLUMN()-COLUMN($GZ$1)+1,0)) -> 0 | HE81: =SUMPRODUCT($B81:$GQ81,INDEX(PLAN_PRODUCCION!$B$4:$GQ$24,COLUMN()-COLUMN($GZ$1)+1,0)) -> 0 | HF81: =SUMPRODUCT($B81:$GQ81,INDEX(PLAN_PRODUCCION!$B$4:$GQ$24,COLUMN()-COLUMN($GZ$1)+1,0)) -> 0 | HG81: =SUMPRODUCT($B81:$GQ81,INDEX(PLAN_PRODUCCION!$B$4:$GQ$24,COLUMN()-COLUMN($GZ$1)+1,0)) -> 0 | ... HT81: =SUMPRODUCT($B81:$GQ81,INDEX(PLAN_PRODUCCION!$B$4:$GQ$24,COLUMN()-COLUMN($GZ$1)+1,0)) -> 0 | HW81: =DIM_BILL[[#This Row],[Tipo]] -> MATERIAL DE EMPAQUE
A82: MEP-0086 | E82: 1 | AU82: 1.02 | GR82: TAPA BLANCA R-38 BLANCA CHILD PROOF | GS82: 2 | GT82: XIOMARA GONZALEZ LOPEZ | GU82: MATERIAL DE EMPAQUE | GV82: =SUMIF(FACT_A1[cve_prod],DIM_BILL[[#This Row],[CODIGO]],FACT_A1[Existencia]) -> 0 | GW82: =SUMIF(FACT_A2[cve_prod],DIM_BILL[[#This Row],[CODIGO]],FACT_A2[Existencia]) -> 0 | GY82: Cortos + PO's Confirmadas | GZ82: =GV82+GW82+GX82+GZ80-GZ81 -> -2000 | HA82: =GZ82+HA80-HA81 -> -2000 | HB82: =HA82+HB80-HB81 -> -2000 | HC82: =HB82+HC80-HC81 -> -2000 | HD82: =HC82+HD80-HD81 -> -2000 | HE82: =HD82+HE80-HE81 -> -2000 | HF82: =HE82+HF80-HF81 -> -2000 | HG82: =HF82+HG80-HG81 -> -2000 | HH82: =HG82+HH80-HH81 -> -2000 | ... HT82: =HS82+HT80-HT81 -> -2000 | HU82: =COUNTIF(GZ82:HT82,"<0") -> 21 | HW82: =DIM_BILL[[#This Row],[Tipo]] -> MATERIAL DE EMPAQUE
A83: MEP-0090 | F83: 0.0074210526 | G83: 0.00225 | H83: 0.001606 | GR83: BOBINA ALUMINIO AZ-VITE | GS83: 2 | GT83: COMERCIALIZADORA NEFUR | GU83: MATERIAL DE EMPAQUE | GV83: =SUMIF(FACT_A1[cve_prod],DIM_BILL[[#This Row],[CODIGO]],FACT_A1[Existencia]) -> 0 | GW83: =SUMIF(FACT_A2[cve_prod],DIM_BILL[[#This Row],[CODIGO]],FACT_A2[Existencia]) -> 0 | GY83: Por Surtir & Parcial | GZ83: =SUMIFS(POs[saldo],POs[cve_prod],DIM_BILL[[#This Row],[CODIGO]],POs[status],$GY83,POs[f_ent],GZ$1) -> 0 | HA83: =SUMIFS(POs[saldo],POs[cve_prod],DIM_BILL[[#This Row],[CODIGO]],POs[status],$GY83,POs[f_ent],HA$1) -> 0 | HB83: =SUMIFS(POs[saldo],POs[cve_prod],DIM_BILL[[#This Row],[CODIGO]],POs[status],$GY83,POs[f_ent],HB$1) -> 0 | HC83: =SUMIFS(POs[saldo],POs[cve_prod],DIM_BILL[[#This Row],[CODIGO]],POs[status],$GY83,POs[f_ent],HC$1) -> 0 | HD83: =SUMIFS(POs[saldo],POs[cve_prod],DIM_BILL[[#This Row],[CODIGO]],POs[status],$GY83,POs[f_ent],HD$1) -> 0 | HE83: =SUMIFS(POs[saldo],POs[cve_prod],DIM_BILL[[#This Row],[CODIGO]],POs[status],$GY83,POs[f_ent],HE$1) -> 0 | HF83: =SUMIFS(POs[saldo],POs[cve_prod],DIM_BILL[[#This Row],[CODIGO]],POs[status],$GY83,POs[Semana],WEEKNUM(HF$1)) -> 0 | HG83: =SUMIFS(POs[saldo],POs[cve_prod],DIM_BILL[[#This Row],[CODIGO]],POs[status],$GY83,POs[Semana],WEEKNUM(HG$1)) -> 0 | HH83: =SUMIFS(POs[saldo],POs[cve_prod],DIM_BILL[[#This Row],[CODIGO]],POs[status],$GY83,POs[Semana],WEEKNUM(HH$1)) -> 0 | HI83: =SUMIFS(POs[saldo],POs[cve_prod],DIM_BILL[[#This Row],[CODIGO]],POs[status],$GY83,POs[Semana],WEEKNUM(HI$1)) -> 0 | HJ83: =SUMIFS(POs[saldo],POs[cve_prod],DIM_BILL[[#This Row],[CODIGO]],POs[status],$GY83,POs[Semana],WEEKNUM(HJ$1)) -> 0 | HK83: =SUMIFS(POs[saldo],POs[cve_prod],DIM_BILL[[#This Row],[CODIGO]],POs[status],$GY83,POs[Semana],WEEKNUM(HK$1)) -> 0 | HL83: =SUMIFS(POs[saldo],POs[cve_prod],DIM_BILL[[#This Row],[CODIGO]],POs[status],$GY83,POs[Semana],WEEKNUM(HL$1)) -> 0 | HM83: =SUMIFS(POs[saldo],POs[cve_prod],DIM_BILL[[#This Row],[CODIGO]],POs[status],$GY83,POs[Semana],WEEKNUM(HM$1)) -> 0 | ... HT83: =SUMIFS(POs[saldo],POs[cve_prod],DIM_BILL[[#This Row],[CODIGO]],POs[status],$GY83,POs[Semana],WEEKNUM(HT$1)) -> 0 | HW83: =DIM_BILL[[#This Row],[Tipo]] -> MATERIAL DE EMPAQUE
A84: MEP-0090 | F84: 0.0074210526 | G84: 0.00225 | H84: 0.001606 | GR84: BOBINA ALUMINIO AZ-VITE | GS84: 2 | GT84: COMERCIALIZADORA NEFUR | GU84: MATERIAL DE EMPAQUE | GV84: =SUMIF(FACT_A1[cve_prod],DIM_BILL[[#This Row],[CODIGO]],FACT_A1[Existencia]) -> 0 | GW84: =SUMIF(FACT_A2[cve_prod],DIM_BILL[[#This Row],[CODIGO]],FACT_A2[Existencia]) -> 0 | GY84: Demanda | GZ84: =SUMPRODUCT($B84:$GQ84,INDEX(PLAN_PRODUCCION!$B$4:$GQ$24,COLUMN()-COLUMN($GZ$1)+1,0)) -> 55.51 | HA84: =SUMPRODUCT($B84:$GQ84,INDEX(PLAN_PRODUCCION!$B$4:$GQ$24,COLUMN()-COLUMN($GZ$1)+1,0)) -> 0 | HB84: =SUMPRODUCT($B84:$GQ84,INDEX(PLAN_PRODUCCION!$B$4:$GQ$24,COLUMN()-COLUMN($GZ$1)+1,0)) -> 0 | HC84: =SUMPRODUCT($B84:$GQ84,INDEX(PLAN_PRODUCCION!$B$4:$GQ$24,COLUMN()-COLUMN($GZ$1)+1,0)) -> 0 | HD84: =SUMPRODUCT($B84:$GQ84,INDEX(PLAN_PRODUCCION!$B$4:$GQ$24,COLUMN()-COLUMN($GZ$1)+1,0)) -> 0 | HE84: =SUMPRODUCT($B84:$GQ84,INDEX(PLAN_PRODUCCION!$B$4:$GQ$24,COLUMN()-COLUMN($GZ$1)+1,0)) -> 0 | HF84: =SUMPRODUCT($B84:$GQ84,INDEX(PLAN_PRODUCCION!$B$4:$GQ$24,COLUMN()-COLUMN($GZ$1)+1,0)) -> 0 | HG84: =SUMPRODUCT($B84:$GQ84,INDEX(PLAN_PRODUCCION!$B$4:$GQ$24,COLUMN()-COLUMN($GZ$1)+1,0)) -> 0 | ... HT84: =SUMPRODUCT($B84:$GQ84,INDEX(PLAN_PRODUCCION!$B$4:$GQ$24,COLUMN()-COLUMN($GZ$1)+1,0)) -> 0 | HW84: =DIM_BILL[[#This Row],[Tipo]] -> MATERIAL DE EMPAQUE
A85: MEP-0090 | F85: 0.0074210526 | G85: 0.00225 | H85: 0.001606 | GR85: BOBINA ALUMINIO AZ-VITE | GS85: 2 | GT85: COMERCIALIZADORA NEFUR | GU85: MATERIAL DE EMPAQUE | GV85: =SUMIF(FACT_A1[cve_prod],DIM_BILL[[#This Row],[CODIGO]],FACT_A1[Existencia]) -> 0 | GW85: =SUMIF(FACT_A2[cve_prod],DIM_BILL[[#This Row],[CODIGO]],FACT_A2[Existencia]) -> 0 | GY85: Cortos + PO's Confirmadas | GZ85: =GV85+GW85+GX85+GZ83-GZ84 -> -55.51 | HA85: =GZ85+HA83-HA84 -> -55.51 | HB85: =HA85+HB83-HB84 -> -55.51 | HC85: =HB85+HC83-HC84 -> -55.51 | HD85: =HC85+HD83-HD84 -> -55.51 | HE85: =HD85+HE83-HE84 -> -55.51 | HF85: =HE85+HF83-HF84 -> -55.51 | HG85: =HF85+HG83-HG84 -> -55.51 | HH85: =HG85+HH83-HH84 -> -55.51 | ... HT85: =HS85+HT83-HT84 -> -55.51 | HU85: =COUNTIF(GZ85:HT85,"<0") -> 21 | HW85: =DIM_BILL[[#This Row],[Tipo]] -> MATERIAL DE EMPAQUE
A86: MEP-0096 | C86: 1.03 | I86: 1.03 | J86: 1.03 | S86: 1.05 | T86: 1.03 | V86: 1.03 | W86: 1.03 | X86: 1.03 | AG86: 1 | AH86: 1.0101493 | AI86: 1.01 | AQ86: 1.0605489 | AR86: 1.0605489 | AS86: 1.03 | AY86: 1.03 | BA86: 1.02 | BB86: 1.02 | BC86: 1.02 | BD86: 1.02 | FA86: 1.05 | FE86: 1.02 | FF86: 1.02 | FG86: 1.02 | FI86: 1.05 | FK86: 1.02 | FN86: 1.02 | FT86: 1.05 | FY86: 1.02 | FZ86: 1.020102 | GH86: 1.02 | GI86: 1.019949 | GJ86: 1.0502732 | GQ86: 1.05 | GR86: FRASCO CAPSULERO PET 150 mL ÁMBAR R-38 | GS86: 3 | GT86: POLIMEROS ENVASES Y TAPAS TAPATIOS | GU86: MATERIAL DE EMPAQUE | GV86: =SUMIF(FACT_A1[cve_prod],DIM_BILL[[#This Row],[CODIGO]],FACT_A1[Existencia]) -> 0 | GW86: =SUMIF(FACT_A2[cve_prod],DIM_BILL[[#This Row],[CODIGO]],FACT_A2[Existencia]) -> 19440 | GY86: Por Surtir & Parcial | GZ86: =SUMIFS(POs[saldo],POs[cve_prod],DIM_BILL[[#This Row],[CODIGO]],POs[status],$GY86,POs[f_ent],GZ$1) -> 0 | HA86: =SUMIFS(POs[saldo],POs[cve_prod],DIM_BILL[[#This Row],[CODIGO]],POs[status],$GY86,POs[f_ent],HA$1) -> 0 | HB86: =SUMIFS(POs[saldo],POs[cve_prod],DIM_BILL[[#This Row],[CODIGO]],POs[status],$GY86,POs[f_ent],HB$1) -> 0 | HC86: =SUMIFS(POs[saldo],POs[cve_prod],DIM_BILL[[#This Row],[CODIGO]],POs[status],$GY86,POs[f_ent],HC$1) -> 0 | HD86: =SUMIFS(POs[saldo],POs[cve_prod],DIM_BILL[[#This Row],[CODIGO]],POs[status],$GY86,POs[f_ent],HD$1) -> 30240 | HE86: =SUMIFS(POs[saldo],POs[cve_prod],DIM_BILL[[#This Row],[CODIGO]],POs[status],$GY86,POs[f_ent],HE$1) -> 0 | HF86: =SUMIFS(POs[saldo],POs[cve_prod],DIM_BILL[[#This Row],[CODIGO]],POs[status],$GY86,POs[Semana],WEEKNUM(HF$1)) -> 30240 | HG86: =SUMIFS(POs[saldo],POs[cve_prod],DIM_BILL[[#This Row],[CODIGO]],POs[status],$GY86,POs[Semana],WEEKNUM(HG$1)) -> 0 | HH86: =SUMIFS(POs[saldo],POs[cve_prod],DIM_BILL[[#This Row],[CODIGO]],POs[status],$GY86,POs[Semana],WEEKNUM(HH$1)) -> 0 | HI86: =SUMIFS(POs[saldo],POs[cve_prod],DIM_BILL[[#This Row],[CODIGO]],POs[status],$GY86,POs[Semana],WEEKNUM(HI$1)) -> 0 | HJ86: =SUMIFS(POs[saldo],POs[cve_prod],DIM_BILL[[#This Row],[CODIGO]],POs[status],$GY86,POs[Semana],WEEKNUM(HJ$1)) -> 0 | HK86: =SUMIFS(POs[saldo],POs[cve_prod],DIM_BILL[[#This Row],[CODIGO]],POs[status],$GY86,POs[Semana],WEEKNUM(HK$1)) -> 0 | HL86: =SUMIFS(POs[saldo],POs[cve_prod],DIM_BILL[[#This Row],[CODIGO]],POs[status],$GY86,POs[Semana],WEEKNUM(HL$1)) -> 0 | HM86: =SUMIFS(POs[saldo],POs[cve_prod],DIM_BILL[[#This Row],[CODIGO]],POs[status],$GY86,POs[Semana],WEEKNUM(HM$1)) -> 0 | ... HT86: =SUMIFS(POs[saldo],POs[cve_prod],DIM_BILL[[#This Row],[CODIGO]],POs[status],$GY86,POs[Semana],WEEKNUM(HT$1)) -> 0 | HW86: =DIM_BILL[[#This Row],[Tipo]] -> MATERIAL DE EMPAQUE
A87: MEP-0096 | C87: 1.03 | I87: 1.03 | J87: 1.03 | S87: 1.05 | T87: 1.03 | V87: 1.03 | W87: 1.03 | X87: 1.03 | AG87: 1 | AH87: 1.0101493 | AI87: 1.01 | AQ87: 1.0605489 | AR87: 1.0605489 | AS87: 1.03 | AY87: 1.03 | BA87: 1.02 | BB87: 1.02 | BC87: 1.02 | BD87: 1.02 | FA87: 1.05 | FE87: 1.02 | FF87: 1.02 | FG87: 1.02 | FI87: 1.05 | FK87: 1.02 | FN87: 1.02 | FT87: 1.05 | FY87: 1.02 | FZ87: 1.020102 | GH87: 1.02 | GI87: 1.019949 | GJ87: 1.0502732 | GQ87: 1.05 | GR87: FRASCO CAPSULERO PET 150 mL ÁMBAR R-38 | GS87: 3 | GT87: POLIMEROS ENVASES Y TAPAS TAPATIOS | GU87: MATERIAL DE EMPAQUE | GV87: =SUMIF(FACT_A1[cve_prod],DIM_BILL[[#This Row],[CODIGO]],FACT_A1[Existencia]) -> 0 | GW87: =SUMIF(FACT_A2[cve_prod],DIM_BILL[[#This Row],[CODIGO]],FACT_A2[Existencia]) -> 19440 | GY87: Demanda | GZ87: =SUMPRODUCT($B87:$GQ87,INDEX(PLAN_PRODUCCION!$B$4:$GQ$24,COLUMN()-COLUMN($GZ$1)+1,0)) -> 254897.9 | HA87: =SUMPRODUCT($B87:$GQ87,INDEX(PLAN_PRODUCCION!$B$4:$GQ$24,COLUMN()-COLUMN($GZ$1)+1,0)) -> 0 | HB87: =SUMPRODUCT($B87:$GQ87,INDEX(PLAN_PRODUCCION!$B$4:$GQ$24,COLUMN()-COLUMN($GZ$1)+1,0)) -> 0 | HC87: =SUMPRODUCT($B87:$GQ87,INDEX(PLAN_PRODUCCION!$B$4:$GQ$24,COLUMN()-COLUMN($GZ$1)+1,0)) -> 0 | HD87: =SUMPRODUCT($B87:$GQ87,INDEX(PLAN_PRODUCCION!$B$4:$GQ$24,COLUMN()-COLUMN($GZ$1)+1,0)) -> 0 | HE87: =SUMPRODUCT($B87:$GQ87,INDEX(PLAN_PRODUCCION!$B$4:$GQ$24,COLUMN()-COLUMN($GZ$1)+1,0)) -> 0 | HF87: =SUMPRODUCT($B87:$GQ87,INDEX(PLAN_PRODUCCION!$B$4:$GQ$24,COLUMN()-COLUMN($GZ$1)+1,0)) -> 0 | HG87: =SUMPRODUCT($B87:$GQ87,INDEX(PLAN_PRODUCCION!$B$4:$GQ$24,COLUMN()-COLUMN($GZ$1)+1,0)) -> 31620.909 | ... HT87: =SUMPRODUCT($B87:$GQ87,INDEX(PLAN_PRODUCCION!$B$4:$GQ$24,COLUMN()-COLUMN($GZ$1)+1,0)) -> 0 | HW87: =DIM_BILL[[#This Row],[Tipo]] -> MATERIAL DE EMPAQUE
A88: MEP-0096 | C88: 1.03 | I88: 1.03 | J88: 1.03 | S88: 1.05 | T88: 1.03 | V88: 1.03 | W88: 1.03 | X88: 1.03 | AG88: 1 | AH88: 1.0101493 | AI88: 1.01 | AQ88: 1.0605489 | AR88: 1.0605489 | AS88: 1.03 | AY88: 1.03 | BA88: 1.02 | BB88: 1.02 | BC88: 1.02 | BD88: 1.02 | FA88: 1.05 | FE88: 1.02 | FF88: 1.02 | FG88: 1.02 | FI88: 1.05 | FK88: 1.02 | FN88: 1.02 | FT88: 1.05 | FY88: 1.02 | FZ88: 1.020102 | GH88: 1.02 | GI88: 1.019949 | GJ88: 1.0502732 | GQ88: 1.05 | GR88: FRASCO CAPSULERO PET 150 mL ÁMBAR R-38 | GS88: 3 | GT88: POLIMEROS ENVASES Y TAPAS TAPATIOS | GU88: MATERIAL DE EMPAQUE | GV88: =SUMIF(FACT_A1[cve_prod],DIM_BILL[[#This Row],[CODIGO]],FACT_A1[Existencia]) -> 0 | GW88: =SUMIF(FACT_A2[cve_prod],DIM_BILL[[#This Row],[CODIGO]],FACT_A2[Existencia]) -> 19440 | GY88: Cortos + PO's Confirmadas | GZ88: =GV88+GW88+GX88+GZ86-GZ87 -> -235457.9 | HA88: =GZ88+HA86-HA87 -> -235457.9 | HB88: =HA88+HB86-HB87 -> -235457.9 | HC88: =HB88+HC86-HC87 -> -235457.9 | HD88: =HC88+HD86-HD87 -> -205217.9 | HE88: =HD88+HE86-HE87 -> -205217.9 | HF88: =HE88+HF86-HF87 -> -174977.9 | HG88: =HF88+HG86-HG87 -> -206598.81 | HH88: =HG88+HH86-HH87 -> -206598.81 | ... HT88: =HS88+HT86-HT87 -> -231055.94 | HU88: =COUNTIF(GZ88:HT88,"<0") -> 21 | HW88: =DIM_BILL[[#This Row],[Tipo]] -> MATERIAL DE EMPAQUE
A89: MEP-0097 | AP89: 1.03 | GR89: FRASCO PET 150 mL ROSA R-38 | GS89: 3 | GT89: POLIMEROS ENVASES Y TAPAS TAPATIOS | GU89: MATERIAL DE EMPAQUE | GV89: =SUMIF(FACT_A1[cve_prod],DIM_BILL[[#This Row],[CODIGO]],FACT_A1[Existencia]) -> 0 | GW89: =SUMIF(FACT_A2[cve_prod],DIM_BILL[[#This Row],[CODIGO]],FACT_A2[Existencia]) -> 4680 | GY89: Por Surtir & Parcial | GZ89: =SUMIFS(POs[saldo],POs[cve_prod],DIM_BILL[[#This Row],[CODIGO]],POs[status],$GY89,POs[f_ent],GZ$1) -> 0 | HA89: =SUMIFS(POs[saldo],POs[cve_prod],DIM_BILL[[#This Row],[CODIGO]],POs[status],$GY89,POs[f_ent],HA$1) -> 0 | HB89: =SUMIFS(POs[saldo],POs[cve_prod],DIM_BILL[[#This Row],[CODIGO]],POs[status],$GY89,POs[f_ent],HB$1) -> 0 | HC89: =SUMIFS(POs[saldo],POs[cve_prod],DIM_BILL[[#This Row],[CODIGO]],POs[status],$GY89,POs[f_ent],HC$1) -> 0 | HD89: =SUMIFS(POs[saldo],POs[cve_prod],DIM_BILL[[#This Row],[CODIGO]],POs[status],$GY89,POs[f_ent],HD$1) -> 0 | HE89: =SUMIFS(POs[saldo],POs[cve_prod],DIM_BILL[[#This Row],[CODIGO]],POs[status],$GY89,POs[f_ent],HE$1) -> 0 | HF89: =SUMIFS(POs[saldo],POs[cve_prod],DIM_BILL[[#This Row],[CODIGO]],POs[status],$GY89,POs[Semana],WEEKNUM(HF$1)) -> 0 | HG89: =SUMIFS(POs[saldo],POs[cve_prod],DIM_BILL[[#This Row],[CODIGO]],POs[status],$GY89,POs[Semana],WEEKNUM(HG$1)) -> 0 | HH89: =SUMIFS(POs[saldo],POs[cve_prod],DIM_BILL[[#This Row],[CODIGO]],POs[status],$GY89,POs[Semana],WEEKNUM(HH$1)) -> 0 | HI89: =SUMIFS(POs[saldo],POs[cve_prod],DIM_BILL[[#This Row],[CODIGO]],POs[status],$GY89,POs[Semana],WEEKNUM(HI$1)) -> 0 | HJ89: =SUMIFS(POs[saldo],POs[cve_prod],DIM_BILL[[#This Row],[CODIGO]],POs[status],$GY89,POs[Semana],WEEKNUM(HJ$1)) -> 0 | HK89: =SUMIFS(POs[saldo],POs[cve_prod],DIM_BILL[[#This Row],[CODIGO]],POs[status],$GY89,POs[Semana],WEEKNUM(HK$1)) -> 0 | HL89: =SUMIFS(POs[saldo],POs[cve_prod],DIM_BILL[[#This Row],[CODIGO]],POs[status],$GY89,POs[Semana],WEEKNUM(HL$1)) -> 0 | HM89: =SUMIFS(POs[saldo],POs[cve_prod],DIM_BILL[[#This Row],[CODIGO]],POs[status],$GY89,POs[Semana],WEEKNUM(HM$1)) -> 0 | ... HT89: =SUMIFS(POs[saldo],POs[cve_prod],DIM_BILL[[#This Row],[CODIGO]],POs[status],$GY89,POs[Semana],WEEKNUM(HT$1)) -> 0 | HW89: =DIM_BILL[[#This Row],[Tipo]] -> MATERIAL DE EMPAQUE
A90: MEP-0097 | AP90: 1.03 | GR90: FRASCO PET 150 mL ROSA R-38 | GS90: 3 | GT90: POLIMEROS ENVASES Y TAPAS TAPATIOS | GU90: MATERIAL DE EMPAQUE | GV90: =SUMIF(FACT_A1[cve_prod],DIM_BILL[[#This Row],[CODIGO]],FACT_A1[Existencia]) -> 0 | GW90: =SUMIF(FACT_A2[cve_prod],DIM_BILL[[#This Row],[CODIGO]],FACT_A2[Existencia]) -> 4680 | GY90: Demanda | GZ90: =SUMPRODUCT($B90:$GQ90,INDEX(PLAN_PRODUCCION!$B$4:$GQ$24,COLUMN()-COLUMN($GZ$1)+1,0)) -> 0 | HA90: =SUMPRODUCT($B90:$GQ90,INDEX(PLAN_PRODUCCION!$B$4:$GQ$24,COLUMN()-COLUMN($GZ$1)+1,0)) -> 0 | HB90: =SUMPRODUCT($B90:$GQ90,INDEX(PLAN_PRODUCCION!$B$4:$GQ$24,COLUMN()-COLUMN($GZ$1)+1,0)) -> 0 | HC90: =SUMPRODUCT($B90:$GQ90,INDEX(PLAN_PRODUCCION!$B$4:$GQ$24,COLUMN()-COLUMN($GZ$1)+1,0)) -> 0 | HD90: =SUMPRODUCT($B90:$GQ90,INDEX(PLAN_PRODUCCION!$B$4:$GQ$24,COLUMN()-COLUMN($GZ$1)+1,0)) -> 0 | HE90: =SUMPRODUCT($B90:$GQ90,INDEX(PLAN_PRODUCCION!$B$4:$GQ$24,COLUMN()-COLUMN($GZ$1)+1,0)) -> 0 | HF90: =SUMPRODUCT($B90:$GQ90,INDEX(PLAN_PRODUCCION!$B$4:$GQ$24,COLUMN()-COLUMN($GZ$1)+1,0)) -> 0 | HG90: =SUMPRODUCT($B90:$GQ90,INDEX(PLAN_PRODUCCION!$B$4:$GQ$24,COLUMN()-COLUMN($GZ$1)+1,0)) -> 0 | ... HT90: =SUMPRODUCT($B90:$GQ90,INDEX(PLAN_PRODUCCION!$B$4:$GQ$24,COLUMN()-COLUMN($GZ$1)+1,0)) -> 0 | HW90: =DIM_BILL[[#This Row],[Tipo]] -> MATERIAL DE EMPAQUE
A91: MEP-0097 | AP91: 1.03 | GR91: FRASCO PET 150 mL ROSA R-38 | GS91: 3 | GT91: POLIMEROS ENVASES Y TAPAS TAPATIOS | GU91: MATERIAL DE EMPAQUE | GV91: =SUMIF(FACT_A1[cve_prod],DIM_BILL[[#This Row],[CODIGO]],FACT_A1[Existencia]) -> 0 | GW91: =SUMIF(FACT_A2[cve_prod],DIM_BILL[[#This Row],[CODIGO]],FACT_A2[Existencia]) -> 4680 | GY91: Cortos + PO's Confirmadas | GZ91: =GV91+GW91+GX91+GZ89-GZ90 -> 4680 | HA91: =GZ91+HA89-HA90 -> 4680 | HB91: =HA91+HB89-HB90 -> 4680 | HC91: =HB91+HC89-HC90 -> 4680 | HD91: =HC91+HD89-HD90 -> 4680 | HE91: =HD91+HE89-HE90 -> 4680 | HF91: =HE91+HF89-HF90 -> 4680 | HG91: =HF91+HG89-HG90 -> 4680 | HH91: =HG91+HH89-HH90 -> 4680 | ... HT91: =HS91+HT89-HT90 -> 4680 | HU91: =COUNTIF(GZ91:HT91,"<0") -> 0 | HW91: =DIM_BILL[[#This Row],[Tipo]] -> MATERIAL DE EMPAQUE
A92: MEP-0098 | CN92: 1 | GR92: BOLSA STAND POUCH COLAGENO 6g MARACUYA | GS92: 2 | GV92: =SUMIF(FACT_A1[cve_prod],DIM_BILL[[#This Row],[CODIGO]],FACT_A1[Existencia]) -> 0 | GW92: =SUMIF(FACT_A2[cve_prod],DIM_BILL[[#This Row],[CODIGO]],FACT_A2[Existencia]) -> 0 | GY92: Por Surtir & Parcial | GZ92: =SUMIFS(POs[saldo],POs[cve_prod],DIM_BILL[[#This Row],[CODIGO]],POs[status],$GY92,POs[f_ent],GZ$1) -> 0 | HA92: =SUMIFS(POs[saldo],POs[cve_prod],DIM_BILL[[#This Row],[CODIGO]],POs[status],$GY92,POs[f_ent],HA$1) -> 0 | HB92: =SUMIFS(POs[saldo],POs[cve_prod],DIM_BILL[[#This Row],[CODIGO]],POs[status],$GY92,POs[f_ent],HB$1) -> 0 | HC92: =SUMIFS(POs[saldo],POs[cve_prod],DIM_BILL[[#This Row],[CODIGO]],POs[status],$GY92,POs[f_ent],HC$1) -> 0 | HD92: =SUMIFS(POs[saldo],POs[cve_prod],DIM_BILL[[#This Row],[CODIGO]],POs[status],$GY92,POs[f_ent],HD$1) -> 0 | HE92: =SUMIFS(POs[saldo],POs[cve_prod],DIM_BILL[[#This Row],[CODIGO]],POs[status],$GY92,POs[f_ent],HE$1) -> 0 | HF92: =SUMIFS(POs[saldo],POs[cve_prod],DIM_BILL[[#This Row],[CODIGO]],POs[status],$GY92,POs[Semana],WEEKNUM(HF$1)) -> 0 | HG92: =SUMIFS(POs[saldo],POs[cve_prod],DIM_BILL[[#This Row],[CODIGO]],POs[status],$GY92,POs[Semana],WEEKNUM(HG$1)) -> 0 | HH92: =SUMIFS(POs[saldo],POs[cve_prod],DIM_BILL[[#This Row],[CODIGO]],POs[status],$GY92,POs[Semana],WEEKNUM(HH$1)) -> 0 | HI92: =SUMIFS(POs[saldo],POs[cve_prod],DIM_BILL[[#This Row],[CODIGO]],POs[status],$GY92,POs[Semana],WEEKNUM(HI$1)) -> 0 | HJ92: =SUMIFS(POs[saldo],POs[cve_prod],DIM_BILL[[#This Row],[CODIGO]],POs[status],$GY92,POs[Semana],WEEKNUM(HJ$1)) -> 0 | HK92: =SUMIFS(POs[saldo],POs[cve_prod],DIM_BILL[[#This Row],[CODIGO]],POs[status],$GY92,POs[Semana],WEEKNUM(HK$1)) -> 0 | HL92: =SUMIFS(POs[saldo],POs[cve_prod],DIM_BILL[[#This Row],[CODIGO]],POs[status],$GY92,POs[Semana],WEEKNUM(HL$1)) -> 0 | HM92: =SUMIFS(POs[saldo],POs[cve_prod],DIM_BILL[[#This Row],[CODIGO]],POs[status],$GY92,POs[Semana],WEEKNUM(HM$1)) -> 0 | ... HT92: =SUMIFS(POs[saldo],POs[cve_prod],DIM_BILL[[#This Row],[CODIGO]],POs[status],$GY92,POs[Semana],WEEKNUM(HT$1)) -> 0 | HW92: =DIM_BILL[[#This Row],[Tipo]]
A93: MEP-0098 | CN93: 1 | GR93: BOLSA STAND POUCH COLAGENO 6g MARACUYA | GS93: 2 | GV93: =SUMIF(FACT_A1[cve_prod],DIM_BILL[[#This Row],[CODIGO]],FACT_A1[Existencia]) -> 0 | GW93: =SUMIF(FACT_A2[cve_prod],DIM_BILL[[#This Row],[CODIGO]],FACT_A2[Existencia]) -> 0 | GY93: Demanda | GZ93: =SUMPRODUCT($B93:$GQ93,INDEX(PLAN_PRODUCCION!$B$4:$GQ$24,COLUMN()-COLUMN($GZ$1)+1,0)) -> 0 | HA93: =SUMPRODUCT($B93:$GQ93,INDEX(PLAN_PRODUCCION!$B$4:$GQ$24,COLUMN()-COLUMN($GZ$1)+1,0)) -> 0 | HB93: =SUMPRODUCT($B93:$GQ93,INDEX(PLAN_PRODUCCION!$B$4:$GQ$24,COLUMN()-COLUMN($GZ$1)+1,0)) -> 0 | HC93: =SUMPRODUCT($B93:$GQ93,INDEX(PLAN_PRODUCCION!$B$4:$GQ$24,COLUMN()-COLUMN($GZ$1)+1,0)) -> 0 | HD93: =SUMPRODUCT($B93:$GQ93,INDEX(PLAN_PRODUCCION!$B$4:$GQ$24,COLUMN()-COLUMN($GZ$1)+1,0)) -> 0 | HE93: =SUMPRODUCT($B93:$GQ93,INDEX(PLAN_PRODUCCION!$B$4:$GQ$24,COLUMN()-COLUMN($GZ$1)+1,0)) -> 0 | HF93: =SUMPRODUCT($B93:$GQ93,INDEX(PLAN_PRODUCCION!$B$4:$GQ$24,COLUMN()-COLUMN($GZ$1)+1,0)) -> 0 | HG93: =SUMPRODUCT($B93:$GQ93,INDEX(PLAN_PRODUCCION!$B$4:$GQ$24,COLUMN()-COLUMN($GZ$1)+1,0)) -> 0 | ... HT93: =SUMPRODUCT($B93:$GQ93,INDEX(PLAN_PRODUCCION!$B$4:$GQ$24,COLUMN()-COLUMN($GZ$1)+1,0)) -> 0 | HW93: =DIM_BILL[[#This Row],[Tipo]]
A94: MEP-0098 | CN94: 1 | GR94: BOLSA STAND POUCH COLAGENO 6g MARACUYA | GS94: 2 | GV94: =SUMIF(FACT_A1[cve_prod],DIM_BILL[[#This Row],[CODIGO]],FACT_A1[Existencia]) -> 0 | GW94: =SUMIF(FACT_A2[cve_prod],DIM_BILL[[#This Row],[CODIGO]],FACT_A2[Existencia]) -> 0 | GY94: Cortos + PO's Confirmadas | GZ94: =GV94+GW94+GX94+GZ92-GZ93 -> 0 | HA94: =GZ94+HA92-HA93 -> 0 | HB94: =HA94+HB92-HB93 -> 0 | HC94: =HB94+HC92-HC93 -> 0 | HD94: =HC94+HD92-HD93 -> 0 | HE94: =HD94+HE92-HE93 -> 0 | HF94: =HE94+HF92-HF93 -> 0 | HG94: =HF94+HG92-HG93 -> 0 | HH94: =HG94+HH92-HH93 -> 0 | ... HT94: =HS94+HT92-HT93 -> 0 | HU94: =COUNTIF(GZ94:HT94,"<0") -> 0 | HW94: =DIM_BILL[[#This Row],[Tipo]]
A95: MEP-0099 | CN95: 1 | GR95: CUCHARA DOSIFICADORA 30 ML | GS95: 2 | GV95: =SUMIF(FACT_A1[cve_prod],DIM_BILL[[#This Row],[CODIGO]],FACT_A1[Existencia]) -> 0 | GW95: =SUMIF(FACT_A2[cve_prod],DIM_BILL[[#This Row],[CODIGO]],FACT_A2[Existencia]) -> 0 | GY95: Por Surtir & Parcial | GZ95: =SUMIFS(POs[saldo],POs[cve_prod],DIM_BILL[[#This Row],[CODIGO]],POs[status],$GY95,POs[f_ent],GZ$1) -> 0 | HA95: =SUMIFS(POs[saldo],POs[cve_prod],DIM_BILL[[#This Row],[CODIGO]],POs[status],$GY95,POs[f_ent],HA$1) -> 0 | HB95: =SUMIFS(POs[saldo],POs[cve_prod],DIM_BILL[[#This Row],[CODIGO]],POs[status],$GY95,POs[f_ent],HB$1) -> 0 | HC95: =SUMIFS(POs[saldo],POs[cve_prod],DIM_BILL[[#This Row],[CODIGO]],POs[status],$GY95,POs[f_ent],HC$1) -> 0 | HD95: =SUMIFS(POs[saldo],POs[cve_prod],DIM_BILL[[#This Row],[CODIGO]],POs[status],$GY95,POs[f_ent],HD$1) -> 0 | HE95: =SUMIFS(POs[saldo],POs[cve_prod],DIM_BILL[[#This Row],[CODIGO]],POs[status],$GY95,POs[f_ent],HE$1) -> 0 | HF95: =SUMIFS(POs[saldo],POs[cve_prod],DIM_BILL[[#This Row],[CODIGO]],POs[status],$GY95,POs[Semana],WEEKNUM(HF$1)) -> 0 | HG95: =SUMIFS(POs[saldo],POs[cve_prod],DIM_BILL[[#This Row],[CODIGO]],POs[status],$GY95,POs[Semana],WEEKNUM(HG$1)) -> 0 | HH95: =SUMIFS(POs[saldo],POs[cve_prod],DIM_BILL[[#This Row],[CODIGO]],POs[status],$GY95,POs[Semana],WEEKNUM(HH$1)) -> 0 | HI95: =SUMIFS(POs[saldo],POs[cve_prod],DIM_BILL[[#This Row],[CODIGO]],POs[status],$GY95,POs[Semana],WEEKNUM(HI$1)) -> 0 | HJ95: =SUMIFS(POs[saldo],POs[cve_prod],DIM_BILL[[#This Row],[CODIGO]],POs[status],$GY95,POs[Semana],WEEKNUM(HJ$1)) -> 0 | HK95: =SUMIFS(POs[saldo],POs[cve_prod],DIM_BILL[[#This Row],[CODIGO]],POs[status],$GY95,POs[Semana],WEEKNUM(HK$1)) -> 0 | HL95: =SUMIFS(POs[saldo],POs[cve_prod],DIM_BILL[[#This Row],[CODIGO]],POs[status],$GY95,POs[Semana],WEEKNUM(HL$1)) -> 0 | HM95: =SUMIFS(POs[saldo],POs[cve_prod],DIM_BILL[[#This Row],[CODIGO]],POs[status],$GY95,POs[Semana],WEEKNUM(HM$1)) -> 0 | ... HT95: =SUMIFS(POs[saldo],POs[cve_prod],DIM_BILL[[#This Row],[CODIGO]],POs[status],$GY95,POs[Semana],WEEKNUM(HT$1)) -> 0 | HW95: =DIM_BILL[[#This Row],[Tipo]]
A96: MEP-0099 | CN96: 1 | GR96: CUCHARA DOSIFICADORA 30 ML | GS96: 2 | GV96: =SUMIF(FACT_A1[cve_prod],DIM_BILL[[#This Row],[CODIGO]],FACT_A1[Existencia]) -> 0 | GW96: =SUMIF(FACT_A2[cve_prod],DIM_BILL[[#This Row],[CODIGO]],FACT_A2[Existencia]) -> 0 | GY96: Demanda | GZ96: =SUMPRODUCT($B96:$GQ96,INDEX(PLAN_PRODUCCION!$B$4:$GQ$24,COLUMN()-COLUMN($GZ$1)+1,0)) -> 0 | HA96: =SUMPRODUCT($B96:$GQ96,INDEX(PLAN_PRODUCCION!$B$4:$GQ$24,COLUMN()-COLUMN($GZ$1)+1,0)) -> 0 | HB96: =SUMPRODUCT($B96:$GQ96,INDEX(PLAN_PRODUCCION!$B$4:$GQ$24,COLUMN()-COLUMN($GZ$1)+1,0)) -> 0 | HC96: =SUMPRODUCT($B96:$GQ96,INDEX(PLAN_PRODUCCION!$B$4:$GQ$24,COLUMN()-COLUMN($GZ$1)+1,0)) -> 0 | HD96: =SUMPRODUCT($B96:$GQ96,INDEX(PLAN_PRODUCCION!$B$4:$GQ$24,COLUMN()-COLUMN($GZ$1)+1,0)) -> 0 | HE96: =SUMPRODUCT($B96:$GQ96,INDEX(PLAN_PRODUCCION!$B$4:$GQ$24,COLUMN()-COLUMN($GZ$1)+1,0)) -> 0 | HF96: =SUMPRODUCT($B96:$GQ96,INDEX(PLAN_PRODUCCION!$B$4:$GQ$24,COLUMN()-COLUMN($GZ$1)+1,0)) -> 0 | HG96: =SUMPRODUCT($B96:$GQ96,INDEX(PLAN_PRODUCCION!$B$4:$GQ$24,COLUMN()-COLUMN($GZ$1)+1,0)) -> 0 | ... HT96: =SUMPRODUCT($B96:$GQ96,INDEX(PLAN_PRODUCCION!$B$4:$GQ$24,COLUMN()-COLUMN($GZ$1)+1,0)) -> 0 | HW96: =DIM_BILL[[#This Row],[Tipo]]
A97: MEP-0099 | CN97: 1 | GR97: CUCHARA DOSIFICADORA 30 ML | GS97: 2 | GV97: =SUMIF(FACT_A1[cve_prod],DIM_BILL[[#This Row],[CODIGO]],FACT_A1[Existencia]) -> 0 | GW97: =SUMIF(FACT_A2[cve_prod],DIM_BILL[[#This Row],[CODIGO]],FACT_A2[Existencia]) -> 0 | GY97: Cortos + PO's Confirmadas | GZ97: =GV97+GW97+GX97+GZ95-GZ96 -> 0 | HA97: =GZ97+HA95-HA96 -> 0 | HB97: =HA97+HB95-HB96 -> 0 | HC97: =HB97+HC95-HC96 -> 0 | HD97: =HC97+HD95-HD96 -> 0 | HE97: =HD97+HE95-HE96 -> 0 | HF97: =HE97+HF95-HF96 -> 0 | HG97: =HF97+HG95-HG96 -> 0 | HH97: =HG97+HH95-HH96 -> 0 | ... HT97: =HS97+HT95-HT96 -> 0 | HU97: =COUNTIF(GZ97:HT97,"<0") -> 0 | HW97: =DIM_BILL[[#This Row],[Tipo]]
A98: MEP-0104 | BK98: 1.02 | GR98: FRASCO 240 ML. AMBAR R-24 | GS98: 2 | GT98: XIOMARA GONZALEZ LOPEZ | GU98: MATERIAL DE EMPAQUE | GV98: =SUMIF(FACT_A1[cve_prod],DIM_BILL[[#This Row],[CODIGO]],FACT_A1[Existencia]) -> 0 | GW98: =SUMIF(FACT_A2[cve_prod],DIM_BILL[[#This Row],[CODIGO]],FACT_A2[Existencia]) -> 12399 | GY98: Por Surtir & Parcial | GZ98: =SUMIFS(POs[saldo],POs[cve_prod],DIM_BILL[[#This Row],[CODIGO]],POs[status],$GY98,POs[f_ent],GZ$1) -> 0 | HA98: =SUMIFS(POs[saldo],POs[cve_prod],DIM_BILL[[#This Row],[CODIGO]],POs[status],$GY98,POs[f_ent],HA$1) -> 0 | HB98: =SUMIFS(POs[saldo],POs[cve_prod],DIM_BILL[[#This Row],[CODIGO]],POs[status],$GY98,POs[f_ent],HB$1) -> 0 | HC98: =SUMIFS(POs[saldo],POs[cve_prod],DIM_BILL[[#This Row],[CODIGO]],POs[status],$GY98,POs[f_ent],HC$1) -> 0 | HD98: =SUMIFS(POs[saldo],POs[cve_prod],DIM_BILL[[#This Row],[CODIGO]],POs[status],$GY98,POs[f_ent],HD$1) -> 0 | HE98: =SUMIFS(POs[saldo],POs[cve_prod],DIM_BILL[[#This Row],[CODIGO]],POs[status],$GY98,POs[f_ent],HE$1) -> 0 | HF98: =SUMIFS(POs[saldo],POs[cve_prod],DIM_BILL[[#This Row],[CODIGO]],POs[status],$GY98,POs[Semana],WEEKNUM(HF$1)) -> 0 | HG98: =SUMIFS(POs[saldo],POs[cve_prod],DIM_BILL[[#This Row],[CODIGO]],POs[status],$GY98,POs[Semana],WEEKNUM(HG$1)) -> 0 | HH98: =SUMIFS(POs[saldo],POs[cve_prod],DIM_BILL[[#This Row],[CODIGO]],POs[status],$GY98,POs[Semana],WEEKNUM(HH$1)) -> 0 | HI98: =SUMIFS(POs[saldo],POs[cve_prod],DIM_BILL[[#This Row],[CODIGO]],POs[status],$GY98,POs[Semana],WEEKNUM(HI$1)) -> 0 | HJ98: =SUMIFS(POs[saldo],POs[cve_prod],DIM_BILL[[#This Row],[CODIGO]],POs[status],$GY98,POs[Semana],WEEKNUM(HJ$1)) -> 0 | HK98: =SUMIFS(POs[saldo],POs[cve_prod],DIM_BILL[[#This Row],[CODIGO]],POs[status],$GY98,POs[Semana],WEEKNUM(HK$1)) -> 0 | HL98: =SUMIFS(POs[saldo],POs[cve_prod],DIM_BILL[[#This Row],[CODIGO]],POs[status],$GY98,POs[Semana],WEEKNUM(HL$1)) -> 0 | HM98: =SUMIFS(POs[saldo],POs[cve_prod],DIM_BILL[[#This Row],[CODIGO]],POs[status],$GY98,POs[Semana],WEEKNUM(HM$1)) -> 0 | ... HT98: =SUMIFS(POs[saldo],POs[cve_prod],DIM_BILL[[#This Row],[CODIGO]],POs[status],$GY98,POs[Semana],WEEKNUM(HT$1)) -> 0 | HW98: =DIM_BILL[[#This Row],[Tipo]] -> MATERIAL DE EMPAQUE
A99: MEP-0104 | BK99: 1.02 | GR99: FRASCO 240 ML. AMBAR R-24 | GS99: 2 | GT99: XIOMARA GONZALEZ LOPEZ | GU99: MATERIAL DE EMPAQUE | GV99: =SUMIF(FACT_A1[cve_prod],DIM_BILL[[#This Row],[CODIGO]],FACT_A1[Existencia]) -> 0 | GW99: =SUMIF(FACT_A2[cve_prod],DIM_BILL[[#This Row],[CODIGO]],FACT_A2[Existencia]) -> 12399 | GY99: Demanda | GZ99: =SUMPRODUCT($B99:$GQ99,INDEX(PLAN_PRODUCCION!$B$4:$GQ$24,COLUMN()-COLUMN($GZ$1)+1,0)) -> 16320 | HA99: =SUMPRODUCT($B99:$GQ99,INDEX(PLAN_PRODUCCION!$B$4:$GQ$24,COLUMN()-COLUMN($GZ$1)+1,0)) -> 0 | HB99: =SUMPRODUCT($B99:$GQ99,INDEX(PLAN_PRODUCCION!$B$4:$GQ$24,COLUMN()-COLUMN($GZ$1)+1,0)) -> 0 | HC99: =SUMPRODUCT($B99:$GQ99,INDEX(PLAN_PRODUCCION!$B$4:$GQ$24,COLUMN()-COLUMN($GZ$1)+1,0)) -> 0 | HD99: =SUMPRODUCT($B99:$GQ99,INDEX(PLAN_PRODUCCION!$B$4:$GQ$24,COLUMN()-COLUMN($GZ$1)+1,0)) -> 0 | HE99: =SUMPRODUCT($B99:$GQ99,INDEX(PLAN_PRODUCCION!$B$4:$GQ$24,COLUMN()-COLUMN($GZ$1)+1,0)) -> 0 | HF99: =SUMPRODUCT($B99:$GQ99,INDEX(PLAN_PRODUCCION!$B$4:$GQ$24,COLUMN()-COLUMN($GZ$1)+1,0)) -> 0 | HG99: =SUMPRODUCT($B99:$GQ99,INDEX(PLAN_PRODUCCION!$B$4:$GQ$24,COLUMN()-COLUMN($GZ$1)+1,0)) -> 0 | ... HT99: =SUMPRODUCT($B99:$GQ99,INDEX(PLAN_PRODUCCION!$B$4:$GQ$24,COLUMN()-COLUMN($GZ$1)+1,0)) -> 0 | HW99: =DIM_BILL[[#This Row],[Tipo]] -> MATERIAL DE EMPAQUE
A100: MEP-0104 | BK100: 1.02 | GR100: FRASCO 240 ML. AMBAR R-24 | GS100: 2 | GT100: XIOMARA GONZALEZ LOPEZ | GU100: MATERIAL DE EMPAQUE | GV100: =SUMIF(FACT_A1[cve_prod],DIM_BILL[[#This Row],[CODIGO]],FACT_A1[Existencia]) -> 0 | GW100: =SUMIF(FACT_A2[cve_prod],DIM_BILL[[#This Row],[CODIGO]],FACT_A2[Existencia]) -> 12399 | GY100: Cortos + PO's Confirmadas | GZ100: =GV100+GW100+GX100+GZ98-GZ99 -> -3921 | HA100: =GZ100+HA98-HA99 -> -3921 | HB100: =HA100+HB98-HB99 -> -3921 | HC100: =HB100+HC98-HC99 -> -3921 | HD100: =HC100+HD98-HD99 -> -3921 | HE100: =HD100+HE98-HE99 -> -3921 | HF100: =HE100+HF98-HF99 -> -3921 | HG100: =HF100+HG98-HG99 -> -3921 | HH100: =HG100+HH98-HH99 -> -3921 | ... HT100: =HS100+HT98-HT99 -> -3921 | HU100: =COUNTIF(GZ100:HT100,"<0") -> 21 | HW100: =DIM_BILL[[#This Row],[Tipo]] -> MATERIAL DE EMPAQUE
...

Sheet FACT_Explosion
A1: CODIGO | B1: DESCRIPCION | C1: PROVEEDOR | D1: TIPO | E1: LT | F1: INVENTARIO | G1: AGOSTO | H1: SEPTIEMBRE | I1: OCTUBRE | J1: NOVIEMBRE | K1: DICIEMBRE
A2: M1CBOM03 | B2: OMEGA 3 CÁPSULA BLANDA EPA 33/ DHA 22 | C2: LINDY PHARMA | D2: MATERIA PRIMA | E2: =_xlfn.XLOOKUP(FACT_Explosion[[#This Row],[CODIGO]],Proveedores[CODIGO],Proveedores[TIEMPOS DE ENTREGA],0,0,1) -> 3 semana(s) | F2: =_xlfn.XLOOKUP(FACT_Explosion[[#This Row],[CODIGO]],FACT_A2[cve_prod],FACT_A2[Existencia],0,0,1) -> 271166.8 | G2: 714571.7 | H2: 435138.94 | I2: 450138.94 | J2: 375123.5 | K2: 375123.5
A3: MPA-0421 | B3: PEPINO EN POLVO | C3: 2G NUTRITION SAS DE CV | D3: MATERIA PRIMA | E3: =_xlfn.XLOOKUP(FACT_Explosion[[#This Row],[CODIGO]],Proveedores[CODIGO],Proveedores[TIEMPOS DE ENTREGA],0,0,1) -> 3 semana(s) | F3: =_xlfn.XLOOKUP(FACT_Explosion[[#This Row],[CODIGO]],FACT_A2[cve_prod],FACT_A2[Existencia],0,0,1) -> 13.044 | G3: 2.55255 | H3: 1.426425 | I3: 1.35135 | J3: 1.35135 | K3: 1.35135
A4: MEP-0365 | B4: FRASCO BLANCO 150 mL | C4: POLIMEROS ENVASES Y TAPAS TAPATIOS | D4: MATERIAL DE EMPAQUE | E4: =_xlfn.XLOOKUP(FACT_Explosion[[#This Row],[CODIGO]],Proveedores[CODIGO],Proveedores[TIEMPOS DE ENTREGA],0,0,1) -> 3 semnas | F4: =_xlfn.XLOOKUP(FACT_Explosion[[#This Row],[CODIGO]],FACT_A2[cve_prod],FACT_A2[Existencia],0,0,1) -> 24480 | G4: 17932.74 | H4: 14687 | I4: 14687 | J4: 9437 | K4: 9437
A5: MPD-0093 | B5: COLOR CARAMELO 605 polvo | C5: ADITIVES & COLORS S.A. DE C.V. | D5: MATERIA PRIMA | E5: =_xlfn.XLOOKUP(FACT_Explosion[[#This Row],[CODIGO]],Proveedores[CODIGO],Proveedores[TIEMPOS DE ENTREGA],0,0,1) -> 0 | F5: =_xlfn.XLOOKUP(FACT_Explosion[[#This Row],[CODIGO]],FACT_A2[cve_prod],FACT_A2[Existencia],0,0,1) -> 0 | G5: 0 | H5: 0 | I5: 0 | J5: 0 | K5: 0
A6: MEP-0355 | B6: TAPA R-38 CHILD BLANCA C/LINNER IND/ALUM | C6: INDUSTRIAS BOGRI SA DE CV | D6: MATERIAL DE EMPAQUE | E6: =_xlfn.XLOOKUP(FACT_Explosion[[#This Row],[CODIGO]],Proveedores[CODIGO],Proveedores[TIEMPOS DE ENTREGA],0,0,1) -> 5 Semanas | F6: =_xlfn.XLOOKUP(FACT_Explosion[[#This Row],[CODIGO]],FACT_A2[cve_prod],FACT_A2[Existencia],0,0,1) -> 39498 | G6: 27632.457 | H6: 69150.542 | I6: 15967.892 | J6: 20628.818 | K6: 43153.818
A7: MPE-0023 | B7: ISOMALTULOSA | C7: ALFAMEX INDUSTRIAL S.A DE C.V. | D7: MATERIA PRIMA | E7: =_xlfn.XLOOKUP(FACT_Explosion[[#This Row],[CODIGO]],Proveedores[CODIGO],Proveedores[TIEMPOS DE ENTREGA],0,0,1) -> 1 semana(s) | F7: =_xlfn.XLOOKUP(FACT_Explosion[[#This Row],[CODIGO]],FACT_A2[cve_prod],FACT_A2[Existencia],0,0,1) -> 1883.6553 | G7: 1571.8481 | H7: 1256.6815 | I7: 761.97312 | J7: 704.97312 | K7: 769.02312
A8: MEP-0118 | B8: SILICA GEL 0.5 GR | C8: COPALU INSUMOS SA DE CV | D8: MATERIAL DE EMPAQUE | E8: =_xlfn.XLOOKUP(FACT_Explosion[[#This Row],[CODIGO]],Proveedores[CODIGO],Proveedores[TIEMPOS DE ENTREGA],0,0,1) -> 2 semana(s) | F8: =_xlfn.XLOOKUP(FACT_Explosion[[#This Row],[CODIGO]],FACT_A2[cve_prod],FACT_A2[Existencia],0,0,1) -> 196000 | G8: 373112.22 | H8: 219692.16 | I8: 210514.68 | J8: 156794.94 | K8: 177301.94
A9: MPA-0177 | B9: SULFATO DE POTASIO | C9: ALMACEN DE DROGAS LA PAZ S.A DE C.V. | D9: MATERIA PRIMA | E9: =_xlfn.XLOOKUP(FACT_Explosion[[#This Row],[CODIGO]],Proveedores[CODIGO],Proveedores[TIEMPOS DE ENTREGA],0,0,1) -> 1 semana(s) | F9: =_xlfn.XLOOKUP(FACT_Explosion[[#This Row],[CODIGO]],FACT_A2[cve_prod],FACT_A2[Existencia],0,0,1) -> 5 | G9: 1.6418015 | H9: 1.3895684 | I9: 1.0448147 | J9: 1.0448147 | K9: 1.0448147
A10: MPD-0070 | B10: CLORURO DE SODIO | C10: ALMACEN DE DROGAS LA PAZ S.A DE C.V. | D10: MATERIA PRIMA | E10: =_xlfn.XLOOKUP(FACT_Explosion[[#This Row],[CODIGO]],Proveedores[CODIGO],Proveedores[TIEMPOS DE ENTREGA],0,0,1) -> 1 semana(s) | F10: =_xlfn.XLOOKUP(FACT_Explosion[[#This Row],[CODIGO]],FACT_A2[cve_prod],FACT_A2[Existencia],0,0,1) -> 222.339 | G10: 298.9402 | H10: 68.146333 | I10: 34.787333 | J10: 50.316333 | K10: 90.343333
A11: MES-0253 | B11: DIVISION PARA CAJA COLECTIVA 50 ESPACIOS | C11: YADIRA TERRONES MENDOZA | D11: MATERIAL DE EMPAQUE | E11: =_xlfn.XLOOKUP(FACT_Explosion[[#This Row],[CODIGO]],Proveedores[CODIGO],Proveedores[TIEMPOS DE ENTREGA],0,0,1) -> 3 semana(s) | F11: =_xlfn.XLOOKUP(FACT_Explosion[[#This Row],[CODIGO]],FACT_A2[cve_prod],FACT_A2[Existencia],0,0,1) -> 7295 | G11: 11215.902 | H11: 5171.5574 | I11: 6362.7348 | J11: 4251.5502 | K11: 4761.5502
A12: MES-0253 | B12: DIVISION PARA CAJA COLECTIVA 50 ESPACIOS | C12: YADIRA TERRONES MENDOZA | D12: MATERIAL DE EMPAQUE | E12: =_xlfn.XLOOKUP(FACT_Explosion[[#This Row],[CODIGO]],Proveedores[CODIGO],Proveedores[TIEMPOS DE ENTREGA],0,0,1) -> 3 semana(s) | F12: =_xlfn.XLOOKUP(FACT_Explosion[[#This Row],[CODIGO]],FACT_A2[cve_prod],FACT_A2[Existencia],0,0,1) -> 7295 | G12: 11215.902 | H12: 5171.5574 | I12: 6362.7348 | J12: 4251.5502 | K12: 4761.5502
A13: MPD-0085 | B13: CARBONATO DE POTASIO | C13: ALQUIMIA MEXICANA S DE RL | D13: MATERIA PRIMA | E13: =_xlfn.XLOOKUP(FACT_Explosion[[#This Row],[CODIGO]],Proveedores[CODIGO],Proveedores[TIEMPOS DE ENTREGA],0,0,1) -> 2 semana(s) | F13: =_xlfn.XLOOKUP(FACT_Explosion[[#This Row],[CODIGO]],FACT_A2[cve_prod],FACT_A2[Existencia],0,0,1) -> 435.485 | G13: 1.1825 | H13: 0.5375 | I13: 123.8975 | J13: 0.5375 | K13: 0.5375
... A96: MPA-0143 | B96: PULPA DE PIÑA EN POLVO SPRAY DRIED | C96: CAROLINA PEREZ GOMEZ | D96: MATERIA PRIMA | E96: =_xlfn.XLOOKUP(FACT_Explosion[[#This Row],[CODIGO]],Proveedores[CODIGO],Proveedores[TIEMPOS DE ENTREGA],0,0,1) -> 2 semana(s) | F96: =_xlfn.XLOOKUP(FACT_Explosion[[#This Row],[CODIGO]],FACT_A2[cve_prod],FACT_A2[Existencia],0,0,1) -> 44.675 | G96: 4.335 | H96: 4.335 | I96: 0 | J96: 8.67 | K96: 4.335
A97: MPA-0191 | B97: VITAMINA D3 (COLECALCIFEROL) | D97: MATERIA PRIMA | E97: =_xlfn.XLOOKUP(FACT_Explosion[[#This Row],[CODIGO]],Proveedores[CODIGO],Proveedores[TIEMPOS DE ENTREGA],0,0,1) -> 0 | F97: =_xlfn.XLOOKUP(FACT_Explosion[[#This Row],[CODIGO]],FACT_A2[cve_prod],FACT_A2[Existencia],0,0,1) -> 0.002546 | G97: 0.0060748927 | H97: 0.00619 | I97: 0.00435 | J97: 0.00435 | K97: 0.00435
A98: MPA-0219 | B98: TAMARINDO EN POLVO SANITIZADO | C98: CAROLINA PEREZ GOMEZ | D98: MATERIA PRIMA | E98: =_xlfn.XLOOKUP(FACT_Explosion[[#This Row],[CODIGO]],Proveedores[CODIGO],Proveedores[TIEMPOS DE ENTREGA],0,0,1) -> 2 semana(s) | F98: =_xlfn.XLOOKUP(FACT_Explosion[[#This Row],[CODIGO]],FACT_A2[cve_prod],FACT_A2[Existencia],0,0,1) -> 150 | G98: 90.749753 | H98: 48.674876 | I98: 42.074876 | J98: 38.774876 | K98: 38.774876
A99: MES-0229 | B99: CAJA AZVITE / 30 Cápsulas | C99: Imprenta Comercial el debate SA DE CV | D99: MATERIAL DE EMPAQUE | E99: =_xlfn.XLOOKUP(FACT_Explosion[[#This Row],[CODIGO]],Proveedores[CODIGO],Proveedores[TIEMPOS DE ENTREGA],0,0,1) -> 3 semana(s) | F99: =_xlfn.XLOOKUP(FACT_Explosion[[#This Row],[CODIGO]],FACT_A2[cve_prod],FACT_A2[Existencia],0,0,1) -> 3985 | G99: 1010 | H99: 1010 | I99: 606 | J99: 606 | K99: 606
A100: MPA-0220 | B100: CIRUELA EN POLVO SANITIZADO | C100: CAROLINA PEREZ GOMEZ | D100: MATERIA PRIMA | E100: =_xlfn.XLOOKUP(FACT_Explosion[[#This Row],[CODIGO]],Proveedores[CODIGO],Proveedores[TIEMPOS DE ENTREGA],0,0,1) -> 2 semana(s) | F100: =_xlfn.XLOOKUP(FACT_Explosion[[#This Row],[CODIGO]],FACT_A2[cve_prod],FACT_A2[Existencia],0,0,1) -> 145 | G100: 82.499775 | H100: 44.249888 | I100: 38.249888 | J100: 35.249888 | K100: 35.249888
A101: MES-0458 | B101: CAJA INDIVIDUAL AZ VITE CON 2 CAPS | C101: Imprenta Comercial el debate SA DE CV | D101: MATERIAL DE EMPAQUE | E101: =_xlfn.XLOOKUP(FACT_Explosion[[#This Row],[CODIGO]],Proveedores[CODIGO],Proveedores[TIEMPOS DE ENTREGA],0,0,1) -> 0 | F101: =_xlfn.XLOOKUP(FACT_Explosion[[#This Row],[CODIGO]],FACT_A2[cve_prod],FACT_A2[Existencia],0,0,1) -> 0 | G101: 2525 | H101: 0 | I101: 0 | J101: 0 | K101: 0
A102: MPA-0314 | B102: PULPA DE PAPAYA DESHIDRATADA EN POLVO | C102: CAROLINA PEREZ GOMEZ | D102: MATERIA PRIMA | E102: =_xlfn.XLOOKUP(FACT_Explosion[[#This Row],[CODIGO]],Proveedores[CODIGO],Proveedores[TIEMPOS DE ENTREGA],0,0,1) -> 2 semana(s) | F102: =_xlfn.XLOOKUP(FACT_Explosion[[#This Row],[CODIGO]],FACT_A2[cve_prod],FACT_A2[Existencia],0,0,1) -> 0 | G102: 0 | H102: 4.5 | I102: 0 | J102: 3.75 | K102: 0
A103: MPA-0158 | B103: RHODIOLA ROSEAU EXTRACTO SECO AL 3% | C103: GIVAUDAN DE MEXICO | D103: MATERIA PRIMA | E103: =_xlfn.XLOOKUP(FACT_Explosion[[#This Row],[CODIGO]],Proveedores[CODIGO],Proveedores[TIEMPOS DE ENTREGA],0,0,1) -> 15 semana(s) | F103: =_xlfn.XLOOKUP(FACT_Explosion[[#This Row],[CODIGO]],FACT_A2[cve_prod],FACT_A2[Existencia],0,0,1) -> 102.639 | G103: 15.558 | H103: 9 | I103: 10.8 | J103: 8.1 | K103: 8.1
A104: MPA-0352 | B104: CACAO EN POLVO | C104: CAROLINA PEREZ GOMEZ | D104: MATERIA PRIMA | E104: =_xlfn.XLOOKUP(FACT_Explosion[[#This Row],[CODIGO]],Proveedores[CODIGO],Proveedores[TIEMPOS DE ENTREGA],0,0,1) -> 2 semana(s) | F104: =_xlfn.XLOOKUP(FACT_Explosion[[#This Row],[CODIGO]],FACT_A2[cve_prod],FACT_A2[Existencia],0,0,1) -> 44.19 | G104: 0 | H104: 0 | I104: 0 | J104: 0 | K104: 0
A105: MPA-0283 | B105: L TEANINA 98% | C105: PRONAQUIM SA DE CV | D105: MATERIA PRIMA | E105: =_xlfn.XLOOKUP(FACT_Explosion[[#This Row],[CODIGO]],Proveedores[CODIGO],Proveedores[TIEMPOS DE ENTREGA],0,0,1) -> 1 semana(s) | F105: =_xlfn.XLOOKUP(FACT_Explosion[[#This Row],[CODIGO]],FACT_A2[cve_prod],FACT_A2[Existencia],0,0,1) -> 133.82 | G105: 26.113672 | H105: 25.242786 | I105: 13.260036 | J105: 30.560036 | K105: 20.560036
A106: MPA-0377 | B106: ESPINACA EN POLVO | C106: CAROLINA PEREZ GOMEZ | D106: MATERIA PRIMA | E106: =_xlfn.XLOOKUP(FACT_Explosion[[#This Row],[CODIGO]],Proveedores[CODIGO],Proveedores[TIEMPOS DE ENTREGA],0,0,1) -> 3 semana(s) | F106: =_xlfn.XLOOKUP(FACT_Explosion[[#This Row],[CODIGO]],FACT_A2[cve_prod],FACT_A2[Existencia],0,0,1) -> 1593.694 | G106: 1061.948 | H106: 195.338 | I106: 577.74 | J106: 484.208 | K106: 378.265
A107: MEP-0441 | B107: TAPA FLIP TOP R-38 DORADA C/LINNER INDUC | C107: POLIMEROS ENVASES Y TAPAS TAPATIOS | D107: MATERIAL DE EMPAQUE | E107: =_xlfn.XLOOKUP(FACT_Explosion[[#This Row],[CODIGO]],Proveedores[CODIGO],Proveedores[TIEMPOS DE ENTREGA],0,0,1) -> 3 semnas | F107: =_xlfn.XLOOKUP(FACT_Explosion[[#This Row],[CODIGO]],FACT_A2[cve_prod],FACT_A2[Existencia],0,0,1) -> 34150 | G107: 128138.56 | H107: 66511.5 | I107: 76125.5 | J107: 66402 | K107: 66402
A108: MPA-0397 | B108: TÉ VERDE (MATCHA) | C108: CAROLINA PEREZ GOMEZ | D108: MATERIA PRIMA | E108: =_xlfn.XLOOKUP(FACT_Explosion[[#This Row],[CODIGO]],Proveedores[CODIGO],Proveedores[TIEMPOS DE ENTREGA],0,0,1) -> 2 semana(s) | F108: =_xlfn.XLOOKUP(FACT_Explosion[[#This Row],[CODIGO]],FACT_A2[cve_prod],FACT_A2[Existencia],0,0,1) -> 22.84 | G108: 0 | H108: 0 | I108: 0 | J108: 0 | K108: 0
A109: MES-0581 | B109: ETIQUETA BIODIOLA FCO C/30 CAPSULAS | C109: ETIPRESS DE MEXICO | D109: MATERIAL DE EMPAQUE | E109: =_xlfn.XLOOKUP(FACT_Explosion[[#This Row],[CODIGO]],Proveedores[CODIGO],Proveedores[TIEMPOS DE ENTREGA],0,0,1) -> 4 semana (s) | F109: =_xlfn.XLOOKUP(FACT_Explosion[[#This Row],[CODIGO]],FACT_A2[cve_prod],FACT_A2[Existencia],0,0,1) -> 3000 | G109: 397.58 | H109: 1236 | I109: 1236 | J109: 1236 | K109: 1236
... A605: MES-0589 | B605: ETIQ. TAB EFERV VIT. C 20TAB AL NATURAL | C605: sin proveedor | D605: MATERIAL DE EMPAQUE | E605: =_xlfn.XLOOKUP(FACT_Explosion[[#This Row],[CODIGO]],Proveedores[CODIGO],Proveedores[TIEMPOS DE ENTREGA],0,0,1) -> 0 | F605: =_xlfn.XLOOKUP(FACT_Explosion[[#This Row],[CODIGO]],FACT_A2[cve_prod],FACT_A2[Existencia],0,0,1) -> 15300 | G605: 4200 | H605: 4200 | I605: 0 | J605: 0 | K605: 0
A606: MES-0673 | B606: ETIQ. LONGEVITAL OMEGA 3 (DHA/EPA) C/60 | E606: =_xlfn.XLOOKUP(FACT_Explosion[[#This Row],[CODIGO]],Proveedores[CODIGO],Proveedores[TIEMPOS DE ENTREGA],0,0,1) -> 0 | F606: =_xlfn.XLOOKUP(FACT_Explosion[[#This Row],[CODIGO]],FACT_A2[cve_prod],FACT_A2[Existencia],0,0,1) -> 0 | G606: 0 | H606: 0 | I606: 0 | J606: 0 | K606: 0
A607: M1CBOM04 | B607: OMEGA 3 KRILL CÁPSULA BLANDA | E607: =_xlfn.XLOOKUP(FACT_Explosion[[#This Row],[CODIGO]],Proveedores[CODIGO],Proveedores[TIEMPOS DE ENTREGA],0,0,1) -> 0 | F607: =_xlfn.XLOOKUP(FACT_Explosion[[#This Row],[CODIGO]],FACT_A2[cve_prod],FACT_A2[Existencia],0,0,1) -> 21340 | G607: 0 | H607: 0 | I607: 0 | J607: 0 | K607: 0
A608: 41CPAM01 | B608: AMBROTOSE AO CAPSULAS MANNATECH | E608: =_xlfn.XLOOKUP(FACT_Explosion[[#This Row],[CODIGO]],Proveedores[CODIGO],Proveedores[TIEMPOS DE ENTREGA],0,0,1) -> 0 | F608: =_xlfn.XLOOKUP(FACT_Explosion[[#This Row],[CODIGO]],FACT_A2[cve_prod],FACT_A2[Existencia],0,0,1) -> 0 | G608: 0 | H608: 60000 | I608: 0 | J608: 0 | K608: 0
A609: MEP-0492 | B609: FRASCO Y TAPA WU NUTRITION | E609: =_xlfn.XLOOKUP(FACT_Explosion[[#This Row],[CODIGO]],Proveedores[CODIGO],Proveedores[TIEMPOS DE ENTREGA],0,0,1) -> 0 | F609: =_xlfn.XLOOKUP(FACT_Explosion[[#This Row],[CODIGO]],FACT_A2[cve_prod],FACT_A2[Existencia],0,0,1) -> 0 | G609: 15408.8 | H609: 0 | I609: 8755 | J609: 8755 | K609: 8755
A610: MES-0696 | B610: ETIQUETA WU NUTRITION BERBERINA C/120 CA | E610: =_xlfn.XLOOKUP(FACT_Explosion[[#This Row],[CODIGO]],Proveedores[CODIGO],Proveedores[TIEMPOS DE ENTREGA],0,0,1) -> 0 | F610: =_xlfn.XLOOKUP(FACT_Explosion[[#This Row],[CODIGO]],FACT_A2[cve_prod],FACT_A2[Existencia],0,0,1) -> 0 | G610: 1153.6 | H610: 0 | I610: 1030 | J610: 1030 | K610: 1030
A611: MES-0697 | B611: ETIQUETA SELLO DE GARANTIA WU NUTRITION | E611: =_xlfn.XLOOKUP(FACT_Explosion[[#This Row],[CODIGO]],Proveedores[CODIGO],Proveedores[TIEMPOS DE ENTREGA],0,0,1) -> 0 | F611: =_xlfn.XLOOKUP(FACT_Explosion[[#This Row],[CODIGO]],FACT_A2[cve_prod],FACT_A2[Existencia],0,0,1) -> 0 | G611: 15408.8 | H611: 0 | I611: 8755 | J611: 8755 | K611: 8755
A612: MES-0698 | B612: CAJA COLECTIVA WU NUTRITION (8 PZAS) | E612: =_xlfn.XLOOKUP(FACT_Explosion[[#This Row],[CODIGO]],Proveedores[CODIGO],Proveedores[TIEMPOS DE ENTREGA],0,0,1) -> 0 | F612: =_xlfn.XLOOKUP(FACT_Explosion[[#This Row],[CODIGO]],FACT_A2[cve_prod],FACT_A2[Existencia],0,0,1) -> 0 | G612: 1934.8089 | H612: 0 | I612: 1085.5244 | J612: 1085.5244 | K612: 1085.5244
A613: MPE-0406 | B613: POVIDONA K 29/32 | E613: =_xlfn.XLOOKUP(FACT_Explosion[[#This Row],[CODIGO]],Proveedores[CODIGO],Proveedores[TIEMPOS DE ENTREGA],0,0,1) -> 0 | F613: =_xlfn.XLOOKUP(FACT_Explosion[[#This Row],[CODIGO]],FACT_A2[cve_prod],FACT_A2[Existencia],0,0,1) -> 25 | G613: 1.98 | H613: 0 | I613: 4.032 | J613: 0 | K613: 0
A614: MPA-0541 | B614: FOSFATIDILSERINA 20% POLVO | E614: =_xlfn.XLOOKUP(FACT_Explosion[[#This Row],[CODIGO]],Proveedores[CODIGO],Proveedores[TIEMPOS DE ENTREGA],0,0,1) -> 0 | F614: =_xlfn.XLOOKUP(FACT_Explosion[[#This Row],[CODIGO]],FACT_A2[cve_prod],FACT_A2[Existencia],0,0,1) -> 0 | G614: 0 | H614: 0 | I614: 5.76 | J614: 0 | K614: 0
A615: MPA-0542 | B615: LUTEINA EXTRACTO 5% | E615: =_xlfn.XLOOKUP(FACT_Explosion[[#This Row],[CODIGO]],Proveedores[CODIGO],Proveedores[TIEMPOS DE ENTREGA],0,0,1) -> 0 | F615: =_xlfn.XLOOKUP(FACT_Explosion[[#This Row],[CODIGO]],FACT_A2[cve_prod],FACT_A2[Existencia],0,0,1) -> 0 | G615: 0 | H615: 0 | I615: 0.286 | J615: 0 | K615: 0
A616: MPA-0543 | B616: HUPERZINA A 1% | E616: =_xlfn.XLOOKUP(FACT_Explosion[[#This Row],[CODIGO]],Proveedores[CODIGO],Proveedores[TIEMPOS DE ENTREGA],0,0,1) -> 0 | F616: =_xlfn.XLOOKUP(FACT_Explosion[[#This Row],[CODIGO]],FACT_A2[cve_prod],FACT_A2[Existencia],0,0,1) -> 0 | G616: 0 | H616: 0 | I616: 0.024 | J616: 0 | K616: 0
A617: MES-0689 | B617: Etiqueta Dumo Labs Focus Boost c/60 caps | E617: =_xlfn.XLOOKUP(FACT_Explosion[[#This Row],[CODIGO]],Proveedores[CODIGO],Proveedores[TIEMPOS DE ENTREGA],0,0,1) -> 0 | F617: =_xlfn.XLOOKUP(FACT_Explosion[[#This Row],[CODIGO]],FACT_A2[cve_prod],FACT_A2[Existencia],0,0,1) -> 0 | G617: 0 | H617: 0 | I617: 1030 | J617: 0 | K617: 0
... A691: MPA-0316 | B691: ACEROLA EN POLVO | E691: =_xlfn.XLOOKUP(FACT_Explosion[[#This Row],[CODIGO]],Proveedores[CODIGO],Proveedores[TIEMPOS DE ENTREGA],0,0,1) -> 0 | F691: =_xlfn.XLOOKUP(FACT_Explosion[[#This Row],[CODIGO]],FACT_A2[cve_prod],FACT_A2[Existencia],0,0,1) -> 0 | G691: 0 | H691: 0 | I691: 0 | J691: 0 | K691: 0

Sheet PLAN_PRODUCCION
B2: OMEGA 3 CAPS | C2: OMEGA 3 KRILL CAPSULA BLANDA 60 CAPS | D2: MULTIBLUE OMEGA 3 60 CAPSULAS BLANDAS | E2: AMBROTOSE AO 30 CAPSULAS | F2: AZVITE CON 90 CAPSULAS | G2: AZVITE CON 30 CAPSULAS | H2: AZVITE MM C/2 CAPSULAS | I2: BIODIOLA FCO C/30 CAPS PT | J2: BIODIOLA FCO C/60 CAPS PT | K2: BERBERINA CAPSULAS C/120 | L2: WU NUTRITION BERBERINA C/120 CAPS | M2: COMPLETE ACTIVE FCO/60 CAPS | N2: MULTIBLUE COMPLEJO B C/30 CAPS | O2: CALCIO, VIT. D3 Y COLÁGENO FCO/60 CAPS | P2: COLSIMB 485 MG C/15 CAPS | Q2: COLSIMB 485 MG C/2 CAPS | R2: COENZIMAQ10, OM3, VIT Y MIN FCO/30 CAPS | S2: D-GELAC+FS C/30 CAPS. | T2: D-GELAC+FS C/60 CAPS. | U2: DIALAVIT C/30 CAPS | V2: DUMO LABS DELTA NIGHT C/60 CAPS | W2: DUMO LABS FOCUS BOOST C/60 CAPS | X2: DUMO LABS FOCUS BOOST BLACK C/60 CAPS | Y2: MULTIBLUE PRÓBIOTIC FIT MM 2 CAPS | Z2: MULTIBLUE PRÓBIOTIC FIT 30 CAPS PT | AA2: MULTIBLUE PRÓBIOTIC FIT 60 CAPS PT | AB2: FLOS-PRO C/14 CAPS. | AC2: FLOS-PRO C/2 CAPS. | AD2: GINKGO BILOBA C/30 CAPS SPRING VALLEY | AE2: GESTOMEG C/30 CAPS. | AF2: GESTOMEG C/2 CAPS. | AG2: GLICINATO DE MAGNESIO C/30 CAPS F.A. | AH2: KAMINA CAPS FCO/60 | AI2: KAMINA CAPS FCO/30 | AJ2: TRIPLE MAGNESIO C/60 CAPS | AK2: PROBIOTICOS Y PREBIOTICOS C/60 CAPS | AL2: RHODIOLA + L-TEANINA C/30 CAPS | AM2: MULTIBLUE PRÓBIOTICOS FCO/30 CAPS | AN2: MULTIBLUE MAGNESIO CAPS FCO/120 | AO2: MULTIBLUE MAGNESIO CAPS FCO/60 | AP2: MULTIBLUE SKIN HAIR NAILS C/60 CAPS | AQ2: OMEGA 3, 6 Y 9 C/60 CAPS AL NATURAL | AR2: OMEGA 3 C/60 CAPS AL NATURAL | AS2: OMEGA 3 C/30 SOFTGELS F. AHORRO | AT2: PROBIOTICOS 25 BILL C/30 CAPS SPR VALLEY | AU2: PHYTALOE CON 30 CAPSULAS | AV2: PROBIOTICOS MUJER C/30 CAPS SPR VAL | AW2: REMNURAL C/30 CAPS. | AX2: REMNURAL C/2 CAPS. | AY2: VITAMINA A 200 MG C/30 CAPSULAS BLANDAS | AZ2: VITAMINA B12 C/30 CÁPSULAS 400mg | BA2: VITABIOM Q10 /30 CAPS. | BB2: BIOMIVIT 400 30 / CAPS | BC2: VITEM 3RA /30 CAPS. | BD2: VITEM 3RA /60 CAPS. | BE2: WU NUTRITION BRILLA C/120 CAPS PT | BF2: WU NUTRITION PAZ C/120 | BG2: WU NUTRITION QUERIDA C/120 CAPS PT | BH2: WU NUTRITION REGRESA C/120 CAPS | BI2: VANESIR GEL 200 G | BJ2: MIEL/PROPOLEO/MENTA Y EUCALIPTO 240ML | BK2: NATUBRON CERO JARABE 240 ML | BL2: ABLAZOR CAJA CON 30 SOBRES 10G MEXICO | BM2: ABLAZOR SOBRE CON 10G | BN2: BLOOM CALOSTRO S/SABOR 25 PORCIONES | BO2: BLOOM CALOSTRO S/SABOR 50 PORCIONES | BP2: BLOOM CREATINA LIMÓN TARRO 40 PORCIONES | BQ2: BLOOM CREATINA LIMÓN TARRO 80 PORCIONES | BR2: BLOOM CREATINA LIMÓN C/14 SACHETS | BS2: COLÁGENO + BIOTINA 300G SPRING VALLEY | BT2: BLOOM MX SABOR FRESA-KIWI 14 PORCIONES | BU2: BLOOM MX SABOR FRESA-KIWI 145g | BV2: CBOOST KIDS CAJA CON 10 SOBRES 6 g | BW2: BLOOM MX SABOR FRUTOS ROJOS TARRO C/145g | BX2: BLOOM MX FRUTOS ROJOS 14 porciones 5.77g | BY2: BLOOM MX SABOR FRUTOS ROJOS TARRO C/289g | BZ2: BLOOM MX SABOR MANGO TARRO C/145g | CA2: BLOOM MX SABOR MANGO 14 porciones 5.77g | CB2: BLOOM MX SABOR MANGO TARRO C/289g | CC2: BLOOM GREENS PACK MARACUYA/MANGO C/20 S | CD2: BLOOM GREENS VARIATY PACK C/15 SOBRES DE 5.77G | CE2: CREATINA TARRO 200g C/40 PORCIONES | CF2: CREATINA TARRO 400g C/80 PORCIONES | CG2: CREATINA BLOOM C/14 SACHETS | CH2: C-BOOST NF CAJA CON 10 SOBRES DE 6 G | CI2: C-BOOST NF CAJA CON 15 SOBRES DE 6 G | CJ2: C-BOOST NF CAJA CON 30 SOBRES DE 6 G | CK2: COLÁGENO + VIT C+ VIT D 300G SPRING VALL | CL2: COLÁGENO HIDROLIZADO 300G SPRING VALLEY | CM2: COLAGENER 3 PEPINO-LIMON 150 G | CN2: COLAGENO 6 gr MARACUYA SAN PABLO NAT. | CO2: COLAGENER 10 NARANJA 360 G | CP2: COLÁGENO HEARTHY FOODS 500G | CQ2: C-REVITAL CAJA C/11 SOBRES DE 9 g C/U | CR2: C-REVITAL SIN AZUCAR C/11 SOBRES 9 g | CS2: CREATINA HEARHY FOODS 500G | CT2: C-VYM NARANJA-MANDARINA C/11 SOBRES | CU2: C-VYM CERO AZUCAR C/11 SOBRES | CV2: CART X-3 CAJA CON 30 SOBRES 12.5GR | CW2: CARTACTION CAJA C/30 SOBRES 23.35G | CX2: CARTACTION CAJA C/15 SOBRES 23.35G | CY2: CARTMAX CAJA C/30 SOBRES 12.54 G | CZ2: DUMOLABS ELECTROLITOS CITRUS CAJ C/30S | DA2: DUMOLABS ELECTROLITOS NARANJA CAJ C/30S | DB2: DUMOLABS ELECTROLITOS SANDIA CAJ C/30S | DC2: DUMOLABS ELECTROLITOS MORA AZUL CAJ C/30 | DD2: DUMOLABS ELECTROLITOS SIN SABOR CAJ C/30 | DE2: ELECTROLITOS FRESA 10 SOBRES | DF2: ELECTROLITOS LIMON 10 SOBRES | DG2: COLÁGENO SABOR FRESA BOLSA CON 300 GR | DH2: FLOS-PRO C/10 SOBRES 1g | DI2: FLOS-PRO C/1 SOBRE 1g | DJ2: FIBOTAX 10g C/10 SOBRES | DK2: FIBOTAX SIMILARES 10g C/10 SOBRES | DL2: FIBOTAX 10g C/30 SOBRES | DM2: GRENETINA HEARTHY FOODS 500G | DN2: GELASIMIFORTE 5G C/15 SOBRES | DO2: GLYCOLAGENO 12gr CAJA CON 20 SOBRES | DP2: HIDRA2GO FRESA CAJA C/10 SOBRES DE 6g | DQ2: HIDRA2GO LIMA LIMÓN CAJA C/10 SOBRES 6G | DR2: HIDRA2GO NARANJA MANDARINA CAJA C/10S 6G | DS2: HIDRA2GO SABOR UVA TARRO 300G | DT2: HIDRA2GO SABOR FRESA-KIWI TARRO 300G | DU2: HIDRA2GO SABOR LIMA-LIMON TARRO 300G | DV2: HIDRA2GO SABOR NARANJA-MANDA TARRO 300G | DW2: HIDRA2GO SABOR FRESA TARRO 300G | DX2: HIDRA2GO UVA CAJA C/10 SOBRES DE 6g | DY2: HIDRA2GO MORA AZUL CAJA C/10 SOBRES DE 6 | DZ2: HIDRA2GO SABOR MORA AZUL TARRO 300G | EA2: HIDRA2GO FRESA-KIWI CAJA C/10 SOBRES | EB2: HIDRA2GO MX LIMA-LIMÓN BOLSA C/20 SOBRES | EC2: HIDRA2GO MX NARANJA-MANDARINA BOLSA C/20 | ED2: HIDRA2GO MX UVA BOLSA C/20 S | EE2: HIDRA2GO MX MORA AZUL BOLSA C/20 S | EF2: HIDRA2GO MX FRESA BOLSA C/20 S | EG2: HIDRA2GO MX FRESA-KIWI MX BOLSA C/20 S | EH2: HIDRA2GO MX MIX BOLSA C/30 SOBRES | EI2: H2GO MX FRESA KIWI NF CAJA C/10S | EJ2: H2GO MX NARANJA-MAND NF CAJA C/10S | EK2: H2GO MX UVA NF CAJA C/10S | EL2: H2GO MX FRESA NF CAJA C/10S | EM2: H2GO MX MORA AZUL NF CAJA C/10S | EN2: H2GO MX LIMÓN NF CAJA C/10S | EO2: LF H2GO KIDS NARANJA CAJA C/10S | EP2: LF H2GO KIDS MORA AZUL CAJA C/10S | EQ2: LF H2GO KIDS MANZANA CAJA C/10S | ER2: KIDDYLAC 6 SOBRES DE 5GR C/U | ES2: CREATINA 200g TARRO | ET2: COLAGENER 6 PIÑA 300 G | EU2: BLOOM PREWORKOUT PINK LIMONADE MX C/175 | EV2: BLOOM PREWORKOUT PINK LIMONADE MX C/350 | EW2: BLOOM PREWORKOUT PINK LIMONADE 14 SACHET | EX2: SIMIFX 8G C/15 SOBRES | EY2: TRUCOFFEE 340 g | EZ2: COLÁGENO SABOR VAINILLA BOLSA CON 600 g | FA2: ACIDO FOLICO C/30 TABS AL NATURAL | FB2: ÁCIDO FÓLICO + HIERRO C/30 TABS SPRING V | FC2: ÁCIDO FÓLICO / PROTEÍNA DE ARROZ | FD2: COLÁGENO + BIOTINA C/60 TABS SPRING VALL | FE2: BIOFOLIC 400 / 60 TABS. | FF2: BIOVIT FOR MEN FRASCO CON 30 TABLETS | FG2: BIOVIT FOR WOMEN FRASCO CON 30 TABLETAS | FH2: CASTIN PLUSS C/50 TABS. | FI2: COMPLEJO B C/30 TABS. AL NATURAL | FJ2: COMPLEJO B SPRING VALLEY C/30 TABS | FK2: COLAGENER C/60 TABS. | FL2: CALCIO MAGNESIO ZINC C/60 TABS SPRING VA | FM2: C-REVITAL KIDS FCO 50 TABS DE 800 mg | FN2: C-VYM CON 30 TABLETAS MASTICABLES | FO2: COMPLEJO B AL NATURAL C/20 TABS EFE | FP2: COLAGENO AL NATURAL C/20 TABS EF | FQ2: VITAMINA K2 + D3 AL NATURAL C/20 TABS EF | FR2: KIDS MULTI AL NATURAL C/20 TABS EF | FS2: VITAMINA C C/20 TABS EFER SPR. VALLEY | FT2: EXZON C/90 TABS. | FU2: FIBRA/BIOFLAV/LACTOB/VITAMINAS 90 TABS | FV2: COMPLETE KIDDY 60 TABS | FW2: COLAGENO+VITAMINA C 60 TABS | FX2: MULTILYTE COCO C/20 TABS EFER | FY2: MEM-EH C/30 TABS | FZ2: MEM-EH C/45 TABS | GA2: MULTILYTE FRESA KIWI C/20 TABS EFER | GB2: MULTILYTE LIMONADA C/20 TABS EFER | GC2: MULTILYTE MIX 4 SABORES | GD2: MULTILYTE NARANJA C/20 TABS EFER | GE2: MULTIVITAMINICO AL NATURAL C/20 TABS EFE | GF2: TABLETAS EFER MAGNESIO ZINC 4g | GG2: PLENIFORM 40 /30 TABS. | GH2: TAMARIN-LX /30 CAPS. | GI2: TAMARIN-LX /45 CAPS. | GJ2: VITAMINA B12 C/30 TABS AL NATURAL | GK2: VITAMINA C AL NATURAL C/20 TABS EFERV. | GL2: VITAMINA C C/60 TABS SPRING VALLEY | GM2: VITAMINA D3 C/30 TABS SPRING VALLEY | GN2: VITAMINA C Y BIOFLAVONOIDES FCO/60 TABS | GO2: VIT B12 + REMOLACHA C/30 TABS SPRING VAL | GP2: VITAMINA C, D, Zn Y ACEROLA FCO C/30 TAB | GQ2: ZINC C/30 TABS AL NATURAL
A3: Fecha | B3: 51CBLO01 | C3: 51CBOM04 | D3: 51CBOM05 | E3: 51CPAM01 | F3: 51CPAZ03 | G3: 51CPAZ04 | H3: 51CPAZ05 | I3: 51CPBD01 | J3: 51CPBD02 | K3: 51CPBR01 | L3: 51CPBW01 | M3: 51CPCA01 | N3: 51CPCB01 | O3: 51CPCD01 | P3: 51CPCS01 | Q3: 51CPCS02 | R3: 51CPCV01 | S3: 51CPDG05 | T3: 51CPDG06 | U3: 51CPDL01 | V3: 51CPDN01 | W3: 51CPFB01 | X3: 51CPFBB01 | Y3: 51CPFIT01 | Z3: 51CPFIT02 | AA3: 51CPFIT03 | AB3: 51CPFP01 | AC3: 51CPFP02 | AD3: 51CPGBS01 | AE3: 51CPGM01 | AF3: 51CPGM02 | AG3: 51CPGMFA01 | AH3: 51CPKM01 | AI3: 51CPKM02 | AJ3: 51CPLM01 | AK3: 51CPLP01 | AL3: 51CPLR01 | AM3: 51CPMB01 | AN3: 51CPMM01 | AO3: 51CPMM02 | AP3: 51CPMS01 | AQ3: 51CPOM01 | AR3: 51CPOM02 | AS3: 51CPOM03 | AT3: 51CPPBS01 | AU3: 51CPPH01 | AV3: 51CPPMS01 | AW3: 51CPRM01 | AX3: 51CPRM02 | AY3: 51CPVAF01 | AZ3: 51CPVB01 | BA3: 51CPVB02 | BB3: 51CPVF01 | BC3: 51CPVT03 | BD3: 51CPVT05 | BE3: 51CPWB01 | BF3: 51CPWP01 | BG3: 51CPWQU01 | BH3: 51CPWR01 | BI3: 51GLVA04 | BJ3: 51JBMP01 | BK3: 51JBNC01 | BL3: 51PLAB01 | BM3: 51PLAB02 | BN3: 51PLBC01 | BO3: 51PLBC02 | BP3: 51PLBCL01 | BQ3: 51PLBCL02 | BR3: 51PLBCL03 | BS3: 51PLBCS01 | BT3: 51PLBFK01 | BU3: 51PLBFK02 | BV3: 51PLBK01 | BW3: 51PLBMF01 | BX3: 51PLBMF03 | BY3: 51PLBMF04 | BZ3: 51PLBMM01 | CA3: 51PLBMM03 | CB3: 51PLBMM04 | CC3: 51PLBMY01 | CD3: 51PLBVP01 | CE3: 51PLC201 | CF3: 51PLC202 | CG3: 51PLC203 | CH3: 51PLCB03 | CI3: 51PLCB04 | CJ3: 51PLCB06 | CK3: 51PLCCDS01 | CL3: 51PLCHS01 | CM3: 51PLCL01 | CN3: 51PLCM01 | CO3: 51PLCN01 | CP3: 51PLCOH01 | CQ3: 51PLCR01 | CR3: 51PLCR02 | CS3: 51PLCRH01 | CT3: 51PLCV01 | CU3: 51PLCV03 | CV3: 51PLCX01 | CW3: 51PLCXA01 | CX3: 51PLCXA02 | CY3: 51PLCXM01 | CZ3: 51PLDL01 | DA3: 51PLDL02 | DB3: 51PLDL03 | DC3: 51PLDL04 | DD3: 51PLDL05 | DE3: 51PLEF01 | DF3: 51PLEL01 | DG3: 51PLFC01 | DH3: 51PLFP01 | DI3: 51PLFP02 | DJ3: 51PLFX01 | DK3: 51PLFX02 | DL3: 51PLFX04 | DM3: 51PLGRH01 | DN3: 51PLGS01 | DO3: 51PLGY01 | DP3: 51PLHG01 | DQ3: 51PLHG02 | DR3: 51PLHG03 | DS3: 51PLHG07 | DT3: 51PLHG09 | DU3: 51PLHG10 | DV3: 51PLHG11 | DW3: 51PLHG12 | DX3: 51PLHG18 | DY3: 51PLHG20 | DZ3: 51PLHG21 | EA3: 51PLHG23 | EB3: 51PLHG24 | EC3: 51PLHG25 | ED3: 51PLHG26 | EE3: 51PLHG27 | EF3: 51PLHG28 | EG3: 51PLHG29 | EH3: 51PLHG30 | EI3: 51PLHG31 | EJ3: 51PLHG32 | EK3: 51PLHG33 | EL3: 51PLHG34 | EM3: 51PLHG35 | EN3: 51PLHG36 | EO3: 51PLHK01 | EP3: 51PLHK02 | EQ3: 51PLHK03 | ER3: 51PLKL01 | ES3: 51PLLC01 | ET3: 51PLPC01 | EU3: 51PLPW01 | EV3: 51PLPW02 | EW3: 51PLPW03 | EX3: 51PLSF01 | EY3: 51PLTF01 | EZ3: 51PLVC01 | FA3: 51TBAC01 | FB3: 51TBAFS01 | FC3: 51TBAP01 | FD3: 51TBBCS01 | FE3: 51TBBF02 | FF3: 51TBBH01 | FG3: 51TBBM01 | FH3: 51TBCA05 | FI3: 51TBCB01 | FJ3: 51TBCBS01 | FK3: 51TBCG01 | FL3: 51TBCMZS01 | FM3: 51TBCR01 | FN3: 51TBCV01 | FO3: 51TBECBA01 | FP3: 51TBECGA01 | FQ3: 51TBEKDA01 | FR3: 51TBEMKA01 | FS3: 51TBEVCS01 | FT3: 51TBEX01 | FU3: 51TBEX03 | FV3: 51TBKY01 | FW3: 51TBLC01 | FX3: 51TBMC01 | FY3: 51TBME01 | FZ3: 51TBME03 | GA3: 51TBMF01 | GB3: 51TBML01 | GC3: 51TBMM01 | GD3: 51TBMN01 | GE3: 51TBMVA01 | GF3: 51TBMZ01 | GG3: 51TBPF01 | GH3: 51TBTM01 | GI3: 51TBTM05 | GJ3: 51TBVB01 | GK3: 51TBVCA01 | GL3: 51TBVCS01 | GM3: 51TBVDS01 | GN3: 51TBVK01 | GO3: 51TBVRS01 | GP3: 51TBZA01 | GQ3: 51TBZN01
A4: 45887 | B4: 0 | C4: 0 | D4: 10000 | E4: 2000 | F4: 3800 | G4: 5000 | H4: 10000 | I4: 5000 | J4: 0 | K4: 20000 | L4: 1500 | M4: 2000 | N4: 0 | O4: 10000 | P4: 0 | Q4: 0 | R4: 3000 | S4: 22933 | T4: 4700 | U4: 5000 | V4: 1000 | W4: 1000 | X4: 1000 | Y4: 0 | Z4: 0 | AA4: 0 | AB4: 0 | AC4: 0 | AD4: 0 | AE4: 0 | AF4: 0 | AG4: 10000 | AH4: 3350 | AI4: 13400 | AJ4: 0 | AK4: 0 | AL4: 0 | AM4: 0 | AN4: 0 | AO4: 6700 | AP4: 0 | AQ4: 4830 | AR4: 7902 | AS4: 7336 | AT4: 10500 | AU4: 0 | AV4: 9270 | AW4: 0 | AX4: 0 | AY4: 0 | AZ4: 2000 | BA4: 15000 | BB4: 16826 | BC4: 7512 | BD4: 2600 | BE4: 5000 | BF4: 1800 | BG4: 3000 | BH4: 0 | BI4: 22000 | BJ4: 2000 | BK4: 16000 | BL4: 5763 | BM4: 0 | BN4: 10000 | BO4: 10000 | BP4: 10800 | BQ4: 0 | BR4: 0 | BS4: 950 | BT4: 4400 | BU4: 5000 | BV4: 0 | BW4: 5000 | BX4: 0 | BY4: 7500 | BZ4: 0 | CA4: 0 | CB4: 0 | CC4: 0 | CD4: 3000 | CE4: 0 | CF4: 0 | CG4: 848 | CH4: 0 | CI4: 22222 | CJ4: 11111 | CK4: 63 | CL4: 0 | CM4: 2000 | CN4: 0 | CO4: 2000 | CP4: 0 | CQ4: 15000 | CR4: 15000 | CS4: 0 | CT4: 5125 | CU4: 10000 | CV4: 2000 | CW4: 0 | CX4: 120 | CY4: 0 | CZ4: 0 | DA4: 0 | DB4: 0 | DC4: 1200 | DD4: 0 | DE4: 9000 | DF4: 9000 | DG4: 45 | DH4: 0 | DI4: 0 | DJ4: 2677 | DK4: 0 | DL4: 345 | DM4: 0 | DN4: 0 | DO4: 0 | DP4: 3600 | DQ4: 0 | DR4: 1800 | DS4: 0 | DT4: 0 | DU4: 0 | DV4: 0 | DW4: 0 | DX4: 0 | DY4: 3600 | DZ4: 0 | EA4: 0 | EB4: 0 | EC4: 0 | ED4: 0 | EE4: 0 | EF4: 0 | EG4: 0 | EH4: 0 | EI4: 0 | EJ4: 0 | EK4: 0 | EL4: 0 | EM4: 0 | EN4: 0 | EO4: 4000 | EP4: 4000 | EQ4: 4000 | ER4: 8081 | ES4: 0 | ET4: 0 | EU4: 0 | EV4: 0 | EW4: 3500 | EX4: 33333 | EY4: 0 | EZ4: 488 | FA4: 4000 | FB4: 10600 | FC4: 5000 | FD4: 287 | FE4: 10000 | FF4: 0 | FG4: 0 | FH4: 0 | FI4: 5400 | FJ4: 10850 | FK4: 9000 | FL4: 10500 | FM4: 0 | FN4: 11100 | FO4: 2000 | FP4: 2024 | FQ4: 4000 | FR4: 4000 | FS4: 2340 | FT4: 36090 | FU4: 1260 | FV4: 5000 | FW4: 0 | FX4: 0 | FY4: 10000 | FZ4: 3333 | GA4: 13000 | GB4: 19500 | GC4: 7000 | GD4: 0 | GE4: 4200 | GF4: 3165 | GG4: 27000 | GH4: 20400 | GI4: 6667 | GJ4: 3660 | GK4: 1780 | GL4: 100 | GM4: 10500 | GN4: 2000 | GO4: 0 | GP4: 0 | GQ4: 3300
A5: =WORKDAY.INTL(A4,1,11) -> 45888 | B5: 0 | C5: 0 | D5: 0 | E5: 0 | F5: 0 | G5: 0 | H5: 0 | I5: 0 | J5: 0 | K5: 0 | L5: 0 | M5: 0 | N5: 0 | O5: 0 | P5: 0 | Q5: 0 | R5: 0 | S5: 0 | T5: 0 | U5: 0 | V5: 0 | W5: 0 | X5: 0 | Y5: 0 | Z5: 0 | AA5: 0 | AB5: 0 | AC5: 0 | AD5: 0 | AE5: 0 | AF5: 0 | AG5: 0 | AH5: 0 | AI5: 0 | AJ5: 0 | AK5: 0 | AL5: 0 | AM5: 0 | AN5: 0 | AO5: 0 | AP5: 0 | AQ5: 0 | AR5: 0 | AS5: 0 | AT5: 0 | AU5: 0 | AV5: 0 | AW5: 0 | AX5: 0 | AY5: 0 | AZ5: 0 | BA5: 0 | BB5: 0 | BC5: 0 | BD5: 0 | BE5: 0 | BF5: 0 | BG5: 0 | BH5: 0 | BI5: 0 | BJ5: 0 | BK5: 0 | BL5: 0 | BM5: 0 | BN5: 0 | BO5: 0 | BP5: 0 | BQ5: 0 | BR5: 0 | BS5: 0 | BT5: 0 | BU5: 0 | BV5: 0 | BW5: 0 | BX5: 0 | BY5: 0 | BZ5: 0 | CA5: 0 | CB5: 0 | CC5: 0 | CD5: 0 | CE5: 0 | CF5: 0 | CG5: 0 | CH5: 0 | CI5: 0 | CJ5: 0 | CK5: 0 | CL5: 0 | CM5: 0 | CN5: 0 | CO5: 0 | CP5: 0 | CQ5: 0 | CR5: 0 | CS5: 0 | CT5: 0 | CU5: 0 | CV5: 0 | CW5: 0 | CX5: 0 | CY5: 0 | CZ5: 0 | DA5: 0 | DB5: 0 | DC5: 0 | DD5: 0 | DE5: 0 | DF5: 0 | DG5: 0 | DH5: 0 | DI5: 0 | DJ5: 0 | DK5: 0 | DL5: 0 | DM5: 0 | DN5: 0 | DO5: 0 | DP5: 0 | DQ5: 0 | DR5: 0 | DS5: 0 | DT5: 0 | DU5: 0 | DV5: 0 | DW5: 0 | DX5: 0 | DY5: 0 | DZ5: 0 | EA5: 0 | EB5: 0 | EC5: 0 | ED5: 0 | EE5: 0 | EF5: 0 | EG5: 0 | EH5: 0 | EI5: 0 | EJ5: 0 | EK5: 0 | EL5: 0 | EM5: 0 | EN5: 0 | EO5: 0 | EP5: 0 | EQ5: 0 | ER5: 0 | ES5: 0 | ET5: 0 | EU5: 0 | EV5: 0 | EW5: 0 | EX5: 0 | EY5: 0 | EZ5: 0 | FA5: 0 | FB5: 0 | FC5: 0 | FD5: 0 | FE5: 0 | FF5: 0 | FG5: 0 | FH5: 0 | FI5: 0 | FJ5: 0 | FK5: 0 | FL5: 0 | FM5: 0 | FN5: 0 | FO5: 0 | FP5: 0 | FQ5: 0 | FR5: 0 | FS5: 0 | FT5: 0 | FU5: 0 | FV5: 0 | FW5: 0 | FX5: 0 | FY5: 0 | FZ5: 0 | GA5: 0 | GB5: 0 | GC5: 0 | GD5: 0 | GE5: 0 | GF5: 0 | GG5: 0 | GH5: 0 | GI5: 0 | GJ5: 0 | GK5: 0 | GL5: 0 | GM5: 0 | GN5: 0 | GO5: 0 | GP5: 0 | GQ5: 0
A6: =WORKDAY.INTL(A5,1,11) -> 45889 | B6: 0 | C6: 0 | D6: 0 | E6: 0 | F6: 0 | G6: 0 | H6: 0 | I6: 0 | J6: 0 | K6: 0 | L6: 0 | M6: 0 | N6: 0 | O6: 0 | P6: 0 | Q6: 0 | R6: 0 | S6: 0 | T6: 0 | U6: 0 | V6: 0 | W6: 0 | X6: 0 | Y6: 0 | Z6: 0 | AA6: 0 | AB6: 0 | AC6: 0 | AD6: 0 | AE6: 0 | AF6: 0 | AG6: 0 | AH6: 0 | AI6: 0 | AJ6: 0 | AK6: 0 | AL6: 0 | AM6: 0 | AN6: 0 | AO6: 0 | AP6: 0 | AQ6: 0 | AR6: 0 | AS6: 0 | AT6: 0 | AU6: 0 | AV6: 0 | AW6: 0 | AX6: 0 | AY6: 0 | AZ6: 0 | BA6: 0 | BB6: 0 | BC6: 0 | BD6: 0 | BE6: 0 | BF6: 0 | BG6: 0 | BH6: 0 | BI6: 0 | BJ6: 0 | BK6: 0 | BL6: 0 | BM6: 0 | BN6: 0 | BO6: 0 | BP6: 0 | BQ6: 0 | BR6: 0 | BS6: 0 | BT6: 0 | BU6: 0 | BV6: 0 | BW6: 0 | BX6: 0 | BY6: 0 | BZ6: 0 | CA6: 0 | CB6: 0 | CC6: 0 | CD6: 0 | CE6: 0 | CF6: 0 | CG6: 0 | CH6: 0 | CI6: 0 | CJ6: 0 | CK6: 0 | CL6: 0 | CM6: 0 | CN6: 0 | CO6: 0 | CP6: 0 | CQ6: 0 | CR6: 0 | CS6: 0 | CT6: 0 | CU6: 0 | CV6: 0 | CW6: 0 | CX6: 0 | CY6: 0 | CZ6: 0 | DA6: 0 | DB6: 0 | DC6: 0 | DD6: 0 | DE6: 0 | DF6: 0 | DG6: 0 | DH6: 0 | DI6: 0 | DJ6: 0 | DK6: 0 | DL6: 0 | DM6: 0 | DN6: 0 | DO6: 0 | DP6: 0 | DQ6: 0 | DR6: 0 | DS6: 0 | DT6: 0 | DU6: 0 | DV6: 0 | DW6: 0 | DX6: 0 | DY6: 0 | DZ6: 0 | EA6: 0 | EB6: 0 | EC6: 0 | ED6: 0 | EE6: 0 | EF6: 0 | EG6: 0 | EH6: 0 | EI6: 0 | EJ6: 0 | EK6: 0 | EL6: 0 | EM6: 0 | EN6: 0 | EO6: 0 | EP6: 0 | EQ6: 0 | ER6: 0 | ES6: 0 | ET6: 0 | EU6: 0 | EV6: 0 | EW6: 0 | EX6: 0 | EY6: 0 | EZ6: 0 | FA6: 0 | FB6: 0 | FC6: 0 | FD6: 0 | FE6: 0 | FF6: 0 | FG6: 0 | FH6: 0 | FI6: 0 | FJ6: 0 | FK6: 0 | FL6: 0 | FM6: 0 | FN6: 0 | FO6: 0 | FP6: 0 | FQ6: 0 | FR6: 0 | FS6: 0 | FT6: 0 | FU6: 0 | FV6: 0 | FW6: 0 | FX6: 0 | FY6: 0 | FZ6: 0 | GA6: 0 | GB6: 0 | GC6: 0 | GD6: 0 | GE6: 0 | GF6: 0 | GG6: 0 | GH6: 0 | GI6: 0 | GJ6: 0 | GK6: 0 | GL6: 0 | GM6: 0 | GN6: 0 | GO6: 0 | GP6: 0 | GQ6: 0
A7: =WORKDAY.INTL(A6,1,11) -> 45890 | B7: 0 | C7: 0 | D7: 0 | E7: 0 | F7: 0 | G7: 0 | H7: 0 | I7: 0 | J7: 0 | K7: 0 | L7: 0 | M7: 0 | N7: 0 | O7: 0 | P7: 0 | Q7: 0 | R7: 0 | S7: 0 | T7: 0 | U7: 0 | V7: 0 | W7: 0 | X7: 0 | Y7: 0 | Z7: 0 | AA7: 0 | AB7: 0 | AC7: 0 | AD7: 0 | AE7: 0 | AF7: 0 | AG7: 0 | AH7: 0 | AI7: 0 | AJ7: 0 | AK7: 0 | AL7: 0 | AM7: 0 | AN7: 0 | AO7: 0 | AP7: 0 | AQ7: 0 | AR7: 0 | AS7: 0 | AT7: 0 | AU7: 0 | AV7: 0 | AW7: 0 | AX7: 0 | AY7: 0 | AZ7: 0 | BA7: 0 | BB7: 0 | BC7: 0 | BD7: 0 | BE7: 0 | BF7: 0 | BG7: 0 | BH7: 0 | BI7: 0 | BJ7: 0 | BK7: 0 | BL7: 0 | BM7: 0 | BN7: 0 | BO7: 0 | BP7: 0 | BQ7: 0 | BR7: 0 | BS7: 0 | BT7: 0 | BU7: 0 | BV7: 0 | BW7: 0 | BX7: 0 | BY7: 0 | BZ7: 0 | CA7: 0 | CB7: 0 | CC7: 0 | CD7: 0 | CE7: 0 | CF7: 0 | CG7: 0 | CH7: 0 | CI7: 0 | CJ7: 0 | CK7: 0 | CL7: 0 | CM7: 0 | CN7: 0 | CO7: 0 | CP7: 0 | CQ7: 0 | CR7: 0 | CS7: 0 | CT7: 0 | CU7: 0 | CV7: 0 | CW7: 0 | CX7: 0 | CY7: 0 | CZ7: 0 | DA7: 0 | DB7: 0 | DC7: 0 | DD7: 0 | DE7: 0 | DF7: 0 | DG7: 0 | DH7: 0 | DI7: 0 | DJ7: 0 | DK7: 0 | DL7: 0 | DM7: 0 | DN7: 0 | DO7: 0 | DP7: 0 | DQ7: 0 | DR7: 0 | DS7: 0 | DT7: 0 | DU7: 0 | DV7: 0 | DW7: 0 | DX7: 0 | DY7: 0 | DZ7: 0 | EA7: 0 | EB7: 0 | EC7: 0 | ED7: 0 | EE7: 0 | EF7: 0 | EG7: 0 | EH7: 0 | EI7: 0 | EJ7: 0 | EK7: 0 | EL7: 0 | EM7: 0 | EN7: 0 | EO7: 0 | EP7: 0 | EQ7: 0 | ER7: 0 | ES7: 0 | ET7: 0 | EU7: 0 | EV7: 0 | EW7: 0 | EX7: 0 | EY7: 0 | EZ7: 0 | FA7: 0 | FB7: 0 | FC7: 0 | FD7: 0 | FE7: 0 | FF7: 0 | FG7: 0 | FH7: 0 | FI7: 0 | FJ7: 0 | FK7: 0 | FL7: 0 | FM7: 0 | FN7: 0 | FO7: 0 | FP7: 0 | FQ7: 0 | FR7: 0 | FS7: 0 | FT7: 0 | FU7: 0 | FV7: 0 | FW7: 0 | FX7: 0 | FY7: 0 | FZ7: 0 | GA7: 0 | GB7: 0 | GC7: 0 | GD7: 0 | GE7: 0 | GF7: 0 | GG7: 0 | GH7: 0 | GI7: 0 | GJ7: 0 | GK7: 0 | GL7: 0 | GM7: 0 | GN7: 0 | GO7: 0 | GP7: 0 | GQ7: 0
A8: =WORKDAY.INTL(A7,1,11) -> 45891 | B8: 0 | C8: 0 | D8: 0 | E8: 0 | F8: 0 | G8: 0 | H8: 0 | I8: 0 | J8: 0 | K8: 0 | L8: 0 | M8: 0 | N8: 0 | O8: 0 | P8: 0 | Q8: 0 | R8: 0 | S8: 0 | T8: 0 | U8: 0 | V8: 0 | W8: 0 | X8: 0 | Y8: 0 | Z8: 0 | AA8: 0 | AB8: 0 | AC8: 0 | AD8: 0 | AE8: 0 | AF8: 0 | AG8: 0 | AH8: 0 | AI8: 0 | AJ8: 0 | AK8: 0 | AL8: 0 | AM8: 0 | AN8: 0 | AO8: 0 | AP8: 0 | AQ8: 0 | AR8: 0 | AS8: 0 | AT8: 0 | AU8: 0 | AV8: 0 | AW8: 0 | AX8: 0 | AY8: 0 | AZ8: 0 | BA8: 0 | BB8: 0 | BC8: 0 | BD8: 0 | BE8: 0 | BF8: 0 | BG8: 0 | BH8: 0 | BI8: 0 | BJ8: 0 | BK8: 0 | BL8: 0 | BM8: 0 | BN8: 0 | BO8: 0 | BP8: 0 | BQ8: 0 | BR8: 0 | BS8: 0 | BT8: 0 | BU8: 0 | BV8: 0 | BW8: 0 | BX8: 0 | BY8: 0 | BZ8: 0 | CA8: 0 | CB8: 0 | CC8: 0 | CD8: 0 | CE8: 0 | CF8: 0 | CG8: 0 | CH8: 0 | CI8: 0 | CJ8: 0 | CK8: 0 | CL8: 0 | CM8: 0 | CN8: 0 | CO8: 0 | CP8: 0 | CQ8: 0 | CR8: 0 | CS8: 0 | CT8: 0 | CU8: 0 | CV8: 0 | CW8: 0 | CX8: 0 | CY8: 0 | CZ8: 0 | DA8: 0 | DB8: 0 | DC8: 0 | DD8: 0 | DE8: 0 | DF8: 0 | DG8: 0 | DH8: 0 | DI8: 0 | DJ8: 0 | DK8: 0 | DL8: 0 | DM8: 0 | DN8: 0 | DO8: 0 | DP8: 0 | DQ8: 0 | DR8: 0 | DS8: 0 | DT8: 0 | DU8: 0 | DV8: 0 | DW8: 0 | DX8: 0 | DY8: 0 | DZ8: 0 | EA8: 0 | EB8: 0 | EC8: 0 | ED8: 0 | EE8: 0 | EF8: 0 | EG8: 0 | EH8: 0 | EI8: 0 | EJ8: 0 | EK8: 0 | EL8: 0 | EM8: 0 | EN8: 0 | EO8: 0 | EP8: 0 | EQ8: 0 | ER8: 0 | ES8: 0 | ET8: 0 | EU8: 0 | EV8: 0 | EW8: 0 | EX8: 0 | EY8: 0 | EZ8: 0 | FA8: 0 | FB8: 0 | FC8: 0 | FD8: 0 | FE8: 0 | FF8: 0 | FG8: 0 | FH8: 0 | FI8: 0 | FJ8: 0 | FK8: 0 | FL8: 0 | FM8: 0 | FN8: 0 | FO8: 0 | FP8: 0 | FQ8: 0 | FR8: 0 | FS8: 0 | FT8: 0 | FU8: 0 | FV8: 0 | FW8: 0 | FX8: 0 | FY8: 0 | FZ8: 0 | GA8: 0 | GB8: 0 | GC8: 0 | GD8: 0 | GE8: 0 | GF8: 0 | GG8: 0 | GH8: 0 | GI8: 0 | GJ8: 0 | GK8: 0 | GL8: 0 | GM8: 0 | GN8: 0 | GO8: 0 | GP8: 0 | GQ8: 0
A9: =WORKDAY.INTL(A8,1,11) -> 45892 | B9: 0 | C9: 0 | D9: 0 | E9: 0 | F9: 0 | G9: 0 | H9: 0 | I9: 0 | J9: 0 | K9: 0 | L9: 0 | M9: 0 | N9: 0 | O9: 0 | P9: 0 | Q9: 0 | R9: 0 | S9: 0 | T9: 0 | U9: 0 | V9: 0 | W9: 0 | X9: 0 | Y9: 0 | Z9: 0 | AA9: 0 | AB9: 0 | AC9: 0 | AD9: 0 | AE9: 0 | AF9: 0 | AG9: 0 | AH9: 0 | AI9: 0 | AJ9: 0 | AK9: 0 | AL9: 0 | AM9: 0 | AN9: 0 | AO9: 0 | AP9: 0 | AQ9: 0 | AR9: 0 | AS9: 0 | AT9: 0 | AU9: 0 | AV9: 0 | AW9: 0 | AX9: 0 | AY9: 0 | AZ9: 0 | BA9: 0 | BB9: 0 | BC9: 0 | BD9: 0 | BE9: 0 | BF9: 0 | BG9: 0 | BH9: 0 | BI9: 0 | BJ9: 0 | BK9: 0 | BL9: 0 | BM9: 0 | BN9: 0 | BO9: 0 | BP9: 0 | BQ9: 0 | BR9: 0 | BS9: 0 | BT9: 0 | BU9: 0 | BV9: 0 | BW9: 0 | BX9: 0 | BY9: 0 | BZ9: 0 | CA9: 0 | CB9: 0 | CC9: 0 | CD9: 0 | CE9: 0 | CF9: 0 | CG9: 0 | CH9: 0 | CI9: 0 | CJ9: 0 | CK9: 0 | CL9: 0 | CM9: 0 | CN9: 0 | CO9: 0 | CP9: 0 | CQ9: 0 | CR9: 0 | CS9: 0 | CT9: 0 | CU9: 0 | CV9: 0 | CW9: 0 | CX9: 0 | CY9: 0 | CZ9: 0 | DA9: 0 | DB9: 0 | DC9: 0 | DD9: 0 | DE9: 0 | DF9: 0 | DG9: 0 | DH9: 0 | DI9: 0 | DJ9: 0 | DK9: 0 | DL9: 0 | DM9: 0 | DN9: 0 | DO9: 0 | DP9: 0 | DQ9: 0 | DR9: 0 | DS9: 0 | DT9: 0 | DU9: 0 | DV9: 0 | DW9: 0 | DX9: 0 | DY9: 0 | DZ9: 0 | EA9: 0 | EB9: 0 | EC9: 0 | ED9: 0 | EE9: 0 | EF9: 0 | EG9: 0 | EH9: 0 | EI9: 0 | EJ9: 0 | EK9: 0 | EL9: 0 | EM9: 0 | EN9: 0 | EO9: 0 | EP9: 0 | EQ9: 0 | ER9: 0 | ES9: 0 | ET9: 0 | EU9: 0 | EV9: 0 | EW9: 0 | EX9: 0 | EY9: 0 | EZ9: 0 | FA9: 0 | FB9: 0 | FC9: 0 | FD9: 0 | FE9: 0 | FF9: 0 | FG9: 0 | FH9: 0 | FI9: 0 | FJ9: 0 | FK9: 0 | FL9: 0 | FM9: 0 | FN9: 0 | FO9: 0 | FP9: 0 | FQ9: 0 | FR9: 0 | FS9: 0 | FT9: 0 | FU9: 0 | FV9: 0 | FW9: 0 | FX9: 0 | FY9: 0 | FZ9: 0 | GA9: 0 | GB9: 0 | GC9: 0 | GD9: 0 | GE9: 0 | GF9: 0 | GG9: 0 | GH9: 0 | GI9: 0 | GJ9: 0 | GK9: 0 | GL9: 0 | GM9: 0 | GN9: 0 | GO9: 0 | GP9: 0 | GQ9: 0
A10: =WORKDAY.INTL(A9,1,11) -> 45894 | B10: 0 | C10: 0 | D10: 0 | E10: 0 | F10: 0 | G10: 0 | H10: 0 | I10: 0 | J10: 0 | K10: 0 | L10: 0 | M10: 0 | N10: 0 | O10: 0 | P10: 0 | Q10: 0 | R10: 0 | S10: 0 | T10: 0 | U10: 0 | V10: 0 | W10: 0 | X10: 0 | Y10: 0 | Z10: 0 | AA10: 0 | AB10: 0 | AC10: 0 | AD10: 0 | AE10: 0 | AF10: 0 | AG10: 0 | AH10: 0 | AI10: 0 | AJ10: 0 | AK10: 0 | AL10: 0 | AM10: 0 | AN10: 0 | AO10: 0 | AP10: 0 | AQ10: 0 | AR10: 0 | AS10: 0 | AT10: 0 | AU10: 0 | AV10: 0 | AW10: 0 | AX10: 0 | AY10: 0 | AZ10: 0 | BA10: 0 | BB10: 0 | BC10: 0 | BD10: 0 | BE10: 0 | BF10: 0 | BG10: 0 | BH10: 0 | BI10: 0 | BJ10: 0 | BK10: 0 | BL10: 6800 | BM10: 0 | BN10: 0 | BO10: 0 | BP10: 0 | BQ10: 0 | BR10: 0 | BS10: 0 | BT10: 0 | BU10: 0 | BV10: 0 | BW10: 0 | BX10: 0 | BY10: 0 | BZ10: 0 | CA10: 0 | CB10: 0 | CC10: 0 | CD10: 0 | CE10: 0 | CF10: 0 | CG10: 0 | CH10: 0 | CI10: 0 | CJ10: 0 | CK10: 0 | CL10: 0 | CM10: 0 | CN10: 0 | CO10: 0 | CP10: 0 | CQ10: 0 | CR10: 0 | CS10: 0 | CT10: 0 | CU10: 0 | CV10: 0 | CW10: 0 | CX10: 0 | CY10: 0 | CZ10: 0 | DA10: 0 | DB10: 0 | DC10: 0 | DD10: 0 | DE10: 0 | DF10: 0 | DG10: 0 | DH10: 0 | DI10: 0 | DJ10: 0 | DK10: 0 | DL10: 0 | DM10: 0 | DN10: 0 | DO10: 0 | DP10: 0 | DQ10: 0 | DR10: 0 | DS10: 0 | DT10: 0 | DU10: 0 | DV10: 0 | DW10: 0 | DX10: 0 | DY10: 0 | DZ10: 0 | EA10: 0 | EB10: 0 | EC10: 0 | ED10: 0 | EE10: 0 | EF10: 0 | EG10: 0 | EH10: 0 | EI10: 0 | EJ10: 0 | EK10: 0 | EL10: 0 | EM10: 0 | EN10: 0 | EO10: 0 | EP10: 0 | EQ10: 0 | ER10: 0 | ES10: 0 | ET10: 0 | EU10: 0 | EV10: 0 | EW10: 0 | EX10: 0 | EY10: 0 | EZ10: 0 | FA10: 0 | FB10: 0 | FC10: 0 | FD10: 0 | FE10: 0 | FF10: 0 | FG10: 0 | FH10: 0 | FI10: 0 | FJ10: 0 | FK10: 0 | FL10: 0 | FM10: 0 | FN10: 0 | FO10: 0 | FP10: 0 | FQ10: 0 | FR10: 0 | FS10: 0 | FT10: 0 | FU10: 0 | FV10: 0 | FW10: 0 | FX10: 0 | FY10: 0 | FZ10: 0 | GA10: 0 | GB10: 0 | GC10: 0 | GD10: 0 | GE10: 0 | GF10: 0 | GG10: 0 | GH10: 0 | GI10: 0 | GJ10: 0 | GK10: 0 | GL10: 0 | GM10: 0 | GN10: 0 | GO10: 0 | GP10: 0 | GQ10: 0
A11: =A10+7-WEEKDAY(A10-1)+1 -> 45901 | B11: 0 | C11: 0 | D11: 0 | E11: 0 | F11: 0 | G11: 0 | H11: 0 | I11: 0 | J11: 0 | K11: 0 | L11: 0 | M11: 0 | N11: 0 | O11: 0 | P11: 0 | Q11: 0 | R11: 0 | S11: 20000 | T11: 0 | U11: 0 | V11: 0 | W11: 0 | X11: 0 | Y11: 0 | Z11: 0 | AA11: 0 | AB11: 0 | AC11: 0 | AD11: 0 | AE11: 0 | AF11: 0 | AG11: 5000 | AH11: 0 | AI11: 0 | AJ11: 0 | AK11: 0 | AL11: 0 | AM11: 0 | AN11: 0 | AO11: 0 | AP11: 0 | AQ11: 1000 | AR11: 4300 | AS11: 0 | AT11: 0 | AU11: 0 | AV11: 0 | AW11: 0 | AX11: 0 | AY11: 0 | AZ11: 0 | BA11: 0 | BB11: 0 | BC11: 0 | BD11: 0 | BE11: 0 | BF11: 0 | BG11: 0 | BH11: 0 | BI11: 0 | BJ11: 0 | BK11: 0 | BL11: 6800 | BM11: 0 | BN11: 0 | BO11: 0 | BP11: 0 | BQ11: 0 | BR11: 0 | BS11: 0 | BT11: 0 | BU11: 0 | BV11: 0 | BW11: 0 | BX11: 0 | BY11: 0 | BZ11: 0 | CA11: 0 | CB11: 0 | CC11: 0 | CD11: 0 | CE11: 0 | CF11: 0 | CG11: 0 | CH11: 0 | CI11: 0 | CJ11: 0 | CK11: 0 | CL11: 0 | CM11: 0 | CN11: 0 | CO11: 0 | CP11: 0 | CQ11: 0 | CR11: 0 | CS11: 0 | CT11: 0 | CU11: 0 | CV11: 0 | CW11: 0 | CX11: 0 | CY11: 0 | CZ11: 0 | DA11: 0 | DB11: 0 | DC11: 0 | DD11: 0 | DE11: 9000 | DF11: 9000 | DG11: 0 | DH11: 0 | DI11: 0 | DJ11: 0 | DK11: 0 | DL11: 0 | DM11: 0 | DN11: 0 | DO11: 0 | DP11: 0 | DQ11: 0 | DR11: 0 | DS11: 0 | DT11: 0 | DU11: 0 | DV11: 0 | DW11: 0 | DX11: 0 | DY11: 0 | DZ11: 0 | EA11: 0 | EB11: 0 | EC11: 0 | ED11: 0 | EE11: 0 | EF11: 0 | EG11: 0 | EH11: 0 | EI11: 0 | EJ11: 0 | EK11: 0 | EL11: 0 | EM11: 0 | EN11: 0 | EO11: 0 | EP11: 0 | EQ11: 0 | ER11: 0 | ES11: 0 | ET11: 0 | EU11: 0 | EV11: 0 | EW11: 0 | EX11: 66666 | EY11: 0 | EZ11: 0 | FA11: 0 | FB11: 0 | FC11: 0 | FD11: 0 | FE11: 0 | FF11: 0 | FG11: 0 | FH11: 0 | FI11: 0 | FJ11: 0 | FK11: 0 | FL11: 0 | FM11: 0 | FN11: 0 | FO11: 0 | FP11: 0 | FQ11: 0 | FR11: 0 | FS11: 0 | FT11: 0 | FU11: 0 | FV11: 0 | FW11: 0 | FX11: 0 | FY11: 0 | FZ11: 0 | GA11: 0 | GB11: 0 | GC11: 0 | GD11: 0 | GE11: 0 | GF11: 0 | GG11: 0 | GH11: 0 | GI11: 0 | GJ11: 0 | GK11: 0 | GL11: 0 | GM11: 0 | GN11: 0 | GO11: 0 | GP11: 0 | GQ11: 0
A12: =A11+7-WEEKDAY(A11-1)+1 -> 45908 | B12: 0 | C12: 0 | D12: 0 | E12: 0 | F12: 0 | G12: 0 | H12: 0 | I12: 0 | J12: 0 | K12: 0 | L12: 0 | M12: 0 | N12: 0 | O12: 0 | P12: 0 | Q12: 0 | R12: 0 | S12: 0 | T12: 0 | U12: 0 | V12: 0 | W12: 0 | X12: 0 | Y12: 0 | Z12: 0 | AA12: 0 | AB12: 0 | AC12: 0 | AD12: 0 | AE12: 0 | AF12: 0 | AG12: 0 | AH12: 0 | AI12: 0 | AJ12: 0 | AK12: 0 | AL12: 0 | AM12: 0 | AN12: 0 | AO12: 0 | AP12: 0 | AQ12: 0 | AR12: 0 | AS12: 0 | AT12: 0 | AU12: 0 | AV12: 0 | AW12: 0 | AX12: 0 | AY12: 0 | AZ12: 0 | BA12: 0 | BB12: 0 | BC12: 0 | BD12: 0 | BE12: 0 | BF12: 0 | BG12: 0 | BH12: 0 | BI12: 0 | BJ12: 0 | BK12: 0 | BL12: 0 | BM12: 0 | BN12: 0 | BO12: 0 | BP12: 0 | BQ12: 0 | BR12: 0 | BS12: 0 | BT12: 0 | BU12: 0 | BV12: 0 | BW12: 0 | BX12: 0 | BY12: 0 | BZ12: 0 | CA12: 0 | CB12: 0 | CC12: 0 | CD12: 0 | CE12: 0 | CF12: 0 | CG12: 0 | CH12: 0 | CI12: 0 | CJ12: 0 | CK12: 0 | CL12: 0 | CM12: 0 | CN12: 0 | CO12: 0 | CP12: 0 | CQ12: 0 | CR12: 0 | CS12: 0 | CT12: 0 | CU12: 0 | CV12: 0 | CW12: 0 | CX12: 0 | CY12: 0 | CZ12: 0 | DA12: 0 | DB12: 0 | DC12: 0 | DD12: 0 | DE12: 0 | DF12: 0 | DG12: 0 | DH12: 0 | DI12: 0 | DJ12: 0 | DK12: 0 | DL12: 0 | DM12: 0 | DN12: 0 | DO12: 0 | DP12: 0 | DQ12: 0 | DR12: 0 | DS12: 0 | DT12: 0 | DU12: 0 | DV12: 0 | DW12: 0 | DX12: 0 | DY12: 0 | DZ12: 0 | EA12: 0 | EB12: 0 | EC12: 0 | ED12: 0 | EE12: 0 | EF12: 0 | EG12: 0 | EH12: 0 | EI12: 0 | EJ12: 0 | EK12: 0 | EL12: 0 | EM12: 0 | EN12: 0 | EO12: 0 | EP12: 0 | EQ12: 0 | ER12: 0 | ES12: 0 | ET12: 0 | EU12: 0 | EV12: 0 | EW12: 0 | EX12: 33333 | EY12: 0 | EZ12: 0 | FA12: 0 | FB12: 0 | FC12: 0 | FD12: 0 | FE12: 0 | FF12: 0 | FG12: 0 | FH12: 0 | FI12: 0 | FJ12: 0 | FK12: 0 | FL12: 0 | FM12: 0 | FN12: 0 | FO12: 0 | FP12: 0 | FQ12: 0 | FR12: 0 | FS12: 0 | FT12: 0 | FU12: 0 | FV12: 0 | FW12: 0 | FX12: 0 | FY12: 0 | FZ12: 0 | GA12: 0 | GB12: 0 | GC12: 0 | GD12: 0 | GE12: 0 | GF12: 0 | GG12: 0 | GH12: 0 | GI12: 0 | GJ12: 0 | GK12: 0 | GL12: 0 | GM12: 0 | GN12: 0 | GO12: 0 | GP12: 0 | GQ12: 0
A13: =A12+7-WEEKDAY(A12-1)+1 -> 45915 | B13: 0 | C13: 0 | D13: 0 | E13: 0 | F13: 0 | G13: 0 | H13: 0 | I13: 0 | J13: 0 | K13: 0 | L13: 0 | M13: 0 | N13: 0 | O13: 0 | P13: 0 | Q13: 0 | R13: 0 | S13: 0 | T13: 0 | U13: 0 | V13: 0 | W13: 0 | X13: 0 | Y13: 0 | Z13: 0 | AA13: 0 | AB13: 0 | AC13: 0 | AD13: 0 | AE13: 0 | AF13: 0 | AG13: 0 | AH13: 0 | AI13: 0 | AJ13: 0 | AK13: 0 | AL13: 0 | AM13: 0 | AN13: 0 | AO13: 0 | AP13: 0 | AQ13: 0 | AR13: 0 | AS13: 0 | AT13: 0 | AU13: 0 | AV13: 0 | AW13: 0 | AX13: 0 | AY13: 0 | AZ13: 0 | BA13: 0 | BB13: 0 | BC13: 0 | BD13: 0 | BE13: 0 | BF13: 0 | BG13: 0 | BH13: 0 | BI13: 0 | BJ13: 0 | BK13: 0 | BL13: 0 | BM13: 0 | BN13: 0 | BO13: 0 | BP13: 0 | BQ13: 0 | BR13: 0 | BS13: 0 | BT13: 0 | BU13: 0 | BV13: 0 | BW13: 0 | BX13: 0 | BY13: 0 | BZ13: 0 | CA13: 0 | CB13: 0 | CC13: 0 | CD13: 0 | CE13: 0 | CF13: 0 | CG13: 0 | CH13: 0 | CI13: 0 | CJ13: 0 | CK13: 0 | CL13: 0 | CM13: 0 | CN13: 0 | CO13: 0 | CP13: 0 | CQ13: 0 | CR13: 0 | CS13: 0 | CT13: 0 | CU13: 0 | CV13: 0 | CW13: 0 | CX13: 0 | CY13: 0 | CZ13: 0 | DA13: 0 | DB13: 0 | DC13: 0 | DD13: 0 | DE13: 0 | DF13: 0 | DG13: 0 | DH13: 0 | DI13: 0 | DJ13: 0 | DK13: 0 | DL13: 0 | DM13: 0 | DN13: 0 | DO13: 0 | DP13: 0 | DQ13: 0 | DR13: 0 | DS13: 0 | DT13: 0 | DU13: 0 | DV13: 0 | DW13: 0 | DX13: 0 | DY13: 0 | DZ13: 0 | EA13: 0 | EB13: 0 | EC13: 0 | ED13: 0 | EE13: 0 | EF13: 0 | EG13: 0 | EH13: 0 | EI13: 0 | EJ13: 0 | EK13: 0 | EL13: 0 | EM13: 0 | EN13: 0 | EO13: 0 | EP13: 0 | EQ13: 0 | ER13: 0 | ES13: 0 | ET13: 0 | EU13: 0 | EV13: 0 | EW13: 0 | EX13: 33333 | EY13: 0 | EZ13: 0 | FA13: 0 | FB13: 0 | FC13: 0 | FD13: 0 | FE13: 0 | FF13: 0 | FG13: 0 | FH13: 0 | FI13: 0 | FJ13: 0 | FK13: 0 | FL13: 0 | FM13: 0 | FN13: 0 | FO13: 0 | FP13: 0 | FQ13: 0 | FR13: 0 | FS13: 0 | FT13: 0 | FU13: 0 | FV13: 0 | FW13: 0 | FX13: 0 | FY13: 0 | FZ13: 0 | GA13: 0 | GB13: 0 | GC13: 0 | GD13: 0 | GE13: 0 | GF13: 0 | GG13: 0 | GH13: 0 | GI13: 0 | GJ13: 0 | GK13: 0 | GL13: 0 | GM13: 0 | GN13: 0 | GO13: 0 | GP13: 0 | GQ13: 0
A14: =A13+7-WEEKDAY(A13-1)+1 -> 45922 | B14: 0 | C14: 0 | D14: 0 | E14: 0 | F14: 0 | G14: 0 | H14: 0 | I14: 0 | J14: 0 | K14: 0 | L14: 0 | M14: 0 | N14: 0 | O14: 0 | P14: 0 | Q14: 0 | R14: 0 | S14: 0 | T14: 0 | U14: 0 | V14: 0 | W14: 0 | X14: 0 | Y14: 0 | Z14: 0 | AA14: 0 | AB14: 0 | AC14: 0 | AD14: 0 | AE14: 0 | AF14: 0 | AG14: 0 | AH14: 0 | AI14: 0 | AJ14: 0 | AK14: 0 | AL14: 0 | AM14: 0 | AN14: 0 | AO14: 0 | AP14: 0 | AQ14: 0 | AR14: 0 | AS14: 0 | AT14: 0 | AU14: 0 | AV14: 0 | AW14: 0 | AX14: 0 | AY14: 0 | AZ14: 0 | BA14: 0 | BB14: 0 | BC14: 0 | BD14: 0 | BE14: 0 | BF14: 0 | BG14: 0 | BH14: 0 | BI14: 0 | BJ14: 0 | BK14: 0 | BL14: 0 | BM14: 0 | BN14: 0 | BO14: 0 | BP14: 0 | BQ14: 0 | BR14: 0 | BS14: 0 | BT14: 0 | BU14: 0 | BV14: 0 | BW14: 0 | BX14: 0 | BY14: 0 | BZ14: 0 | CA14: 0 | CB14: 0 | CC14: 0 | CD14: 0 | CE14: 0 | CF14: 0 | CG14: 0 | CH14: 0 | CI14: 0 | CJ14: 0 | CK14: 0 | CL14: 0 | CM14: 0 | CN14: 0 | CO14: 0 | CP14: 0 | CQ14: 0 | CR14: 0 | CS14: 0 | CT14: 0 | CU14: 0 | CV14: 0 | CW14: 0 | CX14: 0 | CY14: 0 | CZ14: 0 | DA14: 0 | DB14: 0 | DC14: 0 | DD14: 0 | DE14: 0 | DF14: 0 | DG14: 0 | DH14: 0 | DI14: 0 | DJ14: 0 | DK14: 0 | DL14: 0 | DM14: 0 | DN14: 0 | DO14: 0 | DP14: 0 | DQ14: 0 | DR14: 0 | DS14: 0 | DT14: 0 | DU14: 0 | DV14: 0 | DW14: 0 | DX14: 0 | DY14: 0 | DZ14: 0 | EA14: 0 | EB14: 0 | EC14: 0 | ED14: 0 | EE14: 0 | EF14: 0 | EG14: 0 | EH14: 0 | EI14: 0 | EJ14: 0 | EK14: 0 | EL14: 0 | EM14: 0 | EN14: 0 | EO14: 0 | EP14: 0 | EQ14: 0 | ER14: 0 | ES14: 0 | ET14: 0 | EU14: 0 | EV14: 0 | EW14: 0 | EX14: 0 | EY14: 0 | EZ14: 0 | FA14: 0 | FB14: 0 | FC14: 0 | FD14: 0 | FE14: 0 | FF14: 0 | FG14: 0 | FH14: 0 | FI14: 0 | FJ14: 0 | FK14: 0 | FL14: 0 | FM14: 0 | FN14: 0 | FO14: 0 | FP14: 0 | FQ14: 0 | FR14: 0 | FS14: 0 | FT14: 0 | FU14: 0 | FV14: 0 | FW14: 0 | FX14: 0 | FY14: 0 | FZ14: 0 | GA14: 0 | GB14: 0 | GC14: 0 | GD14: 0 | GE14: 0 | GF14: 0 | GG14: 0 | GH14: 0 | GI14: 0 | GJ14: 0 | GK14: 0 | GL14: 0 | GM14: 0 | GN14: 0 | GO14: 0 | GP14: 0 | GQ14: 0
A15: =A14+7-WEEKDAY(A14-1)+1 -> 45929 | B15: 0 | C15: 0 | D15: 0 | E15: 0 | F15: 0 | G15: 0 | H15: 0 | I15: 0 | J15: 0 | K15: 0 | L15: 0 | M15: 0 | N15: 0 | O15: 0 | P15: 0 | Q15: 0 | R15: 0 | S15: 0 | T15: 0 | U15: 0 | V15: 0 | W15: 0 | X15: 0 | Y15: 0 | Z15: 0 | AA15: 0 | AB15: 0 | AC15: 0 | AD15: 0 | AE15: 0 | AF15: 0 | AG15: 0 | AH15: 0 | AI15: 0 | AJ15: 0 | AK15: 0 | AL15: 0 | AM15: 0 | AN15: 0 | AO15: 0 | AP15: 0 | AQ15: 1000 | AR15: 4000 | AS15: 0 | AT15: 0 | AU15: 0 | AV15: 0 | AW15: 0 | AX15: 0 | AY15: 0 | AZ15: 0 | BA15: 0 | BB15: 0 | BC15: 0 | BD15: 0 | BE15: 0 | BF15: 0 | BG15: 0 | BH15: 0 | BI15: 0 | BJ15: 0 | BK15: 0 | BL15: 0 | BM15: 0 | BN15: 0 | BO15: 0 | BP15: 0 | BQ15: 0 | BR15: 0 | BS15: 0 | BT15: 0 | BU15: 0 | BV15: 0 | BW15: 0 | BX15: 0 | BY15: 0 | BZ15: 0 | CA15: 0 | CB15: 0 | CC15: 0 | CD15: 0 | CE15: 0 | CF15: 0 | CG15: 0 | CH15: 0 | CI15: 0 | CJ15: 0 | CK15: 0 | CL15: 0 | CM15: 0 | CN15: 0 | CO15: 0 | CP15: 0 | CQ15: 0 | CR15: 0 | CS15: 0 | CT15: 0 | CU15: 0 | CV15: 2000 | CW15: 0 | CX15: 0 | CY15: 0 | CZ15: 0 | DA15: 0 | DB15: 0 | DC15: 0 | DD15: 0 | DE15: 0 | DF15: 0 | DG15: 0 | DH15: 0 | DI15: 0 | DJ15: 0 | DK15: 0 | DL15: 0 | DM15: 0 | DN15: 0 | DO15: 0 | DP15: 0 | DQ15: 0 | DR15: 0 | DS15: 0 | DT15: 0 | DU15: 0 | DV15: 0 | DW15: 0 | DX15: 0 | DY15: 0 | DZ15: 0 | EA15: 0 | EB15: 0 | EC15: 0 | ED15: 0 | EE15: 0 | EF15: 0 | EG15: 0 | EH15: 0 | EI15: 0 | EJ15: 0 | EK15: 0 | EL15: 0 | EM15: 0 | EN15: 0 | EO15: 0 | EP15: 0 | EQ15: 0 | ER15: 0 | ES15: 0 | ET15: 0 | EU15: 0 | EV15: 0 | EW15: 0 | EX15: 0 | EY15: 0 | EZ15: 0 | FA15: 0 | FB15: 0 | FC15: 0 | FD15: 0 | FE15: 0 | FF15: 0 | FG15: 0 | FH15: 0 | FI15: 5400 | FJ15: 0 | FK15: 0 | FL15: 0 | FM15: 0 | FN15: 0 | FO15: 0 | FP15: 0 | FQ15: 0 | FR15: 0 | FS15: 0 | FT15: 0 | FU15: 0 | FV15: 0 | FW15: 0 | FX15: 0 | FY15: 0 | FZ15: 0 | GA15: 0 | GB15: 0 | GC15: 0 | GD15: 0 | GE15: 0 | GF15: 0 | GG15: 0 | GH15: 0 | GI15: 0 | GJ15: 0 | GK15: 0 | GL15: 0 | GM15: 0 | GN15: 0 | GO15: 0 | GP15: 0 | GQ15: 0
A16: =A15+7-WEEKDAY(A15-1)+1 -> 45936 | B16: 0 | C16: 0 | D16: 0 | E16: 0 | F16: 0 | G16: 0 | H16: 0 | I16: 0 | J16: 0 | K16: 0 | L16: 0 | M16: 0 | N16: 0 | O16: 0 | P16: 0 | Q16: 0 | R16: 0 | S16: 0 | T16: 0 | U16: 0 | V16: 0 | W16: 0 | X16: 0 | Y16: 0 | Z16: 0 | AA16: 0 | AB16: 0 | AC16: 0 | AD16: 0 | AE16: 0 | AF16: 0 | AG16: 5000 | AH16: 0 | AI16: 0 | AJ16: 0 | AK16: 0 | AL16: 0 | AM16: 0 | AN16: 0 | AO16: 0 | AP16: 0 | AQ16: 0 | AR16: 0 | AS16: 0 | AT16: 0 | AU16: 0 | AV16: 0 | AW16: 0 | AX16: 0 | AY16: 0 | AZ16: 0 | BA16: 0 | BB16: 0 | BC16: 0 | BD16: 0 | BE16: 0 | BF16: 0 | BG16: 0 | BH16: 0 | BI16: 0 | BJ16: 0 | BK16: 0 | BL16: 0 | BM16: 0 | BN16: 0 | BO16: 0 | BP16: 0 | BQ16: 0 | BR16: 0 | BS16: 0 | BT16: 0 | BU16: 0 | BV16: 0 | BW16: 0 | BX16: 0 | BY16: 0 | BZ16: 0 | CA16: 0 | CB16: 0 | CC16: 0 | CD16: 0 | CE16: 0 | CF16: 0 | CG16: 0 | CH16: 0 | CI16: 0 | CJ16: 0 | CK16: 0 | CL16: 0 | CM16: 0 | CN16: 0 | CO16: 0 | CP16: 0 | CQ16: 0 | CR16: 0 | CS16: 0 | CT16: 0 | CU16: 0 | CV16: 0 | CW16: 0 | CX16: 0 | CY16: 0 | CZ16: 0 | DA16: 0 | DB16: 0 | DC16: 0 | DD16: 0 | DE16: 0 | DF16: 0 | DG16: 0 | DH16: 0 | DI16: 0 | DJ16: 0 | DK16: 0 | DL16: 0 | DM16: 0 | DN16: 0 | DO16: 0 | DP16: 0 | DQ16: 0 | DR16: 0 | DS16: 0 | DT16: 0 | DU16: 0 | DV16: 0 | DW16: 0 | DX16: 0 | DY16: 0 | DZ16: 0 | EA16: 0 | EB16: 0 | EC16: 0 | ED16: 0 | EE16: 0 | EF16: 0 | EG16: 0 | EH16: 0 | EI16: 0 | EJ16: 0 | EK16: 0 | EL16: 0 | EM16: 0 | EN16: 0 | EO16: 0 | EP16: 0 | EQ16: 0 | ER16: 0 | ES16: 0 | ET16: 0 | EU16: 0 | EV16: 0 | EW16: 0 | EX16: 0 | EY16: 0 | EZ16: 0 | FA16: 0 | FB16: 0 | FC16: 0 | FD16: 0 | FE16: 0 | FF16: 0 | FG16: 0 | FH16: 0 | FI16: 0 | FJ16: 0 | FK16: 0 | FL16: 0 | FM16: 0 | FN16: 0 | FO16: 0 | FP16: 0 | FQ16: 0 | FR16: 0 | FS16: 0 | FT16: 0 | FU16: 0 | FV16: 0 | FW16: 0 | FX16: 0 | FY16: 0 | FZ16: 0 | GA16: 0 | GB16: 0 | GC16: 0 | GD16: 0 | GE16: 0 | GF16: 0 | GG16: 0 | GH16: 0 | GI16: 0 | GJ16: 0 | GK16: 0 | GL16: 0 | GM16: 0 | GN16: 0 | GO16: 0 | GP16: 0 | GQ16: 0
A17: =A16+7-WEEKDAY(A16-1)+1 -> 45943 | B17: 0 | C17: 0 | D17: 0 | E17: 0 | F17: 0 | G17: 0 | H17: 0 | I17: 0 | J17: 0 | K17: 0 | L17: 0 | M17: 0 | N17: 0 | O17: 0 | P17: 0 | Q17: 0 | R17: 0 | S17: 0 | T17: 0 | U17: 0 | V17: 0 | W17: 0 | X17: 0 | Y17: 0 | Z17: 0 | AA17: 0 | AB17: 0 | AC17: 0 | AD17: 0 | AE17: 0 | AF17: 0 | AG17: 0 | AH17: 0 | AI17: 0 | AJ17: 0 | AK17: 0 | AL17: 0 | AM17: 0 | AN17: 0 | AO17: 0 | AP17: 0 | AQ17: 0 | AR17: 0 | AS17: 0 | AT17: 0 | AU17: 0 | AV17: 0 | AW17: 0 | AX17: 0 | AY17: 0 | AZ17: 0 | BA17: 0 | BB17: 0 | BC17: 0 | BD17: 0 | BE17: 0 | BF17: 0 | BG17: 0 | BH17: 0 | BI17: 0 | BJ17: 0 | BK17: 0 | BL17: 0 | BM17: 0 | BN17: 0 | BO17: 0 | BP17: 0 | BQ17: 0 | BR17: 0 | BS17: 0 | BT17: 0 | BU17: 0 | BV17: 0 | BW17: 0 | BX17: 0 | BY17: 0 | BZ17: 0 | CA17: 0 | CB17: 0 | CC17: 0 | CD17: 0 | CE17: 0 | CF17: 0 | CG17: 0 | CH17: 0 | CI17: 0 | CJ17: 0 | CK17: 0 | CL17: 0 | CM17: 0 | CN17: 0 | CO17: 0 | CP17: 0 | CQ17: 0 | CR17: 0 | CS17: 0 | CT17: 0 | CU17: 0 | CV17: 0 | CW17: 0 | CX17: 0 | CY17: 0 | CZ17: 0 | DA17: 0 | DB17: 0 | DC17: 0 | DD17: 0 | DE17: 0 | DF17: 0 | DG17: 0 | DH17: 0 | DI17: 0 | DJ17: 0 | DK17: 0 | DL17: 0 | DM17: 0 | DN17: 0 | DO17: 0 | DP17: 0 | DQ17: 0 | DR17: 0 | DS17: 0 | DT17: 0 | DU17: 0 | DV17: 0 | DW17: 0 | DX17: 0 | DY17: 0 | DZ17: 0 | EA17: 0 | EB17: 0 | EC17: 0 | ED17: 0 | EE17: 0 | EF17: 0 | EG17: 0 | EH17: 0 | EI17: 0 | EJ17: 0 | EK17: 0 | EL17: 0 | EM17: 0 | EN17: 0 | EO17: 0 | EP17: 0 | EQ17: 0 | ER17: 0 | ES17: 0 | ET17: 0 | EU17: 0 | EV17: 0 | EW17: 0 | EX17: 0 | EY17: 0 | EZ17: 0 | FA17: 0 | FB17: 0 | FC17: 0 | FD17: 0 | FE17: 0 | FF17: 0 | FG17: 0 | FH17: 0 | FI17: 0 | FJ17: 0 | FK17: 0 | FL17: 0 | FM17: 0 | FN17: 0 | FO17: 0 | FP17: 0 | FQ17: 0 | FR17: 0 | FS17: 0 | FT17: 0 | FU17: 0 | FV17: 0 | FW17: 0 | FX17: 0 | FY17: 0 | FZ17: 0 | GA17: 0 | GB17: 0 | GC17: 0 | GD17: 0 | GE17: 0 | GF17: 0 | GG17: 0 | GH17: 0 | GI17: 0 | GJ17: 0 | GK17: 0 | GL17: 0 | GM17: 0 | GN17: 0 | GO17: 0 | GP17: 0 | GQ17: 0
